Workbook

Sheet Reporte de ejecución - Entrega1
A1: GhostMan - Entrega 1 - Reporte de ejecución de casos de prueba (V1, ciclo 1)
A2: Completar las columnas Estado, Ejecutor, Fecha, Defectos y Observaciones (en azul). Estados según la sección 12.2: Aprobado, Fallido, Bloqueado, No ejecutado, No aplica. Un caso Fallido debe indicar su defecto (DEF-nnn) en la columna Defectos. El ID de cada caso abre su hoja de detalle.
A3: Test case ID | B3: Épica | C3: Prioridad | D3: Título | E3: Historia de usuario | F3: Camino feliz | G3: Estado | H3: Ejecutor | I3: Fecha | J3: Defectos | K3: Observaciones | M3: Identificación del ciclo (sección 12.1)
A4: CP-001 | B4: E1 | C4: Alta | D4: Movimiento de Pacman con las flechas | E4: HU-01 | F4: Sí | M4: Ciclo de ejecución | N4: Nº 1
A5: CP-002 | B5: E1 | C5: Alta | D5: Movimiento de Pacman con WASD | E5: HU-01 | F5: Sí | M5: Versión bajo prueba | N5: V1
A6: CP-003 | B6: E1 | C6: Alta | D6: Avance continuo sin mantener la tecla | E6: HU-01 | F6: Sí | M6: Commit
A7: CP-004 | B7: E1 | C7: Media | D7: Giro postergado hasta la primera celda posible | E7: HU-01 | F7: No | M7: Entorno (URL de despliegue)
A8: CP-005 | B8: E1 | C8: Alta | D8: Dirección bloqueada por un muro | E8: HU-01 | F8: No | M8: Navegador y versión
A9: CP-006 | B9: E1 | C9: Media | D9: Inversión de marcha a mitad de corredor | E9: HU-01 | F9: No | M9: Fecha de inicio
A10: CP-007 | B10: E1 | C10: Alta | D10: Pacman no atraviesa los muros | E10: HU-02 | F10: No | M10: Fecha de cierre
A11: CP-008 | B11: E1 | C11: Alta | D11: Pacman no sale de los límites del mapa | E11: HU-02 | F11: No | M11: Ejecutores | N11: Rodriguez Castro, Tsai
A12: CP-009 | B12: E1 | C12: Alta | D12: Los fantasmas clásicos no atraviesan muros | E12: HU-02 | F12: No
A13: CP-010 | B13: E1 | C13: Media | D13: Zona transitable coincidente con el mapa dibujado | E13: HU-02 | F13: No | M13: Resumen cuantitativo (sección 12.4)
A14: CP-011 | B14: E1 | C14: Alta | D14: Consumo de una esfera común | E14: HU-03 | F14: Sí | M14: Casos diseñados para la V1 | N14: =COUNTA($A$4:$A$69) -> 66
A15: CP-012 | B15: E1 | C15: Alta | D15: Una esfera consumida no reaparece al perder una vida | E15: HU-03 | F15: No | M15: Casos ejecutados (Aprobado + Fallido) | N15: =COUNTIF($G$4:$G$69,"Aprobado")+COUNTIF($G$4:$G$69,"Fallido") -> 0
A16: CP-013 | B16: E1 | C16: Media | D16: Los fantasmas no consumen esferas | E16: HU-03 | F16: No | M16: Casos aprobados | N16: =COUNTIF($G$4:$G$69,"Aprobado") -> 0
A17: CP-014 | B17: E1 | C17: Alta | D17: Finalización del nivel al consumir la última esfera | E17: HU-04 | F17: Sí | M17: Casos fallidos | N17: =COUNTIF($G$4:$G$69,"Fallido") -> 0
A18: CP-015 | B18: E1 | C18: Alta | D18: El nivel no se completa si queda una esfera grande | E18: HU-04 | F18: No | M18: Casos bloqueados | N18: =COUNTIF($G$4:$G$69,"Bloqueado") -> 0
A19: CP-016 | B19: E1 | C19: Alta | D19: Paso al nivel siguiente conservando puntaje y vidas | E19: HU-04 | F19: Sí | M19: Casos no ejecutados (incluye sin estado) | N19: =COUNTIF($G$4:$G$69,"No ejecutado")+COUNTBLANK($G$4:$G$69) -> 66
A20: CP-017 | B20: E1 | C20: Alta | D20: Victoria al completar el nivel 3 | E20: HU-04 | F20: Sí | M20: Casos no aplica | N20: =COUNTIF($G$4:$G$69,"No aplica") -> 0
A21: CP-018 | B21: E2 | C21: Alta | D21: Activación automática del PowerUp | E21: HU-05 | F21: Sí
A22: CP-019 | B22: E2 | C22: Alta | D22: Duración del PowerUp | E22: HU-05 | F22: No | M22: Indicadores
A23: CP-020 | B23: E2 | C23: Alta | D23: Los fantasmas huyen durante el PowerUp | E23: HU-05 | F23: No | M23: Avance de la ejecución (ejecutados / diseñados) | N23: =IFERROR($N$15/$N$14,0) -> 0
A24: CP-021 | B24: E2 | C24: Media | D24: Reinicio del temporizador por una segunda esfera grande | E24: HU-05 | F24: No | M24: Tasa de aprobación (aprobados / ejecutados) | N24: =IFERROR($N$16/$N$15,0) -> 0
A25: CP-022 | B25: E2 | C25: Media | D25: Reinicio de la escala de puntos por una segunda esfera grande | E25: HU-05 | F25: No | M25: Tasa de fallo (fallidos / ejecutados) | N25: =IFERROR($N$17/$N$15,0) -> 0
A26: CP-023 | B26: E2 | C26: Alta | D26: Escala de puntos por fantasmas comidos | E26: HU-06 | F26: Sí | M26: Cobertura de prioridad Alta (ejecutados Alta / diseñados Alta) | N26: =IFERROR((COUNTIFS($C$4:$C$69,"Alta",$G$4:$G$69,"Aprobado")+COUNTIFS($C$4:$C$69,"Alta",$G$4:$G$69,"Fallido"))/COUNTIF($C$4:$C$69,"Alta"),0) -> 0
A27: CP-024 | B27: E2 | C27: Alta | D27: Reinicio de la escala al terminar el PowerUp | E27: HU-06 | F27: No | M27: Densidad de defectos (defectos / casos ejecutados) | N27: =IFERROR(COUNTA('Registro de defectos'!$A$5:$A$104)/$N$15,0) -> 0
A28: CP-025 | B28: E2 | C28: Alta | D28: Comer un fantasma no descuenta vidas | E28: HU-06 | F28: No
A29: CP-026 | B29: E2 | C29: Media | D29: Reaparición del fantasma comido | E29: HU-06 | F29: No | M29: Resultados por épica (sección 12.5)
A30: CP-027 | B30: E2 | C30: Media | D30: Fantasma que reaparece con el PowerUp aún activo | E30: HU-06 | F30: No | M30: Épica | N30: Diseñados | O30: Ejecutados | P30: Aprobados | Q30: Fallidos | R30: Bloqueados | S30: Tasa de aprobación
A31: CP-028 | B31: E2 | C31: Media | D31: Parpadeo en los últimos 2 segundos del PowerUp | E31: HU-07 | F31: No | M31: E1 — Núcleo de juego y movimiento | N31: =COUNTIF($B$4:$B$69,"E1") -> 17 | O31: =COUNTIFS($B$4:$B$69,"E1",$G$4:$G$69,"Aprobado")+COUNTIFS($B$4:$B$69,"E1",$G$4:$G$69,"Fallido") -> 0 | P31: =COUNTIFS($B$4:$B$69,"E1",$G$4:$G$69,"Aprobado") -> 0 | Q31: =COUNTIFS($B$4:$B$69,"E1",$G$4:$G$69,"Fallido") -> 0 | R31: =COUNTIFS($B$4:$B$69,"E1",$G$4:$G$69,"Bloqueado") -> 0 | S31: =IFERROR(P31/O31,0) -> 0
A32: CP-029 | B32: E2 | C32: Media | D32: Esfera grande consumida durante el parpadeo | E32: HU-07 | F32: No | M32: E2 — PowerUp e interacción con fantasmas | N32: =COUNTIF($B$4:$B$69,"E2") -> 16 | O32: =COUNTIFS($B$4:$B$69,"E2",$G$4:$G$69,"Aprobado")+COUNTIFS($B$4:$B$69,"E2",$G$4:$G$69,"Fallido") -> 0 | P32: =COUNTIFS($B$4:$B$69,"E2",$G$4:$G$69,"Aprobado") -> 0 | Q32: =COUNTIFS($B$4:$B$69,"E2",$G$4:$G$69,"Fallido") -> 0 | R32: =COUNTIFS($B$4:$B$69,"E2",$G$4:$G$69,"Bloqueado") -> 0 | S32: =IFERROR(P32/O32,0) -> 0
A33: CP-030 | B33: E2 | C33: Alta | D33: Descuento de una vida por contacto con un fantasma | E33: HU-08 | F33: Sí | M33: E3 — Vidas, puntaje y fin de partida | N33: =COUNTIF($B$4:$B$69,"E3") -> 13 | O33: =COUNTIFS($B$4:$B$69,"E3",$G$4:$G$69,"Aprobado")+COUNTIFS($B$4:$B$69,"E3",$G$4:$G$69,"Fallido") -> 0 | P33: =COUNTIFS($B$4:$B$69,"E3",$G$4:$G$69,"Aprobado") -> 0 | Q33: =COUNTIFS($B$4:$B$69,"E3",$G$4:$G$69,"Fallido") -> 0 | R33: =COUNTIFS($B$4:$B$69,"E3",$G$4:$G$69,"Bloqueado") -> 0 | S33: =IFERROR(P33/O33,0) -> 0
A34: CP-031 | B34: E2 | C34: Alta | D34: Un solo contacto no descuenta más de una vida | E34: HU-08 | F34: No | M34: E4 — Niveles y progresión de dificultad | N34: =COUNTIF($B$4:$B$69,"E4") -> 16 | O34: =COUNTIFS($B$4:$B$69,"E4",$G$4:$G$69,"Aprobado")+COUNTIFS($B$4:$B$69,"E4",$G$4:$G$69,"Fallido") -> 0 | P34: =COUNTIFS($B$4:$B$69,"E4",$G$4:$G$69,"Aprobado") -> 0 | Q34: =COUNTIFS($B$4:$B$69,"E4",$G$4:$G$69,"Fallido") -> 0 | R34: =COUNTIFS($B$4:$B$69,"E4",$G$4:$G$69,"Bloqueado") -> 0 | S34: =IFERROR(P34/O34,0) -> 0
A35: CP-032 | B35: E2 | C35: Media | D35: El PowerUp se cancela al perder una vida | E35: HU-08 | F35: No | M35: E5 — Control de la partida | N35: =COUNTIF($B$4:$B$69,"E5") -> 4 | O35: =COUNTIFS($B$4:$B$69,"E5",$G$4:$G$69,"Aprobado")+COUNTIFS($B$4:$B$69,"E5",$G$4:$G$69,"Fallido") -> 0 | P35: =COUNTIFS($B$4:$B$69,"E5",$G$4:$G$69,"Aprobado") -> 0 | Q35: =COUNTIFS($B$4:$B$69,"E5",$G$4:$G$69,"Fallido") -> 0 | R35: =COUNTIFS($B$4:$B$69,"E5",$G$4:$G$69,"Bloqueado") -> 0 | S35: =IFERROR(P35/O35,0) -> 0
A36: CP-033 | B36: E2 | C36: Alta | D36: Reanudación del nivel tras perder una vida | E36: HU-08 | F36: No | M36: Total | N36: =SUM(N31:N35) -> 66 | O36: =SUM(O31:O35) -> 0 | P36: =SUM(P31:P35) -> 0 | Q36: =SUM(Q31:Q35) -> 0 | R36: =SUM(R31:R35) -> 0 | S36: =IFERROR(P36/O36,0) -> 0
A37: CP-034 | B37: E3 | C37: Media | D37: Presentación del contador de vidas | E37: HU-09 | F37: No
A38: CP-035 | B38: E3 | C38: Media | D38: Actualización inmediata del contador de vidas | E38: HU-09 | F38: No | M38: Organización del equipo de testing (sección 6.1)
A39: CP-036 | B39: E3 | C39: Alta | D39: Game Over al perder la tercera vida | E39: HU-10 | F39: Sí | M39: Test Lead | N39: Savoia
A40: CP-037 | B40: E3 | C40: Media | D40: Game Over en un nivel distinto del primero | E40: HU-10 | F40: No | M40: Diseño de casos de prueba (V1) | N40: Cruz, Luzzi
A41: CP-038 | B41: E3 | C41: Media | D41: Puntaje visible y actualizado en el HUD | E41: HU-11 | F41: Sí | M41: Ejecución y reporte de defectos (V1) | N41: Rodriguez Castro, Tsai
A42: CP-039 | B42: E3 | C42: Media | D42: El puntaje no disminuye ni se reinicia entre niveles | E42: HU-11 | F42: No
A43: CP-040 | B43: E3 | C43: Media | D43: Consumo de una fruta | E43: HU-12 | F43: Sí
A44: CP-041 | B44: E3 | C44: Baja | D44: Desaparición de una fruta no consumida | E44: HU-12 | F44: No
A45: CP-042 | B45: E3 | C45: Media | D45: Cálculo del bonus por tiempo | E45: HU-13 | F45: No
A46: CP-043 | B46: E3 | C46: Media | D46: Bonus por tiempo al exceder el tiempo objetivo | E46: HU-13 | F46: No
A47: CP-044 | B47: E3 | C47: Media | D47: Bonus por vidas restantes y consistencia del desglose | E47: HU-13 | F47: No
A48: CP-045 | B48: E3 | C48: Media | D48: Bonus por vidas en un Game Over | E48: HU-13 | F48: No
A49: CP-046 | B49: E3 | C49: Baja | D49: Contador de esferas restantes | E49: HU-14 | F49: No
A50: CP-047 | B50: E4 | C50: Alta | D50: Los tres niveles y sus mapas | E50: HU-15 | F50: Sí
A51: CP-048 | B51: E4 | C51: Media | D51: Los mapas no varían entre partidas | E51: HU-15 | F51: No
A52: CP-049 | B52: E4 | C52: Alta | D52: Solo fantasmas clásicos en el nivel 1 | E52: HU-16 | F52: No
A53: CP-050 | B53: E4 | C53: Alta | D53: Reaparición como clásico en el nivel 1 | E53: HU-16 | F53: No
... A69: CP-066 | B69: E5 | C69: Baja | D69: La barra espaciadora no tiene efecto en modo Pacman | E69: HU-21 | F69: No

Sheet Registro de defectos
A1: GhostMan - Entrega 1 - Registro de defectos (V1, ciclo 1)
A2: Una fila por defecto, en orden de detección (DEF-001, DEF-002, …). Campos de la sección 13.3; severidad y prioridad según 13.1; estado según 13.2. El detalle completo (pasos, resultados, evidencia) va en una hoja copiada de «DF - Plantilla» y nombrada con el ID del defecto.
A3: Todo defecto debe ser confirmado por un integrante distinto del que lo reportó antes de pasar a corrección (13.2).
A4: ID | B4: Título | C4: Caso de prueba | D4: HU | E4: Severidad | F4: Prioridad | G4: Estado | H4: Versión / commit | I4: Entorno (navegador, resolución) | J4: Reproducibilidad | K4: Reportado por | L4: Confirmado por | M4: Fecha | N4: Observaciones | Q4: Defectos por severidad
Q5: Bloqueante | R5: =COUNTIF($E$5:$E$104,"Bloqueante") -> 0
Q6: Crítica | R6: =COUNTIF($E$5:$E$104,"Crítica") -> 0
Q7: Mayor | R7: =COUNTIF($E$5:$E$104,"Mayor") -> 0
Q8: Menor | R8: =COUNTIF($E$5:$E$104,"Menor") -> 0
Q9: Trivial | R9: =COUNTIF($E$5:$E$104,"Trivial") -> 0
Q10: Total | R10: =COUNTA($A$5:$A$104) -> 0
Q12: Defectos por estado
Q13: Nuevo | R13: =COUNTIF($G$5:$G$104,"Nuevo") -> 0
Q14: Confirmado | R14: =COUNTIF($G$5:$G$104,"Confirmado") -> 0
Q15: No reproducible | R15: =COUNTIF($G$5:$G$104,"No reproducible") -> 0
Q16: En corrección | R16: =COUNTIF($G$5:$G$104,"En corrección") -> 0
Q17: Corregido | R17: =COUNTIF($G$5:$G$104,"Corregido") -> 0
Q18: Verificado | R18: =COUNTIF($G$5:$G$104,"Verificado") -> 0
Q19: Diferido | R19: =COUNTIF($G$5:$G$104,"Diferido") -> 0
Q20: Rechazado | R20: =COUNTIF($G$5:$G$104,"Rechazado") -> 0
Q22: Defectos por épica (según el CP)
Q23: E1 (CP-001 a CP-017) | R23: =COUNTIFS($C$5:$C$104,">=CP-001",$C$5:$C$104,"<=CP-017") -> 0
Q24: E2 (CP-018 a CP-033) | R24: =COUNTIFS($C$5:$C$104,">=CP-018",$C$5:$C$104,"<=CP-033") -> 0
Q25: E3 (CP-034 a CP-046) | R25: =COUNTIFS($C$5:$C$104,">=CP-034",$C$5:$C$104,"<=CP-046") -> 0
Q26: E4 (CP-047 a CP-062) | R26: =COUNTIFS($C$5:$C$104,">=CP-047",$C$5:$C$104,"<=CP-062") -> 0
Q27: E5 (CP-063 a CP-066) | R27: =COUNTIFS($C$5:$C$104,">=CP-063",$C$5:$C$104,"<=CP-066") -> 0
Q28: Exploratoria | R28: =COUNTIF($C$5:$C$104,"Exploratoria") -> 0

Sheet CP-001
A1: Test Case ID | B1: CP-001 | C1: Descripción / Funcionalidad | D1: HU-01 · Mover a Pacman por el mapa | G1: Registro de ejecución
A2: Creado por | B2: Cruz, Luzzi | C2: Versión | D2: 1 | G2: Ciclo | H2: Fecha | I2: Ejecutor | J2: Estado | K2: Resultado obtenido | L2: Defecto
A3: Reporte de ejecución 1 | C3: Estado en la Entrega 1 | D3: =IF(INDEX('Reporte de ejecución - Entrega1'!$G$4:$G$69,MATCH($B$1,'Reporte de ejecución - Entrega1'!$A$4:$A$69,0))="","Sin ejecutar",INDEX('Reporte de ejecución - Entrega1'!$G$4:$G$69,MATCH($B$1,'Reporte de ejecución - Entrega1'!$A$4:$A$69,0))) -> Sin ejecutar | G3: Ciclo 1
G4: Ciclo 2
A5: Prioridad (Alta, Media, Baja) | B5: Alta | C5: Técnica de diseño | D5: Partición de equivalencia | G5: Ciclo 3
G6: Estado del ciclo 1: cargarlo en la hoja del reporte; la celda «Estado en la Entrega 1» lo toma de ahí. Este registro es para el resultado obtenido y los reintentos.
A7: # | B7: Pre-requisitos | D7: Datos de prueba
A8: 1 | B8: Abrir la aplicación desplegada en un navegador de escritorio. | D8: Entorno: | E8: Aplicación desplegada en Vercel (URL en el Anexo C)
A9: 2 | B9: Iniciar una partida en modo Pacman. | D9: Navegador: | E9: Google Chrome de escritorio
A10: 3 | B10: Partida en curso (N1). | D10: Modo de juego: | E10: Pacman
D11: Nivel inicial: | E11: 1
D12: Vidas iniciales: | E12: 3
D13: PowerUp: | E13: Inactivo
A15: Título del CP | B15: Movimiento de Pacman con las flechas
A18: Historias de Usuario | B18: HU-01 | C18: Épica | D18: E1 — Núcleo de juego y movimiento
A19: Estado Automatización | B19: No automatizado | C19: Camino feliz | D19: Sí
A21: Pasos # | B21: Detalle de pasos | D21: Resultado esperado
A22: 1 | B22: Presionar ←. | D22: Pacman se desplaza hacia la izquierda.
A23: 2 | B23: Presionar ↑. | D23: Pacman se desplaza hacia arriba.
A24: 3 | B24: Presionar →. | D24: Pacman se desplaza hacia la derecha.
A25: 4 | B25: Presionar ↓. | D25: Pacman se desplaza en la dirección de cada tecla presionada, siempre que el camino esté libre.
A26: El caso se aprueba solo si se cumple todo el resultado esperado del último paso (en negrita); si cualquier parte no se cumple, se registra como Fallido.

Sheet CP-002
A1: Test Case ID | B1: CP-002 | C1: Descripción / Funcionalidad | D1: HU-01 · Mover a Pacman por el mapa | G1: Registro de ejecución
A2: Creado por | B2: Cruz, Luzzi | C2: Versión | D2: 1 | G2: Ciclo | H2: Fecha | I2: Ejecutor | J2: Estado | K2: Resultado obtenido | L2: Defecto
A3: Reporte de ejecución 1 | C3: Estado en la Entrega 1 | D3: =IF(INDEX('Reporte de ejecución - Entrega1'!$G$4:$G$69,MATCH($B$1,'Reporte de ejecución - Entrega1'!$A$4:$A$69,0))="","Sin ejecutar",INDEX('Reporte de ejecución - Entrega1'!$G$4:$G$69,MATCH($B$1,'Reporte de ejecución - Entrega1'!$A$4:$A$69,0))) -> Sin ejecutar | G3: Ciclo 1
G4: Ciclo 2
A5: Prioridad (Alta, Media, Baja) | B5: Alta | C5: Técnica de diseño | D5: Partición de equivalencia | G5: Ciclo 3
G6: Estado del ciclo 1: cargarlo en la hoja del reporte; la celda «Estado en la Entrega 1» lo toma de ahí. Este registro es para el resultado obtenido y los reintentos.
A7: # | B7: Pre-requisitos | D7: Datos de prueba
A8: 1 | B8: Abrir la aplicación desplegada en un navegador de escritorio. | D8: Entorno: | E8: Aplicación desplegada en Vercel (URL en el Anexo C)
A9: 2 | B9: Iniciar una partida en modo Pacman. | D9: Navegador: | E9: Google Chrome de escritorio
A10: 3 | B10: Partida en curso (N1). | D10: Modo de juego: | E10: Pacman
D11: Nivel inicial: | E11: 1
D12: Vidas iniciales: | E12: 3
D13: PowerUp: | E13: Inactivo
A15: Título del CP | B15: Movimiento de Pacman con WASD
A18: Historias de Usuario | B18: HU-01 | C18: Épica | D18: E1 — Núcleo de juego y movimiento
A19: Estado Automatización | B19: No automatizado | C19: Camino feliz | D19: Sí
A21: Pasos # | B21: Detalle de pasos | D21: Resultado esperado
A22: 1 | B22: Presionar A. | D22: Pacman se desplaza hacia la izquierda, igual que con ←.
A23: 2 | B23: Presionar W. | D23: Pacman se desplaza hacia arriba, igual que con ↑.
A24: 3 | B24: Presionar D. | D24: Pacman se desplaza hacia la derecha, igual que con →.
A25: 4 | B25: Presionar S. | D25: Cada tecla produce el mismo desplazamiento que ←, ↑, → y ↓ respectivamente.
A26: El caso se aprueba solo si se cumple todo el resultado esperado del último paso (en negrita); si cualquier parte no se cumple, se registra como Fallido.

Sheet CP-003
A1: Test Case ID | B1: CP-003 | C1: Descripción / Funcionalidad | D1: HU-01 · Mover a Pacman por el mapa | G1: Registro de ejecución
A2: Creado por | B2: Cruz, Luzzi | C2: Versión | D2: 1 | G2: Ciclo | H2: Fecha | I2: Ejecutor | J2: Estado | K2: Resultado obtenido | L2: Defecto
A3: Reporte de ejecución 1 | C3: Estado en la Entrega 1 | D3: =IF(INDEX('Reporte de ejecución - Entrega1'!$G$4:$G$69,MATCH($B$1,'Reporte de ejecución - Entrega1'!$A$4:$A$69,0))="","Sin ejecutar",INDEX('Reporte de ejecución - Entrega1'!$G$4:$G$69,MATCH($B$1,'Reporte de ejecución - Entrega1'!$A$4:$A$69,0))) -> Sin ejecutar | G3: Ciclo 1
G4: Ciclo 2
A5: Prioridad (Alta, Media, Baja) | B5: Alta | C5: Técnica de diseño | D5: Adivinación de errores | G5: Ciclo 3
G6: Estado del ciclo 1: cargarlo en la hoja del reporte; la celda «Estado en la Entrega 1» lo toma de ahí. Este registro es para el resultado obtenido y los reintentos.
A7: # | B7: Pre-requisitos | D7: Datos de prueba
A8: 1 | B8: Abrir la aplicación desplegada en un navegador de escritorio. | D8: Entorno: | E8: Aplicación desplegada en Vercel (URL en el Anexo C)
A9: 2 | B9: Iniciar una partida en modo Pacman. | D9: Navegador: | E9: Google Chrome de escritorio
A10: 3 | B10: Partida en curso (N1), Pacman en un corredor libre. | D10: Modo de juego: | E10: Pacman
D11: Nivel inicial: | E11: 1
D12: Vidas iniciales: | E12: 3
D13: PowerUp: | E13: Inactivo
A15: Título del CP | B15: Avance continuo sin mantener la tecla
A18: Historias de Usuario | B18: HU-01 | C18: Épica | D18: E1 — Núcleo de juego y movimiento
A19: Estado Automatización | B19: No automatizado | C19: Camino feliz | D19: Sí
A21: Pasos # | B21: Detalle de pasos | D21: Resultado esperado
A22: 1 | B22: Presionar y liberar de inmediato la tecla de una dirección libre. | D22: Pacman comienza a avanzar en la dirección indicada.
A23: 2 | B23: Observar durante 3 segundos sin tocar el teclado. | D23: Pacman sigue avanzando en esa dirección durante los 3 segundos, hasta encontrar un muro.
A24: El caso se aprueba solo si se cumple todo el resultado esperado del último paso (en negrita); si cualquier parte no se cumple, se registra como Fallido.

Sheet CP-004
A1: Test Case ID | B1: CP-004 | C1: Descripción / Funcionalidad | D1: HU-01 · Mover a Pacman por el mapa | G1: Registro de ejecución
A2: Creado por | B2: Cruz, Luzzi | C2: Versión | D2: 1 | G2: Ciclo | H2: Fecha | I2: Ejecutor | J2: Estado | K2: Resultado obtenido | L2: Defecto
A3: Reporte de ejecución 1 | C3: Estado en la Entrega 1 | D3: =IF(INDEX('Reporte de ejecución - Entrega1'!$G$4:$G$69,MATCH($B$1,'Reporte de ejecución - Entrega1'!$A$4:$A$69,0))="","Sin ejecutar",INDEX('Reporte de ejecución - Entrega1'!$G$4:$G$69,MATCH($B$1,'Reporte de ejecución - Entrega1'!$A$4:$A$69,0))) -> Sin ejecutar | G3: Ciclo 1
G4: Ciclo 2
A5: Prioridad (Alta, Media, Baja) | B5: Media | C5: Técnica de diseño | D5: Transición de estados | G5: Ciclo 3
G6: Estado del ciclo 1: cargarlo en la hoja del reporte; la celda «Estado en la Entrega 1» lo toma de ahí. Este registro es para el resultado obtenido y los reintentos.
A7: # | B7: Pre-requisitos | D7: Datos de prueba
A8: 1 | B8: Abrir la aplicación desplegada en un navegador de escritorio. | D8: Entorno: | E8: Aplicación desplegada en Vercel (URL en el Anexo C)
A9: 2 | B9: Iniciar una partida en modo Pacman. | D9: Navegador: | E9: Google Chrome de escritorio
A10: 3 | B10: Partida en curso (N1), Pacman avanzando por un corredor horizontal con una intersección hacia arriba a 3 celdas de distancia. | D10: Modo de juego: | E10: Pacman
D11: Nivel inicial: | E11: 1
D12: Vidas iniciales: | E12: 3
D13: PowerUp: | E13: Inactivo
A15: Título del CP | B15: Giro postergado hasta la primera celda posible
A18: Historias de Usuario | B18: HU-01 | C18: Épica | D18: E1 — Núcleo de juego y movimiento
A19: Estado Automatización | B19: No automatizado | C19: Camino feliz | D19: No
A21: Pasos # | B21: Detalle de pasos | D21: Resultado esperado
A22: 1 | B22: Con Pacman en movimiento horizontal, presionar ↑ antes de llegar a la intersección. | D22: Pacman continúa avanzando en horizontal y gira hacia arriba al llegar a la intersección, sin detenerse en el trayecto.
A23: El caso se aprueba solo si se cumple todo el resultado esperado del último paso (en negrita); si cualquier parte no se cumple, se registra como Fallido.

Sheet CP-005
A1: Test Case ID | B1: CP-005 | C1: Descripción / Funcionalidad | D1: HU-01 · Mover a Pacman por el mapa | G1: Registro de ejecución
A2: Creado por | B2: Cruz, Luzzi | C2: Versión | D2: 1 | G2: Ciclo | H2: Fecha | I2: Ejecutor | J2: Estado | K2: Resultado obtenido | L2: Defecto
A3: Reporte de ejecución 1 | C3: Estado en la Entrega 1 | D3: =IF(INDEX('Reporte de ejecución - Entrega1'!$G$4:$G$69,MATCH($B$1,'Reporte de ejecución - Entrega1'!$A$4:$A$69,0))="","Sin ejecutar",INDEX('Reporte de ejecución - Entrega1'!$G$4:$G$69,MATCH($B$1,'Reporte de ejecución - Entrega1'!$A$4:$A$69,0))) -> Sin ejecutar | G3: Ciclo 1
G4: Ciclo 2
A5: Prioridad (Alta, Media, Baja) | B5: Alta | C5: Técnica de diseño | D5: Valores límite | G5: Ciclo 3
G6: Estado del ciclo 1: cargarlo en la hoja del reporte; la celda «Estado en la Entrega 1» lo toma de ahí. Este registro es para el resultado obtenido y los reintentos.
A7: # | B7: Pre-requisitos | D7: Datos de prueba
A8: 1 | B8: Abrir la aplicación desplegada en un navegador de escritorio. | D8: Entorno: | E8: Aplicación desplegada en Vercel (URL en el Anexo C)
A9: 2 | B9: Iniciar una partida en modo Pacman. | D9: Navegador: | E9: Google Chrome de escritorio
A10: 3 | B10: Partida en curso (N1), Pacman avanzando por un corredor horizontal con muros arriba y abajo. | D10: Modo de juego: | E10: Pacman
D11: Nivel inicial: | E11: 1
D12: Vidas iniciales: | E12: 3
D13: PowerUp: | E13: Inactivo
A15: Título del CP | B15: Dirección bloqueada por un muro
A18: Historias de Usuario | B18: HU-01 | C18: Épica | D18: E1 — Núcleo de juego y movimiento
A19: Estado Automatización | B19: No automatizado | C19: Camino feliz | D19: No
A21: Pasos # | B21: Detalle de pasos | D21: Resultado esperado
A22: 1 | B22: Presionar ↑ con el muro inmediatamente arriba. | D22: Pacman mantiene su dirección horizontal de avance. No se detiene ni queda trabado.
A23: El caso se aprueba solo si se cumple todo el resultado esperado del último paso (en negrita); si cualquier parte no se cumple, se registra como Fallido.

Sheet CP-006
A1: Test Case ID | B1: CP-006 | C1: Descripción / Funcionalidad | D1: HU-01 · Mover a Pacman por el mapa | G1: Registro de ejecución
A2: Creado por | B2: Cruz, Luzzi | C2: Versión | D2: 1 | G2: Ciclo | H2: Fecha | I2: Ejecutor | J2: Estado | K2: Resultado obtenido | L2: Defecto
A3: Reporte de ejecución 1 | C3: Estado en la Entrega 1 | D3: =IF(INDEX('Reporte de ejecución - Entrega1'!$G$4:$G$69,MATCH($B$1,'Reporte de ejecución - Entrega1'!$A$4:$A$69,0))="","Sin ejecutar",INDEX('Reporte de ejecución - Entrega1'!$G$4:$G$69,MATCH($B$1,'Reporte de ejecución - Entrega1'!$A$4:$A$69,0))) -> Sin ejecutar | G3: Ciclo 1
G4: Ciclo 2
A5: Prioridad (Alta, Media, Baja) | B5: Media | C5: Técnica de diseño | D5: Partición de equivalencia | G5: Ciclo 3
G6: Estado del ciclo 1: cargarlo en la hoja del reporte; la celda «Estado en la Entrega 1» lo toma de ahí. Este registro es para el resultado obtenido y los reintentos.
A7: # | B7: Pre-requisitos | D7: Datos de prueba
A8: 1 | B8: Abrir la aplicación desplegada en un navegador de escritorio. | D8: Entorno: | E8: Aplicación desplegada en Vercel (URL en el Anexo C)
A9: 2 | B9: Iniciar una partida en modo Pacman. | D9: Navegador: | E9: Google Chrome de escritorio
A10: 3 | B10: Partida en curso (N1), Pacman avanzando hacia la derecha en un corredor. | D10: Modo de juego: | E10: Pacman
D11: Nivel inicial: | E11: 1
D12: Vidas iniciales: | E12: 3
D13: PowerUp: | E13: Inactivo
A15: Título del CP | B15: Inversión de marcha a mitad de corredor
A18: Historias de Usuario | B18: HU-01 | C18: Épica | D18: E1 — Núcleo de juego y movimiento
A19: Estado Automatización | B19: No automatizado | C19: Camino feliz | D19: No
A21: Pasos # | B21: Detalle de pasos | D21: Resultado esperado
A22: 1 | B22: Presionar ← a mitad del corredor. | D22: Pacman invierte su marcha de inmediato, sin necesidad de llegar a una intersección.
A23: El caso se aprueba solo si se cumple todo el resultado esperado del último paso (en negrita); si cualquier parte no se cumple, se registra como Fallido.

Sheet CP-007
A1: Test Case ID | B1: CP-007 | C1: Descripción / Funcionalidad | D1: HU-02 · Impedir el paso a través de los muros | G1: Registro de ejecución
A2: Creado por | B2: Cruz, Luzzi | C2: Versión | D2: 1 | G2: Ciclo | H2: Fecha | I2: Ejecutor | J2: Estado | K2: Resultado obtenido | L2: Defecto
A3: Reporte de ejecución 1 | C3: Estado en la Entrega 1 | D3: =IF(INDEX('Reporte de ejecución - Entrega1'!$G$4:$G$69,MATCH($B$1,'Reporte de ejecución - Entrega1'!$A$4:$A$69,0))="","Sin ejecutar",INDEX('Reporte de ejecución - Entrega1'!$G$4:$G$69,MATCH($B$1,'Reporte de ejecución - Entrega1'!$A$4:$A$69,0))) -> Sin ejecutar | G3: Ciclo 1
G4: Ciclo 2
A5: Prioridad (Alta, Media, Baja) | B5: Alta | C5: Técnica de diseño | D5: Valores límite | G5: Ciclo 3
G6: Estado del ciclo 1: cargarlo en la hoja del reporte; la celda «Estado en la Entrega 1» lo toma de ahí. Este registro es para el resultado obtenido y los reintentos.
A7: # | B7: Pre-requisitos | D7: Datos de prueba
A8: 1 | B8: Abrir la aplicación desplegada en un navegador de escritorio. | D8: Entorno: | E8: Aplicación desplegada en Vercel (URL en el Anexo C)
A9: 2 | B9: Iniciar una partida en modo Pacman. | D9: Navegador: | E9: Google Chrome de escritorio
A10: 3 | B10: Partida en curso (N1). | D10: Modo de juego: | E10: Pacman
D11: Nivel inicial: | E11: 1
D12: Vidas iniciales: | E12: 3
D13: PowerUp: | E13: Inactivo
A15: Título del CP | B15: Pacman no atraviesa los muros
A18: Historias de Usuario | B18: HU-02 | C18: Épica | D18: E1 — Núcleo de juego y movimiento
A19: Estado Automatización | B19: No automatizado | C19: Camino feliz | D19: No
A21: Pasos # | B21: Detalle de pasos | D21: Resultado esperado
A22: 1 | B22: Dirigir a Pacman contra un muro. | D22: Pacman avanza hasta quedar junto al muro.
A23: 2 | B23: Mantener presionada la tecla de esa dirección durante 5 segundos. | D23: Pacman se detiene contra el muro, no lo atraviesa, no queda superpuesto al muro y no queda encajado: al indicar otra dirección válida se mueve con normalidad.
A24: El caso se aprueba solo si se cumple todo el resultado esperado del último paso (en negrita); si cualquier parte no se cumple, se registra como Fallido.

Sheet CP-008
A1: Test Case ID | B1: CP-008 | C1: Descripción / Funcionalidad | D1: HU-02 · Impedir el paso a través de los muros | G1: Registro de ejecución
A2: Creado por | B2: Cruz, Luzzi | C2: Versión | D2: 1 | G2: Ciclo | H2: Fecha | I2: Ejecutor | J2: Estado | K2: Resultado obtenido | L2: Defecto
A3: Reporte de ejecución 1 | C3: Estado en la Entrega 1 | D3: =IF(INDEX('Reporte de ejecución - Entrega1'!$G$4:$G$69,MATCH($B$1,'Reporte de ejecución - Entrega1'!$A$4:$A$69,0))="","Sin ejecutar",INDEX('Reporte de ejecución - Entrega1'!$G$4:$G$69,MATCH($B$1,'Reporte de ejecución - Entrega1'!$A$4:$A$69,0))) -> Sin ejecutar | G3: Ciclo 1
G4: Ciclo 2
A5: Prioridad (Alta, Media, Baja) | B5: Alta | C5: Técnica de diseño | D5: Valores límite | G5: Ciclo 3
G6: Estado del ciclo 1: cargarlo en la hoja del reporte; la celda «Estado en la Entrega 1» lo toma de ahí. Este registro es para el resultado obtenido y los reintentos.
A7: # | B7: Pre-requisitos | D7: Datos de prueba
A8: 1 | B8: Abrir la aplicación desplegada en un navegador de escritorio. | D8: Entorno: | E8: Aplicación desplegada en Vercel (URL en el Anexo C)
A9: 2 | B9: Iniciar una partida en modo Pacman. | D9: Navegador: | E9: Google Chrome de escritorio
A10: 3 | B10: Partida en curso (N1). | D10: Modo de juego: | E10: Pacman
D11: Nivel inicial: | E11: 1
D12: Vidas iniciales: | E12: 3
D13: PowerUp: | E13: Inactivo
A15: Título del CP | B15: Pacman no sale de los límites del mapa
A18: Historias de Usuario | B18: HU-02 | C18: Épica | D18: E1 — Núcleo de juego y movimiento
A19: Estado Automatización | B19: No automatizado | C19: Camino feliz | D19: No
A21: Pasos # | B21: Detalle de pasos | D21: Resultado esperado
A22: 1 | B22: Llevar a Pacman al borde del mapa por cada uno de los cuatro lados. | D22: Pacman llega al borde del mapa en cada lado.
A23: 2 | B23: Presionar la tecla que apunta hacia afuera del mapa. | D23: Pacman no sale del mapa por ninguno de los cuatro lados y permanece visible en pantalla.
A24: El caso se aprueba solo si se cumple todo el resultado esperado del último paso (en negrita); si cualquier parte no se cumple, se registra como Fallido.

Sheet CP-009
A1: Test Case ID | B1: CP-009 | C1: Descripción / Funcionalidad | D1: HU-02 · Impedir el paso a través de los muros | G1: Registro de ejecución
A2: Creado por | B2: Cruz, Luzzi | C2: Versión | D2: 1 | G2: Ciclo | H2: Fecha | I2: Ejecutor | J2: Estado | K2: Resultado obtenido | L2: Defecto
A3: Reporte de ejecución 1 | C3: Estado en la Entrega 1 | D3: =IF(INDEX('Reporte de ejecución - Entrega1'!$G$4:$G$69,MATCH($B$1,'Reporte de ejecución - Entrega1'!$A$4:$A$69,0))="","Sin ejecutar",INDEX('Reporte de ejecución - Entrega1'!$G$4:$G$69,MATCH($B$1,'Reporte de ejecución - Entrega1'!$A$4:$A$69,0))) -> Sin ejecutar | G3: Ciclo 1
G4: Ciclo 2
A5: Prioridad (Alta, Media, Baja) | B5: Alta | C5: Técnica de diseño | D5: Adivinación de errores | G5: Ciclo 3
G6: Estado del ciclo 1: cargarlo en la hoja del reporte; la celda «Estado en la Entrega 1» lo toma de ahí. Este registro es para el resultado obtenido y los reintentos.
A7: # | B7: Pre-requisitos | D7: Datos de prueba
A8: 1 | B8: Abrir la aplicación desplegada en un navegador de escritorio. | D8: Entorno: | E8: Aplicación desplegada en Vercel (URL en el Anexo C)
A9: 2 | B9: Iniciar una partida en modo Pacman. | D9: Navegador: | E9: Google Chrome de escritorio
A10: 3 | B10: Partida en curso (N1). | D10: Modo de juego: | E10: Pacman
D11: Nivel inicial: | E11: 1
D12: Vidas iniciales: | E12: 3
D13: PowerUp: | E13: Inactivo
A15: Título del CP | B15: Los fantasmas clásicos no atraviesan muros
A18: Historias de Usuario | B18: HU-02 | C18: Épica | D18: E1 — Núcleo de juego y movimiento
A19: Estado Automatización | B19: No automatizado | C19: Camino feliz | D19: No
A21: Pasos # | B21: Detalle de pasos | D21: Resultado esperado
A22: 1 | B22: Observar el desplazamiento de los cuatro fantasmas durante 60 segundos. | D22: Ningún fantasma atraviesa un muro ni sale de los límites del mapa en ningún momento.
A23: El caso se aprueba solo si se cumple todo el resultado esperado del último paso (en negrita); si cualquier parte no se cumple, se registra como Fallido.

Sheet CP-010
A1: Test Case ID | B1: CP-010 | C1: Descripción / Funcionalidad | D1: HU-02 · Impedir el paso a través de los muros | G1: Registro de ejecución
A2: Creado por | B2: Cruz, Luzzi | C2: Versión | D2: 1 | G2: Ciclo | H2: Fecha | I2: Ejecutor | J2: Estado | K2: Resultado obtenido | L2: Defecto
A3: Reporte de ejecución 1 | C3: Estado en la Entrega 1 | D3: =IF(INDEX('Reporte de ejecución - Entrega1'!$G$4:$G$69,MATCH($B$1,'Reporte de ejecución - Entrega1'!$A$4:$A$69,0))="","Sin ejecutar",INDEX('Reporte de ejecución - Entrega1'!$G$4:$G$69,MATCH($B$1,'Reporte de ejecución - Entrega1'!$A$4:$A$69,0))) -> Sin ejecutar | G3: Ciclo 1
G4: Ciclo 2
A5: Prioridad (Alta, Media, Baja) | B5: Media | C5: Técnica de diseño | D5: Adivinación de errores | G5: Ciclo 3
G6: Estado del ciclo 1: cargarlo en la hoja del reporte; la celda «Estado en la Entrega 1» lo toma de ahí. Este registro es para el resultado obtenido y los reintentos.
A7: # | B7: Pre-requisitos | D7: Datos de prueba
A8: 1 | B8: Abrir la aplicación desplegada en un navegador de escritorio. | D8: Entorno: | E8: Aplicación desplegada en Vercel (URL en el Anexo C)
A9: 2 | B9: Iniciar una partida en modo Pacman. | D9: Navegador: | E9: Google Chrome de escritorio
A10: 3 | B10: Partida en curso (N1). | D10: Modo de juego: | E10: Pacman
D11: Nivel inicial: | E11: 1
D12: Vidas iniciales: | E12: 3
D13: PowerUp: | E13: Inactivo
A15: Título del CP | B15: Zona transitable coincidente con el mapa dibujado
A18: Historias de Usuario | B18: HU-02 | C18: Épica | D18: E1 — Núcleo de juego y movimiento
A19: Estado Automatización | B19: No automatizado | C19: Camino feliz | D19: No
A21: Pasos # | B21: Detalle de pasos | D21: Resultado esperado
A22: 1 | B22: Recorrer con Pacman los caminos marcados con puntos blancos. | D22: Todos los caminos marcados son transitables, y no existe ninguna celda transitable que no esté marcada como camino.
A23: El caso se aprueba solo si se cumple todo el resultado esperado del último paso (en negrita); si cualquier parte no se cumple, se registra como Fallido.

Sheet CP-011
A1: Test Case ID | B1: CP-011 | C1: Descripción / Funcionalidad | D1: HU-03 · Consumir las esferas del mapa | G1: Registro de ejecución
A2: Creado por | B2: Cruz, Luzzi | C2: Versión | D2: 1 | G2: Ciclo | H2: Fecha | I2: Ejecutor | J2: Estado | K2: Resultado obtenido | L2: Defecto
A3: Reporte de ejecución 1 | C3: Estado en la Entrega 1 | D3: =IF(INDEX('Reporte de ejecución - Entrega1'!$G$4:$G$69,MATCH($B$1,'Reporte de ejecución - Entrega1'!$A$4:$A$69,0))="","Sin ejecutar",INDEX('Reporte de ejecución - Entrega1'!$G$4:$G$69,MATCH($B$1,'Reporte de ejecución - Entrega1'!$A$4:$A$69,0))) -> Sin ejecutar | G3: Ciclo 1
G4: Ciclo 2
A5: Prioridad (Alta, Media, Baja) | B5: Alta | C5: Técnica de diseño | D5: Partición de equivalencia | G5: Ciclo 3
G6: Estado del ciclo 1: cargarlo en la hoja del reporte; la celda «Estado en la Entrega 1» lo toma de ahí. Este registro es para el resultado obtenido y los reintentos.
A7: # | B7: Pre-requisitos | D7: Datos de prueba
A8: 1 | B8: Abrir la aplicación desplegada en un navegador de escritorio. | D8: Entorno: | E8: Aplicación desplegada en Vercel (URL en el Anexo C)
A9: 2 | B9: Iniciar una partida en modo Pacman. | D9: Navegador: | E9: Google Chrome de escritorio
A10: 3 | B10: Partida en curso (N1), puntaje 0. | D10: Modo de juego: | E10: Pacman
D11: Nivel inicial: | E11: 1
D12: Vidas iniciales: | E12: 3
D13: PowerUp: | E13: Inactivo
A15: Título del CP | B15: Consumo de una esfera común
A18: Historias de Usuario | B18: HU-03 | C18: Épica | D18: E1 — Núcleo de juego y movimiento
A19: Estado Automatización | B19: No automatizado | C19: Camino feliz | D19: Sí
A21: Pasos # | B21: Detalle de pasos | D21: Resultado esperado
A22: 1 | B22: Registrar el puntaje y el contador de esferas restantes. | D22: Puntaje y contador de esferas anotados como valores de referencia.
A23: 2 | B23: Desplazar a Pacman sobre una esfera común. | D23: Pacman pasa por la celda de la esfera.
A24: 3 | B24: Registrar ambos valores. | D24: La esfera desaparece del mapa, el puntaje aumenta exactamente 10 y el contador de esferas restantes disminuye exactamente 1.
A25: El caso se aprueba solo si se cumple todo el resultado esperado del último paso (en negrita); si cualquier parte no se cumple, se registra como Fallido.

Sheet CP-012
A1: Test Case ID | B1: CP-012 | C1: Descripción / Funcionalidad | D1: HU-03 · Consumir las esferas del mapa | G1: Registro de ejecución
A2: Creado por | B2: Cruz, Luzzi | C2: Versión | D2: 1 | G2: Ciclo | H2: Fecha | I2: Ejecutor | J2: Estado | K2: Resultado obtenido | L2: Defecto
A3: Reporte de ejecución 1 | C3: Estado en la Entrega 1 | D3: =IF(INDEX('Reporte de ejecución - Entrega1'!$G$4:$G$69,MATCH($B$1,'Reporte de ejecución - Entrega1'!$A$4:$A$69,0))="","Sin ejecutar",INDEX('Reporte de ejecución - Entrega1'!$G$4:$G$69,MATCH($B$1,'Reporte de ejecución - Entrega1'!$A$4:$A$69,0))) -> Sin ejecutar | G3: Ciclo 1
G4: Ciclo 2
A5: Prioridad (Alta, Media, Baja) | B5: Alta | C5: Técnica de diseño | D5: Adivinación de errores | G5: Ciclo 3
G6: Estado del ciclo 1: cargarlo en la hoja del reporte; la celda «Estado en la Entrega 1» lo toma de ahí. Este registro es para el resultado obtenido y los reintentos.
A7: # | B7: Pre-requisitos | D7: Datos de prueba
A8: 1 | B8: Abrir la aplicación desplegada en un navegador de escritorio. | D8: Entorno: | E8: Aplicación desplegada en Vercel (URL en el Anexo C)
A9: 2 | B9: Iniciar una partida en modo Pacman. | D9: Navegador: | E9: Google Chrome de escritorio
A10: 3 | B10: Partida en curso (N1). | D10: Modo de juego: | E10: Pacman
D11: Nivel inicial: | E11: 1
D12: Vidas iniciales: | E12: 3
D13: PowerUp: | E13: Inactivo
A15: Título del CP | B15: Una esfera consumida no reaparece al perder una vida
A18: Historias de Usuario | B18: HU-03 | C18: Épica | D18: E1 — Núcleo de juego y movimiento
A19: Estado Automatización | B19: No automatizado | C19: Camino feliz | D19: No
A21: Pasos # | B21: Detalle de pasos | D21: Resultado esperado
A22: 1 | B22: Consumir al menos 10 esferas y registrar la zona despejada. | D22: Contador disminuido en 10 y zona sin esferas identificada.
A23: 2 | B23: Dejar que un fantasma alcance a Pacman. | D23: Se descuenta una vida y los personajes vuelven a su posición inicial.
A24: 3 | B24: Observar la zona despejada al reanudarse el nivel. | D24: Las esferas consumidas antes de perder la vida siguen ausentes del mapa.
A25: El caso se aprueba solo si se cumple todo el resultado esperado del último paso (en negrita); si cualquier parte no se cumple, se registra como Fallido.

Sheet CP-013
A1: Test Case ID | B1: CP-013 | C1: Descripción / Funcionalidad | D1: HU-03 · Consumir las esferas del mapa | G1: Registro de ejecución
A2: Creado por | B2: Cruz, Luzzi | C2: Versión | D2: 1 | G2: Ciclo | H2: Fecha | I2: Ejecutor | J2: Estado | K2: Resultado obtenido | L2: Defecto
A3: Reporte de ejecución 1 | C3: Estado en la Entrega 1 | D3: =IF(INDEX('Reporte de ejecución - Entrega1'!$G$4:$G$69,MATCH($B$1,'Reporte de ejecución - Entrega1'!$A$4:$A$69,0))="","Sin ejecutar",INDEX('Reporte de ejecución - Entrega1'!$G$4:$G$69,MATCH($B$1,'Reporte de ejecución - Entrega1'!$A$4:$A$69,0))) -> Sin ejecutar | G3: Ciclo 1
G4: Ciclo 2
A5: Prioridad (Alta, Media, Baja) | B5: Media | C5: Técnica de diseño | D5: Adivinación de errores | G5: Ciclo 3
G6: Estado del ciclo 1: cargarlo en la hoja del reporte; la celda «Estado en la Entrega 1» lo toma de ahí. Este registro es para el resultado obtenido y los reintentos.
A7: # | B7: Pre-requisitos | D7: Datos de prueba
A8: 1 | B8: Abrir la aplicación desplegada en un navegador de escritorio. | D8: Entorno: | E8: Aplicación desplegada en Vercel (URL en el Anexo C)
A9: 2 | B9: Iniciar una partida en modo Pacman. | D9: Navegador: | E9: Google Chrome de escritorio
A10: 3 | B10: Partida en curso (N1). | D10: Modo de juego: | E10: Pacman
D11: Nivel inicial: | E11: 1
D12: Vidas iniciales: | E12: 3
D13: PowerUp: | E13: Inactivo
A15: Título del CP | B15: Los fantasmas no consumen esferas
A18: Historias de Usuario | B18: HU-03 | C18: Épica | D18: E1 — Núcleo de juego y movimiento
A19: Estado Automatización | B19: No automatizado | C19: Camino feliz | D19: No
A21: Pasos # | B21: Detalle de pasos | D21: Resultado esperado
A22: 1 | B22: Registrar el contador de esferas restantes. | D22: Valor del contador anotado como referencia.
A23: 2 | B23: Observar durante 30 segundos sin mover a Pacman, mientras los fantasmas recorren el mapa sobre celdas con esferas. | D23: El contador de esferas restantes no cambia y las esferas por las que pasaron los fantasmas siguen en el mapa.
A24: El caso se aprueba solo si se cumple todo el resultado esperado del último paso (en negrita); si cualquier parte no se cumple, se registra como Fallido.

Sheet CP-014
A1: Test Case ID | B1: CP-014 | C1: Descripción / Funcionalidad | D1: HU-04 · Completar el nivel al consumir todas las esferas | G1: Registro de ejecución
A2: Creado por | B2: Cruz, Luzzi | C2: Versión | D2: 1 | G2: Ciclo | H2: Fecha | I2: Ejecutor | J2: Estado | K2: Resultado obtenido | L2: Defecto
A3: Reporte de ejecución 1 | C3: Estado en la Entrega 1 | D3: =IF(INDEX('Reporte de ejecución - Entrega1'!$G$4:$G$69,MATCH($B$1,'Reporte de ejecución - Entrega1'!$A$4:$A$69,0))="","Sin ejecutar",INDEX('Reporte de ejecución - Entrega1'!$G$4:$G$69,MATCH($B$1,'Reporte de ejecución - Entrega1'!$A$4:$A$69,0))) -> Sin ejecutar | G3: Ciclo 1
G4: Ciclo 2
A5: Prioridad (Alta, Media, Baja) | B5: Alta | C5: Técnica de diseño | D5: Valores límite | G5: Ciclo 3
G6: Estado del ciclo 1: cargarlo en la hoja del reporte; la celda «Estado en la Entrega 1» lo toma de ahí. Este registro es para el resultado obtenido y los reintentos.
A7: # | B7: Pre-requisitos | D7: Datos de prueba
A8: 1 | B8: Abrir la aplicación desplegada en un navegador de escritorio. | D8: Entorno: | E8: Aplicación desplegada en Vercel (URL en el Anexo C)
A9: 2 | B9: Iniciar una partida en modo Pacman. | D9: Navegador: | E9: Google Chrome de escritorio
A10: 3 | B10: Partida en curso (N1) con una sola esfera restante en el mapa. | D10: Modo de juego: | E10: Pacman
D11: Nivel inicial: | E11: 1
D12: Vidas iniciales: | E12: 3
D13: PowerUp: | E13: Inactivo
A15: Título del CP | B15: Finalización del nivel al consumir la última esfera
A18: Historias de Usuario | B18: HU-04 | C18: Épica | D18: E1 — Núcleo de juego y movimiento
A19: Estado Automatización | B19: No automatizado | C19: Camino feliz | D19: Sí
A21: Pasos # | B21: Detalle de pasos | D21: Resultado esperado
A22: 1 | B22: Consumir la última esfera. | D22: El nivel se completa, la partida se detiene y se muestra el resultado del nivel con su puntaje.
A23: El caso se aprueba solo si se cumple todo el resultado esperado del último paso (en negrita); si cualquier parte no se cumple, se registra como Fallido.

Sheet CP-015
A1: Test Case ID | B1: CP-015 | C1: Descripción / Funcionalidad | D1: HU-04 · Completar el nivel al consumir todas las esferas | G1: Registro de ejecución
A2: Creado por | B2: Cruz, Luzzi | C2: Versión | D2: 1 | G2: Ciclo | H2: Fecha | I2: Ejecutor | J2: Estado | K2: Resultado obtenido | L2: Defecto
A3: Reporte de ejecución 1 | C3: Estado en la Entrega 1 | D3: =IF(INDEX('Reporte de ejecución - Entrega1'!$G$4:$G$69,MATCH($B$1,'Reporte de ejecución - Entrega1'!$A$4:$A$69,0))="","Sin ejecutar",INDEX('Reporte de ejecución - Entrega1'!$G$4:$G$69,MATCH($B$1,'Reporte de ejecución - Entrega1'!$A$4:$A$69,0))) -> Sin ejecutar | G3: Ciclo 1
G4: Ciclo 2
A5: Prioridad (Alta, Media, Baja) | B5: Alta | C5: Técnica de diseño | D5: Valores límite | G5: Ciclo 3
G6: Estado del ciclo 1: cargarlo en la hoja del reporte; la celda «Estado en la Entrega 1» lo toma de ahí. Este registro es para el resultado obtenido y los reintentos.
A7: # | B7: Pre-requisitos | D7: Datos de prueba
A8: 1 | B8: Abrir la aplicación desplegada en un navegador de escritorio. | D8: Entorno: | E8: Aplicación desplegada en Vercel (URL en el Anexo C)
A9: 2 | B9: Iniciar una partida en modo Pacman. | D9: Navegador: | E9: Google Chrome de escritorio
A10: 3 | B10: Partida en curso (N1) con todas las esferas comunes consumidas y una esfera grande sin consumir. | D10: Modo de juego: | E10: Pacman
D11: Nivel inicial: | E11: 1
D12: Vidas iniciales: | E12: 3
D13: PowerUp: | E13: Inactivo
A15: Título del CP | B15: El nivel no se completa si queda una esfera grande
A18: Historias de Usuario | B18: HU-04 | C18: Épica | D18: E1 — Núcleo de juego y movimiento
A19: Estado Automatización | B19: No automatizado | C19: Camino feliz | D19: No
A21: Pasos # | B21: Detalle de pasos | D21: Resultado esperado
A22: 1 | B22: Observar el estado de la partida. | D22: La partida sigue en curso: el nivel no se da por completado.
A23: 2 | B23: Verificar el contador de esferas restantes. | D23: El nivel no se completa y el contador indica 1 esfera restante. La partida continúa.
A24: El caso se aprueba solo si se cumple todo el resultado esperado del último paso (en negrita); si cualquier parte no se cumple, se registra como Fallido.

Sheet CP-016
A1: Test Case ID | B1: CP-016 | C1: Descripción / Funcionalidad | D1: HU-04 · Completar el nivel al consumir todas las esferas | G1: Registro de ejecución
A2: Creado por | B2: Cruz, Luzzi | C2: Versión | D2: 1 | G2: Ciclo | H2: Fecha | I2: Ejecutor | J2: Estado | K2: Resultado obtenido | L2: Defecto
A3: Reporte de ejecución 1 | C3: Estado en la Entrega 1 | D3: =IF(INDEX('Reporte de ejecución - Entrega1'!$G$4:$G$69,MATCH($B$1,'Reporte de ejecución - Entrega1'!$A$4:$A$69,0))="","Sin ejecutar",INDEX('Reporte de ejecución - Entrega1'!$G$4:$G$69,MATCH($B$1,'Reporte de ejecución - Entrega1'!$A$4:$A$69,0))) -> Sin ejecutar | G3: Ciclo 1
G4: Ciclo 2
A5: Prioridad (Alta, Media, Baja) | B5: Alta | C5: Técnica de diseño | D5: Transición de estados | G5: Ciclo 3
G6: Estado del ciclo 1: cargarlo en la hoja del reporte; la celda «Estado en la Entrega 1» lo toma de ahí. Este registro es para el resultado obtenido y los reintentos.
A7: # | B7: Pre-requisitos | D7: Datos de prueba
A8: 1 | B8: Abrir la aplicación desplegada en un navegador de escritorio. | D8: Entorno: | E8: Aplicación desplegada en Vercel (URL en el Anexo C)
A9: 2 | B9: Iniciar una partida en modo Pacman. | D9: Navegador: | E9: Google Chrome de escritorio
A10: 3 | B10: Partida en curso (N1) próxima a completarse, con 2 vidas restantes y puntaje registrado. | D10: Modo de juego: | E10: Pacman
D11: Nivel inicial: | E11: 1
D12: Vidas iniciales: | E12: 3
D13: PowerUp: | E13: Inactivo
A15: Título del CP | B15: Paso al nivel siguiente conservando puntaje y vidas
A18: Historias de Usuario | B18: HU-04 | C18: Épica | D18: E1 — Núcleo de juego y movimiento
A19: Estado Automatización | B19: No automatizado | C19: Camino feliz | D19: Sí
A21: Pasos # | B21: Detalle de pasos | D21: Resultado esperado
A22: 1 | B22: Registrar puntaje y vidas. | D22: Puntaje y vidas anotados como valores de referencia.
A23: 2 | B23: Completar el nivel 1. | D23: Se muestra el resultado del nivel 1 con su puntaje.
A24: 3 | B24: Registrar puntaje, vidas y número de nivel. | D24: Se inicia el nivel 2, el puntaje acumulado se conserva y el contador de vidas sigue en 2.
A25: El caso se aprueba solo si se cumple todo el resultado esperado del último paso (en negrita); si cualquier parte no se cumple, se registra como Fallido.

Sheet CP-017
A1: Test Case ID | B1: CP-017 | C1: Descripción / Funcionalidad | D1: HU-04 · Completar el nivel al consumir todas las esferas | G1: Registro de ejecución
A2: Creado por | B2: Cruz, Luzzi | C2: Versión | D2: 1 | G2: Ciclo | H2: Fecha | I2: Ejecutor | J2: Estado | K2: Resultado obtenido | L2: Defecto
A3: Reporte de ejecución 1 | C3: Estado en la Entrega 1 | D3: =IF(INDEX('Reporte de ejecución - Entrega1'!$G$4:$G$69,MATCH($B$1,'Reporte de ejecución - Entrega1'!$A$4:$A$69,0))="","Sin ejecutar",INDEX('Reporte de ejecución - Entrega1'!$G$4:$G$69,MATCH($B$1,'Reporte de ejecución - Entrega1'!$A$4:$A$69,0))) -> Sin ejecutar | G3: Ciclo 1
G4: Ciclo 2
A5: Prioridad (Alta, Media, Baja) | B5: Alta | C5: Técnica de diseño | D5: Transición de estados | G5: Ciclo 3
G6: Estado del ciclo 1: cargarlo en la hoja del reporte; la celda «Estado en la Entrega 1» lo toma de ahí. Este registro es para el resultado obtenido y los reintentos.
A7: # | B7: Pre-requisitos | D7: Datos de prueba
A8: 1 | B8: Abrir la aplicación desplegada en un navegador de escritorio. | D8: Entorno: | E8: Aplicación desplegada en Vercel (URL en el Anexo C)
A9: 2 | B9: Iniciar una partida en modo Pacman. | D9: Navegador: | E9: Google Chrome de escritorio
A10: 3 | B10: Partida en curso en el nivel 3, próxima a completarse. | D10: Modo de juego: | E10: Pacman
D11: Nivel: | E11: 3
A13: Título del CP | B13: Victoria al completar el nivel 3
A16: Historias de Usuario | B16: HU-04 | C16: Épica | D16: E1 — Núcleo de juego y movimiento
A17: Estado Automatización | B17: No automatizado | C17: Camino feliz | D17: Sí
A19: Pasos # | B19: Detalle de pasos | D19: Resultado esperado
A20: 1 | B20: Consumir la última esfera del nivel 3. | D20: La partida termina en victoria y se muestra la pantalla de Victoria con el puntaje final.
A21: El caso se aprueba solo si se cumple todo el resultado esperado del último paso (en negrita); si cualquier parte no se cumple, se registra como Fallido.

Sheet CP-018
A1: Test Case ID | B1: CP-018 | C1: Descripción / Funcionalidad | D1: HU-05 · Obtener el PowerUp al consumir una esfera grande | G1: Registro de ejecución
A2: Creado por | B2: Cruz, Luzzi | C2: Versión | D2: 1 | G2: Ciclo | H2: Fecha | I2: Ejecutor | J2: Estado | K2: Resultado obtenido | L2: Defecto
A3: Reporte de ejecución 1 | C3: Estado en la Entrega 1 | D3: =IF(INDEX('Reporte de ejecución - Entrega1'!$G$4:$G$69,MATCH($B$1,'Reporte de ejecución - Entrega1'!$A$4:$A$69,0))="","Sin ejecutar",INDEX('Reporte de ejecución - Entrega1'!$G$4:$G$69,MATCH($B$1,'Reporte de ejecución - Entrega1'!$A$4:$A$69,0))) -> Sin ejecutar | G3: Ciclo 1
G4: Ciclo 2
A5: Prioridad (Alta, Media, Baja) | B5: Alta | C5: Técnica de diseño | D5: Transición de estados | G5: Ciclo 3
G6: Estado del ciclo 1: cargarlo en la hoja del reporte; la celda «Estado en la Entrega 1» lo toma de ahí. Este registro es para el resultado obtenido y los reintentos.
A7: # | B7: Pre-requisitos | D7: Datos de prueba
A8: 1 | B8: Abrir la aplicación desplegada en un navegador de escritorio. | D8: Entorno: | E8: Aplicación desplegada en Vercel (URL en el Anexo C)
A9: 2 | B9: Iniciar una partida en modo Pacman. | D9: Navegador: | E9: Google Chrome de escritorio
A10: 3 | B10: Partida en curso (N1), sin PowerUp activo. | D10: Modo de juego: | E10: Pacman
D11: Nivel inicial: | E11: 1
D12: Vidas iniciales: | E12: 3
D13: PowerUp: | E13: Inactivo
A15: Título del CP | B15: Activación automática del PowerUp
A18: Historias de Usuario | B18: HU-05 | C18: Épica | D18: E2 — PowerUp e interacción con fantasmas
A19: Estado Automatización | B19: No automatizado | C19: Camino feliz | D19: Sí
A21: Pasos # | B21: Detalle de pasos | D21: Resultado esperado
A22: 1 | B22: Registrar el puntaje. | D22: Puntaje anotado como valor de referencia.
A23: 2 | B23: Consumir una esfera grande sin presionar ninguna otra tecla. | D23: El PowerUp se activa de inmediato sin intervención del jugador, el puntaje aumenta exactamente 50, los fantasmas cambian su diseño y se alejan de Pacman.
A24: El caso se aprueba solo si se cumple todo el resultado esperado del último paso (en negrita); si cualquier parte no se cumple, se registra como Fallido.

Sheet CP-019
A1: Test Case ID | B1: CP-019 | C1: Descripción / Funcionalidad | D1: HU-05 · Obtener el PowerUp al consumir una esfera grande | G1: Registro de ejecución
A2: Creado por | B2: Cruz, Luzzi | C2: Versión | D2: 1 | G2: Ciclo | H2: Fecha | I2: Ejecutor | J2: Estado | K2: Resultado obtenido | L2: Defecto
A3: Reporte de ejecución 1 | C3: Estado en la Entrega 1 | D3: =IF(INDEX('Reporte de ejecución - Entrega1'!$G$4:$G$69,MATCH($B$1,'Reporte de ejecución - Entrega1'!$A$4:$A$69,0))="","Sin ejecutar",INDEX('Reporte de ejecución - Entrega1'!$G$4:$G$69,MATCH($B$1,'Reporte de ejecución - Entrega1'!$A$4:$A$69,0))) -> Sin ejecutar | G3: Ciclo 1
G4: Ciclo 2
A5: Prioridad (Alta, Media, Baja) | B5: Alta | C5: Técnica de diseño | D5: Valores límite | G5: Ciclo 3
G6: Estado del ciclo 1: cargarlo en la hoja del reporte; la celda «Estado en la Entrega 1» lo toma de ahí. Este registro es para el resultado obtenido y los reintentos.
A7: # | B7: Pre-requisitos | D7: Datos de prueba
A8: 1 | B8: Abrir la aplicación desplegada en un navegador de escritorio. | D8: Entorno: | E8: Aplicación desplegada en Vercel (URL en el Anexo C)
A9: 2 | B9: Iniciar una partida en modo Pacman. | D9: Navegador: | E9: Google Chrome de escritorio
A10: 3 | B10: Partida en curso (N1). | D10: Modo de juego: | E10: Pacman
D11: Nivel inicial: | E11: 1
D12: Vidas iniciales: | E12: 3
D13: PowerUp: | E13: Inactivo
A15: Título del CP | B15: Duración del PowerUp
A18: Historias de Usuario | B18: HU-05 | C18: Épica | D18: E2 — PowerUp e interacción con fantasmas
A19: Estado Automatización | B19: No automatizado | C19: Camino feliz | D19: No
A21: Pasos # | B21: Detalle de pasos | D21: Resultado esperado
A22: 1 | B22: Consumir una esfera grande y cronometrar desde ese instante. | D22: El PowerUp se activa y los fantasmas cambian a su diseño vulnerable.
A23: 2 | B23: Observar el estado de los fantasmas a los 7 segundos. | D23: A los 7 segundos los fantasmas siguen vulnerables (parpadeando).
A24: 3 | B24: Observarlo a los 9 segundos. | D24: A los 7 segundos los fantasmas siguen en estado vulnerable; a los 9 segundos recuperaron su diseño normal y volvieron a perseguir a Pacman. La duración total es de 8 segundos.
A25: El caso se aprueba solo si se cumple todo el resultado esperado del último paso (en negrita); si cualquier parte no se cumple, se registra como Fallido.

Sheet CP-020
A1: Test Case ID | B1: CP-020 | C1: Descripción / Funcionalidad | D1: HU-05 · Obtener el PowerUp al consumir una esfera grande | G1: Registro de ejecución
A2: Creado por | B2: Cruz, Luzzi | C2: Versión | D2: 1 | G2: Ciclo | H2: Fecha | I2: Ejecutor | J2: Estado | K2: Resultado obtenido | L2: Defecto
A3: Reporte de ejecución 1 | C3: Estado en la Entrega 1 | D3: =IF(INDEX('Reporte de ejecución - Entrega1'!$G$4:$G$69,MATCH($B$1,'Reporte de ejecución - Entrega1'!$A$4:$A$69,0))="","Sin ejecutar",INDEX('Reporte de ejecución - Entrega1'!$G$4:$G$69,MATCH($B$1,'Reporte de ejecución - Entrega1'!$A$4:$A$69,0))) -> Sin ejecutar | G3: Ciclo 1
G4: Ciclo 2
A5: Prioridad (Alta, Media, Baja) | B5: Alta | C5: Técnica de diseño | D5: Adivinación de errores | G5: Ciclo 3
G6: Estado del ciclo 1: cargarlo en la hoja del reporte; la celda «Estado en la Entrega 1» lo toma de ahí. Este registro es para el resultado obtenido y los reintentos.
A7: # | B7: Pre-requisitos | D7: Datos de prueba
A8: 1 | B8: Abrir la aplicación desplegada en un navegador de escritorio. | D8: Entorno: | E8: Aplicación desplegada en Vercel (URL en el Anexo C)
A9: 2 | B9: Iniciar una partida en modo Pacman. | D9: Navegador: | E9: Google Chrome de escritorio
A10: 3 | B10: Partida en curso (N1), un fantasma persiguiendo a Pacman a corta distancia. | D10: Modo de juego: | E10: Pacman
D11: Nivel inicial: | E11: 1
D12: Vidas iniciales: | E12: 3
D13: PowerUp: | E13: Inactivo
A15: Título del CP | B15: Los fantasmas huyen durante el PowerUp
A18: Historias de Usuario | B18: HU-05 | C18: Épica | D18: E2 — PowerUp e interacción con fantasmas
A19: Estado Automatización | B19: No automatizado | C19: Camino feliz | D19: No
A21: Pasos # | B21: Detalle de pasos | D21: Resultado esperado
A22: 1 | B22: Consumir una esfera grande. | D22: El PowerUp se activa y los fantasmas cambian a su diseño vulnerable.
A23: 2 | B23: Observar la trayectoria del fantasma que perseguía a Pacman. | D23: El fantasma deja de acercarse a Pacman y se desplaza alejándose de él.
A24: El caso se aprueba solo si se cumple todo el resultado esperado del último paso (en negrita); si cualquier parte no se cumple, se registra como Fallido.

Sheet CP-021
A1: Test Case ID | B1: CP-021 | C1: Descripción / Funcionalidad | D1: HU-05 · Obtener el PowerUp al consumir una esfera grande | G1: Registro de ejecución
A2: Creado por | B2: Cruz, Luzzi | C2: Versión | D2: 1 | G2: Ciclo | H2: Fecha | I2: Ejecutor | J2: Estado | K2: Resultado obtenido | L2: Defecto
A3: Reporte de ejecución 1 | C3: Estado en la Entrega 1 | D3: =IF(INDEX('Reporte de ejecución - Entrega1'!$G$4:$G$69,MATCH($B$1,'Reporte de ejecución - Entrega1'!$A$4:$A$69,0))="","Sin ejecutar",INDEX('Reporte de ejecución - Entrega1'!$G$4:$G$69,MATCH($B$1,'Reporte de ejecución - Entrega1'!$A$4:$A$69,0))) -> Sin ejecutar | G3: Ciclo 1
G4: Ciclo 2
A5: Prioridad (Alta, Media, Baja) | B5: Media | C5: Técnica de diseño | D5: Valores límite | G5: Ciclo 3
G6: Estado del ciclo 1: cargarlo en la hoja del reporte; la celda «Estado en la Entrega 1» lo toma de ahí. Este registro es para el resultado obtenido y los reintentos.
A7: # | B7: Pre-requisitos | D7: Datos de prueba
A8: 1 | B8: Abrir la aplicación desplegada en un navegador de escritorio. | D8: Entorno: | E8: Aplicación desplegada en Vercel (URL en el Anexo C)
A9: 2 | B9: Iniciar una partida en modo Pacman. | D9: Navegador: | E9: Google Chrome de escritorio
A10: 3 | B10: Partida en curso (N1), dos esferas grandes accesibles. | D10: Modo de juego: | E10: Pacman
D11: Nivel inicial: | E11: 1
D12: Vidas iniciales: | E12: 3
D13: PowerUp: | E13: Inactivo
A15: Título del CP | B15: Reinicio del temporizador por una segunda esfera grande
A18: Historias de Usuario | B18: HU-05 | C18: Épica | D18: E2 — PowerUp e interacción con fantasmas
A19: Estado Automatización | B19: No automatizado | C19: Camino feliz | D19: No
A21: Pasos # | B21: Detalle de pasos | D21: Resultado esperado
A22: 1 | B22: Consumir una esfera grande. | D22: El PowerUp se activa.
A23: 2 | B23: A los 5 segundos, consumir la segunda esfera grande. | D23: La segunda esfera grande desaparece y el PowerUp sigue activo.
A24: 3 | B24: Cronometrar desde el segundo consumo. | D24: El PowerUp permanece activo 8 segundos completos a partir del segundo consumo, no 3.
A25: El caso se aprueba solo si se cumple todo el resultado esperado del último paso (en negrita); si cualquier parte no se cumple, se registra como Fallido.

Sheet CP-022
A1: Test Case ID | B1: CP-022 | C1: Descripción / Funcionalidad | D1: HU-05 · Obtener el PowerUp al consumir una esfera grande | G1: Registro de ejecución
A2: Creado por | B2: Cruz, Luzzi | C2: Versión | D2: 1 | G2: Ciclo | H2: Fecha | I2: Ejecutor | J2: Estado | K2: Resultado obtenido | L2: Defecto
A3: Reporte de ejecución 1 | C3: Estado en la Entrega 1 | D3: =IF(INDEX('Reporte de ejecución - Entrega1'!$G$4:$G$69,MATCH($B$1,'Reporte de ejecución - Entrega1'!$A$4:$A$69,0))="","Sin ejecutar",INDEX('Reporte de ejecución - Entrega1'!$G$4:$G$69,MATCH($B$1,'Reporte de ejecución - Entrega1'!$A$4:$A$69,0))) -> Sin ejecutar | G3: Ciclo 1
G4: Ciclo 2
A5: Prioridad (Alta, Media, Baja) | B5: Media | C5: Técnica de diseño | D5: Tabla de decisión | G5: Ciclo 3
G6: Estado del ciclo 1: cargarlo en la hoja del reporte; la celda «Estado en la Entrega 1» lo toma de ahí. Este registro es para el resultado obtenido y los reintentos.
A7: # | B7: Pre-requisitos | D7: Datos de prueba
A8: 1 | B8: Abrir la aplicación desplegada en un navegador de escritorio. | D8: Entorno: | E8: Aplicación desplegada en Vercel (URL en el Anexo C)
A9: 2 | B9: Iniciar una partida en modo Pacman. | D9: Navegador: | E9: Google Chrome de escritorio
A10: 3 | B10: Partida en curso (N1), dos esferas grandes accesibles. | D10: Modo de juego: | E10: Pacman
D11: Nivel inicial: | E11: 1
D12: Vidas iniciales: | E12: 3
D13: PowerUp: | E13: Inactivo
A15: Título del CP | B15: Reinicio de la escala de puntos por una segunda esfera grande
A18: Historias de Usuario | B18: HU-05 | C18: Épica | D18: E2 — PowerUp e interacción con fantasmas
A19: Estado Automatización | B19: No automatizado | C19: Camino feliz | D19: No
A21: Pasos # | B21: Detalle de pasos | D21: Resultado esperado
A22: 1 | B22: Consumir una esfera grande. | D22: El PowerUp se activa.
A23: 2 | B23: Comer un fantasma y registrar los puntos obtenidos. | D23: El fantasma es comido y suma 200 puntos.
A24: 3 | B24: Consumir la segunda esfera grande. | D24: La segunda esfera grande desaparece y el PowerUp sigue activo.
A25: 4 | B25: Comer otro fantasma y registrar los puntos obtenidos. | D25: El fantasma del paso 2 suma 200 puntos y el del paso 4 suma 200 puntos, no 400.
A26: El caso se aprueba solo si se cumple todo el resultado esperado del último paso (en negrita); si cualquier parte no se cumple, se registra como Fallido.

Sheet CP-023
A1: Test Case ID | B1: CP-023 | C1: Descripción / Funcionalidad | D1: HU-06 · Comer fantasmas durante el PowerUp | G1: Registro de ejecución
A2: Creado por | B2: Cruz, Luzzi | C2: Versión | D2: 1 | G2: Ciclo | H2: Fecha | I2: Ejecutor | J2: Estado | K2: Resultado obtenido | L2: Defecto
A3: Reporte de ejecución 1 | C3: Estado en la Entrega 1 | D3: =IF(INDEX('Reporte de ejecución - Entrega1'!$G$4:$G$69,MATCH($B$1,'Reporte de ejecución - Entrega1'!$A$4:$A$69,0))="","Sin ejecutar",INDEX('Reporte de ejecución - Entrega1'!$G$4:$G$69,MATCH($B$1,'Reporte de ejecución - Entrega1'!$A$4:$A$69,0))) -> Sin ejecutar | G3: Ciclo 1
G4: Ciclo 2
A5: Prioridad (Alta, Media, Baja) | B5: Alta | C5: Técnica de diseño | D5: Valores límite | G5: Ciclo 3
G6: Estado del ciclo 1: cargarlo en la hoja del reporte; la celda «Estado en la Entrega 1» lo toma de ahí. Este registro es para el resultado obtenido y los reintentos.
A7: # | B7: Pre-requisitos | D7: Datos de prueba
A8: 1 | B8: Abrir la aplicación desplegada en un navegador de escritorio. | D8: Entorno: | E8: Aplicación desplegada en Vercel (URL en el Anexo C)
A9: 2 | B9: Iniciar una partida en modo Pacman. | D9: Navegador: | E9: Google Chrome de escritorio
A10: 3 | B10: Partida en curso (N1), cuatro fantasmas próximos a Pacman. | D10: Modo de juego: | E10: Pacman
D11: Nivel inicial: | E11: 1
D12: Vidas iniciales: | E12: 3
D13: PowerUp: | E13: Inactivo
A15: Título del CP | B15: Escala de puntos por fantasmas comidos
A18: Historias de Usuario | B18: HU-06 | C18: Épica | D18: E2 — PowerUp e interacción con fantasmas
A19: Estado Automatización | B19: No automatizado | C19: Camino feliz | D19: Sí
A21: Pasos # | B21: Detalle de pasos | D21: Resultado esperado
A22: 1 | B22: Consumir una esfera grande. | D22: El PowerUp se activa.
A23: 2 | B23: Comer los cuatro fantasmas dentro de la duración del PowerUp, registrando el puntaje antes y después de cada uno. | D23: Los incrementos de puntaje son exactamente 200, 400, 800 y 1600, en ese orden.
A24: El caso se aprueba solo si se cumple todo el resultado esperado del último paso (en negrita); si cualquier parte no se cumple, se registra como Fallido.

Sheet CP-024
A1: Test Case ID | B1: CP-024 | C1: Descripción / Funcionalidad | D1: HU-06 · Comer fantasmas durante el PowerUp | G1: Registro de ejecución
A2: Creado por | B2: Cruz, Luzzi | C2: Versión | D2: 1 | G2: Ciclo | H2: Fecha | I2: Ejecutor | J2: Estado | K2: Resultado obtenido | L2: Defecto
A3: Reporte de ejecución 1 | C3: Estado en la Entrega 1 | D3: =IF(INDEX('Reporte de ejecución - Entrega1'!$G$4:$G$69,MATCH($B$1,'Reporte de ejecución - Entrega1'!$A$4:$A$69,0))="","Sin ejecutar",INDEX('Reporte de ejecución - Entrega1'!$G$4:$G$69,MATCH($B$1,'Reporte de ejecución - Entrega1'!$A$4:$A$69,0))) -> Sin ejecutar | G3: Ciclo 1
G4: Ciclo 2
A5: Prioridad (Alta, Media, Baja) | B5: Alta | C5: Técnica de diseño | D5: Transición de estados | G5: Ciclo 3
G6: Estado del ciclo 1: cargarlo en la hoja del reporte; la celda «Estado en la Entrega 1» lo toma de ahí. Este registro es para el resultado obtenido y los reintentos.
A7: # | B7: Pre-requisitos | D7: Datos de prueba
A8: 1 | B8: Abrir la aplicación desplegada en un navegador de escritorio. | D8: Entorno: | E8: Aplicación desplegada en Vercel (URL en el Anexo C)
A9: 2 | B9: Iniciar una partida en modo Pacman. | D9: Navegador: | E9: Google Chrome de escritorio
A10: 3 | B10: Partida en curso (N1). | D10: Modo de juego: | E10: Pacman
D11: Nivel inicial: | E11: 1
D12: Vidas iniciales: | E12: 3
D13: PowerUp: | E13: Inactivo
A15: Título del CP | B15: Reinicio de la escala al terminar el PowerUp
A18: Historias de Usuario | B18: HU-06 | C18: Épica | D18: E2 — PowerUp e interacción con fantasmas
A19: Estado Automatización | B19: No automatizado | C19: Camino feliz | D19: No
A21: Pasos # | B21: Detalle de pasos | D21: Resultado esperado
A22: 1 | B22: Consumir una esfera grande y comer un fantasma (200 puntos). | D22: El fantasma es comido y el puntaje aumenta 200.
A23: 2 | B23: Esperar a que el PowerUp termine. | D23: Los fantasmas recuperan su diseño normal.
A24: 3 | B24: Consumir otra esfera grande y comer un fantasma, registrando el incremento. | D24: El fantasma del paso 3 suma 200 puntos, no 400.
A25: El caso se aprueba solo si se cumple todo el resultado esperado del último paso (en negrita); si cualquier parte no se cumple, se registra como Fallido.

Sheet CP-025
A1: Test Case ID | B1: CP-025 | C1: Descripción / Funcionalidad | D1: HU-06 · Comer fantasmas durante el PowerUp | G1: Registro de ejecución
A2: Creado por | B2: Cruz, Luzzi | C2: Versión | D2: 1 | G2: Ciclo | H2: Fecha | I2: Ejecutor | J2: Estado | K2: Resultado obtenido | L2: Defecto
A3: Reporte de ejecución 1 | C3: Estado en la Entrega 1 | D3: =IF(INDEX('Reporte de ejecución - Entrega1'!$G$4:$G$69,MATCH($B$1,'Reporte de ejecución - Entrega1'!$A$4:$A$69,0))="","Sin ejecutar",INDEX('Reporte de ejecución - Entrega1'!$G$4:$G$69,MATCH($B$1,'Reporte de ejecución - Entrega1'!$A$4:$A$69,0))) -> Sin ejecutar | G3: Ciclo 1
G4: Ciclo 2
A5: Prioridad (Alta, Media, Baja) | B5: Alta | C5: Técnica de diseño | D5: Tabla de decisión | G5: Ciclo 3
G6: Estado del ciclo 1: cargarlo en la hoja del reporte; la celda «Estado en la Entrega 1» lo toma de ahí. Este registro es para el resultado obtenido y los reintentos.
A7: # | B7: Pre-requisitos | D7: Datos de prueba
A8: 1 | B8: Abrir la aplicación desplegada en un navegador de escritorio. | D8: Entorno: | E8: Aplicación desplegada en Vercel (URL en el Anexo C)
A9: 2 | B9: Iniciar una partida en modo Pacman. | D9: Navegador: | E9: Google Chrome de escritorio
A10: 3 | B10: Partida en curso (N1), 3 vidas, PowerUp activo. | D10: Modo de juego: | E10: Pacman
D11: Nivel inicial: | E11: 1
D12: Vidas iniciales: | E12: 3
D13: PowerUp: | E13: Inactivo
A15: Título del CP | B15: Comer un fantasma no descuenta vidas
A18: Historias de Usuario | B18: HU-06 | C18: Épica | D18: E2 — PowerUp e interacción con fantasmas
A19: Estado Automatización | B19: No automatizado | C19: Camino feliz | D19: No
A21: Pasos # | B21: Detalle de pasos | D21: Resultado esperado
A22: 1 | B22: Registrar el contador de vidas. | D22: Contador de vidas anotado como referencia.
A23: 2 | B23: Tocar un fantasma con el PowerUp activo. | D23: El fantasma es comido y desaparece del mapa.
A24: 3 | B24: Registrar el contador de vidas. | D24: El fantasma desaparece del mapa, el contador de vidas sigue en 3 y el nivel no se reinicia.
A25: El caso se aprueba solo si se cumple todo el resultado esperado del último paso (en negrita); si cualquier parte no se cumple, se registra como Fallido.

Sheet CP-026
A1: Test Case ID | B1: CP-026 | C1: Descripción / Funcionalidad | D1: HU-06 · Comer fantasmas durante el PowerUp | G1: Registro de ejecución
A2: Creado por | B2: Cruz, Luzzi | C2: Versión | D2: 1 | G2: Ciclo | H2: Fecha | I2: Ejecutor | J2: Estado | K2: Resultado obtenido | L2: Defecto
A3: Reporte de ejecución 1 | C3: Estado en la Entrega 1 | D3: =IF(INDEX('Reporte de ejecución - Entrega1'!$G$4:$G$69,MATCH($B$1,'Reporte de ejecución - Entrega1'!$A$4:$A$69,0))="","Sin ejecutar",INDEX('Reporte de ejecución - Entrega1'!$G$4:$G$69,MATCH($B$1,'Reporte de ejecución - Entrega1'!$A$4:$A$69,0))) -> Sin ejecutar | G3: Ciclo 1
G4: Ciclo 2
A5: Prioridad (Alta, Media, Baja) | B5: Media | C5: Técnica de diseño | D5: Valores límite | G5: Ciclo 3
G6: Estado del ciclo 1: cargarlo en la hoja del reporte; la celda «Estado en la Entrega 1» lo toma de ahí. Este registro es para el resultado obtenido y los reintentos.
A7: # | B7: Pre-requisitos | D7: Datos de prueba
A8: 1 | B8: Abrir la aplicación desplegada en un navegador de escritorio. | D8: Entorno: | E8: Aplicación desplegada en Vercel (URL en el Anexo C)
A9: 2 | B9: Iniciar una partida en modo Pacman. | D9: Navegador: | E9: Google Chrome de escritorio
A10: 3 | B10: Partida en curso (N1), PowerUp activo. | D10: Modo de juego: | E10: Pacman
D11: Nivel inicial: | E11: 1
D12: Vidas iniciales: | E12: 3
D13: PowerUp: | E13: Inactivo
A15: Título del CP | B15: Reaparición del fantasma comido
A18: Historias de Usuario | B18: HU-06 | C18: Épica | D18: E2 — PowerUp e interacción con fantasmas
A19: Estado Automatización | B19: No automatizado | C19: Camino feliz | D19: No
A21: Pasos # | B21: Detalle de pasos | D21: Resultado esperado
A22: 1 | B22: Comer un fantasma y cronometrar. | D22: El fantasma desaparece del mapa.
A23: 2 | B23: Observar el punto de reaparición y el momento en que reaparece. | D23: El fantasma reaparece en su punto de reaparición a los 5 segundos y retoma su comportamiento normal.
A24: El caso se aprueba solo si se cumple todo el resultado esperado del último paso (en negrita); si cualquier parte no se cumple, se registra como Fallido.

Sheet CP-027
A1: Test Case ID | B1: CP-027 | C1: Descripción / Funcionalidad | D1: HU-06 · Comer fantasmas durante el PowerUp | G1: Registro de ejecución
A2: Creado por | B2: Cruz, Luzzi | C2: Versión | D2: 1 | G2: Ciclo | H2: Fecha | I2: Ejecutor | J2: Estado | K2: Resultado obtenido | L2: Defecto
A3: Reporte de ejecución 1 | C3: Estado en la Entrega 1 | D3: =IF(INDEX('Reporte de ejecución - Entrega1'!$G$4:$G$69,MATCH($B$1,'Reporte de ejecución - Entrega1'!$A$4:$A$69,0))="","Sin ejecutar",INDEX('Reporte de ejecución - Entrega1'!$G$4:$G$69,MATCH($B$1,'Reporte de ejecución - Entrega1'!$A$4:$A$69,0))) -> Sin ejecutar | G3: Ciclo 1
G4: Ciclo 2
A5: Prioridad (Alta, Media, Baja) | B5: Media | C5: Técnica de diseño | D5: Tabla de decisión | G5: Ciclo 3
G6: Estado del ciclo 1: cargarlo en la hoja del reporte; la celda «Estado en la Entrega 1» lo toma de ahí. Este registro es para el resultado obtenido y los reintentos.
A7: # | B7: Pre-requisitos | D7: Datos de prueba
A8: 1 | B8: Abrir la aplicación desplegada en un navegador de escritorio. | D8: Entorno: | E8: Aplicación desplegada en Vercel (URL en el Anexo C)
A9: 2 | B9: Iniciar una partida en modo Pacman. | D9: Navegador: | E9: Google Chrome de escritorio
A10: 3 | B10: Partida en curso (N1). | D10: Modo de juego: | E10: Pacman
D11: Nivel inicial: | E11: 1
D12: Vidas iniciales: | E12: 3
D13: PowerUp: | E13: Inactivo
A15: Título del CP | B15: Fantasma que reaparece con el PowerUp aún activo
A18: Historias de Usuario | B18: HU-06 | C18: Épica | D18: E2 — PowerUp e interacción con fantasmas
A19: Estado Automatización | B19: No automatizado | C19: Camino feliz | D19: No
A21: Pasos # | B21: Detalle de pasos | D21: Resultado esperado
A22: 1 | B22: Consumir una esfera grande. | D22: El PowerUp se activa.
A23: 2 | B23: Comer un fantasma de inmediato (200 puntos). | D23: El fantasma es comido y suma 200 puntos.
A24: 3 | B24: Esperar su reaparición dentro de los 8 segundos del PowerUp. | D24: El fantasma reaparece en su punto de reaparición a los 5 segundos.
A25: 4 | B25: Comerlo otra vez y registrar el incremento. | D25: El fantasma reaparece en estado vulnerable, puede volver a ser comido y el incremento del paso 4 es de 400 puntos: la escala continúa y no se reinicia.
A26: El caso se aprueba solo si se cumple todo el resultado esperado del último paso (en negrita); si cualquier parte no se cumple, se registra como Fallido.

Sheet CP-028
A1: Test Case ID | B1: CP-028 | C1: Descripción / Funcionalidad | D1: HU-07 · Advertir el fin del PowerUp | G1: Registro de ejecución
A2: Creado por | B2: Cruz, Luzzi | C2: Versión | D2: 1 | G2: Ciclo | H2: Fecha | I2: Ejecutor | J2: Estado | K2: Resultado obtenido | L2: Defecto
A3: Reporte de ejecución 1 | C3: Estado en la Entrega 1 | D3: =IF(INDEX('Reporte de ejecución - Entrega1'!$G$4:$G$69,MATCH($B$1,'Reporte de ejecución - Entrega1'!$A$4:$A$69,0))="","Sin ejecutar",INDEX('Reporte de ejecución - Entrega1'!$G$4:$G$69,MATCH($B$1,'Reporte de ejecución - Entrega1'!$A$4:$A$69,0))) -> Sin ejecutar | G3: Ciclo 1
G4: Ciclo 2
A5: Prioridad (Alta, Media, Baja) | B5: Media | C5: Técnica de diseño | D5: Valores límite | G5: Ciclo 3
G6: Estado del ciclo 1: cargarlo en la hoja del reporte; la celda «Estado en la Entrega 1» lo toma de ahí. Este registro es para el resultado obtenido y los reintentos.
A7: # | B7: Pre-requisitos | D7: Datos de prueba
A8: 1 | B8: Abrir la aplicación desplegada en un navegador de escritorio. | D8: Entorno: | E8: Aplicación desplegada en Vercel (URL en el Anexo C)
A9: 2 | B9: Iniciar una partida en modo Pacman. | D9: Navegador: | E9: Google Chrome de escritorio
A10: 3 | B10: Partida en curso (N1). | D10: Modo de juego: | E10: Pacman
D11: Nivel inicial: | E11: 1
D12: Vidas iniciales: | E12: 3
D13: PowerUp: | E13: Inactivo
A15: Título del CP | B15: Parpadeo en los últimos 2 segundos del PowerUp
A18: Historias de Usuario | B18: HU-07 | C18: Épica | D18: E2 — PowerUp e interacción con fantasmas
A19: Estado Automatización | B19: No automatizado | C19: Camino feliz | D19: No
A21: Pasos # | B21: Detalle de pasos | D21: Resultado esperado
A22: 1 | B22: Consumir una esfera grande y cronometrar. | D22: El PowerUp se activa y los fantasmas cambian a su diseño vulnerable estable.
A23: 2 | B23: Observar el aspecto de los fantasmas a los 5 segundos y a los 7 segundos. | D23: A los 5 segundos los fantasmas muestran el estado vulnerable estable; a los 7 segundos parpadean. El parpadeo se distingue tanto del estado vulnerable estable como del diseño normal.
A24: El caso se aprueba solo si se cumple todo el resultado esperado del último paso (en negrita); si cualquier parte no se cumple, se registra como Fallido.

Sheet CP-029
A1: Test Case ID | B1: CP-029 | C1: Descripción / Funcionalidad | D1: HU-07 · Advertir el fin del PowerUp | G1: Registro de ejecución
A2: Creado por | B2: Cruz, Luzzi | C2: Versión | D2: 1 | G2: Ciclo | H2: Fecha | I2: Ejecutor | J2: Estado | K2: Resultado obtenido | L2: Defecto
A3: Reporte de ejecución 1 | C3: Estado en la Entrega 1 | D3: =IF(INDEX('Reporte de ejecución - Entrega1'!$G$4:$G$69,MATCH($B$1,'Reporte de ejecución - Entrega1'!$A$4:$A$69,0))="","Sin ejecutar",INDEX('Reporte de ejecución - Entrega1'!$G$4:$G$69,MATCH($B$1,'Reporte de ejecución - Entrega1'!$A$4:$A$69,0))) -> Sin ejecutar | G3: Ciclo 1
G4: Ciclo 2
A5: Prioridad (Alta, Media, Baja) | B5: Media | C5: Técnica de diseño | D5: Transición de estados | G5: Ciclo 3
G6: Estado del ciclo 1: cargarlo en la hoja del reporte; la celda «Estado en la Entrega 1» lo toma de ahí. Este registro es para el resultado obtenido y los reintentos.
A7: # | B7: Pre-requisitos | D7: Datos de prueba
A8: 1 | B8: Abrir la aplicación desplegada en un navegador de escritorio. | D8: Entorno: | E8: Aplicación desplegada en Vercel (URL en el Anexo C)
A9: 2 | B9: Iniciar una partida en modo Pacman. | D9: Navegador: | E9: Google Chrome de escritorio
A10: 3 | B10: Partida en curso (N1), una esfera grande accesible. | D10: Modo de juego: | E10: Pacman
D11: Nivel inicial: | E11: 1
D12: Vidas iniciales: | E12: 3
D13: PowerUp: | E13: Inactivo
A15: Título del CP | B15: Esfera grande consumida durante el parpadeo
A18: Historias de Usuario | B18: HU-07 | C18: Épica | D18: E2 — PowerUp e interacción con fantasmas
A19: Estado Automatización | B19: No automatizado | C19: Camino feliz | D19: No
A21: Pasos # | B21: Detalle de pasos | D21: Resultado esperado
A22: 1 | B22: Consumir una esfera grande. | D22: El PowerUp se activa.
A23: 2 | B23: Al iniciarse el parpadeo, consumir la segunda esfera grande. | D23: La segunda esfera grande desaparece.
A24: 3 | B24: Observar el aspecto de los fantasmas. | D24: El parpadeo cesa, los fantasmas vuelven al estado vulnerable estable y el PowerUp se extiende 8 segundos desde el segundo consumo.
A25: El caso se aprueba solo si se cumple todo el resultado esperado del último paso (en negrita); si cualquier parte no se cumple, se registra como Fallido.

Sheet CP-030
A1: Test Case ID | B1: CP-030 | C1: Descripción / Funcionalidad | D1: HU-08 · Perder una vida al ser alcanzado por un fantasma | G1: Registro de ejecución
A2: Creado por | B2: Cruz, Luzzi | C2: Versión | D2: 1 | G2: Ciclo | H2: Fecha | I2: Ejecutor | J2: Estado | K2: Resultado obtenido | L2: Defecto
A3: Reporte de ejecución 1 | C3: Estado en la Entrega 1 | D3: =IF(INDEX('Reporte de ejecución - Entrega1'!$G$4:$G$69,MATCH($B$1,'Reporte de ejecución - Entrega1'!$A$4:$A$69,0))="","Sin ejecutar",INDEX('Reporte de ejecución - Entrega1'!$G$4:$G$69,MATCH($B$1,'Reporte de ejecución - Entrega1'!$A$4:$A$69,0))) -> Sin ejecutar | G3: Ciclo 1
G4: Ciclo 2
A5: Prioridad (Alta, Media, Baja) | B5: Alta | C5: Técnica de diseño | D5: Tabla de decisión | G5: Ciclo 3
G6: Estado del ciclo 1: cargarlo en la hoja del reporte; la celda «Estado en la Entrega 1» lo toma de ahí. Este registro es para el resultado obtenido y los reintentos.
A7: # | B7: Pre-requisitos | D7: Datos de prueba
A8: 1 | B8: Abrir la aplicación desplegada en un navegador de escritorio. | D8: Entorno: | E8: Aplicación desplegada en Vercel (URL en el Anexo C)
A9: 2 | B9: Iniciar una partida en modo Pacman. | D9: Navegador: | E9: Google Chrome de escritorio
A10: 3 | B10: Partida en curso (N1), 3 vidas, sin PowerUp activo. | D10: Modo de juego: | E10: Pacman
D11: Nivel inicial: | E11: 1
D12: Vidas iniciales: | E12: 3
D13: PowerUp: | E13: Inactivo
A15: Título del CP | B15: Descuento de una vida por contacto con un fantasma
A18: Historias de Usuario | B18: HU-08 | C18: Épica | D18: E2 — PowerUp e interacción con fantasmas
A19: Estado Automatización | B19: No automatizado | C19: Camino feliz | D19: Sí
A21: Pasos # | B21: Detalle de pasos | D21: Resultado esperado
A22: 1 | B22: Registrar el contador de vidas y el puntaje. | D22: Vidas y puntaje anotados como valores de referencia.
A23: 2 | B23: Dejar que un fantasma alcance a Pacman. | D23: Se produce el contacto entre Pacman y el fantasma.
A24: 3 | B24: Registrar ambos valores. | D24: El contador de vidas baja a 2, el puntaje acumulado se conserva, y Pacman y los fantasmas vuelven a sus posiciones iniciales.
A25: El caso se aprueba solo si se cumple todo el resultado esperado del último paso (en negrita); si cualquier parte no se cumple, se registra como Fallido.

Sheet CP-031
A1: Test Case ID | B1: CP-031 | C1: Descripción / Funcionalidad | D1: HU-08 · Perder una vida al ser alcanzado por un fantasma | G1: Registro de ejecución
A2: Creado por | B2: Cruz, Luzzi | C2: Versión | D2: 1 | G2: Ciclo | H2: Fecha | I2: Ejecutor | J2: Estado | K2: Resultado obtenido | L2: Defecto
A3: Reporte de ejecución 1 | C3: Estado en la Entrega 1 | D3: =IF(INDEX('Reporte de ejecución - Entrega1'!$G$4:$G$69,MATCH($B$1,'Reporte de ejecución - Entrega1'!$A$4:$A$69,0))="","Sin ejecutar",INDEX('Reporte de ejecución - Entrega1'!$G$4:$G$69,MATCH($B$1,'Reporte de ejecución - Entrega1'!$A$4:$A$69,0))) -> Sin ejecutar | G3: Ciclo 1
G4: Ciclo 2
A5: Prioridad (Alta, Media, Baja) | B5: Alta | C5: Técnica de diseño | D5: Adivinación de errores | G5: Ciclo 3
G6: Estado del ciclo 1: cargarlo en la hoja del reporte; la celda «Estado en la Entrega 1» lo toma de ahí. Este registro es para el resultado obtenido y los reintentos.
A7: # | B7: Pre-requisitos | D7: Datos de prueba
A8: 1 | B8: Abrir la aplicación desplegada en un navegador de escritorio. | D8: Entorno: | E8: Aplicación desplegada en Vercel (URL en el Anexo C)
A9: 2 | B9: Iniciar una partida en modo Pacman. | D9: Navegador: | E9: Google Chrome de escritorio
A10: 3 | B10: Partida en curso (N1), 3 vidas. | D10: Modo de juego: | E10: Pacman
D11: Nivel inicial: | E11: 1
D12: Vidas iniciales: | E12: 3
D13: PowerUp: | E13: Inactivo
A15: Título del CP | B15: Un solo contacto no descuenta más de una vida
A18: Historias de Usuario | B18: HU-08 | C18: Épica | D18: E2 — PowerUp e interacción con fantasmas
A19: Estado Automatización | B19: No automatizado | C19: Camino feliz | D19: No
A21: Pasos # | B21: Detalle de pasos | D21: Resultado esperado
A22: 1 | B22: Dirigir a Pacman de frente contra un fantasma, sin cambiar de dirección durante el contacto. | D22: Se produce un único contacto con el fantasma.
A23: 2 | B23: Registrar el contador de vidas inmediatamente después. | D23: Se descuenta exactamente una vida. El contador queda en 2 y no en 1 ni en 0.
A24: El caso se aprueba solo si se cumple todo el resultado esperado del último paso (en negrita); si cualquier parte no se cumple, se registra como Fallido.

Sheet CP-032
A1: Test Case ID | B1: CP-032 | C1: Descripción / Funcionalidad | D1: HU-08 · Perder una vida al ser alcanzado por un fantasma | G1: Registro de ejecución
A2: Creado por | B2: Cruz, Luzzi | C2: Versión | D2: 1 | G2: Ciclo | H2: Fecha | I2: Ejecutor | J2: Estado | K2: Resultado obtenido | L2: Defecto
A3: Reporte de ejecución 1 | C3: Estado en la Entrega 1 | D3: =IF(INDEX('Reporte de ejecución - Entrega1'!$G$4:$G$69,MATCH($B$1,'Reporte de ejecución - Entrega1'!$A$4:$A$69,0))="","Sin ejecutar",INDEX('Reporte de ejecución - Entrega1'!$G$4:$G$69,MATCH($B$1,'Reporte de ejecución - Entrega1'!$A$4:$A$69,0))) -> Sin ejecutar | G3: Ciclo 1
G4: Ciclo 2
A5: Prioridad (Alta, Media, Baja) | B5: Media | C5: Técnica de diseño | D5: Transición de estados | G5: Ciclo 3
G6: Estado del ciclo 1: cargarlo en la hoja del reporte; la celda «Estado en la Entrega 1» lo toma de ahí. Este registro es para el resultado obtenido y los reintentos.
A7: # | B7: Pre-requisitos | D7: Datos de prueba
A8: 1 | B8: Abrir la aplicación desplegada en un navegador de escritorio. | D8: Entorno: | E8: Aplicación desplegada en Vercel (URL en el Anexo C)
A9: 2 | B9: Iniciar una partida en modo Pacman. | D9: Navegador: | E9: Google Chrome de escritorio
A10: 3 | B10: Partida en curso (N1), PowerUp activo, un fantasma en estado de gracia o recién reaparecido. | D10: Modo de juego: | E10: Pacman
D11: Nivel inicial: | E11: 1
D12: Vidas iniciales: | E12: 3
D13: PowerUp: | E13: Inactivo
A15: Título del CP | B15: El PowerUp se cancela al perder una vida
A18: Historias de Usuario | B18: HU-08 | C18: Épica | D18: E2 — PowerUp e interacción con fantasmas
A19: Estado Automatización | B19: No automatizado | C19: Camino feliz | D19: No
A21: Pasos # | B21: Detalle de pasos | D21: Resultado esperado
A22: 1 | B22: Con el PowerUp activo, perder una vida por contacto con un fantasma no vulnerable. | D22: Se descuenta una vida.
A23: 2 | B23: Observar el estado de los fantasmas al reanudarse el nivel. | D23: El PowerUp queda cancelado: los fantasmas muestran su diseño normal y persiguen a Pacman.
A24: El caso se aprueba solo si se cumple todo el resultado esperado del último paso (en negrita); si cualquier parte no se cumple, se registra como Fallido.

Sheet CP-033
A1: Test Case ID | B1: CP-033 | C1: Descripción / Funcionalidad | D1: HU-08 · Perder una vida al ser alcanzado por un fantasma | G1: Registro de ejecución
A2: Creado por | B2: Cruz, Luzzi | C2: Versión | D2: 1 | G2: Ciclo | H2: Fecha | I2: Ejecutor | J2: Estado | K2: Resultado obtenido | L2: Defecto
A3: Reporte de ejecución 1 | C3: Estado en la Entrega 1 | D3: =IF(INDEX('Reporte de ejecución - Entrega1'!$G$4:$G$69,MATCH($B$1,'Reporte de ejecución - Entrega1'!$A$4:$A$69,0))="","Sin ejecutar",INDEX('Reporte de ejecución - Entrega1'!$G$4:$G$69,MATCH($B$1,'Reporte de ejecución - Entrega1'!$A$4:$A$69,0))) -> Sin ejecutar | G3: Ciclo 1
G4: Ciclo 2
A5: Prioridad (Alta, Media, Baja) | B5: Alta | C5: Técnica de diseño | D5: Transición de estados | G5: Ciclo 3
G6: Estado del ciclo 1: cargarlo en la hoja del reporte; la celda «Estado en la Entrega 1» lo toma de ahí. Este registro es para el resultado obtenido y los reintentos.
A7: # | B7: Pre-requisitos | D7: Datos de prueba
A8: 1 | B8: Abrir la aplicación desplegada en un navegador de escritorio. | D8: Entorno: | E8: Aplicación desplegada en Vercel (URL en el Anexo C)
A9: 2 | B9: Iniciar una partida en modo Pacman. | D9: Navegador: | E9: Google Chrome de escritorio
A10: 3 | B10: Partida en curso (N1), 3 vidas, al menos 15 esferas consumidas. | D10: Modo de juego: | E10: Pacman
D11: Nivel inicial: | E11: 1
D12: Vidas iniciales: | E12: 3
D13: PowerUp: | E13: Inactivo
A15: Título del CP | B15: Reanudación del nivel tras perder una vida
A18: Historias de Usuario | B18: HU-08 | C18: Épica | D18: E2 — PowerUp e interacción con fantasmas
A19: Estado Automatización | B19: No automatizado | C19: Camino feliz | D19: No
A21: Pasos # | B21: Detalle de pasos | D21: Resultado esperado
A22: 1 | B22: Perder una vida. | D22: Se descuenta una vida.
A23: 2 | B23: Observar el nivel, el puntaje, las esferas y las posiciones de los personajes. | D23: Se reanuda el mismo nivel 1, con el puntaje conservado, las esferas consumidas ausentes y los personajes en sus posiciones iniciales.
A24: El caso se aprueba solo si se cumple todo el resultado esperado del último paso (en negrita); si cualquier parte no se cumple, se registra como Fallido.

Sheet CP-034
A1: Test Case ID | B1: CP-034 | C1: Descripción / Funcionalidad | D1: HU-09 · Ver la cantidad de vidas restantes | G1: Registro de ejecución
A2: Creado por | B2: Cruz, Luzzi | C2: Versión | D2: 1 | G2: Ciclo | H2: Fecha | I2: Ejecutor | J2: Estado | K2: Resultado obtenido | L2: Defecto
A3: Reporte de ejecución 1 | C3: Estado en la Entrega 1 | D3: =IF(INDEX('Reporte de ejecución - Entrega1'!$G$4:$G$69,MATCH($B$1,'Reporte de ejecución - Entrega1'!$A$4:$A$69,0))="","Sin ejecutar",INDEX('Reporte de ejecución - Entrega1'!$G$4:$G$69,MATCH($B$1,'Reporte de ejecución - Entrega1'!$A$4:$A$69,0))) -> Sin ejecutar | G3: Ciclo 1
G4: Ciclo 2
A5: Prioridad (Alta, Media, Baja) | B5: Media | C5: Técnica de diseño | D5: Partición de equivalencia | G5: Ciclo 3
G6: Estado del ciclo 1: cargarlo en la hoja del reporte; la celda «Estado en la Entrega 1» lo toma de ahí. Este registro es para el resultado obtenido y los reintentos.
A7: # | B7: Pre-requisitos | D7: Datos de prueba
A8: 1 | B8: Abrir la aplicación desplegada en un navegador de escritorio. | D8: Entorno: | E8: Aplicación desplegada en Vercel (URL en el Anexo C)
A9: 2 | B9: Iniciar una partida en modo Pacman. | D9: Navegador: | E9: Google Chrome de escritorio
A10: 3 | B10: Partida recién iniciada en modo Pacman. | D10: Modo de juego: | E10: Pacman
A12: Título del CP | B12: Presentación del contador de vidas
A15: Historias de Usuario | B15: HU-09 | C15: Épica | D15: E3 — Vidas, puntaje y fin de partida
A16: Estado Automatización | B16: No automatizado | C16: Camino feliz | D16: No
A18: Pasos # | B18: Detalle de pasos | D18: Resultado esperado
A19: 1 | B19: Observar el extremo inferior izquierdo de la pantalla. | D19: Se muestran 3 íconos de Pacman como contador de vidas, no un número.
A20: El caso se aprueba solo si se cumple todo el resultado esperado del último paso (en negrita); si cualquier parte no se cumple, se registra como Fallido.

Sheet CP-035
A1: Test Case ID | B1: CP-035 | C1: Descripción / Funcionalidad | D1: HU-09 · Ver la cantidad de vidas restantes | G1: Registro de ejecución
A2: Creado por | B2: Cruz, Luzzi | C2: Versión | D2: 1 | G2: Ciclo | H2: Fecha | I2: Ejecutor | J2: Estado | K2: Resultado obtenido | L2: Defecto
A3: Reporte de ejecución 1 | C3: Estado en la Entrega 1 | D3: =IF(INDEX('Reporte de ejecución - Entrega1'!$G$4:$G$69,MATCH($B$1,'Reporte de ejecución - Entrega1'!$A$4:$A$69,0))="","Sin ejecutar",INDEX('Reporte de ejecución - Entrega1'!$G$4:$G$69,MATCH($B$1,'Reporte de ejecución - Entrega1'!$A$4:$A$69,0))) -> Sin ejecutar | G3: Ciclo 1
G4: Ciclo 2
A5: Prioridad (Alta, Media, Baja) | B5: Media | C5: Técnica de diseño | D5: Valores límite | G5: Ciclo 3
G6: Estado del ciclo 1: cargarlo en la hoja del reporte; la celda «Estado en la Entrega 1» lo toma de ahí. Este registro es para el resultado obtenido y los reintentos.
A7: # | B7: Pre-requisitos | D7: Datos de prueba
A8: 1 | B8: Abrir la aplicación desplegada en un navegador de escritorio. | D8: Entorno: | E8: Aplicación desplegada en Vercel (URL en el Anexo C)
A9: 2 | B9: Iniciar una partida en modo Pacman. | D9: Navegador: | E9: Google Chrome de escritorio
A10: 3 | B10: Partida en curso (N1), 3 vidas. | D10: Modo de juego: | E10: Pacman
D11: Nivel inicial: | E11: 1
D12: Vidas iniciales: | E12: 3
D13: PowerUp: | E13: Inactivo
A15: Título del CP | B15: Actualización inmediata del contador de vidas
A18: Historias de Usuario | B18: HU-09 | C18: Épica | D18: E3 — Vidas, puntaje y fin de partida
A19: Estado Automatización | B19: No automatizado | C19: Camino feliz | D19: No
A21: Pasos # | B21: Detalle de pasos | D21: Resultado esperado
A22: 1 | B22: Perder una vida y observar el contador. | D22: El contador pasa de 3 a 2 íconos en el momento de la pérdida.
A23: 2 | B23: Perder una segunda vida y observar. | D23: El contador pasa de 2 a 1 ícono en el momento de la pérdida.
A24: 3 | B24: Perder la tercera y observar. | D24: El contador muestra 2 íconos, luego 1, y finalmente ninguno. La actualización ocurre en el momento de cada pérdida.
A25: El caso se aprueba solo si se cumple todo el resultado esperado del último paso (en negrita); si cualquier parte no se cumple, se registra como Fallido.

Sheet CP-036
A1: Test Case ID | B1: CP-036 | C1: Descripción / Funcionalidad | D1: HU-10 · Terminar la partida al agotar las vidas | G1: Registro de ejecución
A2: Creado por | B2: Cruz, Luzzi | C2: Versión | D2: 1 | G2: Ciclo | H2: Fecha | I2: Ejecutor | J2: Estado | K2: Resultado obtenido | L2: Defecto
A3: Reporte de ejecución 1 | C3: Estado en la Entrega 1 | D3: =IF(INDEX('Reporte de ejecución - Entrega1'!$G$4:$G$69,MATCH($B$1,'Reporte de ejecución - Entrega1'!$A$4:$A$69,0))="","Sin ejecutar",INDEX('Reporte de ejecución - Entrega1'!$G$4:$G$69,MATCH($B$1,'Reporte de ejecución - Entrega1'!$A$4:$A$69,0))) -> Sin ejecutar | G3: Ciclo 1
G4: Ciclo 2
A5: Prioridad (Alta, Media, Baja) | B5: Alta | C5: Técnica de diseño | D5: Valores límite | G5: Ciclo 3
G6: Estado del ciclo 1: cargarlo en la hoja del reporte; la celda «Estado en la Entrega 1» lo toma de ahí. Este registro es para el resultado obtenido y los reintentos.
A7: # | B7: Pre-requisitos | D7: Datos de prueba
A8: 1 | B8: Abrir la aplicación desplegada en un navegador de escritorio. | D8: Entorno: | E8: Aplicación desplegada en Vercel (URL en el Anexo C)
A9: 2 | B9: Iniciar una partida en modo Pacman. | D9: Navegador: | E9: Google Chrome de escritorio
A10: 3 | B10: Partida en curso (N1), 1 vida restante. | D10: Modo de juego: | E10: Pacman
D11: Nivel inicial: | E11: 1
D12: Vidas iniciales: | E12: 3
D13: PowerUp: | E13: Inactivo
A15: Título del CP | B15: Game Over al perder la tercera vida
A18: Historias de Usuario | B18: HU-10 | C18: Épica | D18: E3 — Vidas, puntaje y fin de partida
A19: Estado Automatización | B19: No automatizado | C19: Camino feliz | D19: Sí
A21: Pasos # | B21: Detalle de pasos | D21: Resultado esperado
A22: 1 | B22: Perder la última vida. | D22: El contador de vidas queda sin íconos.
A23: 2 | B23: Observar la pantalla y esperar 5 segundos. | D23: La partida termina, se muestra la pantalla de Game Over con el puntaje final, y el nivel no se reinicia ni se reanuda.
A24: El caso se aprueba solo si se cumple todo el resultado esperado del último paso (en negrita); si cualquier parte no se cumple, se registra como Fallido.

Sheet CP-037
A1: Test Case ID | B1: CP-037 | C1: Descripción / Funcionalidad | D1: HU-10 · Terminar la partida al agotar las vidas | G1: Registro de ejecución
A2: Creado por | B2: Cruz, Luzzi | C2: Versión | D2: 1 | G2: Ciclo | H2: Fecha | I2: Ejecutor | J2: Estado | K2: Resultado obtenido | L2: Defecto
A3: Reporte de ejecución 1 | C3: Estado en la Entrega 1 | D3: =IF(INDEX('Reporte de ejecución - Entrega1'!$G$4:$G$69,MATCH($B$1,'Reporte de ejecución - Entrega1'!$A$4:$A$69,0))="","Sin ejecutar",INDEX('Reporte de ejecución - Entrega1'!$G$4:$G$69,MATCH($B$1,'Reporte de ejecución - Entrega1'!$A$4:$A$69,0))) -> Sin ejecutar | G3: Ciclo 1
G4: Ciclo 2
A5: Prioridad (Alta, Media, Baja) | B5: Media | C5: Técnica de diseño | D5: Partición de equivalencia | G5: Ciclo 3
G6: Estado del ciclo 1: cargarlo en la hoja del reporte; la celda «Estado en la Entrega 1» lo toma de ahí. Este registro es para el resultado obtenido y los reintentos.
A7: # | B7: Pre-requisitos | D7: Datos de prueba
A8: 1 | B8: Abrir la aplicación desplegada en un navegador de escritorio. | D8: Entorno: | E8: Aplicación desplegada en Vercel (URL en el Anexo C)
A9: 2 | B9: Iniciar una partida en modo Pacman. | D9: Navegador: | E9: Google Chrome de escritorio
A10: 3 | B10: Partida en curso en el nivel 3, 1 vida restante. | D10: Modo de juego: | E10: Pacman
D11: Nivel: | E11: 3
A13: Título del CP | B13: Game Over en un nivel distinto del primero
A16: Historias de Usuario | B16: HU-10 | C16: Épica | D16: E3 — Vidas, puntaje y fin de partida
A17: Estado Automatización | B17: No automatizado | C17: Camino feliz | D17: No
A19: Pasos # | B19: Detalle de pasos | D19: Resultado esperado
A20: 1 | B20: Perder la última vida. | D20: La partida termina con Game Over en el nivel 3, con el mismo comportamiento que en el nivel 1.
A21: El caso se aprueba solo si se cumple todo el resultado esperado del último paso (en negrita); si cualquier parte no se cumple, se registra como Fallido.

Sheet CP-038
A1: Test Case ID | B1: CP-038 | C1: Descripción / Funcionalidad | D1: HU-11 · Ver el puntaje durante la partida | G1: Registro de ejecución
A2: Creado por | B2: Cruz, Luzzi | C2: Versión | D2: 1 | G2: Ciclo | H2: Fecha | I2: Ejecutor | J2: Estado | K2: Resultado obtenido | L2: Defecto
A3: Reporte de ejecución 1 | C3: Estado en la Entrega 1 | D3: =IF(INDEX('Reporte de ejecución - Entrega1'!$G$4:$G$69,MATCH($B$1,'Reporte de ejecución - Entrega1'!$A$4:$A$69,0))="","Sin ejecutar",INDEX('Reporte de ejecución - Entrega1'!$G$4:$G$69,MATCH($B$1,'Reporte de ejecución - Entrega1'!$A$4:$A$69,0))) -> Sin ejecutar | G3: Ciclo 1
G4: Ciclo 2
A5: Prioridad (Alta, Media, Baja) | B5: Media | C5: Técnica de diseño | D5: Partición de equivalencia | G5: Ciclo 3
G6: Estado del ciclo 1: cargarlo en la hoja del reporte; la celda «Estado en la Entrega 1» lo toma de ahí. Este registro es para el resultado obtenido y los reintentos.
A7: # | B7: Pre-requisitos | D7: Datos de prueba
A8: 1 | B8: Abrir la aplicación desplegada en un navegador de escritorio. | D8: Entorno: | E8: Aplicación desplegada en Vercel (URL en el Anexo C)
A9: 2 | B9: Iniciar una partida en modo Pacman. | D9: Navegador: | E9: Google Chrome de escritorio
A10: 3 | B10: Partida recién iniciada en modo Pacman. | D10: Modo de juego: | E10: Pacman
A12: Título del CP | B12: Puntaje visible y actualizado en el HUD
A15: Historias de Usuario | B15: HU-11 | C15: Épica | D15: E3 — Vidas, puntaje y fin de partida
A16: Estado Automatización | B16: No automatizado | C16: Camino feliz | D16: Sí
A18: Pasos # | B18: Detalle de pasos | D18: Resultado esperado
A19: 1 | B19: Verificar el puntaje inicial. | D19: El HUD muestra puntaje 0.
A20: 2 | B20: Consumir una esfera común, una esfera grande y un fantasma con el PowerUp activo, observando el HUD después de cada acción. | D20: El puntaje inicia en 0 y se actualiza de manera inmediata tras cada acción, en +10, +50 y +200 respectivamente.
A21: El caso se aprueba solo si se cumple todo el resultado esperado del último paso (en negrita); si cualquier parte no se cumple, se registra como Fallido.

Sheet CP-039
A1: Test Case ID | B1: CP-039 | C1: Descripción / Funcionalidad | D1: HU-11 · Ver el puntaje durante la partida | G1: Registro de ejecución
A2: Creado por | B2: Cruz, Luzzi | C2: Versión | D2: 1 | G2: Ciclo | H2: Fecha | I2: Ejecutor | J2: Estado | K2: Resultado obtenido | L2: Defecto
A3: Reporte de ejecución 1 | C3: Estado en la Entrega 1 | D3: =IF(INDEX('Reporte de ejecución - Entrega1'!$G$4:$G$69,MATCH($B$1,'Reporte de ejecución - Entrega1'!$A$4:$A$69,0))="","Sin ejecutar",INDEX('Reporte de ejecución - Entrega1'!$G$4:$G$69,MATCH($B$1,'Reporte de ejecución - Entrega1'!$A$4:$A$69,0))) -> Sin ejecutar | G3: Ciclo 1
G4: Ciclo 2
A5: Prioridad (Alta, Media, Baja) | B5: Media | C5: Técnica de diseño | D5: Adivinación de errores | G5: Ciclo 3
G6: Estado del ciclo 1: cargarlo en la hoja del reporte; la celda «Estado en la Entrega 1» lo toma de ahí. Este registro es para el resultado obtenido y los reintentos.
A7: # | B7: Pre-requisitos | D7: Datos de prueba
A8: 1 | B8: Abrir la aplicación desplegada en un navegador de escritorio. | D8: Entorno: | E8: Aplicación desplegada en Vercel (URL en el Anexo C)
A9: 2 | B9: Iniciar una partida en modo Pacman. | D9: Navegador: | E9: Google Chrome de escritorio
A10: 3 | B10: Partida en curso (N1) con puntaje mayor a 0. | D10: Modo de juego: | E10: Pacman
D11: Nivel inicial: | E11: 1
D12: Vidas iniciales: | E12: 3
D13: PowerUp: | E13: Inactivo
A15: Título del CP | B15: El puntaje no disminuye ni se reinicia entre niveles
A18: Historias de Usuario | B18: HU-11 | C18: Épica | D18: E3 — Vidas, puntaje y fin de partida
A19: Estado Automatización | B19: No automatizado | C19: Camino feliz | D19: No
A21: Pasos # | B21: Detalle de pasos | D21: Resultado esperado
A22: 1 | B22: Registrar el puntaje. | D22: Puntaje anotado como valor de referencia.
A23: 2 | B23: Perder una vida y registrar. | D23: El puntaje es igual al anotado en el paso anterior.
A24: 3 | B24: Completar el nivel y registrar al inicio del nivel 2. | D24: El puntaje no disminuye en ningún momento y se conserva al cambiar de nivel.
A25: El caso se aprueba solo si se cumple todo el resultado esperado del último paso (en negrita); si cualquier parte no se cumple, se registra como Fallido.

Sheet CP-040
A1: Test Case ID | B1: CP-040 | C1: Descripción / Funcionalidad | D1: HU-12 · Sumar puntos por las frutas | G1: Registro de ejecución
A2: Creado por | B2: Cruz, Luzzi | C2: Versión | D2: 1 | G2: Ciclo | H2: Fecha | I2: Ejecutor | J2: Estado | K2: Resultado obtenido | L2: Defecto
A3: Reporte de ejecución 1 | C3: Estado en la Entrega 1 | D3: =IF(INDEX('Reporte de ejecución - Entrega1'!$G$4:$G$69,MATCH($B$1,'Reporte de ejecución - Entrega1'!$A$4:$A$69,0))="","Sin ejecutar",INDEX('Reporte de ejecución - Entrega1'!$G$4:$G$69,MATCH($B$1,'Reporte de ejecución - Entrega1'!$A$4:$A$69,0))) -> Sin ejecutar | G3: Ciclo 1
G4: Ciclo 2
A5: Prioridad (Alta, Media, Baja) | B5: Media | C5: Técnica de diseño | D5: Partición de equivalencia | G5: Ciclo 3
G6: Estado del ciclo 1: cargarlo en la hoja del reporte; la celda «Estado en la Entrega 1» lo toma de ahí. Este registro es para el resultado obtenido y los reintentos.
A7: # | B7: Pre-requisitos | D7: Datos de prueba
A8: 1 | B8: Abrir la aplicación desplegada en un navegador de escritorio. | D8: Entorno: | E8: Aplicación desplegada en Vercel (URL en el Anexo C)
A9: 2 | B9: Iniciar una partida en modo Pacman. | D9: Navegador: | E9: Google Chrome de escritorio
A10: 3 | B10: Partida en curso en el nivel 3, con una fruta presente en el mapa. | D10: Modo de juego: | E10: Pacman
D11: Nivel: | E11: 3
A13: Título del CP | B13: Consumo de una fruta
A16: Historias de Usuario | B16: HU-12 | C16: Épica | D16: E3 — Vidas, puntaje y fin de partida
A17: Estado Automatización | B17: No automatizado | C17: Camino feliz | D17: Sí
A19: Pasos # | B19: Detalle de pasos | D19: Resultado esperado
A20: 1 | B20: Registrar el puntaje y el contador de esferas restantes. | D20: Puntaje y contador de esferas anotados como valores de referencia.
A21: 2 | B21: Consumir la fruta. | D21: La fruta desaparece del mapa.
A22: 3 | B22: Registrar ambos valores. | D22: La fruta desaparece, el puntaje aumenta exactamente 100 y el contador de esferas restantes no cambia.
A23: El caso se aprueba solo si se cumple todo el resultado esperado del último paso (en negrita); si cualquier parte no se cumple, se registra como Fallido.

Sheet CP-041
A1: Test Case ID | B1: CP-041 | C1: Descripción / Funcionalidad | D1: HU-12 · Sumar puntos por las frutas | G1: Registro de ejecución
A2: Creado por | B2: Cruz, Luzzi | C2: Versión | D2: 1 | G2: Ciclo | H2: Fecha | I2: Ejecutor | J2: Estado | K2: Resultado obtenido | L2: Defecto
A3: Reporte de ejecución 1 | C3: Estado en la Entrega 1 | D3: =IF(INDEX('Reporte de ejecución - Entrega1'!$G$4:$G$69,MATCH($B$1,'Reporte de ejecución - Entrega1'!$A$4:$A$69,0))="","Sin ejecutar",INDEX('Reporte de ejecución - Entrega1'!$G$4:$G$69,MATCH($B$1,'Reporte de ejecución - Entrega1'!$A$4:$A$69,0))) -> Sin ejecutar | G3: Ciclo 1
G4: Ciclo 2
A5: Prioridad (Alta, Media, Baja) | B5: Baja | C5: Técnica de diseño | D5: Valores límite | G5: Ciclo 3
G6: Estado del ciclo 1: cargarlo en la hoja del reporte; la celda «Estado en la Entrega 1» lo toma de ahí. Este registro es para el resultado obtenido y los reintentos.
A7: # | B7: Pre-requisitos | D7: Datos de prueba
A8: 1 | B8: Abrir la aplicación desplegada en un navegador de escritorio. | D8: Entorno: | E8: Aplicación desplegada en Vercel (URL en el Anexo C)
A9: 2 | B9: Iniciar una partida en modo Pacman. | D9: Navegador: | E9: Google Chrome de escritorio
A10: 3 | B10: Partida en curso en el nivel 3, con una fruta que acaba de aparecer. | D10: Modo de juego: | E10: Pacman
D11: Nivel: | E11: 3
A13: Título del CP | B13: Desaparición de una fruta no consumida
A16: Historias de Usuario | B16: HU-12 | C16: Épica | D16: E3 — Vidas, puntaje y fin de partida
A17: Estado Automatización | B17: No automatizado | C17: Camino feliz | D17: No
A19: Pasos # | B19: Detalle de pasos | D19: Resultado esperado
A20: 1 | B20: Cronometrar desde la aparición de la fruta sin consumirla. | D20: Cronómetro iniciado en el instante en que aparece la fruta.
A21: 2 | B21: Observar el mapa a los 14 segundos y a los 16 segundos. | D21: A los 14 segundos la fruta sigue en el mapa; a los 16 segundos ya no está.
A22: El caso se aprueba solo si se cumple todo el resultado esperado del último paso (en negrita); si cualquier parte no se cumple, se registra como Fallido.

Sheet CP-042
A1: Test Case ID | B1: CP-042 | C1: Descripción / Funcionalidad | D1: HU-13 · Conocer el puntaje final desglosado | G1: Registro de ejecución
A2: Creado por | B2: Cruz, Luzzi | C2: Versión | D2: 1 | G2: Ciclo | H2: Fecha | I2: Ejecutor | J2: Estado | K2: Resultado obtenido | L2: Defecto
A3: Reporte de ejecución 1 | C3: Estado en la Entrega 1 | D3: =IF(INDEX('Reporte de ejecución - Entrega1'!$G$4:$G$69,MATCH($B$1,'Reporte de ejecución - Entrega1'!$A$4:$A$69,0))="","Sin ejecutar",INDEX('Reporte de ejecución - Entrega1'!$G$4:$G$69,MATCH($B$1,'Reporte de ejecución - Entrega1'!$A$4:$A$69,0))) -> Sin ejecutar | G3: Ciclo 1
G4: Ciclo 2
A5: Prioridad (Alta, Media, Baja) | B5: Media | C5: Técnica de diseño | D5: Valores límite | G5: Ciclo 3
G6: Estado del ciclo 1: cargarlo en la hoja del reporte; la celda «Estado en la Entrega 1» lo toma de ahí. Este registro es para el resultado obtenido y los reintentos.
A7: # | B7: Pre-requisitos | D7: Datos de prueba
A8: 1 | B8: Abrir la aplicación desplegada en un navegador de escritorio. | D8: Entorno: | E8: Aplicación desplegada en Vercel (URL en el Anexo C)
A9: 2 | B9: Iniciar una partida en modo Pacman. | D9: Navegador: | E9: Google Chrome de escritorio
A10: 3 | B10: Partida en curso (N1). | D10: Modo de juego: | E10: Pacman
D11: Nivel inicial: | E11: 1
D12: Vidas iniciales: | E12: 3
D13: PowerUp: | E13: Inactivo
A15: Título del CP | B15: Cálculo del bonus por tiempo
A18: Historias de Usuario | B18: HU-13 | C18: Épica | D18: E3 — Vidas, puntaje y fin de partida
A19: Estado Automatización | B19: No automatizado | C19: Camino feliz | D19: No
A21: Pasos # | B21: Detalle de pasos | D21: Resultado esperado
A22: 1 | B22: Completar el nivel 1 en menos de 120 segundos, registrando el tiempo empleado. | D22: Nivel completado y tiempo empleado anotado.
A23: 2 | B23: Verificar el bonus por tiempo en el desglose. | D23: El bonus por tiempo es igual a 10 multiplicado por los segundos **enteros** restantes respecto de los 120 segundos objetivo, descartando la fracción. Por ejemplo, un tiempo de 100,5 s deja 19 s y da un bonus de 190 (sección 4.2).
A24: El caso se aprueba solo si se cumple todo el resultado esperado del último paso (en negrita); si cualquier parte no se cumple, se registra como Fallido.

Sheet CP-043
A1: Test Case ID | B1: CP-043 | C1: Descripción / Funcionalidad | D1: HU-13 · Conocer el puntaje final desglosado | G1: Registro de ejecución
A2: Creado por | B2: Cruz, Luzzi | C2: Versión | D2: 1 | G2: Ciclo | H2: Fecha | I2: Ejecutor | J2: Estado | K2: Resultado obtenido | L2: Defecto
A3: Reporte de ejecución 1 | C3: Estado en la Entrega 1 | D3: =IF(INDEX('Reporte de ejecución - Entrega1'!$G$4:$G$69,MATCH($B$1,'Reporte de ejecución - Entrega1'!$A$4:$A$69,0))="","Sin ejecutar",INDEX('Reporte de ejecución - Entrega1'!$G$4:$G$69,MATCH($B$1,'Reporte de ejecución - Entrega1'!$A$4:$A$69,0))) -> Sin ejecutar | G3: Ciclo 1
G4: Ciclo 2
A5: Prioridad (Alta, Media, Baja) | B5: Media | C5: Técnica de diseño | D5: Valores límite | G5: Ciclo 3
G6: Estado del ciclo 1: cargarlo en la hoja del reporte; la celda «Estado en la Entrega 1» lo toma de ahí. Este registro es para el resultado obtenido y los reintentos.
A7: # | B7: Pre-requisitos | D7: Datos de prueba
A8: 1 | B8: Abrir la aplicación desplegada en un navegador de escritorio. | D8: Entorno: | E8: Aplicación desplegada en Vercel (URL en el Anexo C)
A9: 2 | B9: Iniciar una partida en modo Pacman. | D9: Navegador: | E9: Google Chrome de escritorio
A10: 3 | B10: Partida en curso (N1). | D10: Modo de juego: | E10: Pacman
D11: Nivel inicial: | E11: 1
D12: Vidas iniciales: | E12: 3
D13: PowerUp: | E13: Inactivo
A15: Título del CP | B15: Bonus por tiempo al exceder el tiempo objetivo
A18: Historias de Usuario | B18: HU-13 | C18: Épica | D18: E3 — Vidas, puntaje y fin de partida
A19: Estado Automatización | B19: No automatizado | C19: Camino feliz | D19: No
A21: Pasos # | B21: Detalle de pasos | D21: Resultado esperado
A22: 1 | B22: Completar el nivel 1 en más de 120 segundos. | D22: Nivel completado después de los 120 segundos.
A23: 2 | B23: Verificar el bonus por tiempo. | D23: El bonus por tiempo es 0 y en ningún caso un valor negativo.
A24: El caso se aprueba solo si se cumple todo el resultado esperado del último paso (en negrita); si cualquier parte no se cumple, se registra como Fallido.

Sheet CP-044
A1: Test Case ID | B1: CP-044 | C1: Descripción / Funcionalidad | D1: HU-13 · Conocer el puntaje final desglosado | G1: Registro de ejecución
A2: Creado por | B2: Cruz, Luzzi | C2: Versión | D2: 1 | G2: Ciclo | H2: Fecha | I2: Ejecutor | J2: Estado | K2: Resultado obtenido | L2: Defecto
A3: Reporte de ejecución 1 | C3: Estado en la Entrega 1 | D3: =IF(INDEX('Reporte de ejecución - Entrega1'!$G$4:$G$69,MATCH($B$1,'Reporte de ejecución - Entrega1'!$A$4:$A$69,0))="","Sin ejecutar",INDEX('Reporte de ejecución - Entrega1'!$G$4:$G$69,MATCH($B$1,'Reporte de ejecución - Entrega1'!$A$4:$A$69,0))) -> Sin ejecutar | G3: Ciclo 1
G4: Ciclo 2
A5: Prioridad (Alta, Media, Baja) | B5: Media | C5: Técnica de diseño | D5: Valores límite | G5: Ciclo 3
G6: Estado del ciclo 1: cargarlo en la hoja del reporte; la celda «Estado en la Entrega 1» lo toma de ahí. Este registro es para el resultado obtenido y los reintentos.
A7: # | B7: Pre-requisitos | D7: Datos de prueba
A8: 1 | B8: Abrir la aplicación desplegada en un navegador de escritorio. | D8: Entorno: | E8: Aplicación desplegada en Vercel (URL en el Anexo C)
A9: 2 | B9: Iniciar una partida en modo Pacman. | D9: Navegador: | E9: Google Chrome de escritorio
A10: 3 | B10: Partida completada en victoria con 2 vidas restantes. | D10: Modo de juego: | E10: Pacman
A12: Título del CP | B12: Bonus por vidas restantes y consistencia del desglose
A15: Historias de Usuario | B15: HU-13 | C15: Épica | D15: E3 — Vidas, puntaje y fin de partida
A16: Estado Automatización | B16: No automatizado | C16: Camino feliz | D16: No
A18: Pasos # | B18: Detalle de pasos | D18: Resultado esperado
A19: 1 | B19: Registrar cada componente del desglose y el total. | D19: Componentes del desglose y total anotados.
A20: 2 | B20: Sumar los componentes manualmente. | D20: El bonus por vidas es de 1000 puntos (500 por cada una de las 2 vidas) y la suma de todos los componentes coincide exactamente con el total mostrado.
A21: El caso se aprueba solo si se cumple todo el resultado esperado del último paso (en negrita); si cualquier parte no se cumple, se registra como Fallido.

Sheet CP-045
A1: Test Case ID | B1: CP-045 | C1: Descripción / Funcionalidad | D1: HU-13 · Conocer el puntaje final desglosado | G1: Registro de ejecución
A2: Creado por | B2: Cruz, Luzzi | C2: Versión | D2: 1 | G2: Ciclo | H2: Fecha | I2: Ejecutor | J2: Estado | K2: Resultado obtenido | L2: Defecto
A3: Reporte de ejecución 1 | C3: Estado en la Entrega 1 | D3: =IF(INDEX('Reporte de ejecución - Entrega1'!$G$4:$G$69,MATCH($B$1,'Reporte de ejecución - Entrega1'!$A$4:$A$69,0))="","Sin ejecutar",INDEX('Reporte de ejecución - Entrega1'!$G$4:$G$69,MATCH($B$1,'Reporte de ejecución - Entrega1'!$A$4:$A$69,0))) -> Sin ejecutar | G3: Ciclo 1
G4: Ciclo 2
A5: Prioridad (Alta, Media, Baja) | B5: Media | C5: Técnica de diseño | D5: Valores límite | G5: Ciclo 3
G6: Estado del ciclo 1: cargarlo en la hoja del reporte; la celda «Estado en la Entrega 1» lo toma de ahí. Este registro es para el resultado obtenido y los reintentos.
A7: # | B7: Pre-requisitos | D7: Datos de prueba
A8: 1 | B8: Abrir la aplicación desplegada en un navegador de escritorio. | D8: Entorno: | E8: Aplicación desplegada en Vercel (URL en el Anexo C)
A9: 2 | B9: Iniciar una partida en modo Pacman. | D9: Navegador: | E9: Google Chrome de escritorio
A10: 3 | B10: Partida terminada en Game Over. | D10: Modo de juego: | E10: Pacman
A12: Título del CP | B12: Bonus por vidas en un Game Over
A15: Historias de Usuario | B15: HU-13 | C15: Épica | D15: E3 — Vidas, puntaje y fin de partida
A16: Estado Automatización | B16: No automatizado | C16: Camino feliz | D16: No
A18: Pasos # | B18: Detalle de pasos | D18: Resultado esperado
A19: 1 | B19: Verificar el bonus por vidas restantes en el desglose. | D19: El bonus por vidas restantes es 0.
A20: El caso se aprueba solo si se cumple todo el resultado esperado del último paso (en negrita); si cualquier parte no se cumple, se registra como Fallido.

Sheet CP-046
A1: Test Case ID | B1: CP-046 | C1: Descripción / Funcionalidad | D1: HU-14 · Ver el progreso de esferas del nivel | G1: Registro de ejecución
A2: Creado por | B2: Cruz, Luzzi | C2: Versión | D2: 1 | G2: Ciclo | H2: Fecha | I2: Ejecutor | J2: Estado | K2: Resultado obtenido | L2: Defecto
A3: Reporte de ejecución 1 | C3: Estado en la Entrega 1 | D3: =IF(INDEX('Reporte de ejecución - Entrega1'!$G$4:$G$69,MATCH($B$1,'Reporte de ejecución - Entrega1'!$A$4:$A$69,0))="","Sin ejecutar",INDEX('Reporte de ejecución - Entrega1'!$G$4:$G$69,MATCH($B$1,'Reporte de ejecución - Entrega1'!$A$4:$A$69,0))) -> Sin ejecutar | G3: Ciclo 1
G4: Ciclo 2
A5: Prioridad (Alta, Media, Baja) | B5: Baja | C5: Técnica de diseño | D5: Valores límite | G5: Ciclo 3
G6: Estado del ciclo 1: cargarlo en la hoja del reporte; la celda «Estado en la Entrega 1» lo toma de ahí. Este registro es para el resultado obtenido y los reintentos.
A7: # | B7: Pre-requisitos | D7: Datos de prueba
A8: 1 | B8: Abrir la aplicación desplegada en un navegador de escritorio. | D8: Entorno: | E8: Aplicación desplegada en Vercel (URL en el Anexo C)
A9: 2 | B9: Iniciar una partida en modo Pacman. | D9: Navegador: | E9: Google Chrome de escritorio
A10: 3 | B10: Partida recién iniciada en modo Pacman. | D10: Modo de juego: | E10: Pacman
A12: Título del CP | B12: Contador de esferas restantes
A15: Historias de Usuario | B15: HU-14 | C15: Épica | D15: E3 — Vidas, puntaje y fin de partida
A16: Estado Automatización | B16: No automatizado | C16: Camino feliz | D16: No
A18: Pasos # | B18: Detalle de pasos | D18: Resultado esperado
A19: 1 | B19: Registrar el valor inicial del contador y contar las esferas del mapa, incluidas las grandes. | D19: El valor inicial coincide con el total de esferas contadas, incluidas las grandes.
A20: 2 | B20: Consumir 5 esferas y verificar el contador. | D20: El contador disminuyó exactamente 5.
A21: 3 | B21: Completar el nivel y verificar el contador al llegar a la última esfera. | D21: El contador llega a 0 al consumir la última esfera.
A22: 4 | B22: Verificar el contador al iniciar el nivel 2. | D22: El valor inicial coincide con el total de esferas del mapa incluidas las grandes, disminuye en 1 por esfera consumida, llega a 0 exactamente al completarse el nivel, y se reinicia al total del nivel 2.
A23: El caso se aprueba solo si se cumple todo el resultado esperado del último paso (en negrita); si cualquier parte no se cumple, se registra como Fallido.

Sheet CP-047
A1: Test Case ID | B1: CP-047 | C1: Descripción / Funcionalidad | D1: HU-15 · Jugar tres niveles con mapas propios | G1: Registro de ejecución
A2: Creado por | B2: Cruz, Luzzi | C2: Versión | D2: 1 | G2: Ciclo | H2: Fecha | I2: Ejecutor | J2: Estado | K2: Resultado obtenido | L2: Defecto
A3: Reporte de ejecución 1 | C3: Estado en la Entrega 1 | D3: =IF(INDEX('Reporte de ejecución - Entrega1'!$G$4:$G$69,MATCH($B$1,'Reporte de ejecución - Entrega1'!$A$4:$A$69,0))="","Sin ejecutar",INDEX('Reporte de ejecución - Entrega1'!$G$4:$G$69,MATCH($B$1,'Reporte de ejecución - Entrega1'!$A$4:$A$69,0))) -> Sin ejecutar | G3: Ciclo 1
G4: Ciclo 2
A5: Prioridad (Alta, Media, Baja) | B5: Alta | C5: Técnica de diseño | D5: Partición de equivalencia | G5: Ciclo 3
G6: Estado del ciclo 1: cargarlo en la hoja del reporte; la celda «Estado en la Entrega 1» lo toma de ahí. Este registro es para el resultado obtenido y los reintentos.
A7: # | B7: Pre-requisitos | D7: Datos de prueba
A8: 1 | B8: Abrir la aplicación desplegada en un navegador de escritorio. | D8: Entorno: | E8: Aplicación desplegada en Vercel (URL en el Anexo C)
A9: 2 | B9: Iniciar una partida en modo Pacman. | D9: Navegador: | E9: Google Chrome de escritorio
A10: 3 | B10: Ninguna. | D10: Modo de juego: | E10: Pacman
A12: Título del CP | B12: Los tres niveles y sus mapas
A15: Historias de Usuario | B15: HU-15 | C15: Épica | D15: E4 — Niveles y progresión de dificultad
A16: Estado Automatización | B16: No automatizado | C16: Camino feliz | D16: Sí
A18: Pasos # | B18: Detalle de pasos | D18: Resultado esperado
A19: 1 | B19: Jugar una partida completando los tres niveles. | D19: La partida recorre los niveles 1, 2 y 3 en ese orden.
A20: 2 | B20: Registrar la forma y la paleta de cada mapa, y el número de nivel del HUD. | D20: Los niveles se juegan en orden 1, 2, 3; cada mapa tiene forma propia distinta de la de los otros dos; el nivel 1 es negro con franjas rojas y contorno celeste, el 2 azul sobre negro con contorno azul y sin franjas, el 3 verde brillante; los caminos están marcados con puntos blancos en los tres; el HUD indica el nivel en curso.
A21: El caso se aprueba solo si se cumple todo el resultado esperado del último paso (en negrita); si cualquier parte no se cumple, se registra como Fallido.

Sheet CP-048
A1: Test Case ID | B1: CP-048 | C1: Descripción / Funcionalidad | D1: HU-15 · Jugar tres niveles con mapas propios | G1: Registro de ejecución
A2: Creado por | B2: Cruz, Luzzi | C2: Versión | D2: 1 | G2: Ciclo | H2: Fecha | I2: Ejecutor | J2: Estado | K2: Resultado obtenido | L2: Defecto
A3: Reporte de ejecución 1 | C3: Estado en la Entrega 1 | D3: =IF(INDEX('Reporte de ejecución - Entrega1'!$G$4:$G$69,MATCH($B$1,'Reporte de ejecución - Entrega1'!$A$4:$A$69,0))="","Sin ejecutar",INDEX('Reporte de ejecución - Entrega1'!$G$4:$G$69,MATCH($B$1,'Reporte de ejecución - Entrega1'!$A$4:$A$69,0))) -> Sin ejecutar | G3: Ciclo 1
G4: Ciclo 2
A5: Prioridad (Alta, Media, Baja) | B5: Media | C5: Técnica de diseño | D5: Adivinación de errores | G5: Ciclo 3
G6: Estado del ciclo 1: cargarlo en la hoja del reporte; la celda «Estado en la Entrega 1» lo toma de ahí. Este registro es para el resultado obtenido y los reintentos.
A7: # | B7: Pre-requisitos | D7: Datos de prueba
A8: 1 | B8: Abrir la aplicación desplegada en un navegador de escritorio. | D8: Entorno: | E8: Aplicación desplegada en Vercel (URL en el Anexo C)
A9: 2 | B9: Iniciar una partida en modo Pacman. | D9: Navegador: | E9: Google Chrome de escritorio
A10: 3 | B10: Una partida jugada, con el mapa del nivel 1 registrado. | D10: Modo de juego: | E10: Pacman
D11: Nivel: | E11: 1
A13: Título del CP | B13: Los mapas no varían entre partidas
A16: Historias de Usuario | B16: HU-15 | C16: Épica | D16: E4 — Niveles y progresión de dificultad
A17: Estado Automatización | B17: No automatizado | C17: Camino feliz | D17: No
A19: Pasos # | B19: Detalle de pasos | D19: Resultado esperado
A20: 1 | B20: Iniciar una partida nueva. | D20: Se inicia una partida nueva en el nivel 1.
A21: 2 | B21: Comparar el mapa del nivel 1 con el registrado. | D21: El mapa del nivel 1 es idéntico al de la partida anterior, en forma, distribución de esferas y ubicación de las esferas grandes.
A22: El caso se aprueba solo si se cumple todo el resultado esperado del último paso (en negrita); si cualquier parte no se cumple, se registra como Fallido.

Sheet CP-049
A1: Test Case ID | B1: CP-049 | C1: Descripción / Funcionalidad | D1: HU-16 · Enfrentar solo fantasmas clásicos en el nivel 1 | G1: Registro de ejecución
A2: Creado por | B2: Cruz, Luzzi | C2: Versión | D2: 1 | G2: Ciclo | H2: Fecha | I2: Ejecutor | J2: Estado | K2: Resultado obtenido | L2: Defecto
A3: Reporte de ejecución 1 | C3: Estado en la Entrega 1 | D3: =IF(INDEX('Reporte de ejecución - Entrega1'!$G$4:$G$69,MATCH($B$1,'Reporte de ejecución - Entrega1'!$A$4:$A$69,0))="","Sin ejecutar",INDEX('Reporte de ejecución - Entrega1'!$G$4:$G$69,MATCH($B$1,'Reporte de ejecución - Entrega1'!$A$4:$A$69,0))) -> Sin ejecutar | G3: Ciclo 1
G4: Ciclo 2
A5: Prioridad (Alta, Media, Baja) | B5: Alta | C5: Técnica de diseño | D5: Partición de equivalencia | G5: Ciclo 3
G6: Estado del ciclo 1: cargarlo en la hoja del reporte; la celda «Estado en la Entrega 1» lo toma de ahí. Este registro es para el resultado obtenido y los reintentos.
A7: # | B7: Pre-requisitos | D7: Datos de prueba
A8: 1 | B8: Abrir la aplicación desplegada en un navegador de escritorio. | D8: Entorno: | E8: Aplicación desplegada en Vercel (URL en el Anexo C)
A9: 2 | B9: Iniciar una partida en modo Pacman. | D9: Navegador: | E9: Google Chrome de escritorio
A10: 3 | B10: Partida en curso (N1). | D10: Modo de juego: | E10: Pacman
D11: Nivel inicial: | E11: 1
D12: Vidas iniciales: | E12: 3
D13: PowerUp: | E13: Inactivo
A15: Título del CP | B15: Solo fantasmas clásicos en el nivel 1
A18: Historias de Usuario | B18: HU-16 | C18: Épica | D18: E4 — Niveles y progresión de dificultad
A19: Estado Automatización | B19: No automatizado | C19: Camino feliz | D19: No
A21: Pasos # | B21: Detalle de pasos | D21: Resultado esperado
A22: 1 | B22: Observar los cuatro fantasmas durante todo el nivel 1. | D22: Durante el nivel 1 se observan los cuatro fantasmas.
A23: 2 | B23: Comparar sus velocidades de desplazamiento. | D23: Los cuatro fantasmas son clásicos, ninguno atraviesa muros, se teletransporta, coloca frutas falsas ni ejecuta un dash, y los cuatro se desplazan a la misma velocidad.
A24: El caso se aprueba solo si se cumple todo el resultado esperado del último paso (en negrita); si cualquier parte no se cumple, se registra como Fallido.

Sheet CP-050
A1: Test Case ID | B1: CP-050 | C1: Descripción / Funcionalidad | D1: HU-16 · Enfrentar solo fantasmas clásicos en el nivel 1 | G1: Registro de ejecución
A2: Creado por | B2: Cruz, Luzzi | C2: Versión | D2: 1 | G2: Ciclo | H2: Fecha | I2: Ejecutor | J2: Estado | K2: Resultado obtenido | L2: Defecto
A3: Reporte de ejecución 1 | C3: Estado en la Entrega 1 | D3: =IF(INDEX('Reporte de ejecución - Entrega1'!$G$4:$G$69,MATCH($B$1,'Reporte de ejecución - Entrega1'!$A$4:$A$69,0))="","Sin ejecutar",INDEX('Reporte de ejecución - Entrega1'!$G$4:$G$69,MATCH($B$1,'Reporte de ejecución - Entrega1'!$A$4:$A$69,0))) -> Sin ejecutar | G3: Ciclo 1
G4: Ciclo 2
A5: Prioridad (Alta, Media, Baja) | B5: Alta | C5: Técnica de diseño | D5: Partición de equivalencia | G5: Ciclo 3
G6: Estado del ciclo 1: cargarlo en la hoja del reporte; la celda «Estado en la Entrega 1» lo toma de ahí. Este registro es para el resultado obtenido y los reintentos.
A7: # | B7: Pre-requisitos | D7: Datos de prueba
A8: 1 | B8: Abrir la aplicación desplegada en un navegador de escritorio. | D8: Entorno: | E8: Aplicación desplegada en Vercel (URL en el Anexo C)
A9: 2 | B9: Iniciar una partida en modo Pacman. | D9: Navegador: | E9: Google Chrome de escritorio
A10: 3 | B10: Partida en curso (N1). | D10: Modo de juego: | E10: Pacman
D11: Nivel inicial: | E11: 1
D12: Vidas iniciales: | E12: 3
D13: PowerUp: | E13: Inactivo
A15: Título del CP | B15: Reaparición como clásico en el nivel 1
A18: Historias de Usuario | B18: HU-16 | C18: Épica | D18: E4 — Niveles y progresión de dificultad
A19: Estado Automatización | B19: No automatizado | C19: Camino feliz | D19: No
A21: Pasos # | B21: Detalle de pasos | D21: Resultado esperado
A22: 1 | B22: Comer al menos 4 fantasmas a lo largo del nivel 1. | D22: Cada fantasma comido desaparece del mapa y reaparece a los 5 segundos.
A23: 2 | B23: Observar el tipo de cada fantasma que reaparece. | D23: Todos los fantasmas reaparecen como clásicos, sin excepción.
A24: El caso se aprueba solo si se cumple todo el resultado esperado del último paso (en negrita); si cualquier parte no se cumple, se registra como Fallido.

Sheet CP-051
A1: Test Case ID | B1: CP-051 | C1: Descripción / Funcionalidad | D1: HU-17 · Enfrentar fantasmas con poderes a partir del nivel 2 | G1: Registro de ejecución
A2: Creado por | B2: Cruz, Luzzi | C2: Versión | D2: 1 | G2: Ciclo | H2: Fecha | I2: Ejecutor | J2: Estado | K2: Resultado obtenido | L2: Defecto
A3: Reporte de ejecución 1 | C3: Estado en la Entrega 1 | D3: =IF(INDEX('Reporte de ejecución - Entrega1'!$G$4:$G$69,MATCH($B$1,'Reporte de ejecución - Entrega1'!$A$4:$A$69,0))="","Sin ejecutar",INDEX('Reporte de ejecución - Entrega1'!$G$4:$G$69,MATCH($B$1,'Reporte de ejecución - Entrega1'!$A$4:$A$69,0))) -> Sin ejecutar | G3: Ciclo 1
G4: Ciclo 2
A5: Prioridad (Alta, Media, Baja) | B5: Alta | C5: Técnica de diseño | D5: Partición de equivalencia | G5: Ciclo 3
G6: Estado del ciclo 1: cargarlo en la hoja del reporte; la celda «Estado en la Entrega 1» lo toma de ahí. Este registro es para el resultado obtenido y los reintentos.
A7: # | B7: Pre-requisitos | D7: Datos de prueba
A8: 1 | B8: Abrir la aplicación desplegada en un navegador de escritorio. | D8: Entorno: | E8: Aplicación desplegada en Vercel (URL en el Anexo C)
A9: 2 | B9: Iniciar una partida en modo Pacman. | D9: Navegador: | E9: Google Chrome de escritorio
A10: 3 | B10: Nivel 2 recién iniciado. | D10: Modo de juego: | E10: Pacman
A12: Título del CP | B12: Composición inicial de fantasmas del nivel 2
A15: Historias de Usuario | B15: HU-17 | C15: Épica | D15: E4 — Niveles y progresión de dificultad
A16: Estado Automatización | B16: No automatizado | C16: Camino feliz | D16: No
A18: Pasos # | B18: Detalle de pasos | D18: Resultado esperado
A19: 1 | B19: Observar el tipo de los cuatro fantasmas al comenzar el nivel. | D19: Los cuatro fantasmas son de tipo clásico al inicio del nivel 2.
A20: El caso se aprueba solo si se cumple todo el resultado esperado del último paso (en negrita); si cualquier parte no se cumple, se registra como Fallido.

Sheet CP-052
A1: Test Case ID | B1: CP-052 | C1: Descripción / Funcionalidad | D1: HU-17 · Enfrentar fantasmas con poderes a partir del nivel 2 | G1: Registro de ejecución
A2: Creado por | B2: Cruz, Luzzi | C2: Versión | D2: 1 | G2: Ciclo | H2: Fecha | I2: Ejecutor | J2: Estado | K2: Resultado obtenido | L2: Defecto
A3: Reporte de ejecución 1 | C3: Estado en la Entrega 1 | D3: =IF(INDEX('Reporte de ejecución - Entrega1'!$G$4:$G$69,MATCH($B$1,'Reporte de ejecución - Entrega1'!$A$4:$A$69,0))="","Sin ejecutar",INDEX('Reporte de ejecución - Entrega1'!$G$4:$G$69,MATCH($B$1,'Reporte de ejecución - Entrega1'!$A$4:$A$69,0))) -> Sin ejecutar | G3: Ciclo 1
G4: Ciclo 2
A5: Prioridad (Alta, Media, Baja) | B5: Alta | C5: Técnica de diseño | D5: Partición de equivalencia | G5: Ciclo 3
G6: Estado del ciclo 1: cargarlo en la hoja del reporte; la celda «Estado en la Entrega 1» lo toma de ahí. Este registro es para el resultado obtenido y los reintentos.
A7: # | B7: Pre-requisitos | D7: Datos de prueba
A8: 1 | B8: Abrir la aplicación desplegada en un navegador de escritorio. | D8: Entorno: | E8: Aplicación desplegada en Vercel (URL en el Anexo C)
A9: 2 | B9: Iniciar una partida en modo Pacman. | D9: Navegador: | E9: Google Chrome de escritorio
A10: 3 | B10: Partida en curso en el nivel 2. | D10: Modo de juego: | E10: Pacman
D11: Nivel: | E11: 2
A13: Título del CP | B13: Reaparición con poderes en el nivel 2
A16: Historias de Usuario | B16: HU-17 | C16: Épica | D16: E4 — Niveles y progresión de dificultad
A17: Estado Automatización | B17: No automatizado | C17: Camino feliz | D17: No
A19: Pasos # | B19: Detalle de pasos | D19: Resultado esperado
A20: 1 | B20: Comer al menos 8 fantasmas a lo largo del nivel 2, registrando el tipo de cada reaparición. | D20: Aparecen reapariciones de ambos tipos, clásico y espectro, en una proporción consistente con el 50 % especificado. Los espectros son visualmente distinguibles de los clásicos.
A21: El caso se aprueba solo si se cumple todo el resultado esperado del último paso (en negrita); si cualquier parte no se cumple, se registra como Fallido.

Sheet CP-053
A1: Test Case ID | B1: CP-053 | C1: Descripción / Funcionalidad | D1: HU-17 · Enfrentar fantasmas con poderes a partir del nivel 2 | G1: Registro de ejecución
A2: Creado por | B2: Cruz, Luzzi | C2: Versión | D2: 1 | G2: Ciclo | H2: Fecha | I2: Ejecutor | J2: Estado | K2: Resultado obtenido | L2: Defecto
A3: Reporte de ejecución 1 | C3: Estado en la Entrega 1 | D3: =IF(INDEX('Reporte de ejecución - Entrega1'!$G$4:$G$69,MATCH($B$1,'Reporte de ejecución - Entrega1'!$A$4:$A$69,0))="","Sin ejecutar",INDEX('Reporte de ejecución - Entrega1'!$G$4:$G$69,MATCH($B$1,'Reporte de ejecución - Entrega1'!$A$4:$A$69,0))) -> Sin ejecutar | G3: Ciclo 1
G4: Ciclo 2
A5: Prioridad (Alta, Media, Baja) | B5: Alta | C5: Técnica de diseño | D5: Partición de equivalencia | G5: Ciclo 3
G6: Estado del ciclo 1: cargarlo en la hoja del reporte; la celda «Estado en la Entrega 1» lo toma de ahí. Este registro es para el resultado obtenido y los reintentos.
A7: # | B7: Pre-requisitos | D7: Datos de prueba
A8: 1 | B8: Abrir la aplicación desplegada en un navegador de escritorio. | D8: Entorno: | E8: Aplicación desplegada en Vercel (URL en el Anexo C)
A9: 2 | B9: Iniciar una partida en modo Pacman. | D9: Navegador: | E9: Google Chrome de escritorio
A10: 3 | B10: Nivel 3 recién iniciado. | D10: Modo de juego: | E10: Pacman
A12: Título del CP | B12: Todos los fantasmas con poderes en el nivel 3
A15: Historias de Usuario | B15: HU-17 | C15: Épica | D15: E4 — Niveles y progresión de dificultad
A16: Estado Automatización | B16: No automatizado | C16: Camino feliz | D16: No
A18: Pasos # | B18: Detalle de pasos | D18: Resultado esperado
A19: 1 | B19: Observar el tipo de los cuatro fantasmas al comenzar el nivel. | D19: Los cuatro fantasmas tienen poderes desde el inicio del nivel 3.
A20: El caso se aprueba solo si se cumple todo el resultado esperado del último paso (en negrita); si cualquier parte no se cumple, se registra como Fallido.

Sheet CP-054
A1: Test Case ID | B1: CP-054 | C1: Descripción / Funcionalidad | D1: HU-17 · Enfrentar fantasmas con poderes a partir del nivel 2 | G1: Registro de ejecución
A2: Creado por | B2: Cruz, Luzzi | C2: Versión | D2: 1 | G2: Ciclo | H2: Fecha | I2: Ejecutor | J2: Estado | K2: Resultado obtenido | L2: Defecto
A3: Reporte de ejecución 1 | C3: Estado en la Entrega 1 | D3: =IF(INDEX('Reporte de ejecución - Entrega1'!$G$4:$G$69,MATCH($B$1,'Reporte de ejecución - Entrega1'!$A$4:$A$69,0))="","Sin ejecutar",INDEX('Reporte de ejecución - Entrega1'!$G$4:$G$69,MATCH($B$1,'Reporte de ejecución - Entrega1'!$A$4:$A$69,0))) -> Sin ejecutar | G3: Ciclo 1
G4: Ciclo 2
A5: Prioridad (Alta, Media, Baja) | B5: Media | C5: Técnica de diseño | D5: Adivinación de errores | G5: Ciclo 3
G6: Estado del ciclo 1: cargarlo en la hoja del reporte; la celda «Estado en la Entrega 1» lo toma de ahí. Este registro es para el resultado obtenido y los reintentos.
A7: # | B7: Pre-requisitos | D7: Datos de prueba
A8: 1 | B8: Abrir la aplicación desplegada en un navegador de escritorio. | D8: Entorno: | E8: Aplicación desplegada en Vercel (URL en el Anexo C)
A9: 2 | B9: Iniciar una partida en modo Pacman. | D9: Navegador: | E9: Google Chrome de escritorio
A10: 3 | B10: Partida en curso en el nivel 2 con al menos un espectro y un clásico en el mapa. | D10: Modo de juego: | E10: Pacman
D11: Nivel: | E11: 2
A13: Título del CP | B13: Velocidad reducida del espectro
A16: Historias de Usuario | B16: HU-17 | C16: Épica | D16: E4 — Niveles y progresión de dificultad
A17: Estado Automatización | B17: No automatizado | C17: Camino feliz | D17: No
A19: Pasos # | B19: Detalle de pasos | D19: Resultado esperado
A20: 1 | B20: Observar el desplazamiento de un espectro y de un clásico por un tramo recto comparable, midiendo el tiempo de cada uno. | D20: El espectro tarda aproximadamente un 43 % más de tiempo en recorrer el mismo tramo, consistente con una velocidad un 30 % menor.
A21: El caso se aprueba solo si se cumple todo el resultado esperado del último paso (en negrita); si cualquier parte no se cumple, se registra como Fallido.

Sheet CP-055
A1: Test Case ID | B1: CP-055 | C1: Descripción / Funcionalidad | D1: HU-18 · Enfrentar al fantasma espectro | G1: Registro de ejecución
A2: Creado por | B2: Cruz, Luzzi | C2: Versión | D2: 1 | G2: Ciclo | H2: Fecha | I2: Ejecutor | J2: Estado | K2: Resultado obtenido | L2: Defecto
A3: Reporte de ejecución 1 | C3: Estado en la Entrega 1 | D3: =IF(INDEX('Reporte de ejecución - Entrega1'!$G$4:$G$69,MATCH($B$1,'Reporte de ejecución - Entrega1'!$A$4:$A$69,0))="","Sin ejecutar",INDEX('Reporte de ejecución - Entrega1'!$G$4:$G$69,MATCH($B$1,'Reporte de ejecución - Entrega1'!$A$4:$A$69,0))) -> Sin ejecutar | G3: Ciclo 1
G4: Ciclo 2
A5: Prioridad (Alta, Media, Baja) | B5: Alta | C5: Técnica de diseño | D5: Transición de estados | G5: Ciclo 3
G6: Estado del ciclo 1: cargarlo en la hoja del reporte; la celda «Estado en la Entrega 1» lo toma de ahí. Este registro es para el resultado obtenido y los reintentos.
A7: # | B7: Pre-requisitos | D7: Datos de prueba
A8: 1 | B8: Abrir la aplicación desplegada en un navegador de escritorio. | D8: Entorno: | E8: Aplicación desplegada en Vercel (URL en el Anexo C)
A9: 2 | B9: Iniciar una partida en modo Pacman. | D9: Navegador: | E9: Google Chrome de escritorio
A10: 3 | B10: Partida en curso en el nivel 3. | D10: Modo de juego: | E10: Pacman
D11: Nivel: | E11: 3
A13: Título del CP | B13: El espectro atraviesa una pared
A16: Historias de Usuario | B16: HU-18 | C16: Épica | D16: E4 — Niveles y progresión de dificultad
A17: Estado Automatización | B17: No automatizado | C17: Camino feliz | D17: No
A19: Pasos # | B19: Detalle de pasos | D19: Resultado esperado
A20: 1 | B20: Observar el desplazamiento de un espectro durante 60 segundos. | D20: El espectro atraviesa paredes, y en cada activación atraviesa una sola pared: no cruza una secuencia de paredes contiguas en un mismo uso.
A21: El caso se aprueba solo si se cumple todo el resultado esperado del último paso (en negrita); si cualquier parte no se cumple, se registra como Fallido.

Sheet CP-056
A1: Test Case ID | B1: CP-056 | C1: Descripción / Funcionalidad | D1: HU-18 · Enfrentar al fantasma espectro | G1: Registro de ejecución
A2: Creado por | B2: Cruz, Luzzi | C2: Versión | D2: 1 | G2: Ciclo | H2: Fecha | I2: Ejecutor | J2: Estado | K2: Resultado obtenido | L2: Defecto
A3: Reporte de ejecución 1 | C3: Estado en la Entrega 1 | D3: =IF(INDEX('Reporte de ejecución - Entrega1'!$G$4:$G$69,MATCH($B$1,'Reporte de ejecución - Entrega1'!$A$4:$A$69,0))="","Sin ejecutar",INDEX('Reporte de ejecución - Entrega1'!$G$4:$G$69,MATCH($B$1,'Reporte de ejecución - Entrega1'!$A$4:$A$69,0))) -> Sin ejecutar | G3: Ciclo 1
G4: Ciclo 2
A5: Prioridad (Alta, Media, Baja) | B5: Media | C5: Técnica de diseño | D5: Valores límite | G5: Ciclo 3
G6: Estado del ciclo 1: cargarlo en la hoja del reporte; la celda «Estado en la Entrega 1» lo toma de ahí. Este registro es para el resultado obtenido y los reintentos.
A7: # | B7: Pre-requisitos | D7: Datos de prueba
A8: 1 | B8: Abrir la aplicación desplegada en un navegador de escritorio. | D8: Entorno: | E8: Aplicación desplegada en Vercel (URL en el Anexo C)
A9: 2 | B9: Iniciar una partida en modo Pacman. | D9: Navegador: | E9: Google Chrome de escritorio
A10: 3 | B10: Partida en curso en el nivel 3. | D10: Modo de juego: | E10: Pacman
D11: Nivel: | E11: 3
A13: Título del CP | B13: Cooldown de la habilidad del espectro
A16: Historias de Usuario | B16: HU-18 | C16: Épica | D16: E4 — Niveles y progresión de dificultad
A17: Estado Automatización | B17: No automatizado | C17: Camino feliz | D17: No
A19: Pasos # | B19: Detalle de pasos | D19: Resultado esperado
A20: 1 | B20: Registrar el instante en que un espectro atraviesa una pared. | D20: Instante del primer cruce anotado.
A21: 2 | B21: Cronometrar hasta la siguiente pared que atraviesa el mismo espectro. | D21: Entre dos usos de la habilidad transcurren al menos 10 segundos.
A22: El caso se aprueba solo si se cumple todo el resultado esperado del último paso (en negrita); si cualquier parte no se cumple, se registra como Fallido.

Sheet CP-057
A1: Test Case ID | B1: CP-057 | C1: Descripción / Funcionalidad | D1: HU-18 · Enfrentar al fantasma espectro | G1: Registro de ejecución
A2: Creado por | B2: Cruz, Luzzi | C2: Versión | D2: 1 | G2: Ciclo | H2: Fecha | I2: Ejecutor | J2: Estado | K2: Resultado obtenido | L2: Defecto
A3: Reporte de ejecución 1 | C3: Estado en la Entrega 1 | D3: =IF(INDEX('Reporte de ejecución - Entrega1'!$G$4:$G$69,MATCH($B$1,'Reporte de ejecución - Entrega1'!$A$4:$A$69,0))="","Sin ejecutar",INDEX('Reporte de ejecución - Entrega1'!$G$4:$G$69,MATCH($B$1,'Reporte de ejecución - Entrega1'!$A$4:$A$69,0))) -> Sin ejecutar | G3: Ciclo 1
G4: Ciclo 2
A5: Prioridad (Alta, Media, Baja) | B5: Alta | C5: Técnica de diseño | D5: Tabla de decisión | G5: Ciclo 3
G6: Estado del ciclo 1: cargarlo en la hoja del reporte; la celda «Estado en la Entrega 1» lo toma de ahí. Este registro es para el resultado obtenido y los reintentos.
A7: # | B7: Pre-requisitos | D7: Datos de prueba
A8: 1 | B8: Abrir la aplicación desplegada en un navegador de escritorio. | D8: Entorno: | E8: Aplicación desplegada en Vercel (URL en el Anexo C)
A9: 2 | B9: Iniciar una partida en modo Pacman. | D9: Navegador: | E9: Google Chrome de escritorio
A10: 3 | B10: Partida en curso en el nivel 3, sin PowerUp activo, 3 vidas. | D10: Modo de juego: | E10: Pacman
D11: Nivel: | E11: 3
A13: Título del CP | B13: Estado de gracia del espectro tras atravesar un muro
A16: Historias de Usuario | B16: HU-18 | C16: Épica | D16: E4 — Niveles y progresión de dificultad
A17: Estado Automatización | B17: No automatizado | C17: Camino feliz | D17: No
A19: Pasos # | B19: Detalle de pasos | D19: Resultado esperado
A20: 1 | B20: Esperar a que un espectro atraviese una pared. | D20: El espectro atraviesa la pared y se muestra con su estado de gracia.
A21: 2 | B21: Dirigir a Pacman al contacto con ese espectro dentro de los 3 segundos siguientes. | D21: Se produce el contacto dentro de los 3 segundos posteriores al cruce.
A22: 3 | B22: Registrar el contador de vidas. | D22: El contacto no descuenta vidas, el estado del espectro es visualmente distinguible durante esos 3 segundos, y transcurridos los 3 segundos el contacto vuelve a descontar una vida.
A23: El caso se aprueba solo si se cumple todo el resultado esperado del último paso (en negrita); si cualquier parte no se cumple, se registra como Fallido.

Sheet CP-058
A1: Test Case ID | B1: CP-058 | C1: Descripción / Funcionalidad | D1: HU-18 · Enfrentar al fantasma espectro | G1: Registro de ejecución
A2: Creado por | B2: Cruz, Luzzi | C2: Versión | D2: 1 | G2: Ciclo | H2: Fecha | I2: Ejecutor | J2: Estado | K2: Resultado obtenido | L2: Defecto
A3: Reporte de ejecución 1 | C3: Estado en la Entrega 1 | D3: =IF(INDEX('Reporte de ejecución - Entrega1'!$G$4:$G$69,MATCH($B$1,'Reporte de ejecución - Entrega1'!$A$4:$A$69,0))="","Sin ejecutar",INDEX('Reporte de ejecución - Entrega1'!$G$4:$G$69,MATCH($B$1,'Reporte de ejecución - Entrega1'!$A$4:$A$69,0))) -> Sin ejecutar | G3: Ciclo 1
G4: Ciclo 2
A5: Prioridad (Alta, Media, Baja) | B5: Media | C5: Técnica de diseño | D5: Valores límite | G5: Ciclo 3
G6: Estado del ciclo 1: cargarlo en la hoja del reporte; la celda «Estado en la Entrega 1» lo toma de ahí. Este registro es para el resultado obtenido y los reintentos.
A7: # | B7: Pre-requisitos | D7: Datos de prueba
A8: 1 | B8: Abrir la aplicación desplegada en un navegador de escritorio. | D8: Entorno: | E8: Aplicación desplegada en Vercel (URL en el Anexo C)
A9: 2 | B9: Iniciar una partida en modo Pacman. | D9: Navegador: | E9: Google Chrome de escritorio
A10: 3 | B10: Partida en curso en el nivel 3. | D10: Modo de juego: | E10: Pacman
D11: Nivel: | E11: 3
A13: Título del CP | B13: El espectro no sale del mapa con su habilidad
A16: Historias de Usuario | B16: HU-18 | C16: Épica | D16: E4 — Niveles y progresión de dificultad
A17: Estado Automatización | B17: No automatizado | C17: Camino feliz | D17: No
A19: Pasos # | B19: Detalle de pasos | D19: Resultado esperado
A20: 1 | B20: Observar durante 90 segundos el comportamiento de los espectros en los corredores adyacentes al borde del mapa. | D20: Ningún espectro sale de los límites del mapa ni queda ubicado dentro de un bloque de muro sin celda transitable de destino.
A21: El caso se aprueba solo si se cumple todo el resultado esperado del último paso (en negrita); si cualquier parte no se cumple, se registra como Fallido.

Sheet CP-059
A1: Test Case ID | B1: CP-059 | C1: Descripción / Funcionalidad | D1: HU-18 · Enfrentar al fantasma espectro | G1: Registro de ejecución
A2: Creado por | B2: Cruz, Luzzi | C2: Versión | D2: 1 | G2: Ciclo | H2: Fecha | I2: Ejecutor | J2: Estado | K2: Resultado obtenido | L2: Defecto
A3: Reporte de ejecución 1 | C3: Estado en la Entrega 1 | D3: =IF(INDEX('Reporte de ejecución - Entrega1'!$G$4:$G$69,MATCH($B$1,'Reporte de ejecución - Entrega1'!$A$4:$A$69,0))="","Sin ejecutar",INDEX('Reporte de ejecución - Entrega1'!$G$4:$G$69,MATCH($B$1,'Reporte de ejecución - Entrega1'!$A$4:$A$69,0))) -> Sin ejecutar | G3: Ciclo 1
G4: Ciclo 2
A5: Prioridad (Alta, Media, Baja) | B5: Alta | C5: Técnica de diseño | D5: Tabla de decisión | G5: Ciclo 3
G6: Estado del ciclo 1: cargarlo en la hoja del reporte; la celda «Estado en la Entrega 1» lo toma de ahí. Este registro es para el resultado obtenido y los reintentos.
A7: # | B7: Pre-requisitos | D7: Datos de prueba
A8: 1 | B8: Abrir la aplicación desplegada en un navegador de escritorio. | D8: Entorno: | E8: Aplicación desplegada en Vercel (URL en el Anexo C)
A9: 2 | B9: Iniciar una partida en modo Pacman. | D9: Navegador: | E9: Google Chrome de escritorio
A10: 3 | B10: Partida en curso en el nivel 3. | D10: Modo de juego: | E10: Pacman
D11: Nivel: | E11: 3
A13: Título del CP | B13: El espectro es vulnerable durante el PowerUp
A16: Historias de Usuario | B16: HU-18 | C16: Épica | D16: E4 — Niveles y progresión de dificultad
A17: Estado Automatización | B17: No automatizado | C17: Camino feliz | D17: No
A19: Pasos # | B19: Detalle de pasos | D19: Resultado esperado
A20: 1 | B20: Consumir una esfera grande. | D20: El PowerUp se activa y el espectro cambia a su diseño vulnerable.
A21: 2 | B21: Comer un espectro. | D21: El espectro es comido y suma los puntos que correspondan en la escala.
A22: 3 | B22: Registrar el puntaje y el contador de vidas. | D22: El espectro cambia a estado vulnerable, puede ser comido, suma puntos según la escala vigente y no descuenta vidas.
A23: El caso se aprueba solo si se cumple todo el resultado esperado del último paso (en negrita); si cualquier parte no se cumple, se registra como Fallido.

Sheet CP-060
A1: Test Case ID | B1: CP-060 | C1: Descripción / Funcionalidad | D1: HU-19 · Cerrar la partida y volver a jugar | G1: Registro de ejecución
A2: Creado por | B2: Cruz, Luzzi | C2: Versión | D2: 1 | G2: Ciclo | H2: Fecha | I2: Ejecutor | J2: Estado | K2: Resultado obtenido | L2: Defecto
A3: Reporte de ejecución 1 | C3: Estado en la Entrega 1 | D3: =IF(INDEX('Reporte de ejecución - Entrega1'!$G$4:$G$69,MATCH($B$1,'Reporte de ejecución - Entrega1'!$A$4:$A$69,0))="","Sin ejecutar",INDEX('Reporte de ejecución - Entrega1'!$G$4:$G$69,MATCH($B$1,'Reporte de ejecución - Entrega1'!$A$4:$A$69,0))) -> Sin ejecutar | G3: Ciclo 1
G4: Ciclo 2
A5: Prioridad (Alta, Media, Baja) | B5: Alta | C5: Técnica de diseño | D5: Transición de estados | G5: Ciclo 3
G6: Estado del ciclo 1: cargarlo en la hoja del reporte; la celda «Estado en la Entrega 1» lo toma de ahí. Este registro es para el resultado obtenido y los reintentos.
A7: # | B7: Pre-requisitos | D7: Datos de prueba
A8: 1 | B8: Abrir la aplicación desplegada en un navegador de escritorio. | D8: Entorno: | E8: Aplicación desplegada en Vercel (URL en el Anexo C)
A9: 2 | B9: Iniciar una partida en modo Pacman. | D9: Navegador: | E9: Google Chrome de escritorio
A10: 3 | B10: Partida en curso (N1), 1 vida restante. | D10: Modo de juego: | E10: Pacman
D11: Nivel inicial: | E11: 1
D12: Vidas iniciales: | E12: 3
D13: PowerUp: | E13: Inactivo
A15: Título del CP | B15: Pantalla de Game Over
A18: Historias de Usuario | B18: HU-19 | C18: Épica | D18: E4 — Niveles y progresión de dificultad
A19: Estado Automatización | B19: No automatizado | C19: Camino feliz | D19: Sí
A21: Pasos # | B21: Detalle de pasos | D21: Resultado esperado
A22: 1 | B22: Perder la última vida. | D22: El contador de vidas queda sin íconos.
A23: 2 | B23: Observar la pantalla. | D23: Se muestra la pantalla de Game Over con el puntaje final desglosado y con la acción de volver a jugar disponible.
A24: El caso se aprueba solo si se cumple todo el resultado esperado del último paso (en negrita); si cualquier parte no se cumple, se registra como Fallido.

Sheet CP-061
A1: Test Case ID | B1: CP-061 | C1: Descripción / Funcionalidad | D1: HU-19 · Cerrar la partida y volver a jugar | G1: Registro de ejecución
A2: Creado por | B2: Cruz, Luzzi | C2: Versión | D2: 1 | G2: Ciclo | H2: Fecha | I2: Ejecutor | J2: Estado | K2: Resultado obtenido | L2: Defecto
A3: Reporte de ejecución 1 | C3: Estado en la Entrega 1 | D3: =IF(INDEX('Reporte de ejecución - Entrega1'!$G$4:$G$69,MATCH($B$1,'Reporte de ejecución - Entrega1'!$A$4:$A$69,0))="","Sin ejecutar",INDEX('Reporte de ejecución - Entrega1'!$G$4:$G$69,MATCH($B$1,'Reporte de ejecución - Entrega1'!$A$4:$A$69,0))) -> Sin ejecutar | G3: Ciclo 1
G4: Ciclo 2
A5: Prioridad (Alta, Media, Baja) | B5: Alta | C5: Técnica de diseño | D5: Transición de estados | G5: Ciclo 3
G6: Estado del ciclo 1: cargarlo en la hoja del reporte; la celda «Estado en la Entrega 1» lo toma de ahí. Este registro es para el resultado obtenido y los reintentos.
A7: # | B7: Pre-requisitos | D7: Datos de prueba
A8: 1 | B8: Abrir la aplicación desplegada en un navegador de escritorio. | D8: Entorno: | E8: Aplicación desplegada en Vercel (URL en el Anexo C)
A9: 2 | B9: Iniciar una partida en modo Pacman. | D9: Navegador: | E9: Google Chrome de escritorio
A10: 3 | B10: Partida en curso en el nivel 3, próxima a completarse. | D10: Modo de juego: | E10: Pacman
D11: Nivel: | E11: 3
A13: Título del CP | B13: Pantalla de Victoria
A16: Historias de Usuario | B16: HU-19 | C16: Épica | D16: E4 — Niveles y progresión de dificultad
A17: Estado Automatización | B17: No automatizado | C17: Camino feliz | D17: Sí
A19: Pasos # | B19: Detalle de pasos | D19: Resultado esperado
A20: 1 | B20: Completar el nivel 3. | D20: Se completa la última esfera del nivel 3.
A21: 2 | B21: Observar la pantalla. | D21: Se muestra la pantalla de Victoria con el puntaje final desglosado y con la acción de volver a jugar disponible.
A22: El caso se aprueba solo si se cumple todo el resultado esperado del último paso (en negrita); si cualquier parte no se cumple, se registra como Fallido.

Sheet CP-062
A1: Test Case ID | B1: CP-062 | C1: Descripción / Funcionalidad | D1: HU-19 · Cerrar la partida y volver a jugar | G1: Registro de ejecución
A2: Creado por | B2: Cruz, Luzzi | C2: Versión | D2: 1 | G2: Ciclo | H2: Fecha | I2: Ejecutor | J2: Estado | K2: Resultado obtenido | L2: Defecto
A3: Reporte de ejecución 1 | C3: Estado en la Entrega 1 | D3: =IF(INDEX('Reporte de ejecución - Entrega1'!$G$4:$G$69,MATCH($B$1,'Reporte de ejecución - Entrega1'!$A$4:$A$69,0))="","Sin ejecutar",INDEX('Reporte de ejecución - Entrega1'!$G$4:$G$69,MATCH($B$1,'Reporte de ejecución - Entrega1'!$A$4:$A$69,0))) -> Sin ejecutar | G3: Ciclo 1
G4: Ciclo 2
A5: Prioridad (Alta, Media, Baja) | B5: Alta | C5: Técnica de diseño | D5: Adivinación de errores | G5: Ciclo 3
G6: Estado del ciclo 1: cargarlo en la hoja del reporte; la celda «Estado en la Entrega 1» lo toma de ahí. Este registro es para el resultado obtenido y los reintentos.
A7: # | B7: Pre-requisitos | D7: Datos de prueba
A8: 1 | B8: Abrir la aplicación desplegada en un navegador de escritorio. | D8: Entorno: | E8: Aplicación desplegada en Vercel (URL en el Anexo C)
A9: 2 | B9: Iniciar una partida en modo Pacman. | D9: Navegador: | E9: Google Chrome de escritorio
A10: 3 | B10: Partida terminada en Game Over en el nivel 3, con puntaje mayor a 0. | D10: Modo de juego: | E10: Pacman
D11: Nivel: | E11: 3
A13: Título del CP | B13: Reinicio completo del estado al volver a jugar
A16: Historias de Usuario | B16: HU-19 | C16: Épica | D16: E4 — Niveles y progresión de dificultad
A17: Estado Automatización | B17: No automatizado | C17: Camino feliz | D17: Sí
A19: Pasos # | B19: Detalle de pasos | D19: Resultado esperado
A20: 1 | B20: Usar la acción de volver a jugar. | D20: Se inicia una partida nueva.
A21: 2 | B21: Verificar nivel, vidas, puntaje y estado de los mapas. | D21: Nivel 1, 3 vidas, puntaje 0 y el mapa completo con todas sus esferas.
A22: 3 | B22: Completar el nivel 1 y verificar el mapa del nivel 2. | D22: La partida nueva inicia en el nivel 1 con 3 vidas y puntaje 0, con todas las esferas y frutas restablecidas en el nivel 1 y también en los niveles siguientes.
A23: El caso se aprueba solo si se cumple todo el resultado esperado del último paso (en negrita); si cualquier parte no se cumple, se registra como Fallido.

Sheet CP-063
A1: Test Case ID | B1: CP-063 | C1: Descripción / Funcionalidad | D1: HU-20 · Pausar la partida | G1: Registro de ejecución
A2: Creado por | B2: Cruz, Luzzi | C2: Versión | D2: 1 | G2: Ciclo | H2: Fecha | I2: Ejecutor | J2: Estado | K2: Resultado obtenido | L2: Defecto
A3: Reporte de ejecución 1 | C3: Estado en la Entrega 1 | D3: =IF(INDEX('Reporte de ejecución - Entrega1'!$G$4:$G$69,MATCH($B$1,'Reporte de ejecución - Entrega1'!$A$4:$A$69,0))="","Sin ejecutar",INDEX('Reporte de ejecución - Entrega1'!$G$4:$G$69,MATCH($B$1,'Reporte de ejecución - Entrega1'!$A$4:$A$69,0))) -> Sin ejecutar | G3: Ciclo 1
G4: Ciclo 2
A5: Prioridad (Alta, Media, Baja) | B5: Media | C5: Técnica de diseño | D5: Transición de estados | G5: Ciclo 3
G6: Estado del ciclo 1: cargarlo en la hoja del reporte; la celda «Estado en la Entrega 1» lo toma de ahí. Este registro es para el resultado obtenido y los reintentos.
A7: # | B7: Pre-requisitos | D7: Datos de prueba
A8: 1 | B8: Abrir la aplicación desplegada en un navegador de escritorio. | D8: Entorno: | E8: Aplicación desplegada en Vercel (URL en el Anexo C)
A9: 2 | B9: Iniciar una partida en modo Pacman. | D9: Navegador: | E9: Google Chrome de escritorio
A10: 3 | B10: Partida en curso (N1) con los personajes en movimiento. | D10: Modo de juego: | E10: Pacman
D11: Nivel inicial: | E11: 1
D12: Vidas iniciales: | E12: 3
D13: PowerUp: | E13: Inactivo
A15: Título del CP | B15: Pausa y reanudación con ESC
A18: Historias de Usuario | B18: HU-20 | C18: Épica | D18: E5 — Control de la partida
A19: Estado Automatización | B19: No automatizado | C19: Camino feliz | D19: Sí
A21: Pasos # | B21: Detalle de pasos | D21: Resultado esperado
A22: 1 | B22: Presionar ESC. | D22: La partida se detiene y se muestra el cartel de pausa.
A23: 2 | B23: Observar la pantalla durante 5 segundos. | D23: Pacman y los fantasmas permanecen inmóviles.
A24: 3 | B24: Presionar las teclas de movimiento. | D24: Pacman no se mueve.
A25: 4 | B25: Presionar ESC otra vez. | D25: La partida se detiene, los personajes quedan inmóviles, la pantalla indica de manera visible el estado de pausa, las teclas de movimiento no producen efecto, y el segundo ESC reanuda la partida.
A26: El caso se aprueba solo si se cumple todo el resultado esperado del último paso (en negrita); si cualquier parte no se cumple, se registra como Fallido.

Sheet CP-064
A1: Test Case ID | B1: CP-064 | C1: Descripción / Funcionalidad | D1: HU-20 · Pausar la partida | G1: Registro de ejecución
A2: Creado por | B2: Cruz, Luzzi | C2: Versión | D2: 1 | G2: Ciclo | H2: Fecha | I2: Ejecutor | J2: Estado | K2: Resultado obtenido | L2: Defecto
A3: Reporte de ejecución 1 | C3: Estado en la Entrega 1 | D3: =IF(INDEX('Reporte de ejecución - Entrega1'!$G$4:$G$69,MATCH($B$1,'Reporte de ejecución - Entrega1'!$A$4:$A$69,0))="","Sin ejecutar",INDEX('Reporte de ejecución - Entrega1'!$G$4:$G$69,MATCH($B$1,'Reporte de ejecución - Entrega1'!$A$4:$A$69,0))) -> Sin ejecutar | G3: Ciclo 1
G4: Ciclo 2
A5: Prioridad (Alta, Media, Baja) | B5: Media | C5: Técnica de diseño | D5: Adivinación de errores | G5: Ciclo 3
G6: Estado del ciclo 1: cargarlo en la hoja del reporte; la celda «Estado en la Entrega 1» lo toma de ahí. Este registro es para el resultado obtenido y los reintentos.
A7: # | B7: Pre-requisitos | D7: Datos de prueba
A8: 1 | B8: Abrir la aplicación desplegada en un navegador de escritorio. | D8: Entorno: | E8: Aplicación desplegada en Vercel (URL en el Anexo C)
A9: 2 | B9: Iniciar una partida en modo Pacman. | D9: Navegador: | E9: Google Chrome de escritorio
A10: 3 | B10: Partida en curso (N1). | D10: Modo de juego: | E10: Pacman
D11: Nivel inicial: | E11: 1
D12: Vidas iniciales: | E12: 3
D13: PowerUp: | E13: Inactivo
A15: Título del CP | B15: Los temporizadores se detienen durante la pausa
A18: Historias de Usuario | B18: HU-20 | C18: Épica | D18: E5 — Control de la partida
A19: Estado Automatización | B19: No automatizado | C19: Camino feliz | D19: No
A21: Pasos # | B21: Detalle de pasos | D21: Resultado esperado
A22: 1 | B22: Consumir una esfera grande. | D22: El PowerUp se activa.
A23: 2 | B23: A los 2 segundos, presionar ESC. | D23: La partida se pausa con el PowerUp activo.
A24: 3 | B24: Mantener la pausa 15 segundos. | D24: El PowerUp sigue activo y los fantasmas inmóviles durante la pausa.
A25: 4 | B25: Reanudar y cronometrar cuánto dura el PowerUp desde la reanudación. | D25: El PowerUp continúa 6 segundos desde la reanudación. No termina durante la pausa ni al reanudarse.
A26: El caso se aprueba solo si se cumple todo el resultado esperado del último paso (en negrita); si cualquier parte no se cumple, se registra como Fallido.

Sheet CP-065
A1: Test Case ID | B1: CP-065 | C1: Descripción / Funcionalidad | D1: HU-20 · Pausar la partida | G1: Registro de ejecución
A2: Creado por | B2: Cruz, Luzzi | C2: Versión | D2: 1 | G2: Ciclo | H2: Fecha | I2: Ejecutor | J2: Estado | K2: Resultado obtenido | L2: Defecto
A3: Reporte de ejecución 1 | C3: Estado en la Entrega 1 | D3: =IF(INDEX('Reporte de ejecución - Entrega1'!$G$4:$G$69,MATCH($B$1,'Reporte de ejecución - Entrega1'!$A$4:$A$69,0))="","Sin ejecutar",INDEX('Reporte de ejecución - Entrega1'!$G$4:$G$69,MATCH($B$1,'Reporte de ejecución - Entrega1'!$A$4:$A$69,0))) -> Sin ejecutar | G3: Ciclo 1
G4: Ciclo 2
A5: Prioridad (Alta, Media, Baja) | B5: Baja | C5: Técnica de diseño | D5: Adivinación de errores | G5: Ciclo 3
G6: Estado del ciclo 1: cargarlo en la hoja del reporte; la celda «Estado en la Entrega 1» lo toma de ahí. Este registro es para el resultado obtenido y los reintentos.
A7: # | B7: Pre-requisitos | D7: Datos de prueba
A8: 1 | B8: Abrir la aplicación desplegada en un navegador de escritorio. | D8: Entorno: | E8: Aplicación desplegada en Vercel (URL en el Anexo C)
A9: 2 | B9: Iniciar una partida en modo Pacman. | D9: Navegador: | E9: Google Chrome de escritorio
A10: 3 | B10: Partida en curso (N1). | D10: Modo de juego: | E10: Pacman
D11: Nivel inicial: | E11: 1
D12: Vidas iniciales: | E12: 3
D13: PowerUp: | E13: Inactivo
A15: Título del CP | B15: El bonus por tiempo no se afecta por la pausa
A18: Historias de Usuario | B18: HU-20 | C18: Épica | D18: E5 — Control de la partida
A19: Estado Automatización | B19: No automatizado | C19: Camino feliz | D19: No
A21: Pasos # | B21: Detalle de pasos | D21: Resultado esperado
A22: 1 | B22: Completar el nivel 1 con una pausa de 60 segundos en el medio, registrando el tiempo de juego efectivo. | D22: Nivel completado y tiempo de juego efectivo anotado.
A23: 2 | B23: Verificar el bonus por tiempo. | D23: El bonus por tiempo se calcula sobre el tiempo de juego efectivo y no incluye los 60 segundos de pausa.
A24: El caso se aprueba solo si se cumple todo el resultado esperado del último paso (en negrita); si cualquier parte no se cumple, se registra como Fallido.

Sheet CP-066
A1: Test Case ID | B1: CP-066 | C1: Descripción / Funcionalidad | D1: HU-21 · Ignorar la barra espaciadora en modo Pacman | G1: Registro de ejecución
A2: Creado por | B2: Cruz, Luzzi | C2: Versión | D2: 1 | G2: Ciclo | H2: Fecha | I2: Ejecutor | J2: Estado | K2: Resultado obtenido | L2: Defecto
A3: Reporte de ejecución 1 | C3: Estado en la Entrega 1 | D3: =IF(INDEX('Reporte de ejecución - Entrega1'!$G$4:$G$69,MATCH($B$1,'Reporte de ejecución - Entrega1'!$A$4:$A$69,0))="","Sin ejecutar",INDEX('Reporte de ejecución - Entrega1'!$G$4:$G$69,MATCH($B$1,'Reporte de ejecución - Entrega1'!$A$4:$A$69,0))) -> Sin ejecutar | G3: Ciclo 1
G4: Ciclo 2
A5: Prioridad (Alta, Media, Baja) | B5: Baja | C5: Técnica de diseño | D5: Adivinación de errores | G5: Ciclo 3
G6: Estado del ciclo 1: cargarlo en la hoja del reporte; la celda «Estado en la Entrega 1» lo toma de ahí. Este registro es para el resultado obtenido y los reintentos.
A7: # | B7: Pre-requisitos | D7: Datos de prueba
A8: 1 | B8: Abrir la aplicación desplegada en un navegador de escritorio. | D8: Entorno: | E8: Aplicación desplegada en Vercel (URL en el Anexo C)
A9: 2 | B9: Iniciar una partida en modo Pacman. | D9: Navegador: | E9: Google Chrome de escritorio
A10: 3 | B10: Partida en curso (N1), sin PowerUp activo, puntaje y vidas registrados. | D10: Modo de juego: | E10: Pacman
D11: Nivel inicial: | E11: 1
D12: Vidas iniciales: | E12: 3
D13: PowerUp: | E13: Inactivo
A15: Título del CP | B15: La barra espaciadora no tiene efecto en modo Pacman
A18: Historias de Usuario | B18: HU-21 | C18: Épica | D18: E5 — Control de la partida
A19: Estado Automatización | B19: No automatizado | C19: Camino feliz | D19: No
A21: Pasos # | B21: Detalle de pasos | D21: Resultado esperado
A22: 1 | B22: Presionar la barra espaciadora 10 veces. | D22: No se produce ningún cambio visible en la partida.
A23: 2 | B23: Verificar puntaje, vidas, estado de la partida y posición de la página en el navegador. | D23: El estado del juego no cambia en ningún aspecto: la partida no se pausa, el PowerUp no se activa, el puntaje no varía. La página no hace scroll ni ejecuta ninguna acción por defecto del navegador.
A24: El caso se aprueba solo si se cumple todo el resultado esperado del último paso (en negrita); si cualquier parte no se cumple, se registra como Fallido.

Sheet CP - Plantilla
A1: Test Case ID | C1: Descripción / Funcionalidad | G1: Registro de ejecución
A2: Creado por | C2: Versión | G2: Ciclo | H2: Fecha | I2: Ejecutor | J2: Estado | K2: Resultado obtenido | L2: Defecto
A3: Reporte de ejecución 1 | C3: Estado en la Entrega 1
A5: Prioridad (Alta, Media, Baja) | C5: Técnica de diseño
G6: Estado del ciclo 1: cargarlo en la hoja del reporte; la celda «Estado en la Entrega 1» lo toma de ahí. Este registro es para el resultado obtenido y los reintentos.
A7: # | B7: Pre-requisitos | D7: Datos de prueba
A8: 1
A9: 2
A10: 3
A12: Título del CP
A15: Historias de Usuario | C15: Épica
A16: Estado Automatización | C16: Camino feliz
A18: Pasos # | B18: Detalle de pasos | D18: Resultado esperado
A19: 1
A20: 2
A21: 3
A22: El caso se aprueba solo si se cumple todo el resultado esperado del último paso (en negrita); si cualquier parte no se cumple, se registra como Fallido.

Sheet DF - Plantilla
A1: Reporte de defecto
A2: Copiar esta hoja por cada defecto, nombrarla con su ID (DEF-001, …) y registrarlo también en «Registro de defectos». Reemplazar los textos grises.
A4: ID | B4: DEF-nnn
A5: Título | B5: Síntoma en una línea, específico y sin diagnóstico. Ej.: «El PowerUp dura más de 8 segundos».
A6: Caso de prueba | B6: CP que lo detectó (ej.: CP-019 - Duración del PowerUp) o «Exploratoria».
A7: Historia de usuario | B7: HU afectada y criterio de aceptación (ej.: HU-05 - «El PowerUp dura 8 segundos»).
A8: Severidad | B8: Bloqueante / Crítica / Mayor / Menor / Trivial (sección 13.1).
A9: Prioridad | B9: Alta / Media / Baja (sección 13.1).
A10: Estado | B10: Nuevo / Confirmado / No reproducible / En corrección / Corregido / Verificado / Diferido / Rechazado (13.2).
A11: Versión / commit | B11: V1 - hash del commit desplegado.
A12: Entorno | B12: Navegador y versión, resolución, URL de despliegue.
A13: Precondiciones | B13: Estado necesario para reproducirlo.
A14: Pasos para reproducir | B14: 1) … 2) … 3) …
A15: Resultado esperado | B15: Comportamiento especificado, con referencia al criterio de aceptación o al parámetro de la sección 4.
... A21: Fecha | B21: dd/mm/aaaa
