Workbook

Sheet Reporte de ejecución - Entrega2
A1: GhostMan - Entrega 2 - Reporte de ejecución de casos de prueba (V2, ciclo 2)
A2: Todos los casos de prueba ordenados por ID: los nuevos de la V2, la regresión completa de la V1 (35 casos de prioridad Alta, mutados, y 29 de prioridad Media y Baja, ejecutados el 28/10/2026) y las pruebas de confirmación de defectos. Estados según la sección 12.2: Aprobado, Fallido, Bloqueado, No ejecutado, No aplica. «Estado Entrega 1» viene del reporte de la Entrega 1; «¿Cambió?» compara los dos ciclos. El ID de cada caso abre su hoja de detalle.
A3: Test case ID | B3: Tipo de prueba | C3: Épica | D3: Prioridad | E3: Título | F3: Historia de usuario | G3: Camino feliz | H3: Estado Entrega 1 | I3: Estado Entrega 2 | J3: ¿Cambió? | K3: Ejecutor | L3: Fecha | M3: Defectos | N3: Observaciones | P3: Identificación del ciclo (sección 12.1)
A4: CP-001 | B4: Regresión (V1, mutado) | C4: E1 | D4: Alta | E4: Movimiento de Pacman con las flechas | F4: HU-01 | G4: Sí | H4: Aprobado | I4: Aprobado | J4: =IF(OR(H4="—",I4="",I4="No ejecutado"),"—",IF(H4=I4,"No","Sí")) | K4: Luzzi | L4: 46307 | N4: Mutación: Secuencia invertida: ↓ → ↑ ← (la V1 usó ← ↑ → ↓). Desde el cruce (4,6), ↓ → ↑ ← desplazaron a Pacman hacia abajo, derecha, arriba e izquierda respectivamente. (Fantasmas retirados y posiciones preparadas por script para aislar la condición.) | P4: Ciclo de ejecución | Q4: Nº 2 (primer ciclo de la V2)
A5: CP-002 | B5: Regresión (V1, mutado) | C5: E1 | D5: Alta | E5: Movimiento de Pacman con WASD | F5: HU-01 | G5: Sí | H5: Aprobado | I5: Aprobado | J5: =IF(OR(H5="—",I5="",I5="No ejecutado"),"—",IF(H5=I5,"No","Sí")) | K5: Luzzi | L5: 46307 | N5: Mutación: Secuencia invertida: S D W A. S D W A produjeron el mismo desplazamiento que ↓ → ↑ ← (abajo, derecha, arriba, izquierda). (Fantasmas retirados y posiciones preparadas por script para aislar la condición.) | P5: Versión bajo prueba | Q5: V2
A6: CP-003 | B6: Regresión (V1, mutado) | C6: E1 | D6: Alta | E6: Avance continuo sin mantener la tecla | F6: HU-01 | G6: Sí | H6: Aprobado | I6: Aprobado | J6: =IF(OR(H6="—",I6="",I6="No ejecutado"),"—",IF(H6=I6,"No","Sí")) | K6: Luzzi | L6: 46307 | N6: Mutación: Se usa la dirección ↓ desde una celda distinta a la de la V1 (fila 10). Tras un toque de ↓ en (10,6), Pacman siguió bajando sin mantener la tecla hasta el muro inferior (fila 13) y se detuvo ahí. (Fantasmas retirados y posiciones preparadas por script para aislar la condición.) | P6: Commit | Q6: 7ec70df (Corregir DEF-001, rama main)
A7: CP-004 | B7: Regresión (V1, Media/Baja) | C7: E1 | D7: Media | E7: Giro postergado hasta la primera celda posible | F7: HU-01 | G7: No | H7: Aprobado | I7: Aprobado | J7: =IF(OR(H7="—",I7="",I7="No ejecutado"),"—",IF(H7=I7,"No","Sí")) | K7: Luzzi | L7: 46323 | N7: Avanzando a la derecha por la fila 4 desde (4,3), ↑ presionado 3 celdas antes de la intersección: Pacman siguió en horizontal sin detenerse y giró hacia arriba al llegar a la columna 6. (Fantasmas retirados y posiciones preparadas por script para aislar la condición.) | P7: Entorno | Q7: Build de producción local del commit 7ec70df (next build + next start), con una línea agregada solo para la prueba que expone el estado del juego al script (window.__gm, no se commitea) y sin la fuente de Google. Completar la URL de Vercel cuando se despliegue y repetir una muestra de casos ahí.
A8: CP-005 | B8: Regresión (V1, mutado) | C8: E1 | D8: Alta | E8: Dirección bloqueada por un muro | F8: HU-01 | G8: No | H8: Aprobado | I8: Aprobado | J8: =IF(OR(H8="—",I8="",I8="No ejecutado"),"—",IF(H8=I8,"No","Sí")) | K8: Luzzi | L8: 46307 | N8: Mutación: Se ejecuta en la fila 10 con ↓ bloqueado, en lugar de ↑. Avanzando a la derecha por la fila 10 con muro debajo (11,2), ↓ no lo detuvo: siguió hacia la derecha (posición 2.68). (Fantasmas retirados y posiciones preparadas por script para aislar la condición.) | P8: Navegador y versión | Q8: Chromium 141 (Playwright), sin interfaz, ventana de 560 × 600
A9: CP-006 | B9: Regresión (V1, Media/Baja) | C9: E1 | D9: Media | E9: Inversión de marcha a mitad de corredor | F9: HU-01 | G9: No | H9: Aprobado | I9: Aprobado | J9: =IF(OR(H9="—",I9="",I9="No ejecutado"),"—",IF(H9=I9,"No","Sí")) | K9: Luzzi | L9: 46323 | N9: A mitad del corredor de la fila 7 (posición 3.33, sin intersección), ← invirtió la marcha de inmediato: dirección «left», posición 3.33 → 1.92. (Fantasmas retirados y posiciones preparadas por script para aislar la condición.) | P9: Fecha de inicio | Q9: 46307
A10: CP-007 | B10: Regresión (V1, mutado) | C10: E1 | D10: Alta | E10: Pacman no atraviesa los muros | F10: HU-02 | G10: No | H10: Aprobado | I10: Aprobado | J10: =IF(OR(H10="—",I10="",I10="No ejecutado"),"—",IF(H10=I10,"No","Sí")) | K10: Luzzi | L10: 46307 | N10: Mutación: Contra un muro a la izquierda (en la V1, a la derecha). Con ← mantenida 5 s contra el muro izquierdo, Pacman se detuvo en (7,1) sin superponerse; luego ↑ lo movió con normalidad (fila 5). (Fantasmas retirados y posiciones preparadas por script para aislar la condición.) | P10: Fecha de cierre | Q10: 46323
A11: CP-008 | B11: Regresión (V1, mutado) | C11: E1 | D11: Alta | E11: Pacman no sale de los límites del mapa | F11: HU-02 | G11: No | H11: Aprobado | I11: Aprobado | J11: =IF(OR(H11="—",I11="",I11="No ejecutado"),"—",IF(H11=I11,"No","Sí")) | K11: Luzzi | L11: 46307 | N11: Mutación: Bordes recorridos en otro orden: abajo, derecha, arriba, izquierda. En los bordes abajo (13,8), derecha (7,15), arriba (1,8) e izquierda (7,1), con la tecla hacia afuera, Pacman no salió del mapa y quedó visible. (Fantasmas retirados y posiciones preparadas por script para aislar la condición.) | P11: Ejecutores | Q11: Luzzi
A12: CP-009 | B12: Regresión (V1, mutado) | C12: E1 | D12: Alta | E12: Los fantasmas clásicos no atraviesan muros | F12: HU-02 | G12: No | H12: Aprobado | I12: Aprobado | J12: =IF(OR(H12="—",I12="",I12="No ejecutado"),"—",IF(H12=I12,"No","Sí")) | K12: Luzzi | L12: 46307 | N12: Mutación: Observación en el nivel 2 en lugar del 1 (solo clásicos al inicio), 60 s. Nivel 2 durante 60 s: ningún fantasma clásico entró a un muro ni salió del mapa (tipos observados: ['classic']). (Vidas repuestas por script para que la partida no termine.) | P12: Forma de ejecución | Q12: Script de navegador (Playwright) que maneja el juego con el teclado y el mouse y lee el estado del juego para verificar los resultados. Cuando una precondición es difícil de alcanzar jugando (posiciones, vidas, mapa reducido), el script la prepara y la observación lo indica.
A13: CP-010 | B13: Regresión (V1, Media/Baja) | C13: E1 | D13: Media | E13: Zona transitable coincidente con el mapa dibujado | F13: HU-02 | G13: No | H13: Aprobado | I13: Aprobado | J13: =IF(OR(H13="—",I13="",I13="No ejecutado"),"—",IF(H13=I13,"No","Sí")) | K13: Luzzi | L13: 46323 | N13: Nivel 1: 107 celdas transitables, todas alcanzables desde la posición de Pacman; 106 marcadas con esfera y la única sin marca es la celda inicial de Pacman (7,8), que ocupa él mismo. Ningún muro tiene esfera. (Recorrido verificado sobre el mapa del juego.)
A14: CP-011 | B14: Regresión (V1, mutado) | C14: E1 | D14: Alta | E14: Consumo de una esfera común | F14: HU-03 | G14: Sí | H14: Aprobado | I14: Aprobado | J14: =IF(OR(H14="—",I14="",I14="No ejecutado"),"—",IF(H14=I14,"No","Sí")) | K14: Luzzi | L14: 46307 | N14: Mutación: Esfera común de otra fila (fila 4). Esfera de (4,3): desapareció; puntaje 0 → 10 (+10); esferas restantes 105 → 104. (Fantasmas retirados y posiciones preparadas por script para aislar la condición.) | P14: Resultados del ciclo 2 (% sobre los casos ejecutados en el ciclo)
A15: CP-012 | B15: Regresión (V1, mutado) | C15: E1 | D15: Alta | E15: Una esfera consumida no reaparece al perder una vida | F15: HU-03 | G15: No | H15: Aprobado | I15: Aprobado | J15: =IF(OR(H15="—",I15="",I15="No ejecutado"),"—",IF(H15=I15,"No","Sí")) | K15: Luzzi | L15: 46307 | N15: Mutación: 15 esferas en lugar de 10, en la fila 10. Pacman consumió 14 esferas en la fila 10; tras perder una vida (3 → 2) la fila sigue despejada (15 de 15 celdas sin esfera). (Fantasmas retirados y posiciones preparadas por script para aislar la condición.) | P15: Estado | Q15: Casos | R15: %
A16: CP-013 | B16: Regresión (V1, Media/Baja) | C16: E1 | D16: Media | E16: Los fantasmas no consumen esferas | F16: HU-03 | G16: No | H16: Aprobado | I16: Aprobado | J16: =IF(OR(H16="—",I16="",I16="No ejecutado"),"—",IF(H16=I16,"No","Sí")) | K16: Luzzi | L16: 46323 | N16: 30 s con Pacman quieto: los fantasmas pasaron por 48 celdas distintas; el contador siguió en 106 → 106 y las esferas del mapa no cambiaron. (Pacman detenido y vidas repuestas por script.) | P16: Aprobado | Q16: =COUNTIF($I$4:$I$132,"Aprobado") | R16: =IFERROR(Q16/SUM($Q$16:$Q$18),0)
A17: CP-014 | B17: Regresión (V1, mutado) | C17: E1 | D17: Alta | E17: Finalización del nivel al consumir la última esfera | F17: HU-04 | G17: Sí | H17: Aprobado | I17: Aprobado | J17: =IF(OR(H17="—",I17="",I17="No ejecutado"),"—",IF(H17=I17,"No","Sí")) | K17: Luzzi | L17: 46307 | N17: Mutación: La última esfera es una de la fila 13. Al consumir la última esfera (13,5) el nivel se completó, la partida se detuvo y se mostró «¡Nivel 1 completado!» con el puntaje. (Mapa reducido a una esfera por script.) | P17: Fallido | Q17: =COUNTIF($I$4:$I$132,"Fallido") | R17: =IFERROR(Q17/SUM($Q$16:$Q$18),0)
A18: CP-015 | B18: Regresión (V1, mutado) | C18: E1 | D18: Alta | E18: El nivel no se completa si queda una esfera grande | F18: HU-04 | G18: No | H18: Aprobado | I18: Aprobado | J18: =IF(OR(H18="—",I18="",I18="No ejecutado"),"—",IF(H18=I18,"No","Sí")) | K18: Luzzi | L18: 46307 | N18: Mutación: La esfera grande pendiente es la de (13,15) en lugar de la de (1,1). Con solo la esfera grande de (13,15) sin consumir, el nivel no se completó y quedan 1 esferas; la partida sigue. (Mapa preparado por script.) | P18: Bloqueado | Q18: =COUNTIF($I$4:$I$132,"Bloqueado") | R18: =IFERROR(Q18/SUM($Q$16:$Q$18),0)
A19: CP-016 | B19: Regresión (V1, mutado) | C19: E1 | D19: Alta | E19: Paso al nivel siguiente conservando puntaje y vidas | F19: HU-04 | G19: Sí | H19: Aprobado | I19: Aprobado | J19: =IF(OR(H19="—",I19="",I19="No ejecutado"),"—",IF(H19=I19,"No","Sí")) | K19: Luzzi | L19: 46307 | N19: Mutación: Se completa el nivel con 3 vidas en lugar de 2. Completado el nivel 1 con 3 vidas y 1200 puntos: empezó el nivel 2 con 1200 puntos y 3 vidas. (Mapa reducido por script.) | P19: Total | Q19: =SUM(Q16:Q18) | R19: =SUM(R16:R18)
A20: CP-017 | B20: Regresión (V1, mutado) | C20: E1 | D20: Alta | E20: Victoria al completar el nivel 3 | F20: HU-04 | G20: Sí | H20: Aprobado | I20: Aprobado | J20: =IF(OR(H20="—",I20="",I20="No ejecutado"),"—",IF(H20=I20,"No","Sí")) | K20: Luzzi | L20: 46307 | N20: Mutación: Partida completa N1 → N2 → N3 con los fantasmas nuevos de la V2. Partida N1 → N2 → N3; en el nivel 3 los fantasmas fueron ['specter', 'jumper', 'naval', 'accelerated']; al consumir la última esfera se mostró «¡Nivel 3 completado!» y luego «¡Victoria!» con el puntaje final. (Mapas reducidos por script.)
A21: CP-018 | B21: Regresión (V1, mutado) | C21: E2 | D21: Alta | E21: Activación automática del PowerUp | F21: HU-05 | G21: Sí | H21: Aprobado | I21: Aprobado | J21: =IF(OR(H21="—",I21="",I21="No ejecutado"),"—",IF(H21=I21,"No","Sí")) | K21: Luzzi | L21: 46307 | N21: Mutación: Esfera grande de (13,1). Al pasar por (13,1) el PowerUp se activó solo; puntaje +50; los fantasmas cambiaron al diseño vulnerable y se alejaron (suma de distancias 48 → 76). (Fantasmas ubicados en el centro por script.)
A22: CP-019 | B22: Regresión (V1, mutado) | C22: E2 | D22: Alta | E22: Duración del PowerUp | F22: HU-05 | G22: No | H22: Aprobado | I22: Aprobado | J22: =IF(OR(H22="—",I22="",I22="No ejecutado"),"—",IF(H22=I22,"No","Sí")) | K22: Luzzi | L22: 46307 | N22: Mutación: Esfera grande de (1,15); observaciones a 7,5 s y 8,5 s. Esfera grande de (1,15): a los 7,5 s los fantasmas seguían vulnerables; a los 8,5 s recuperaron su diseño y volvieron a perseguir. Duración: 8 s.
A23: CP-020 | B23: Regresión (V1, mutado) | C23: E2 | D23: Alta | E23: Los fantasmas huyen durante el PowerUp | F23: HU-05 | G23: No | H23: Aprobado | I23: Aprobado | J23: =IF(OR(H23="—",I23="",I23="No ejecutado"),"—",IF(H23=I23,"No","Sí")) | K23: Luzzi | L23: 46307 | N23: Mutación: Fantasma perseguidor distinto (el rosa). El fantasma rosa venía hacia Pacman por la fila 4; al consumir la esfera grande dejó de acercarse y se alejó (distancia 2 → 7 celdas). (Fantasmas retirados y posiciones preparadas por script para aislar la condición.)
A24: CP-021 | B24: Regresión (V1, Media/Baja) | C24: E2 | D24: Media | E24: Reinicio del temporizador por una segunda esfera grande | F24: HU-05 | G24: No | H24: Aprobado | I24: Aprobado | J24: =IF(OR(H24="—",I24="",I24="No ejecutado"),"—",IF(H24=I24,"No","Sí")) | K24: Luzzi | L24: 46323 | N24: Primera esfera grande (13,1) y, a los 5 s, la segunda (1,1): el PowerUp siguió activo a los 7,8 s del segundo consumo y terminó antes de los 8,2 s (8 s completos, no 3). (Fantasmas retirados y posiciones preparadas por script para aislar la condición.)
A25: CP-022 | B25: Regresión (V1, Media/Baja) | C25: E2 | D25: Media | E25: Reinicio de la escala de puntos por una segunda esfera grande | F25: HU-05 | G25: No | H25: Aprobado | I25: Aprobado | J25: =IF(OR(H25="—",I25="",I25="No ejecutado"),"—",IF(H25=I25,"No","Sí")) | K25: Luzzi | L25: 46323 | N25: Fantasma comido con la primera esfera grande: +200; tras la segunda esfera grande (PowerUp activo), el siguiente fantasma sumó +200: la escala se reinició. (Fantasmas retirados y posiciones preparadas por script para aislar la condición.)
A26: CP-023 | B26: Regresión (V1, mutado) | C26: E2 | D26: Alta | E26: Escala de puntos por fantasmas comidos | F26: HU-06 | G26: Sí | H26: Aprobado | I26: Aprobado | J26: =IF(OR(H26="—",I26="",I26="No ejecutado"),"—",IF(H26=I26,"No","Sí")) | K26: Luzzi | L26: 46307 | N26: Mutación: Se usa la esfera grande de (13,15). Con la esfera grande de (13,15), los cuatro fantasmas comidos sumaron [200, 400, 800, 1600]. (Fantasmas retirados y posiciones preparadas por script para aislar la condición.)
A27: CP-024 | B27: Regresión (V1, mutado) | C27: E2 | D27: Alta | E27: Reinicio de la escala al terminar el PowerUp | F27: HU-06 | G27: No | H27: Aprobado | I27: Aprobado | J27: =IF(OR(H27="—",I27="",I27="No ejecutado"),"—",IF(H27=I27,"No","Sí")) | K27: Luzzi | L27: 46307 | N27: Mutación: Segundo PowerUp con una esfera grande distinta. Primer PowerUp (13,15): fantasma +200; terminado el PowerUp, segundo PowerUp con la esfera de (1,1): fantasma +200. (Fantasmas retirados y posiciones preparadas por script para aislar la condición.)
A28: CP-025 | B28: Regresión (V1, mutado) | C28: E2 | D28: Alta | E28: Comer un fantasma no descuenta vidas | F28: HU-06 | G28: No | H28: Aprobado | I28: Aprobado | J28: =IF(OR(H28="—",I28="",I28="No ejecutado"),"—",IF(H28=I28,"No","Sí")) | K28: Luzzi | L28: 46307 | N28: Mutación: Con 2 vidas en lugar de 3. Con 2 vidas y PowerUp activo, el fantasma tocado desapareció; vidas 2 → 2; el nivel no se reinició (Pacman siguió en la fila 4). (Vidas fijadas en 2 por script.)
A29: CP-026 | B29: Regresión (V1, Media/Baja) | C29: E2 | D29: Media | E29: Reaparición del fantasma comido | F29: HU-06 | G29: No | H29: Aprobado | I29: Aprobado | J29: =IF(OR(H29="—",I29="",I29="No ejecutado"),"—",IF(H29=I29,"No","Sí")) | K29: Luzzi | L29: 46323 | N29: El fantasma rojo comido desapareció y reapareció a los 5.00 s en su punto de reaparición (1, 1); luego siguió moviéndose. (PowerUp prolongado por script para observar la reaparición.)
A30: CP-027 | B30: Regresión (V1, Media/Baja) | C30: E2 | D30: Media | E30: Fantasma que reaparece con el PowerUp aún activo | F30: HU-06 | G30: No | H30: Aprobado | I30: Aprobado | J30: =IF(OR(H30="—",I30="",I30="No ejecutado"),"—",IF(H30=I30,"No","Sí")) | K30: Luzzi | L30: 46323 | N30: Primer bocado +200; el fantasma reapareció a los 5.03 s con el PowerUp activo y en estado vulnerable; comido otra vez sumó +400: la escala siguió. (Fantasmas retirados y posiciones preparadas por script para aislar la condición.)
A31: CP-028 | B31: Regresión (V1, Media/Baja) | C31: E2 | D31: Media | E31: Parpadeo en los últimos 2 segundos del PowerUp | F31: HU-07 | G31: No | H31: Aprobado | I31: Aprobado | J31: =IF(OR(H31="—",I31="",I31="No ejecutado"),"—",IF(H31=I31,"No","Sí")) | K31: Luzzi | L31: 46323 | N31: A los 5 s los fantasmas se veían azules fijos (colores muestreados: ['azul']); a los 7 s alternaban azul y blanco (parpadeo, colores: ['azul', 'blanco']), distinto del azul fijo y del color normal. (Capturas CP-028-5s y CP-028-7s; colores leídos del canvas.)
... A36: CP-033 | B36: Regresión (V1, mutado) | C36: E2 | D36: Alta | E36: Reanudación del nivel tras perder una vida | F36: HU-08 | G36: No | H36: Aprobado | I36: Aprobado | J36: =IF(OR(H36="—",I36="",I36="No ejecutado"),"—",IF(H36=I36,"No","Sí")) | K36: Luzzi | L36: 46307 | N36: Mutación: Con 20 esferas consumidas. Con 20 esferas consumidas se perdió una vida: siguió el nivel 1, puntaje 200 → 200, las esferas consumidas siguen ausentes y los personajes volvieron a sus posiciones iniciales. (Fantasmas retirados y posiciones preparadas por script para aislar la condición.)
A37: CP-034 | B37: Confirmación DEF-001 | C37: E3 | D37: Media | E37: Presentación del contador de vidas | F37: HU-09 | G37: No | H37: Fallido | I37: Aprobado | J37: =IF(OR(H37="—",I37="",I37="No ejecutado"),"—",IF(H37=I37,"No","Sí")) | K37: Luzzi | L37: 46307 | M37: DEF-001 | N37: Las vidas se muestran abajo a la izquierda, debajo del mapa, como 3 íconos de Pacman (sin número); al perder una vida quedan 2. CP-034: Fallido en Entrega 1 → Aprobado. | P37: Comparación de resultados por entrega (%)
A38: CP-035 | B38: Regresión (V1, Media/Baja) | C38: E3 | D38: Media | E38: Actualización inmediata del contador de vidas | F38: HU-09 | G38: No | H38: Aprobado | I38: Aprobado | J38: =IF(OR(H38="—",I38="",I38="No ejecutado"),"—",IF(H38=I38,"No","Sí")) | K38: Luzzi | L38: 46323 | N38: Íconos de vidas tras cada pérdida: 3 → 2 → 1 → 0; el contador se actualizó en el momento de cada pérdida (la tercera terminó en Game Over). (Fantasmas retirados y posiciones preparadas por script para aislar la condición.) | P38: Estado | Q38: Entrega 1 (V1) | R38: Entrega 2 (V2) | S38: Casos E1 / E2
A39: CP-036 | B39: Regresión (V1, mutado) | C39: E3 | D39: Alta | E39: Game Over al perder la tercera vida | F39: HU-10 | G39: Sí | H39: Aprobado | I39: Aprobado | J39: =IF(OR(H39="—",I39="",I39="No ejecutado"),"—",IF(H39=I39,"No","Sí")) | K39: Luzzi | L39: 46307 | N39: Mutación: Última vida perdida en el nivel 2. Última vida perdida en el nivel 2: se mostró «Game Over» con el puntaje final (0); 5 s después la partida seguía terminada, sin reiniciarse ni reanudarse. (Vidas fijadas en 1 por script.) | P39: Aprobado | Q39: 0.96969697 | R39: =R16 | S39: ="64 / "&Q16
A40: CP-037 | B40: Regresión (V1, Media/Baja) | C40: E3 | D40: Media | E40: Game Over en un nivel distinto del primero | F40: HU-10 | G40: No | H40: Aprobado | I40: Aprobado | J40: =IF(OR(H40="—",I40="",I40="No ejecutado"),"—",IF(H40=I40,"No","Sí")) | K40: Luzzi | L40: 46323 | N40: Última vida perdida en el nivel 3: pantalla «Game Over» con el puntaje final y «Volver a jugar», igual que en el nivel 1; la partida no se reanudó. (Vidas fijadas en 1 por script.) | P40: Fallido | Q40: 0.015151515 | R40: =R17 | S40: ="1 / "&Q17
A41: CP-038 | B41: Regresión (V1, Media/Baja) | C41: E3 | D41: Media | E41: Puntaje visible y actualizado en el HUD | F41: HU-11 | G41: Sí | H41: Aprobado | I41: Aprobado | J41: =IF(OR(H41="—",I41="",I41="No ejecutado"),"—",IF(H41=I41,"No","Sí")) | K41: Luzzi | L41: 46323 | N41: HUD: puntaje inicial 0; después de cada acción [10, 60, 260] (incrementos [10, 50, 200]: esfera común, esfera grande y fantasma). (Fantasmas retirados y posiciones preparadas por script para aislar la condición.) | P41: Bloqueado | Q41: 0.015151515 | R41: =R18 | S41: ="1 / "&Q18
A42: CP-039 | B42: Regresión (V1, Media/Baja) | C42: E3 | D42: Media | E42: El puntaje no disminuye ni se reinicia entre niveles | F42: HU-11 | G42: No | H42: Aprobado | I42: Aprobado | J42: =IF(OR(H42="—",I42="",I42="No ejecutado"),"—",IF(H42=I42,"No","Sí")) | K42: Luzzi | L42: 46323 | N42: Puntaje 60; tras perder una vida: 60; al completar el nivel 1: 1240; al iniciar el nivel 2: 1240. Nunca disminuyó. (Mapa reducido por script para completar el nivel.) | P42: Fuente Entrega 1: reporte de ejecución de la Entrega 1 (66 casos: 64 aprobados, 1 fallido, 1 bloqueado).
A43: CP-040 | B43: Regresión (V1, Media/Baja) | C43: E3 | D43: Media | E43: Consumo de una fruta | F43: HU-12 | G43: Sí | H43: Aprobado | I43: Aprobado | J43: =IF(OR(H43="—",I43="",I43="No ejecutado"),"—",IF(H43=I43,"No","Sí")) | K43: Luzzi | L43: 46323 | N43: Fruta aparecida en (9,8) en el nivel 3: Pacman la consumió, desapareció del mapa, el puntaje subió +100 y el contador de esferas quedó en 124 → 124. (Esfera de la celda retirada por script para medir solo la fruta.)
A44: CP-041 | B44: Regresión (V1, Media/Baja) | C44: E3 | D44: Baja | E44: Desaparición de una fruta no consumida | F44: HU-12 | G44: No | H44: Aprobado | I44: Aprobado | J44: =IF(OR(H44="—",I44="",I44="No ejecutado"),"—",IF(H44=I44,"No","Sí")) | K44: Luzzi | L44: 46323 | N44: Fruta aparecida en (9,4): a los 14 s seguía en el mapa; a los 16 s ya no estaba.
A45: CP-042 | B45: Regresión (V1, Media/Baja) | C45: E3 | D45: Media | E45: Cálculo del bonus por tiempo | F45: HU-13 | G45: No | H45: Aprobado | I45: Aprobado | J45: =IF(OR(H45="—",I45="",I45="No ejecutado"),"—",IF(H45=I45,"No","Sí")) | K45: Luzzi | L45: 46323 | N45: Nivel 1 completado en 3.68 s: bonus por tiempo 1160 = 10 × 116 s enteros restantes (fracción descartada); el desglose lo suma. (Mapa reducido a una esfera por script.)
A46: CP-043 | B46: Regresión (V1, Media/Baja) | C46: E3 | D46: Media | E46: Bonus por tiempo al exceder el tiempo objetivo | F46: HU-13 | G46: No | H46: Aprobado | I46: Aprobado | J46: =IF(OR(H46="—",I46="",I46="No ejecutado"),"—",IF(H46=I46,"No","Sí")) | K46: Luzzi | L46: 46323 | N46: Nivel 1 completado a los 121.75 s (más de 120 s reales de juego): bonus por tiempo 0, no negativo. (Mapa reducido a una esfera por script al final.)
A47: CP-044 | B47: Regresión (V1, Media/Baja) | C47: E3 | D47: Media | E47: Bonus por vidas restantes y consistencia del desglose | F47: HU-13 | G47: No | H47: Aprobado | I47: Aprobado | J47: =IF(OR(H47="—",I47="",I47="No ejecutado"),"—",IF(H47=I47,"No","Sí")) | K47: Luzzi | L47: 46323 | N47: Victoria con 2 vidas: desglose {'Esferas': '30', 'Fantasmas comidos': '0', 'Frutas': '0', 'Bonus por tiempo': '4470', 'Bonus por vidas': '1000', 'Total': '5500'}; bonus por vidas 1000 (500 × 2) y la suma de los componentes coincide con el total. (Vidas fijadas en 2 y mapas reducidos por script.)
A48: CP-045 | B48: Regresión (V1, Media/Baja) | C48: E3 | D48: Media | E48: Bonus por vidas en un Game Over | F48: HU-13 | G48: No | H48: Aprobado | I48: Aprobado | J48: =IF(OR(H48="—",I48="",I48="No ejecutado"),"—",IF(H48=I48,"No","Sí")) | K48: Luzzi | L48: 46323 | N48: Game Over: desglose {'Esferas': '0', 'Fantasmas comidos': '0', 'Frutas': '0', 'Bonus por tiempo': '0', 'Bonus por vidas': '0', 'Total': '0'}; bonus por vidas restantes 0. (Vidas fijadas en 1 por script.)
A49: CP-046 | B49: Regresión (V1, Media/Baja) | C49: E3 | D49: Baja | E49: Contador de esferas restantes | F49: HU-14 | G49: No | H49: Aprobado | I49: Aprobado | J49: =IF(OR(H49="—",I49="",I49="No ejecutado"),"—",IF(H49=I49,"No","Sí")) | K49: Luzzi | L49: 46323 | N49: Inicio: contador 106 = 106 esferas del mapa (incluidas las 4 grandes); tras 5 esferas: 100 (−5); al consumir la última: 0; nivel 2: 131 = 131 esferas de su mapa. (Para la parte final, mapa del nivel 1 reducido a una esfera por script.)
A50: CP-047 | B50: Regresión (V1, mutado) | C50: E4 | D50: Alta | E50: Los tres niveles y sus mapas | F50: HU-15 | G50: Sí | H50: Aprobado | I50: Aprobado | J50: =IF(OR(H50="—",I50="",I50="No ejecutado"),"—",IF(H50=I50,"No","Sí")) | K50: Luzzi | L50: 46307 | N50: Mutación: Partida completa; se registra además la barra inferior de vidas (DEF-001). Niveles 1, 2 y 3 en orden; HUD: ['Nivel 1', 'Nivel 2', 'Nivel 3']. Los tres mapas tienen forma distinta. Color medio de muros: N1 [168, 25, 37] con 148 muestras rojas (franjas), N2 [11, 29, 77] (azul, sin rojo), N3 [14, 78, 18] (verde). Barra inferior de vidas con 3 íconos de Pacman en los tres niveles (DEF-001). (Mapas reducidos por script para avanzar; capturas REG-CP-047-N1..N3.)
A51: CP-048 | B51: Regresión (V1, Media/Baja) | C51: E4 | D51: Media | E51: Los mapas no varían entre partidas | F51: HU-15 | G51: No | H51: Aprobado | I51: Aprobado | J51: =IF(OR(H51="—",I51="",I51="No ejecutado"),"—",IF(H51=I51,"No","Sí")) | K51: Luzzi | L51: 46323 | N51: Dos partidas nuevas: el mapa del nivel 1 es idéntico en forma, esferas y ubicación de las esferas grandes.
A52: CP-049 | B52: Regresión (V1, mutado) | C52: E4 | D52: Alta | E52: Solo fantasmas clásicos en el nivel 1 | F52: HU-16 | G52: No | H52: Aprobado | I52: Aprobado | J52: =IF(OR(H52="—",I52="",I52="No ejecutado"),"—",IF(H52=I52,"No","Sí")) | K52: Luzzi | L52: 46307 | N52: Mutación: Se agregan 30 s más de observación. Nivel 1 observado 40 s (30 s más que en la V1): tipos ['classic'], velocidades [5] celdas/s; ninguno atravesó muros, saltó, colocó frutas ni hizo dash. (Vidas repuestas por script.) Re-ejecutado el 28/10/2026 con la velocidad reducida (decisiones 39 y 40): Aprobado; ver el ciclo 3 en la hoja del caso.
A53: CP-050 | B53: Regresión (V1, mutado) | C53: E4 | D53: Alta | E53: Reaparición como clásico en el nivel 1 | F53: HU-16 | G53: No | H53: Aprobado | I53: Aprobado | J53: =IF(OR(H53="—",I53="",I53="No ejecutado"),"—",IF(H53=I53,"No","Sí")) | K53: Luzzi | L53: 46307 | N53: Mutación: 6 fantasmas comidos en lugar de 4. Nivel 1: 6 fantasmas comidos; reaparecieron como ['classic', 'classic', 'classic', 'classic', 'classic', 'classic']. (PowerUp prolongado y reaparición acelerada por script.)
A54: CP-051 | B54: Regresión (V1, mutado) | C54: E4 | D54: Alta | E54: Composición inicial de fantasmas del nivel 2 | F54: HU-17 | G54: No | H54: Aprobado | I54: Aprobado | J54: =IF(OR(H54="—",I54="",I54="No ejecutado"),"—",IF(H54=I54,"No","Sí")) | K54: Luzzi | L54: 46307 | N54: Mutación: Sin cambios de datos: se verifica tras completar el nivel 1 con 2 vidas. Nivel 1 completado con 2 vidas; al iniciar el nivel 2 los cuatro fantasmas son ['classic', 'classic', 'classic', 'classic']. (Mapa reducido por script.)
... A59: CP-056 | B59: Regresión (V1, Media/Baja) | C59: E4 | D59: Media | E59: Cooldown de la habilidad del espectro | F59: HU-18 | G59: No | H59: Aprobado | I59: Aprobado | J59: =IF(OR(H59="—",I59="",I59="No ejecutado"),"—",IF(H59=I59,"No","Sí")) | K59: Luzzi | L59: 46323 | N59: Nivel 3, 60 s: el espectro empezó a cruzar paredes en t = [2.58, 14.8, 25.7, 35.72, 46.63, 57.55] s; intervalos [12.22, 10.9, 10.02, 10.91, 10.92] s, todos ≥ 10 s. (Vidas repuestas y otros fantasmas retirados por script.)
A60: CP-057 | B60: Regresión (V1, mutado) | C60: E4 | D60: Alta | E60: Estado de gracia del espectro tras atravesar un muro | F60: HU-18 | G60: No | H60: Aprobado | I60: Aprobado | J60: =IF(OR(H60="—",I60="",I60="No ejecutado"),"—",IF(H60=I60,"No","Sí")) | K60: Luzzi | L60: 46307 | N60: Mutación: Precondición ajustada (decisión 23): se identifica al espectro entre los cuatro tipos. Tras atravesar una pared, el contacto dentro de los 3 s no descontó vidas (3 → 3) y el espectro se veía translúcido y punteado (captura); pasados los 3 s el contacto descontó una vida (3 → 2). (Contacto provocado por script.) | P60: Resumen por tipo de prueba (sección 12.4)
A61: CP-058 | B61: Regresión (V1, Media/Baja) | C61: E4 | D61: Media | E61: El espectro no sale del mapa con su habilidad | F61: HU-18 | G61: No | H61: Aprobado | I61: Aprobado | J61: =IF(OR(H61="—",I61="",I61="No ejecutado"),"—",IF(H61=I61,"No","Sí")) | K61: Luzzi | L61: 46323 | N61: Nivel 3, 90 s: el espectro cruzó 8 paredes; nunca salió del mapa ni quedó detenido dentro de un muro (0 muestras fuera de lugar). (Vidas repuestas y otros fantasmas retirados por script.) | P61: Tipo de prueba | Q61: Diseñados | R61: Ejecutados | S61: Aprobados | T61: Fallidos | U61: Bloqueados | V61: Tasa de aprobación
A62: CP-059 | B62: Regresión (V1, mutado) | C62: E4 | D62: Alta | E62: El espectro es vulnerable durante el PowerUp | F62: HU-18 | G62: No | H62: Aprobado | I62: Aprobado | J62: =IF(OR(H62="—",I62="",I62="No ejecutado"),"—",IF(H62=I62,"No","Sí")) | K62: Luzzi | L62: 46307 | N62: Mutación: Precondición ajustada (decisión 23): se identifica al espectro entre los cuatro tipos. Con la esfera grande el espectro pasó a vulnerable; al comerlo sumó +200 (primer fantasma de la escala) y las vidas quedaron en 3. (Fantasmas retirados y posiciones preparadas por script para aislar la condición.) | P62: Casos nuevos de la V2 | Q62: =COUNTIF($B$4:$B$132,"Nuevo (V2)") | R62: =COUNTIFS($B$4:$B$132,"Nuevo (V2)",$I$4:$I$132,"Aprobado")+COUNTIFS($B$4:$B$132,"Nuevo (V2)",$I$4:$I$132,"Fallido") | S62: =COUNTIFS($B$4:$B$132,"Nuevo (V2)",$I$4:$I$132,"Aprobado") | T62: =COUNTIFS($B$4:$B$132,"Nuevo (V2)",$I$4:$I$132,"Fallido") | U62: =COUNTIFS($B$4:$B$132,"Nuevo (V2)",$I$4:$I$132,"Bloqueado") | V62: =IFERROR(S62/R62,0)
A63: CP-060 | B63: Regresión (V1, mutado) | C63: E4 | D63: Alta | E63: Pantalla de Game Over | F63: HU-19 | G63: Sí | H63: Aprobado | I63: Aprobado | J63: =IF(OR(H63="—",I63="",I63="No ejecutado"),"—",IF(H63=I63,"No","Sí")) | K63: Luzzi | L63: 46307 | N63: Mutación: Además se verifica la acción «Menú principal» (decisión 29). Última vida perdida en el nivel 1: pantalla «Game Over» con el puntaje desglosado (Esferas, Fantasmas comidos, Frutas, Bonus por tiempo, Bonus por vidas, Total) y las acciones «Volver a jugar» y «Menú principal»; «Menú principal» llevó al menú. (Vidas fijadas en 1 por script.) | P63: Regresión de la V1, prioridad Alta (mutados) | Q63: =COUNTIF($B$4:$B$132,"Regresión (V1, mutado)") | R63: =COUNTIFS($B$4:$B$132,"Regresión (V1, mutado)",$I$4:$I$132,"Aprobado")+COUNTIFS($B$4:$B$132,"Regresión (V1, mutado)",$I$4:$I$132,"Fallido") | S63: =COUNTIFS($B$4:$B$132,"Regresión (V1, mutado)",$I$4:$I$132,"Aprobado") | T63: =COUNTIFS($B$4:$B$132,"Regresión (V1, mutado)",$I$4:$I$132,"Fallido") | U63: =COUNTIFS($B$4:$B$132,"Regresión (V1, mutado)",$I$4:$I$132,"Bloqueado") | V63: =IFERROR(S63/R63,0)
A64: CP-061 | B64: Regresión (V1, mutado) | C64: E4 | D64: Alta | E64: Pantalla de Victoria | F64: HU-19 | G64: Sí | H64: Aprobado | I64: Aprobado | J64: =IF(OR(H64="—",I64="",I64="No ejecutado"),"—",IF(H64=I64,"No","Sí")) | K64: Luzzi | L64: 46307 | N64: Mutación: Además se verifica la acción «Menú principal» (decisión 29). Completado el nivel 3: pantalla «¡Victoria!» con el puntaje desglosado (Esferas, Fantasmas comidos, Frutas, Bonus por tiempo, Bonus por vidas, Total) y las acciones «Volver a jugar» y «Menú principal»; «Menú principal» llevó al menú. (Mapa reducido por script.) | P64: Re-ejecución de casos bloqueados | Q64: =COUNTIF($B$4:$B$132,"Re-ejecución*") | R64: =COUNTIFS($B$4:$B$132,"Re-ejecución*",$I$4:$I$132,"Aprobado")+COUNTIFS($B$4:$B$132,"Re-ejecución*",$I$4:$I$132,"Fallido") | S64: =COUNTIFS($B$4:$B$132,"Re-ejecución*",$I$4:$I$132,"Aprobado") | T64: =COUNTIFS($B$4:$B$132,"Re-ejecución*",$I$4:$I$132,"Fallido") | U64: =COUNTIFS($B$4:$B$132,"Re-ejecución*",$I$4:$I$132,"Bloqueado") | V64: =IFERROR(S64/R64,0)
A65: CP-062 | B65: Regresión (V1, mutado) | C65: E4 | D65: Alta | E65: Reinicio completo del estado al volver a jugar | F65: HU-19 | G65: Sí | H65: Aprobado | I65: Aprobado | J65: =IF(OR(H65="—",I65="",I65="No ejecutado"),"—",IF(H65=I65,"No","Sí")) | K65: Luzzi | L65: 46307 | N65: Mutación: Game Over en el nivel 2; se verifica además que «Volver a jugar» mantiene el modo Pacman (decisión 29). Game Over en el nivel 2 con 1200 puntos; «Volver a jugar» inició el modo Pacman en el nivel 1 con 3 vidas, puntaje 0 y 106 esferas (mapa completo); al pasar al nivel 2 su mapa también estaba completo (131 esferas). (Mapas reducidos por script para avanzar.) | P65: Confirmación de defectos | Q65: =COUNTIF($B$4:$B$132,"Confirmación*") | R65: =COUNTIFS($B$4:$B$132,"Confirmación*",$I$4:$I$132,"Aprobado")+COUNTIFS($B$4:$B$132,"Confirmación*",$I$4:$I$132,"Fallido") | S65: =COUNTIFS($B$4:$B$132,"Confirmación*",$I$4:$I$132,"Aprobado") | T65: =COUNTIFS($B$4:$B$132,"Confirmación*",$I$4:$I$132,"Fallido") | U65: =COUNTIFS($B$4:$B$132,"Confirmación*",$I$4:$I$132,"Bloqueado") | V65: =IFERROR(S65/R65,0)
A66: CP-063 | B66: Regresión (V1, Media/Baja) | C66: E5 | D66: Media | E66: Pausa y reanudación con ESC | F66: HU-20 | G66: Sí | H66: Aprobado | I66: Aprobado | J66: =IF(OR(H66="—",I66="",I66="No ejecutado"),"—",IF(H66=I66,"No","Sí")) | K66: Luzzi | L66: 46323 | N66: ESC detuvo la partida y mostró el cartel de pausa; durante 5 s Pacman y los fantasmas quedaron inmóviles; las flechas no movieron a Pacman; el segundo ESC reanudó la partida y se quitó el cartel. | P66: Regresión de la V1, prioridad Media y Baja | Q66: =COUNTIF($B$4:$B$132,"Regresión (V1, Media/Baja)") | R66: =COUNTIFS($B$4:$B$132,"Regresión (V1, Media/Baja)",$I$4:$I$132,"Aprobado")+COUNTIFS($B$4:$B$132,"Regresión (V1, Media/Baja)",$I$4:$I$132,"Fallido") | S66: =COUNTIFS($B$4:$B$132,"Regresión (V1, Media/Baja)",$I$4:$I$132,"Aprobado") | T66: =COUNTIFS($B$4:$B$132,"Regresión (V1, Media/Baja)",$I$4:$I$132,"Fallido") | U66: =COUNTIFS($B$4:$B$132,"Regresión (V1, Media/Baja)",$I$4:$I$132,"Bloqueado") | V66: =IFERROR(S66/R66,0)
A67: CP-064 | B67: Regresión (V1, Media/Baja) | C67: E5 | D67: Media | E67: Los temporizadores se detienen durante la pausa | F67: HU-20 | G67: No | H67: Aprobado | I67: Aprobado | J67: =IF(OR(H67="—",I67="",I67="No ejecutado"),"—",IF(H67=I67,"No","Sí")) | K67: Luzzi | L67: 46323 | N67: Pausa a los 2 s del PowerUp durante 15 s: el PowerUp siguió activo con el temporizador detenido en 5.95 s; al reanudar duró 5.97 s más (6 s). (Fantasmas retirados y posiciones preparadas por script para aislar la condición.) | P67: Total | Q67: =SUM(Q62:Q66) | R67: =SUM(R62:R66) | S67: =SUM(S62:S66) | T67: =SUM(T62:T66) | U67: =SUM(U62:U66) | V67: =IFERROR(S67/R67,0)
A68: CP-065 | B68: Regresión (V1, Media/Baja) | C68: E5 | D68: Baja | E68: El bonus por tiempo no se afecta por la pausa | F68: HU-20 | G68: No | H68: Aprobado | I68: Aprobado | J68: =IF(OR(H68="—",I68="",I68="No ejecutado"),"—",IF(H68=I68,"No","Sí")) | K68: Luzzi | L68: 46323 | N68: Nivel 1 con una pausa de 60 s: tiempo de juego efectivo 4.87 s (reloj real ≈ 64 s; durante la pausa el tiempo no avanzó); bonus por tiempo 1150 = 10 × 115, sin descontar la pausa. (Mapa reducido a una esfera por script para completar el nivel.)
A69: CP-066 | B69: Regresión (V1, Media/Baja) | C69: E5 | D69: Baja | E69: La barra espaciadora no tiene efecto en modo Pacman | F69: HU-21 | G69: No | H69: Aprobado | I69: Aprobado | J69: =IF(OR(H69="—",I69="",I69="No ejecutado"),"—",IF(H69=I69,"No","Sí")) | K69: Luzzi | L69: 46323 | N69: 10 pulsaciones de la barra espaciadora: puntaje, vidas, pausa, PowerUp y estado de la partida sin cambios ([0, 3, False, False, False] → [0, 3, False, False, False]); la página no hizo scroll (scrollY 0 → 0). | P69: Indicadores
A70: CP-067 | B70: Nuevo (V2) | C70: E6 | D70: Alta | E70: Selección del modo Pacman | F70: HU-22 | G70: Sí | H70: — | I70: Aprobado | J70: =IF(OR(H70="—",I70="",I70="No ejecutado"),"—",IF(H70=I70,"No","Sí")) | K70: Luzzi | L70: 46307 | N70: Menú con «Modo PacMan» (seleccionada) y «Modo GhostMan». Enter inicia el modo Pacman en el nivel 1; ← mueve a Pacman; 3 íconos de Pacman en la barra inferior. | P70: Avance de la ejecución (ejecutados / diseñados) | Q70: =IFERROR(R67/Q67,0)
A71: CP-068 | B71: Nuevo (V2) | C71: E6 | D71: Alta | E71: Selección del modo GhostMan | F71: HU-22 | G71: Sí | H71: — | I71: Aprobado | J71: =IF(OR(H71="—",I71="",I71="No ejecutado"),"—",IF(H71=I71,"No","Sí")) | K71: Luzzi | L71: 46307 | N71: ↓ selecciona «Modo GhostMan»; Enter abre el carrusel con «Clásico» en el centro. | P71: Tasa de aprobación (aprobados / ejecutados) | Q71: =IFERROR(S67/R67,0)
A72: CP-069 | B72: Nuevo (V2) | C72: E6 | D72: Media | E72: Ícono de vidas según el modo | F72: HU-22 | G72: No | H72: — | I72: Aprobado | J72: =IF(OR(H72="—",I72="",I72="No ejecutado"),"—",IF(H72=I72,"No","Sí")) | K72: Luzzi | L72: 46307 | N72: Modo Pacman: barra «Vidas» con 3 íconos de Pacman. Modo GhostMan: «Vidas de Pacman» con 3 íconos de fantasma. | P72: Tasa de fallo (fallidos / ejecutados) | Q72: =IFERROR(T67/R67,0)
A73: CP-070 | B73: Nuevo (V2) | C73: E6 | D73: Alta | E73: Contenido del carrusel de fantasmas | F73: HU-23 | G73: Sí | H73: — | I73: Aprobado | J73: =IF(OR(H73="—",I73="",I73="No ejecutado"),"—",IF(H73=I73,"No","Sí")) | K73: Luzzi | L73: 46307 | N73: Tipos en orden: Clásico, Espectro, Saltarín, Naval, Acelerado. Cada uno con su nombre debajo y la descripción del poder como subtítulo. | P73: Cobertura de prioridad Alta de la V2 (ejecutados / diseñados) | Q73: =IFERROR((COUNTIFS($B$4:$B$132,"Nuevo (V2)",$D$4:$D$132,"Alta",$I$4:$I$132,"Aprobado")+COUNTIFS($B$4:$B$132,"Nuevo (V2)",$D$4:$D$132,"Alta",$I$4:$I$132,"Fallido"))/COUNTIFS($B$4:$B$132,"Nuevo (V2)",$D$4:$D$132,"Alta"),0)
A74: CP-071 | B74: Nuevo (V2) | C74: E6 | D74: Media | E74: Navegación circular del carrusel | F74: HU-23 | G74: No | H74: — | I74: Aprobado | J74: =IF(OR(H74="—",I74="",I74="No ejecutado"),"—",IF(H74=I74,"No","Sí")) | K74: Luzzi | L74: 46307 | N74: ← → Acelerado; D → Clásico; A → Acelerado. | P74: Defectos nuevos detectados en la V2 | Q74: =COUNTIFS('Registro de defectos'!$H$5:$H$104,"V2*",'Registro de defectos'!$G$5:$G$104,"<>Rechazado")
A75: CP-072 | B75: Nuevo (V2) | C75: E6 | D75: Alta | E75: Confirmación con Enter | F75: HU-23 | G75: Sí | H75: — | I75: Aprobado | J75: =IF(OR(H75="—",I75="",I75="No ejecutado"),"—",IF(H75=I75,"No","Sí")) | K75: Luzzi | L75: 46307 | N75: Enter con el Naval en el centro inicia el modo GhostMan con el Naval (velocidad 4 celdas/s) en la esquina superior izquierda. Re-ejecutado el 28/10/2026 con la velocidad reducida un 25 % (decisión 39): Aprobado; ver el ciclo 3 en la hoja del caso. | P75: Casos que cambiaron de estado respecto de la Entrega 1 | Q75: =COUNTIF($J$4:$J$132,"Sí")
A76: CP-073 | B76: Nuevo (V2) | C76: E6 | D76: Alta | E76: Inmutabilidad de la selección | F76: HU-23 | G76: No | H76: — | I76: Aprobado | J76: =IF(OR(H76="—",I76="",I76="No ejecutado"),"—",IF(H76=I76,"No","Sí")) | K76: Luzzi | L76: 46307 | N76: Con ← → A D Enter durante 4 s el carrusel no se abre; tras pausar y reanudar el fantasma sigue siendo el Espectro.
A77: CP-074 | B77: Nuevo (V2) | C77: E6 | D77: Alta | E77: Control del fantasma con flechas y WASD | F77: HU-24 | G77: Sí | H77: — | I77: Aprobado | J77: =IF(OR(H77="—",I77="",I77="No ejecutado"),"—",IF(H77=I77,"No","Sí")) | K77: Luzzi | L77: 46307 | N77: Con ↓ → el fantasma bajó y giró a la derecha (celda 4,6); con W A subió y giró a la izquierda (celda 4,3). Precondición preparada por script (posiciones y fantasmas de la IA retirados) para aislar la condición. | P77: Casos que cambiaron de estado entre la Entrega 1 y la Entrega 2
A78: CP-075 | B78: Nuevo (V2) | C78: E6 | D78: Alta | E78: El fantasma respeta los muros | F78: HU-24 | G78: No | H78: — | I78: Aprobado | J78: =IF(OR(H78="—",I78="",I78="No ejecutado"),"—",IF(H78=I78,"No","Sí")) | K78: Luzzi | L78: 46307 | N78: Durante 7 s contra el borde superior y los muros de la fila 2, el fantasma nunca entró a un muro ni salió del mapa. Precondición preparada por script (posiciones y fantasmas de la IA retirados) para aislar la condición. | P78: Caso | Q78: Entrega 1 | R78: Entrega 2 | S78: Motivo
A79: CP-076 | B79: Nuevo (V2) | C79: E6 | D79: Alta | E79: Pacman y los demás fantasmas bajo IA | F79: HU-24 | G79: Sí | H79: — | I79: Aprobado | J79: =IF(OR(H79="—",I79="",I79="No ejecutado"),"—",IF(H79=I79,"No","Sí")) | K79: Luzzi | L79: 46307 | N79: En 10 s sin teclas Pacman consumió 39 esferas; los 3 fantasmas de la IA se movieron y el del jugador quedó quieto. | P79: CP-034 · Presentación del contador de vidas | Q79: Fallido | R79: Aprobado | S79: DEF-001 corregido en el commit 7ec70df (vidas abajo a la izquierda con íconos de Pacman); confirmación aprobada.
A80: CP-077 | B80: Nuevo (V2) | C80: E6 | D80: Alta | E80: Derrota de Pacman y reinicio del nivel | F80: HU-25 | G80: Sí | H80: — | I80: Aprobado | J80: =IF(OR(H80="—",I80="",I80="No ejecutado"),"—",IF(H80=I80,"No","Sí")) | K80: Luzzi | L80: 46307 | N80: Vidas de Pacman 3 → 2, puntaje +500; Pacman volvió a su posición inicial (7,8) y el fantasma a (1,1); las esferas consumidas siguen consumidas (86 → 86 restantes). | P80: CP-032 · El PowerUp se cancela al perder una vida | Q80: Bloqueado | R80: Bloqueado | S80: Sin cambio. Se había informado Aprobado el 12/10, pero se corrigió: la precondición no se puede dar en el juego (ver la observación del caso).
A81: CP-078 | B81: Nuevo (V2) | C81: E6 | D81: Alta | E81: Contador de derrotas de Pacman | F81: HU-25 | G81: No | H81: — | I81: Aprobado | J81: =IF(OR(H81="—",I81="",I81="No ejecutado"),"—",IF(H81=I81,"No","Sí")) | K81: Luzzi | L81: 46307 | N81: Contador visible: 3; tras el toque de un fantasma de la IA: 3; tras el toque del jugador: 2. | P81: Los 64 casos de regresión de la V1 (35 Alta y 29 Media/Baja) mantienen el estado Aprobado de la Entrega 1. Solo CP-034 cambió de estado.
A82: CP-079 | B82: Nuevo (V2) | C82: E6 | D82: Alta | E82: Nivel completado con 3 derrotas | F82: HU-25 | G82: Sí | H82: — | I82: Aprobado | J82: =IF(OR(H82="—",I82="",I82="No ejecutado"),"—",IF(H82=I82,"No","Sí")) | K82: Luzzi | L82: 46307 | N82: Tercera derrota: el nivel se completó y se mostró el resultado; a los 3 s empezó el nivel 2 con 3 vidas de Pacman. (Vidas previas fijadas en 1 por script.)
A83: CP-080 | B83: Nuevo (V2) | C83: E6 | D83: Alta | E83: Game Over si Pacman consume la última esfera | F83: HU-26 | G83: No | H83: — | I83: Aprobado | J83: =IF(OR(H83="—",I83="",I83="No ejecutado"),"—",IF(H83=I83,"No","Sí")) | K83: Luzzi | L83: 46307 | N83: Con 1 derrota de Pacman en el nivel (2 vidas), Pacman consumió la última esfera: Game Over con el puntaje y «Volver a jugar». (Mapa reducido a una esfera por script.) | P83: Resultados por épica (sección 12.5)
A84: CP-081 | B84: Nuevo (V2) | C84: E6 | D84: Alta | E84: Vulnerabilidad durante el PowerUp de Pacman | F84: HU-27 | G84: Sí | H84: — | I84: Aprobado | J84: =IF(OR(H84="—",I84="",I84="No ejecutado"),"—",IF(H84=I84,"No","Sí")) | K84: Luzzi | L84: 46307 | N84: Pacman consumió una esfera grande (ubicada junto a él por script) y el fantasma del jugador pasó al diseño vulnerable; al tocar a Pacman no lo derrotó (vidas 3 → 3; el fantasma fue comido: True). | P84: Épica | Q84: Diseñados | R84: Ejecutados | S84: Aprobados | T84: Fallidos | U84: Bloqueados | V84: Tasa de aprobación
A85: CP-082 | B85: Nuevo (V2) | C85: E6 | D85: Media | E85: Reaparición del fantasma del jugador | F85: HU-27 | G85: Sí | H85: — | I85: Aprobado | J85: =IF(OR(H85="—",I85="",I85="No ejecutado"),"—",IF(H85=I85,"No","Sí")) | K85: Luzzi | L85: 46307 | N85: Clásico: reapareció a los 5.03 s; Naval: a los 8.02 s. Durante la espera se ve «Reaparecés en 5» y el fantasma queda en (1,1) sin responder al teclado. | P85: E1 — Núcleo de juego y movimiento | Q85: =COUNTIF($C$4:$C$132,"E1") | R85: =COUNTIFS($C$4:$C$132,"E1",$I$4:$I$132,"Aprobado")+COUNTIFS($C$4:$C$132,"E1",$I$4:$I$132,"Fallido") | S85: =COUNTIFS($C$4:$C$132,"E1",$I$4:$I$132,"Aprobado") | T85: =COUNTIFS($C$4:$C$132,"E1",$I$4:$I$132,"Fallido") | U85: =COUNTIFS($C$4:$C$132,"E1",$I$4:$I$132,"Bloqueado") | V85: =IFERROR(S85/R85,0)
A86: CP-083 | B86: Nuevo (V2) | C86: E6 | D86: Alta | E86: Ser comido no descuenta vidas ni reinicia el nivel | F86: HU-27 | G86: No | H86: — | I86: Aprobado | J86: =IF(OR(H86="—",I86="",I86="No ejecutado"),"—",IF(H86=I86,"No","Sí")) | K86: Luzzi | L86: 46307 | N86: Comido el fantasma: vidas de Pacman 3 → 3; Pacman siguió desde (4, 3) (no volvió al inicio); esferas 96 → 96. El nivel no se reinició. | P86: E2 — PowerUp e interacción con fantasmas | Q86: =COUNTIF($C$4:$C$132,"E2") | R86: =COUNTIFS($C$4:$C$132,"E2",$I$4:$I$132,"Aprobado")+COUNTIFS($C$4:$C$132,"E2",$I$4:$I$132,"Fallido") | S86: =COUNTIFS($C$4:$C$132,"E2",$I$4:$I$132,"Aprobado") | T86: =COUNTIFS($C$4:$C$132,"E2",$I$4:$I$132,"Fallido") | U86: =COUNTIFS($C$4:$C$132,"E2",$I$4:$I$132,"Bloqueado") | V86: =IFERROR(S86/R86,0)
A87: CP-084 | B87: Nuevo (V2) | C87: E7 | D87: Alta | E87: Espectro: atravesar una pared | F87: HU-28 | G87: Sí | H87: — | I87: Aprobado | J87: =IF(OR(H87="—",I87="",I87="No ejecutado"),"—",IF(H87=I87,"No","Sí")) | K87: Luzzi | L87: 46307 | N87: Nivel 2, espectro en (1,7) mirando a la derecha con el muro de una celda (1,8): atravesó y quedó en (1, 10), del otro lado. Precondición preparada por script (posiciones y fantasmas de la IA retirados) para aislar la condición. | P87: E3 — Vidas, puntaje y fin de partida | Q87: =COUNTIF($C$4:$C$132,"E3") | R87: =COUNTIFS($C$4:$C$132,"E3",$I$4:$I$132,"Aprobado")+COUNTIFS($C$4:$C$132,"E3",$I$4:$I$132,"Fallido") | S87: =COUNTIFS($C$4:$C$132,"E3",$I$4:$I$132,"Aprobado") | T87: =COUNTIFS($C$4:$C$132,"E3",$I$4:$I$132,"Fallido") | U87: =COUNTIFS($C$4:$C$132,"E3",$I$4:$I$132,"Bloqueado") | V87: =IFERROR(S87/R87,0)
A88: CP-085 | B88: Nuevo (V2) | C88: E7 | D88: Alta | E88: Espectro: cooldown y estado de gracia | F88: HU-28 | G88: No | H88: — | I88: Aprobado | J88: =IF(OR(H88="—",I88="",I88="No ejecutado"),"—",IF(H88=I88,"No","Sí")) | K88: Luzzi | L88: 46307 | N88: Tras cruzar, el contacto con Pacman dentro de los 3 s no le quitó vidas (3 → 3); el espectro se ve translúcido y punteado. Espacio en cooldown no tuvo efecto; la estrella volvió a los 10 s. Precondición preparada por script (posiciones y fantasmas de la IA retirados) para aislar la condición. | P88: E4 — Niveles y progresión de dificultad | Q88: =COUNTIF($C$4:$C$132,"E4") | R88: =COUNTIFS($C$4:$C$132,"E4",$I$4:$I$132,"Aprobado")+COUNTIFS($C$4:$C$132,"E4",$I$4:$I$132,"Fallido") | S88: =COUNTIFS($C$4:$C$132,"E4",$I$4:$I$132,"Aprobado") | T88: =COUNTIFS($C$4:$C$132,"E4",$I$4:$I$132,"Fallido") | U88: =COUNTIFS($C$4:$C$132,"E4",$I$4:$I$132,"Bloqueado") | V88: =IFERROR(S88/R88,0)
A89: CP-086 | B89: Nuevo (V2) | C89: E7 | D89: Media | E89: Espectro: sin destino válido no se activa | F89: HU-28 | G89: No | H89: — | I89: Aprobado | J89: =IF(OR(H89="—",I89="",I89="No ejecutado"),"—",IF(H89=I89,"No","Sí")) | K89: Luzzi | L89: 46307 | N89: Nivel 1: contra el muro grueso de abajo no atravesó; contra el borde superior no salió del mapa. La estrella siguió disponible en los dos intentos. Precondición preparada por script (posiciones y fantasmas de la IA retirados) para aislar la condición. | P89: E5 — Control de la partida | Q89: =COUNTIF($C$4:$C$132,"E5") | R89: =COUNTIFS($C$4:$C$132,"E5",$I$4:$I$132,"Aprobado")+COUNTIFS($C$4:$C$132,"E5",$I$4:$I$132,"Fallido") | S89: =COUNTIFS($C$4:$C$132,"E5",$I$4:$I$132,"Aprobado") | T89: =COUNTIFS($C$4:$C$132,"E5",$I$4:$I$132,"Fallido") | U89: =COUNTIFS($C$4:$C$132,"E5",$I$4:$I$132,"Bloqueado") | V89: =IFERROR(S89/R89,0)
A90: CP-087 | B90: Nuevo (V2) | C90: E7 | D90: Alta | E90: Saltarín: destino dentro del radio y transitable | F90: HU-29 | G90: Sí | H90: — | I90: Aprobado | J90: =IF(OR(H90="—",I90="",I90="No ejecutado"),"—",IF(H90=I90,"No","Sí")) | K90: Luzzi | L90: 46307 | N90: 10 saltos; distancias Manhattan [4, 6, 5, 9, 5, 6, 7, 5, 9, 8]; todos a celdas transitables dentro del mapa. (Cooldown anulado por script entre saltos para no esperar 100 s.) | P90: E6 — Modo GhostMan | Q90: =COUNTIF($C$4:$C$132,"E6") | R90: =COUNTIFS($C$4:$C$132,"E6",$I$4:$I$132,"Aprobado")+COUNTIFS($C$4:$C$132,"E6",$I$4:$I$132,"Fallido") | S90: =COUNTIFS($C$4:$C$132,"E6",$I$4:$I$132,"Aprobado") | T90: =COUNTIFS($C$4:$C$132,"E6",$I$4:$I$132,"Fallido") | U90: =COUNTIFS($C$4:$C$132,"E6",$I$4:$I$132,"Bloqueado") | V90: =IFERROR(S90/R90,0)
A91: CP-088 | B91: Nuevo (V2) | C91: E7 | D91: Media | E91: Saltarín: cooldown de 10 s | F91: HU-29 | G91: No | H91: — | I91: Aprobado | J91: =IF(OR(H91="—",I91="",I91="No ejecutado"),"—",IF(H91=I91,"No","Sí")) | K91: Luzzi | L91: 46307 | N91: A los 9 s espacio no hizo nada; el poder volvió a los 9.92 s y saltó. | P91: E7 — Poderes de los fantasmas | Q91: =COUNTIF($C$4:$C$132,"E7") | R91: =COUNTIFS($C$4:$C$132,"E7",$I$4:$I$132,"Aprobado")+COUNTIFS($C$4:$C$132,"E7",$I$4:$I$132,"Fallido") | S91: =COUNTIFS($C$4:$C$132,"E7",$I$4:$I$132,"Aprobado") | T91: =COUNTIFS($C$4:$C$132,"E7",$I$4:$I$132,"Fallido") | U91: =COUNTIFS($C$4:$C$132,"E7",$I$4:$I$132,"Bloqueado") | V91: =IFERROR(S91/R91,0)
A92: CP-089 | B92: Nuevo (V2) | C92: E7 | D92: Media | E92: Saltarín: salto sobre Pacman | F92: HU-29 | G92: No | H92: — | I92: Aprobado | J92: =IF(OR(H92="—",I92="",I92="No ejecutado"),"—",IF(H92=I92,"No","Sí")) | K92: Luzzi | L92: 46307 | N92: Repitiendo el salto desde (1,1) con Pacman quieto en (1,3), en el intento 10 el saltarín cayó sobre Pacman: vidas 3 → 2. (Cooldown anulado por script.) | P92: E8 — Dificultad del modo GhostMan | Q92: =COUNTIF($C$4:$C$132,"E8") | R92: =COUNTIFS($C$4:$C$132,"E8",$I$4:$I$132,"Aprobado")+COUNTIFS($C$4:$C$132,"E8",$I$4:$I$132,"Fallido") | S92: =COUNTIFS($C$4:$C$132,"E8",$I$4:$I$132,"Aprobado") | T92: =COUNTIFS($C$4:$C$132,"E8",$I$4:$I$132,"Fallido") | U92: =COUNTIFS($C$4:$C$132,"E8",$I$4:$I$132,"Bloqueado") | V92: =IFERROR(S92/R92,0)
A93: CP-090 | B93: Nuevo (V2) | C93: E7 | D93: Alta | E93: Naval: fruta falsa consumida por Pacman | F93: HU-30 | G93: Sí | H93: — | I93: Aprobado | J93: =IF(OR(H93="—",I93="",I93="No ejecutado"),"—",IF(H93=I93,"No","Sí")) | K93: Luzzi | L93: 46307 | N93: El naval colocó la fruta falsa en (10,8), a 3 celdas de Pacman; Pacman fue por ella, la consumió y perdió una vida (3 → 2); el nivel se reinició (Pacman en (7, 8), fantasma en (1,1)). (Posiciones preparadas por script.) | P93: Total | Q93: =SUM(Q85:Q92) | R93: =SUM(R85:R92) | S93: =SUM(S85:S92) | T93: =SUM(T85:T92) | U93: =SUM(U85:U92) | V93: =IFERROR(S93/R93,0)
A94: CP-091 | B94: Nuevo (V2) | C94: E7 | D94: Alta | E94: Naval: fruta falsa con el PowerUp de Pacman | F94: HU-30 | G94: No | H94: — | I94: Aprobado | J94: =IF(OR(H94="—",I94="",I94="No ejecutado"),"—",IF(H94=I94,"No","Sí")) | K94: Luzzi | L94: 46307 | N94: Con el PowerUp activo Pacman consumió la fruta falsa: desapareció sin efecto (vidas 3 → 3; puntaje 0 → 0, sin descuento). (Posiciones preparadas por script.)
A95: CP-092 | B95: Nuevo (V2) | C95: E7 | D95: Alta | E95: Naval: explosión a los 10 s | F95: HU-30 | G95: Sí | H95: — | I95: Aprobado | J95: =IF(OR(H95="—",I95="",I95="No ejecutado"),"—",IF(H95=I95,"No","Sí")) | K95: Luzzi | L95: 46307 | N95: Explotó a los 9.92 s; cubrió 9 celdas, todas transitables y a ≤ 3 pasos (máx. Manhattan 3); se vio la cuenta regresiva desde los 7 s. | P95: Organización del equipo de testing (sección 6.1)
A96: CP-093 | B96: Nuevo (V2) | C96: E7 | D96: Media | E96: Naval: máximo de 2 frutas y cooldown de 5 s | F96: HU-30 | G96: No | H96: — | I96: Aprobado | J96: =IF(OR(H96="—",I96="",I96="No ejecutado"),"—",IF(H96=I96,"No","Sí")) | K96: Luzzi | L96: 46307 | N96: A los 3 s no colocó (quedó 1); a los 5 s colocó la segunda (2); con 2 en el mapa, la tercera no se colocó (2) y el poder no se consumió (cooldown 0). (Para el tercer intento el cooldown se anuló por script: con 5 s de cooldown y 10 s de vida, la primera fruta explota justo cuando vuelve el poder.) | P96: Test Lead | Q96: Savoia
A97: CP-094 | B97: Nuevo (V2) | C97: E7 | D97: Media | E97: Naval: fruta falsa distinguible de la real | F97: HU-30 | G97: No | H97: — | I97: Aprobado | J97: =IF(OR(H97="—",I97="",I97="No ejecutado"),"—",IF(H97=I97,"No","Sí")) | K97: Luzzi | L97: 46307 | N97: Fruta real (cereza roja) en (1,6) y fruta falsa en (1,4): se distinguen a la vista (ver captura CP-094.png). | P97: Diseño de casos de prueba (V2) y mutación de la regresión | Q97: Luzzi
A98: CP-095 | B98: Nuevo (V2) | C98: E7 | D98: Alta | E98: Acelerado: dash de hasta 3 celdas | F98: HU-31 | G98: Sí | H98: — | I98: Aprobado | J98: =IF(OR(H98="—",I98="",I98="No ejecutado"),"—",IF(H98=I98,"No","Sí")) | K98: Luzzi | L98: 46307 | N98: Desde (1,4) con pasillo libre avanzó 3 celdas (col 7); desde (1,13) con el borde a 2 celdas se detuvo en la última transitable (col 15). | P98: Ejecución y reporte de defectos (V2) | Q98: Luzzi
A99: CP-096 | B99: Nuevo (V2) | C99: E7 | D99: Alta | E99: Acelerado: penalidad de velocidad posterior | F99: HU-31 | G99: No | H99: — | I99: Aprobado | J99: =IF(OR(H99="—",I99="",I99="No ejecutado"),"—",IF(H99=I99,"No","Sí")) | K99: Luzzi | L99: 46307 | N99: Después del dash: 2.46 celdas/s; pasados los 5 s: 5.00 celdas/s. Re-ejecutado el 28/10/2026 con la velocidad reducida un 25 % (decisión 39): Aprobado; ver el ciclo 3 en la hoja del caso.
A100: CP-097 | B100: Nuevo (V2) | C100: E7 | D100: Baja | E100: Acelerado: dash sin dirección de avance | F100: HU-31 | G100: No | H100: — | I100: Aprobado | J100: =IF(OR(H100="—",I100="",I100="No ejecutado"),"—",IF(H100=I100,"No","Sí")) | K100: Luzzi | L100: 46307 | N100: Sin moverlo desde la aparición, espacio no lo desplazó y la estrella siguió disponible.
A101: CP-098 | B101: Nuevo (V2) | C101: E7 | D101: Media | E101: Indicador de poder disponible | F101: HU-32 | G101: Sí | H101: — | I101: Aprobado | J101: =IF(OR(H101="—",I101="",I101="No ejecutado"),"—",IF(H101=I101,"No","Sí")) | K101: Luzzi | L101: 46307 | N101: Estrella encendida abajo a la izquierda junto a las vidas; se apagó al saltar y volvió a encenderse a los 9.93 s.
A102: CP-099 | B102: Nuevo (V2) | C102: E7 | D102: Baja | E102: Sin indicador para el fantasma clásico | F102: HU-32 | G102: No | H102: — | I102: Aprobado | J102: =IF(OR(H102="—",I102="",I102="No ejecutado"),"—",IF(H102=I102,"No","Sí")) | K102: Luzzi | L102: 46307 | N102: Con el Clásico la barra inferior muestra solo las vidas de Pacman; sin estrella, y espacio no hace nada.
A103: CP-100 | B103: Nuevo (V2) | C103: E7 | D103: Media | E103: Espacio durante el cooldown sin efecto | F103: HU-32 | G103: No | H103: — | I103: Aprobado | J103: =IF(OR(H103="—",I103="",I103="No ejecutado"),"—",IF(H103=I103,"No","Sí")) | K103: Luzzi | L103: 46307 | N103: 5 pulsaciones de espacio en cooldown: no se colocó otra fruta y el cooldown siguió bajando (4.42 → 3.88 s).
A104: CP-101 | B104: Nuevo (V2) | C104: E8 | D104: Alta | E104: Pacman destruye hasta 5 paredes en el nivel 2 | F104: HU-33 | G104: Sí | H104: — | I104: Aprobado | J104: =IF(OR(H104="—",I104="",I104="No ejecutado"),"—",IF(H104=I104,"No","Sí")) | K104: Luzzi | L104: 46307 | N104: Nivel 2 sin interferencia: Pacman destruyó 2 paredes, como máximo 2 por esfera grande, ninguna del borde; las celdas rotas quedaron transitables.
A105: CP-102 | B105: Nuevo (V2) | C105: E8 | D105: Alta | E105: El nivel 1 no habilita la destrucción de paredes | F105: HU-33 | G105: No | H105: — | I105: Aprobado | J105: =IF(OR(H105="—",I105="",I105="No ejecutado"),"—",IF(H105=I105,"No","Sí")) | K105: Luzzi | L105: 46307 | N105: Nivel 1 durante 30 s, con Pacman comiendo esferas grandes: no se destruyó ninguna pared.
A106: CP-103 | B106: Nuevo (V2) | C106: E8 | D106: Media | E106: Paredes restablecidas al reiniciarse el nivel | F106: HU-33 | G106: No | H106: — | I106: Aprobado | J106: =IF(OR(H106="—",I106="",I106="No ejecutado"),"—",IF(H106=I106,"No","Sí")) | K106: Luzzi | L106: 46307 | N106: Paredes rotas [[10, 5]]; tras la derrota de Pacman volvieron a existir.
A107: CP-104 | B107: Nuevo (V2) | C107: E8 | D107: Media | E107: Más esferas grandes en el nivel 3 | F107: HU-34 | G107: Sí | H107: — | I107: Aprobado | J107: =IF(OR(H107="—",I107="",I107="No ejecutado"),"—",IF(H107=I107,"No","Sí")) | K107: Luzzi | L107: 46307 | N107: Esferas grandes al iniciar: nivel 1 = 4, nivel 2 = 4, nivel 3 = 6 (esquinas, (7,1) y (7,15)).
A108: CP-105 | B108: Nuevo (V2) | C108: E8 | D108: Media | E108: Aparición dinámica de esferas grandes | F108: HU-34 | G108: Sí | H108: — | I108: Aprobado | J108: =IF(OR(H108="—",I108="",I108="No ejecutado"),"—",IF(H108=I108,"No","Sí")) | K108: Luzzi | L108: 46307 | N108: A los 15 s apareció una esfera grande dinámica en [[3, 1]] (celda transitable). Con solo esa esfera pendiente el nivel no terminó: cuenta para completarlo. (Resto del mapa vaciado por script.)
...

Sheet Registro de defectos
A1: GhostMan - Entrega 2 - Registro de defectos (V1 y V2, ciclo 2)
A2: Una fila por defecto, en orden de detección. Los defectos de la V2 continúan la numeración de la V1 (sección 12 de la Entrega 02). Campos de la sección 13.3; severidad y prioridad según 13.1; estado según 13.2. El detalle completo va en la hoja con el ID del defecto.
A3: Todo defecto debe ser confirmado por un integrante distinto del que lo reportó antes de pasar a corrección, y verificado por un integrante distinto antes de cerrarse (13.2).
A4: ID | B4: Título | C4: Caso de prueba | D4: HU | E4: Severidad | F4: Prioridad | G4: Estado | H4: Versión / commit | I4: Entorno (navegador, resolución) | J4: Reproducibilidad | K4: Reportado por | L4: Confirmado por | M4: Fecha | N4: Observaciones | Q4: Defectos por severidad
A5: DEF-001 | B5: El contador de vidas se muestra arriba a la derecha como círculos amarillos en lugar de íconos de Pacman abajo a la izquierda | C5: CP-034 | D5: HU-09 | E5: Menor | F5: Media | G5: Verificado | H5: V1 - commit a completar (corregido en V2 - 7ec70df) | I5: Chrome 154 escritorio (macOS), 1291 × 693 | J5: Siempre | K5: Rodriguez Castro | L5: Luzzi | M5: 46294 | N5: Detectado en la Entrega 1. Corregido en el commit 7ec70df: las vidas del modo Pacman pasan a una barra debajo del mapa, abajo a la izquierda, con íconos de Pacman. Verificado el 12/10/2026 con la prueba de confirmación (CP-034, Aprobado, Chromium 141). Además, CP-047 de la regresión registró la barra en los tres niveles. | Q5: Bloqueante | R5: =COUNTIF($E$5:$E$104,"Bloqueante")
A6: DEF-002 | B6: El menú principal elige la opción que tiene el puntero encima al cargar la página, aunque el mouse no se haya movido | C6: Exploratoria | D6: HU-22 | E6: Menor | F6: Media | G6: Corregido | H6: V2 - b451d52 (corregido en 65df127) | I6: Chromium sin interfaz (Linux), 700 × 600 | J6: Siempre | K6: Luzzi | M6: 46307 | N6: Lo detectó el script scripts/verify/ui/inc10-menu-carrusel.js: tras elegir Modo GhostMan con un clic y recargar la página, Enter abre el carrusel en lugar de iniciar el Modo PacMan, porque el puntero quedó sobre esa opción. Corrección: la selección cambia solo con un movimiento real del mouse. La prueba de confirmación del 12/10/2026 dio Aprobado; falta que otro integrante lo confirme y lo verifique para pasarlo a Verificado. | Q6: Crítica | R6: =COUNTIF($E$5:$E$104,"Crítica")
A7: DEF-003 | B7: En modo GhostMan, el toque de un fantasma de la IA no le descuenta una vida a Pacman sin PowerUp | C7: Exploratoria | D7: HU-25 | E7: Mayor | F7: Media | G7: Rechazado | H7: V2 - 7ec70df | I7: Completar (navegador y resolución con los que probó Tsai) | J7: Siempre | K7: Tsai | L7: Luzzi | M7: 46307 | N7: Reportado por Tsai al probar el juego. Al triarlo se rechazó: el comportamiento es el especificado. La HU-25 dice «Solo cuentan las derrotas producidas por el fantasma del jugador: las producidas por los fantasmas de la IA no incrementan el contador», y la decisión 19 (sección 5 de la Entrega 02) define que el toque de un fantasma de la IA devuelve a Pacman a su posición inicial sin descontarle vidas. Como en modo GhostMan las vidas de Pacman son el contador de derrotas (decisión 18), descontarlas por la IA contradiría la HU-25. Lo cubren CP-078 y CP-144 (Aprobados en el ciclo 2). Si el equipo quiere cambiar la regla, va como cambio de especificación (decisión 19), no como defecto. | Q7: Mayor | R7: =COUNTIF($E$5:$E$104,"Mayor")
Q8: Menor | R8: =COUNTIF($E$5:$E$104,"Menor")
Q9: Trivial | R9: =COUNTIF($E$5:$E$104,"Trivial")
Q10: Total | R10: =COUNTA($A$5:$A$104)
Q12: Defectos por estado
Q13: Nuevo | R13: =COUNTIF($G$5:$G$104,"Nuevo")
Q14: Confirmado | R14: =COUNTIF($G$5:$G$104,"Confirmado")
Q15: No reproducible | R15: =COUNTIF($G$5:$G$104,"No reproducible")
Q16: En corrección | R16: =COUNTIF($G$5:$G$104,"En corrección")
Q17: Corregido | R17: =COUNTIF($G$5:$G$104,"Corregido")
Q18: Verificado | R18: =COUNTIF($G$5:$G$104,"Verificado")
Q19: Diferido | R19: =COUNTIF($G$5:$G$104,"Diferido")
Q20: Rechazado | R20: =COUNTIF($G$5:$G$104,"Rechazado")
Q22: Defectos por versión en que se detectaron
Q23: V1 | R23: =COUNTIF($H$5:$H$104,"V1*")
Q24: V2 | R24: =COUNTIF($H$5:$H$104,"V2*")
Q26: Defectos de la V2 por funcionalidad (sin rechazados)
Q27: Menú y elección del modo (HU-22) | R27: =COUNTIFS($D$5:$D$104,"HU-22",$H$5:$H$104,"V2*",$G$5:$G$104,"<>Rechazado")
Q28: Carrusel de fantasmas (HU-23) | R28: =COUNTIFS($D$5:$D$104,"HU-23",$H$5:$H$104,"V2*",$G$5:$G$104,"<>Rechazado")
Q29: Control del fantasma e IA de Pacman (HU-24) | R29: =COUNTIFS($D$5:$D$104,"HU-24",$H$5:$H$104,"V2*",$G$5:$G$104,"<>Rechazado")
Q30: Reglas del modo GhostMan: derrota, victoria, puntaje (HU-25 a HU-27) | R30: =COUNTIFS($D$5:$D$104,"HU-25",$H$5:$H$104,"V2*",$G$5:$G$104,"<>Rechazado")+COUNTIFS($D$5:$D$104,"HU-26",$H$5:$H$104,"V2*",$G$5:$G$104,"<>Rechazado")+COUNTIFS($D$5:$D$104,"HU-27",$H$5:$H$104,"V2*",$G$5:$G$104,"<>Rechazado")
Q31: Espectro (HU-28) | R31: =COUNTIFS($D$5:$D$104,"HU-28",$H$5:$H$104,"V2*",$G$5:$G$104,"<>Rechazado")
Q32: Saltarín (HU-29) | R32: =COUNTIFS($D$5:$D$104,"HU-29",$H$5:$H$104,"V2*",$G$5:$G$104,"<>Rechazado")
Q33: Naval y frutas falsas (HU-30) | R33: =COUNTIFS($D$5:$D$104,"HU-30",$H$5:$H$104,"V2*",$G$5:$G$104,"<>Rechazado")
Q34: Acelerado (HU-31) | R34: =COUNTIFS($D$5:$D$104,"HU-31",$H$5:$H$104,"V2*",$G$5:$G$104,"<>Rechazado")
Q35: Indicador de poder (HU-32) | R35: =COUNTIFS($D$5:$D$104,"HU-32",$H$5:$H$104,"V2*",$G$5:$G$104,"<>Rechazado")
Q36: Dificultad del modo GhostMan: paredes y esferas grandes (HU-33, HU-34) | R36: =COUNTIFS($D$5:$D$104,"HU-33",$H$5:$H$104,"V2*",$G$5:$G$104,"<>Rechazado")+COUNTIFS($D$5:$D$104,"HU-34",$H$5:$H$104,"V2*",$G$5:$G$104,"<>Rechazado")
Q37: Fantasmas especiales en el modo Pacman (HU-43) | R37: =COUNTIFS($D$5:$D$104,"HU-43",$H$5:$H$104,"V2*",$G$5:$G$104,"<>Rechazado")
Q38: Total V2 | R38: =SUM(R27:R37)
Q40: Defectos por épica (según el CP)
Q41: E1 — Núcleo de juego y movimiento | R41: =COUNTIF($D$5:$D$104,"HU-01")+COUNTIF($D$5:$D$104,"HU-02")+COUNTIF($D$5:$D$104,"HU-03")+COUNTIF($D$5:$D$104,"HU-04")
Q42: E2 — PowerUp e interacción con fantasmas | R42: =COUNTIF($D$5:$D$104,"HU-05")+COUNTIF($D$5:$D$104,"HU-06")+COUNTIF($D$5:$D$104,"HU-07")+COUNTIF($D$5:$D$104,"HU-08")
Q43: E3 — Vidas, puntaje y fin de partida | R43: =COUNTIF($D$5:$D$104,"HU-09")+COUNTIF($D$5:$D$104,"HU-10")+COUNTIF($D$5:$D$104,"HU-11")+COUNTIF($D$5:$D$104,"HU-12")+COUNTIF($D$5:$D$104,"HU-13")+COUNTIF($D$5:$D$104,"HU-14")
Q44: E4 — Niveles y progresión de dificultad | R44: =COUNTIF($D$5:$D$104,"HU-15")+COUNTIF($D$5:$D$104,"HU-16")+COUNTIF($D$5:$D$104,"HU-17")+COUNTIF($D$5:$D$104,"HU-18")+COUNTIF($D$5:$D$104,"HU-19")+COUNTIF($D$5:$D$104,"HU-43")
Q45: E5 — Control de la partida | R45: =COUNTIF($D$5:$D$104,"HU-20")+COUNTIF($D$5:$D$104,"HU-21")
Q46: E6 — Modo GhostMan | R46: =COUNTIF($D$5:$D$104,"HU-19")+COUNTIF($D$5:$D$104,"HU-22")+COUNTIF($D$5:$D$104,"HU-23")+COUNTIF($D$5:$D$104,"HU-24")+COUNTIF($D$5:$D$104,"HU-25")+COUNTIF($D$5:$D$104,"HU-26")+COUNTIF($D$5:$D$104,"HU-27")
Q47: E7 — Poderes de los fantasmas | R47: =COUNTIF($D$5:$D$104,"HU-28")+COUNTIF($D$5:$D$104,"HU-29")+COUNTIF($D$5:$D$104,"HU-30")+COUNTIF($D$5:$D$104,"HU-31")+COUNTIF($D$5:$D$104,"HU-32")
Q48: E8 — Dificultad del modo GhostMan | R48: =COUNTIF($D$5:$D$104,"HU-33")+COUNTIF($D$5:$D$104,"HU-34")

Sheet CP-001
A1: Test Case ID | B1: CP-001 | C1: Descripción / Funcionalidad | D1: HU-01 · Mover a Pacman por el mapa | G1: Registro de ejecución
A2: Creado por | B2: Cruz, Luzzi (mutación: Luzzi) | C2: Versión | D2: 2 | G2: Ciclo | H2: Fecha | I2: Ejecutor | J2: Estado | K2: Resultado obtenido | L2: Defecto
A3: Reporte de ejecución 2 | C3: Estado en la Entrega 2 | D3: =IFERROR(IF(INDEX('Reporte de ejecución - Entrega2'!$I$4:$I$132,MATCH($B$1,'Reporte de ejecución - Entrega2'!$A$4:$A$132,0))="","Sin ejecutar",INDEX('Reporte de ejecución - Entrega2'!$I$4:$I$132,MATCH($B$1,'Reporte de ejecución - Entrega2'!$A$4:$A$132,0))),"Sin ejecutar") | G3: Ciclo 1 | H3: 46294 | I3: Rodriguez Castro | J3: Aprobado | K3: Las 4 direcciones responden. Corrida 1: ← mueve a la izquierda, ↑ gira hacia arriba en la primera intersección libre, → gira a la derecha. Corrida 2: → desde la posición inicial y ↓ gira hacia abajo en la primera intersección libre. ↓ se verificó en una corrida aparte porque en la secuencia ←↑→↓ un fantasma intercepta a Pacman antes de la intersección (comportamiento esperado, no es defecto). La partida inicia directamente en modo Pacman, sin pantalla de selección.
C4: Estado en la Entrega 1 | D4: Aprobado | G4: Ciclo 2 | H4: 46307 | I4: Luzzi | J4: Aprobado | K4: Desde el cruce (4,6), ↓ → ↑ ← desplazaron a Pacman hacia abajo, derecha, arriba e izquierda respectivamente. (Fantasmas retirados y posiciones preparadas por script para aislar la condición.)
A5: Prioridad (Alta, Media, Baja) | B5: Alta | C5: Técnica de diseño | D5: Partición de equivalencia | G5: Ciclo 3
G6: Ciclo 1 = Entrega 1 (V1). Ciclo 2 = Entrega 2 (V2): ejecución con script de navegador; las precondiciones preparadas por script se aclaran en el resultado obtenido.
A7: # | B7: Pre-requisitos | D7: Datos de prueba
A8: 1 | B8: Abrir la aplicación en un navegador de escritorio. | D8: Entorno: | E8: Build del commit 7ec70df (V2)
A9: 2 | B9: Elegir «Modo PacMan» en el menú principal y presionar Enter (HU-22). | D9: Navegador: | E9: Chromium 141 de escritorio
A10: 3 | B10: Partida en curso (N1). | D10: Modo de juego: | E10: Pacman
A12: Título del CP | B12: Movimiento de Pacman con las flechas
A15: Historias de Usuario | B15: HU-01 | C15: Épica | D15: E1 — Núcleo de juego y movimiento
A16: Estado Automatización | B16: Automatizado (script de navegador, Entrega 2) | C16: Camino feliz | D16: Sí
A18: Mutación (Entrega 2) | B18: Secuencia invertida: ↓ → ↑ ← (la V1 usó ← ↑ → ↓).
A20: Pasos # | B20: Detalle de pasos | D20: Resultado esperado
A21: 1 | B21: Presionar ←. | D21: Pacman se desplaza hacia la izquierda.
A22: 2 | B22: Presionar ↑. | D22: Pacman se desplaza hacia arriba.
A23: 3 | B23: Presionar →. | D23: Pacman se desplaza hacia la derecha.
A24: 4 | B24: Presionar ↓. | D24: Pacman se desplaza en la dirección de cada tecla presionada, siempre que el camino esté libre.
A25: El caso se aprueba solo si se cumple todo el resultado esperado del último paso (en negrita); si cualquier parte no se cumple, se registra como Fallido.

Sheet CP-002
A1: Test Case ID | B1: CP-002 | C1: Descripción / Funcionalidad | D1: HU-01 · Mover a Pacman por el mapa | G1: Registro de ejecución
A2: Creado por | B2: Cruz, Luzzi (mutación: Luzzi) | C2: Versión | D2: 2 | G2: Ciclo | H2: Fecha | I2: Ejecutor | J2: Estado | K2: Resultado obtenido | L2: Defecto
A3: Reporte de ejecución 2 | C3: Estado en la Entrega 2 | D3: =IFERROR(IF(INDEX('Reporte de ejecución - Entrega2'!$I$4:$I$132,MATCH($B$1,'Reporte de ejecución - Entrega2'!$A$4:$A$132,0))="","Sin ejecutar",INDEX('Reporte de ejecución - Entrega2'!$I$4:$I$132,MATCH($B$1,'Reporte de ejecución - Entrega2'!$A$4:$A$132,0))),"Sin ejecutar") | G3: Ciclo 1 | H3: 46294 | I3: Rodriguez Castro | J3: Aprobado | K3: Las 4 teclas responden igual que las flechas. Corrida 1: A izquierda, W arriba, D derecha (mismas trayectorias y tiempos que ←↑→ en CP-001). Corrida 2: D desde la posición inicial y S gira hacia abajo en la primera intersección libre (idéntica a →↓). S se verificó aparte por la intercepción del fantasma.
C4: Estado en la Entrega 1 | D4: Aprobado | G4: Ciclo 2 | H4: 46307 | I4: Luzzi | J4: Aprobado | K4: S D W A produjeron el mismo desplazamiento que ↓ → ↑ ← (abajo, derecha, arriba, izquierda). (Fantasmas retirados y posiciones preparadas por script para aislar la condición.)
A5: Prioridad (Alta, Media, Baja) | B5: Alta | C5: Técnica de diseño | D5: Partición de equivalencia | G5: Ciclo 3
G6: Ciclo 1 = Entrega 1 (V1). Ciclo 2 = Entrega 2 (V2): ejecución con script de navegador; las precondiciones preparadas por script se aclaran en el resultado obtenido.
A7: # | B7: Pre-requisitos | D7: Datos de prueba
A8: 1 | B8: Abrir la aplicación en un navegador de escritorio. | D8: Entorno: | E8: Build del commit 7ec70df (V2)
A9: 2 | B9: Elegir «Modo PacMan» en el menú principal y presionar Enter (HU-22). | D9: Navegador: | E9: Chromium 141 de escritorio
A10: 3 | B10: Partida en curso (N1). | D10: Modo de juego: | E10: Pacman
A12: Título del CP | B12: Movimiento de Pacman con WASD
A15: Historias de Usuario | B15: HU-01 | C15: Épica | D15: E1 — Núcleo de juego y movimiento
A16: Estado Automatización | B16: Automatizado (script de navegador, Entrega 2) | C16: Camino feliz | D16: Sí
A18: Mutación (Entrega 2) | B18: Secuencia invertida: S D W A.
A20: Pasos # | B20: Detalle de pasos | D20: Resultado esperado
A21: 1 | B21: Presionar A. | D21: Pacman se desplaza hacia la izquierda, igual que con ←.
A22: 2 | B22: Presionar W. | D22: Pacman se desplaza hacia arriba, igual que con ↑.
A23: 3 | B23: Presionar D. | D23: Pacman se desplaza hacia la derecha, igual que con →.
A24: 4 | B24: Presionar S. | D24: Cada tecla produce el mismo desplazamiento que ←, ↑, → y ↓ respectivamente.
A25: El caso se aprueba solo si se cumple todo el resultado esperado del último paso (en negrita); si cualquier parte no se cumple, se registra como Fallido.

Sheet CP-003
A1: Test Case ID | B1: CP-003 | C1: Descripción / Funcionalidad | D1: HU-01 · Mover a Pacman por el mapa | G1: Registro de ejecución
A2: Creado por | B2: Cruz, Luzzi (mutación: Luzzi) | C2: Versión | D2: 2 | G2: Ciclo | H2: Fecha | I2: Ejecutor | J2: Estado | K2: Resultado obtenido | L2: Defecto
A3: Reporte de ejecución 2 | C3: Estado en la Entrega 2 | D3: =IFERROR(IF(INDEX('Reporte de ejecución - Entrega2'!$I$4:$I$132,MATCH($B$1,'Reporte de ejecución - Entrega2'!$A$4:$A$132,0))="","Sin ejecutar",INDEX('Reporte de ejecución - Entrega2'!$I$4:$I$132,MATCH($B$1,'Reporte de ejecución - Entrega2'!$A$4:$A$132,0))),"Sin ejecutar") | G3: Ciclo 1 | H3: 46294 | I3: Rodriguez Castro | J3: Aprobado | K3: Aprobado. Avance continuo verificado en el registro de posición cuadro a cuadro. A los 3,0 s un fantasma alcanzó a Pacman, que ya estaba detenido contra el muro; no afecta al resultado.
C4: Estado en la Entrega 1 | D4: Aprobado | G4: Ciclo 2 | H4: 46307 | I4: Luzzi | J4: Aprobado | K4: Tras un toque de ↓ en (10,6), Pacman siguió bajando sin mantener la tecla hasta el muro inferior (fila 13) y se detuvo ahí. (Fantasmas retirados y posiciones preparadas por script para aislar la condición.)
A5: Prioridad (Alta, Media, Baja) | B5: Alta | C5: Técnica de diseño | D5: Adivinación de errores | G5: Ciclo 3
G6: Ciclo 1 = Entrega 1 (V1). Ciclo 2 = Entrega 2 (V2): ejecución con script de navegador; las precondiciones preparadas por script se aclaran en el resultado obtenido.
A7: # | B7: Pre-requisitos | D7: Datos de prueba
A8: 1 | B8: Abrir la aplicación en un navegador de escritorio. | D8: Entorno: | E8: Build del commit 7ec70df (V2)
A9: 2 | B9: Elegir «Modo PacMan» en el menú principal y presionar Enter (HU-22). | D9: Navegador: | E9: Chromium 141 de escritorio
A10: 3 | B10: Partida en curso (N1), Pacman en un corredor libre. | D10: Modo de juego: | E10: Pacman
A12: Título del CP | B12: Avance continuo sin mantener la tecla
A15: Historias de Usuario | B15: HU-01 | C15: Épica | D15: E1 — Núcleo de juego y movimiento
A16: Estado Automatización | B16: Automatizado (script de navegador, Entrega 2) | C16: Camino feliz | D16: Sí
A18: Mutación (Entrega 2) | B18: Se usa la dirección ↓ desde una celda distinta a la de la V1 (fila 10).
A20: Pasos # | B20: Detalle de pasos | D20: Resultado esperado
A21: 1 | B21: Presionar y liberar de inmediato la tecla de una dirección libre. | D21: Pacman comienza a avanzar en la dirección indicada.
A22: 2 | B22: Observar durante 3 segundos sin tocar el teclado. | D22: Pacman sigue avanzando en esa dirección durante los 3 segundos, hasta encontrar un muro.
A23: El caso se aprueba solo si se cumple todo el resultado esperado del último paso (en negrita); si cualquier parte no se cumple, se registra como Fallido.

Sheet CP-004
A1: Test Case ID | B1: CP-004 | C1: Descripción / Funcionalidad | D1: HU-01 · Mover a Pacman por el mapa | G1: Registro de ejecución
A2: Creado por | B2: Cruz, Luzzi | C2: Versión | D2: 1 | G2: Ciclo | H2: Fecha | I2: Ejecutor | J2: Estado | K2: Resultado obtenido | L2: Defecto
A3: Reporte de ejecución 2 | C3: Estado en la Entrega 2 | D3: =IFERROR(IF(INDEX('Reporte de ejecución - Entrega2'!$I$4:$I$132,MATCH($B$1,'Reporte de ejecución - Entrega2'!$A$4:$A$132,0))="","Sin ejecutar",INDEX('Reporte de ejecución - Entrega2'!$I$4:$I$132,MATCH($B$1,'Reporte de ejecución - Entrega2'!$A$4:$A$132,0))),"Sin ejecutar") | G3: Ciclo 1 | H3: 46294 | I3: Rodriguez Castro | J3: Aprobado | K3: Aprobado. La tecla se presionó a unas 4,5 celdas de la intersección, no a 3 como indica el prerrequisito; el comportamiento verificado es el mismo (giro postergado sin frenar).
C4: Estado en la Entrega 1 | D4: Aprobado | G4: Ciclo 2 | H4: 46323 | I4: Luzzi | J4: Aprobado | K4: Avanzando a la derecha por la fila 4 desde (4,3), ↑ presionado 3 celdas antes de la intersección: Pacman siguió en horizontal sin detenerse y giró hacia arriba al llegar a la columna 6. (Fantasmas retirados y posiciones preparadas por script para aislar la condición.)
A5: Prioridad (Alta, Media, Baja) | B5: Media | C5: Técnica de diseño | D5: Transición de estados | G5: Ciclo 3
G6: Ciclo 1 = Entrega 1 (V1). Ciclo 2 = Entrega 2 (V2): ejecución con script de navegador; las precondiciones preparadas por script se aclaran en el resultado obtenido.
A7: # | B7: Pre-requisitos | D7: Datos de prueba
A8: 1 | B8: Abrir la aplicación en un navegador de escritorio. | D8: Entorno: | E8: Build del commit 7ec70df (V2)
A9: 2 | B9: Elegir «Modo PacMan» en el menú principal y presionar Enter (HU-22). | D9: Navegador: | E9: Chromium 141 de escritorio
A10: 3 | B10: Partida en curso (N1), Pacman avanzando por un corredor horizontal con una intersección hacia arriba a 3 celdas de distancia. | D10: Modo de juego: | E10: Pacman
A12: Título del CP | B12: Giro postergado hasta la primera celda posible
A15: Historias de Usuario | B15: HU-01 | C15: Épica | D15: E1 — Núcleo de juego y movimiento
A16: Estado Automatización | B16: Automatizado (script de navegador, Entrega 2) | C16: Camino feliz | D16: No
A18: Pasos # | B18: Detalle de pasos | D18: Resultado esperado
A19: 1 | B19: Con Pacman en movimiento horizontal, presionar ↑ antes de llegar a la intersección. | D19: Pacman continúa avanzando en horizontal y gira hacia arriba al llegar a la intersección, sin detenerse en el trayecto.
A20: El caso se aprueba solo si se cumple todo el resultado esperado del último paso (en negrita); si cualquier parte no se cumple, se registra como Fallido.

Sheet CP-005
A1: Test Case ID | B1: CP-005 | C1: Descripción / Funcionalidad | D1: HU-01 · Mover a Pacman por el mapa | G1: Registro de ejecución
A2: Creado por | B2: Cruz, Luzzi (mutación: Luzzi) | C2: Versión | D2: 2 | G2: Ciclo | H2: Fecha | I2: Ejecutor | J2: Estado | K2: Resultado obtenido | L2: Defecto
A3: Reporte de ejecución 2 | C3: Estado en la Entrega 2 | D3: =IFERROR(IF(INDEX('Reporte de ejecución - Entrega2'!$I$4:$I$132,MATCH($B$1,'Reporte de ejecución - Entrega2'!$A$4:$A$132,0))="","Sin ejecutar",INDEX('Reporte de ejecución - Entrega2'!$I$4:$I$132,MATCH($B$1,'Reporte de ejecución - Entrega2'!$A$4:$A$132,0))),"Sin ejecutar") | G3: Ciclo 1 | H3: 46294 | I3: Rodriguez Castro | J3: Aprobado | K3: Aprobado. No se detuvo ni quedó trabado. El giro posterior en (7,15) corresponde al giro postergado (CP-004).
C4: Estado en la Entrega 1 | D4: Aprobado | G4: Ciclo 2 | H4: 46307 | I4: Luzzi | J4: Aprobado | K4: Avanzando a la derecha por la fila 10 con muro debajo (11,2), ↓ no lo detuvo: siguió hacia la derecha (posición 2.68). (Fantasmas retirados y posiciones preparadas por script para aislar la condición.)
A5: Prioridad (Alta, Media, Baja) | B5: Alta | C5: Técnica de diseño | D5: Valores límite | G5: Ciclo 3
G6: Ciclo 1 = Entrega 1 (V1). Ciclo 2 = Entrega 2 (V2): ejecución con script de navegador; las precondiciones preparadas por script se aclaran en el resultado obtenido.
A7: # | B7: Pre-requisitos | D7: Datos de prueba
A8: 1 | B8: Abrir la aplicación en un navegador de escritorio. | D8: Entorno: | E8: Build del commit 7ec70df (V2)
A9: 2 | B9: Elegir «Modo PacMan» en el menú principal y presionar Enter (HU-22). | D9: Navegador: | E9: Chromium 141 de escritorio
A10: 3 | B10: Partida en curso (N1), Pacman avanzando por un corredor horizontal con muros arriba y abajo. | D10: Modo de juego: | E10: Pacman
A12: Título del CP | B12: Dirección bloqueada por un muro
A15: Historias de Usuario | B15: HU-01 | C15: Épica | D15: E1 — Núcleo de juego y movimiento
A16: Estado Automatización | B16: Automatizado (script de navegador, Entrega 2) | C16: Camino feliz | D16: No
A18: Mutación (Entrega 2) | B18: Se ejecuta en la fila 10 con ↓ bloqueado, en lugar de ↑.
A20: Pasos # | B20: Detalle de pasos | D20: Resultado esperado
A21: 1 | B21: Presionar ↑ con el muro inmediatamente arriba. | D21: Pacman mantiene su dirección horizontal de avance. No se detiene ni queda trabado.
A22: El caso se aprueba solo si se cumple todo el resultado esperado del último paso (en negrita); si cualquier parte no se cumple, se registra como Fallido.

Sheet CP-006
A1: Test Case ID | B1: CP-006 | C1: Descripción / Funcionalidad | D1: HU-01 · Mover a Pacman por el mapa | G1: Registro de ejecución
A2: Creado por | B2: Cruz, Luzzi | C2: Versión | D2: 1 | G2: Ciclo | H2: Fecha | I2: Ejecutor | J2: Estado | K2: Resultado obtenido | L2: Defecto
A3: Reporte de ejecución 2 | C3: Estado en la Entrega 2 | D3: =IFERROR(IF(INDEX('Reporte de ejecución - Entrega2'!$I$4:$I$132,MATCH($B$1,'Reporte de ejecución - Entrega2'!$A$4:$A$132,0))="","Sin ejecutar",INDEX('Reporte de ejecución - Entrega2'!$I$4:$I$132,MATCH($B$1,'Reporte de ejecución - Entrega2'!$A$4:$A$132,0))),"Sin ejecutar") | G3: Ciclo 1 | H3: 46294 | I3: Rodriguez Castro | J3: Aprobado | K3: Aprobado. Inversión inmediata, sin llegar a una intersección.
C4: Estado en la Entrega 1 | D4: Aprobado | G4: Ciclo 2 | H4: 46323 | I4: Luzzi | J4: Aprobado | K4: A mitad del corredor de la fila 7 (posición 3.33, sin intersección), ← invirtió la marcha de inmediato: dirección «left», posición 3.33 → 1.92. (Fantasmas retirados y posiciones preparadas por script para aislar la condición.)
A5: Prioridad (Alta, Media, Baja) | B5: Media | C5: Técnica de diseño | D5: Partición de equivalencia | G5: Ciclo 3
G6: Ciclo 1 = Entrega 1 (V1). Ciclo 2 = Entrega 2 (V2): ejecución con script de navegador; las precondiciones preparadas por script se aclaran en el resultado obtenido.
A7: # | B7: Pre-requisitos | D7: Datos de prueba
A8: 1 | B8: Abrir la aplicación en un navegador de escritorio. | D8: Entorno: | E8: Build del commit 7ec70df (V2)
A9: 2 | B9: Elegir «Modo PacMan» en el menú principal y presionar Enter (HU-22). | D9: Navegador: | E9: Chromium 141 de escritorio
A10: 3 | B10: Partida en curso (N1), Pacman avanzando hacia la derecha en un corredor. | D10: Modo de juego: | E10: Pacman
A12: Título del CP | B12: Inversión de marcha a mitad de corredor
A15: Historias de Usuario | B15: HU-01 | C15: Épica | D15: E1 — Núcleo de juego y movimiento
A16: Estado Automatización | B16: Automatizado (script de navegador, Entrega 2) | C16: Camino feliz | D16: No
A18: Pasos # | B18: Detalle de pasos | D18: Resultado esperado
A19: 1 | B19: Presionar ← a mitad del corredor. | D19: Pacman invierte su marcha de inmediato, sin necesidad de llegar a una intersección.
A20: El caso se aprueba solo si se cumple todo el resultado esperado del último paso (en negrita); si cualquier parte no se cumple, se registra como Fallido.

Sheet CP-007
A1: Test Case ID | B1: CP-007 | C1: Descripción / Funcionalidad | D1: HU-02 · Impedir el paso a través de los muros | G1: Registro de ejecución
A2: Creado por | B2: Cruz, Luzzi (mutación: Luzzi) | C2: Versión | D2: 2 | G2: Ciclo | H2: Fecha | I2: Ejecutor | J2: Estado | K2: Resultado obtenido | L2: Defecto
A3: Reporte de ejecución 2 | C3: Estado en la Entrega 2 | D3: =IFERROR(IF(INDEX('Reporte de ejecución - Entrega2'!$I$4:$I$132,MATCH($B$1,'Reporte de ejecución - Entrega2'!$A$4:$A$132,0))="","Sin ejecutar",INDEX('Reporte de ejecución - Entrega2'!$I$4:$I$132,MATCH($B$1,'Reporte de ejecución - Entrega2'!$A$4:$A$132,0))),"Sin ejecutar") | G3: Ciclo 1 | H3: 46294 | I3: Rodriguez Castro | J3: Aprobado | K3: Aprobado. La tecla sostenida se simuló con pulsaciones repetidas (39 en 5 s). Durante la prueba los fantasmas alcanzaron dos veces a Pacman, que reapareció en la misma celda junto al muro; la verificación continuó sin cambios.
C4: Estado en la Entrega 1 | D4: Aprobado | G4: Ciclo 2 | H4: 46307 | I4: Luzzi | J4: Aprobado | K4: Con ← mantenida 5 s contra el muro izquierdo, Pacman se detuvo en (7,1) sin superponerse; luego ↑ lo movió con normalidad (fila 5). (Fantasmas retirados y posiciones preparadas por script para aislar la condición.)
A5: Prioridad (Alta, Media, Baja) | B5: Alta | C5: Técnica de diseño | D5: Valores límite | G5: Ciclo 3
G6: Ciclo 1 = Entrega 1 (V1). Ciclo 2 = Entrega 2 (V2): ejecución con script de navegador; las precondiciones preparadas por script se aclaran en el resultado obtenido.
A7: # | B7: Pre-requisitos | D7: Datos de prueba
A8: 1 | B8: Abrir la aplicación en un navegador de escritorio. | D8: Entorno: | E8: Build del commit 7ec70df (V2)
A9: 2 | B9: Elegir «Modo PacMan» en el menú principal y presionar Enter (HU-22). | D9: Navegador: | E9: Chromium 141 de escritorio
A10: 3 | B10: Partida en curso (N1). | D10: Modo de juego: | E10: Pacman
A12: Título del CP | B12: Pacman no atraviesa los muros
A15: Historias de Usuario | B15: HU-02 | C15: Épica | D15: E1 — Núcleo de juego y movimiento
A16: Estado Automatización | B16: Automatizado (script de navegador, Entrega 2) | C16: Camino feliz | D16: No
A18: Mutación (Entrega 2) | B18: Contra un muro a la izquierda (en la V1, a la derecha).
A20: Pasos # | B20: Detalle de pasos | D20: Resultado esperado
A21: 1 | B21: Dirigir a Pacman contra un muro. | D21: Pacman avanza hasta quedar junto al muro.
A22: 2 | B22: Mantener presionada la tecla de esa dirección durante 5 segundos. | D22: Pacman se detiene contra el muro, no lo atraviesa, no queda superpuesto al muro y no queda encajado: al indicar otra dirección válida se mueve con normalidad.
A23: El caso se aprueba solo si se cumple todo el resultado esperado del último paso (en negrita); si cualquier parte no se cumple, se registra como Fallido.

Sheet CP-008
A1: Test Case ID | B1: CP-008 | C1: Descripción / Funcionalidad | D1: HU-02 · Impedir el paso a través de los muros | G1: Registro de ejecución
A2: Creado por | B2: Cruz, Luzzi (mutación: Luzzi) | C2: Versión | D2: 2 | G2: Ciclo | H2: Fecha | I2: Ejecutor | J2: Estado | K2: Resultado obtenido | L2: Defecto
A3: Reporte de ejecución 2 | C3: Estado en la Entrega 2 | D3: =IFERROR(IF(INDEX('Reporte de ejecución - Entrega2'!$I$4:$I$132,MATCH($B$1,'Reporte de ejecución - Entrega2'!$A$4:$A$132,0))="","Sin ejecutar",INDEX('Reporte de ejecución - Entrega2'!$I$4:$I$132,MATCH($B$1,'Reporte de ejecución - Entrega2'!$A$4:$A$132,0))),"Sin ejecutar") | G3: Ciclo 1 | H3: 46294 | I3: Rodriguez Castro | J3: Aprobado | K3: Aprobado. Se usaron las esquinas porque las rutas por las columnas centrales son interceptadas por los fantasmas. Al llegar a las esquinas Pacman comió la esfera grande y se activó el PowerUp; no afecta la verificación de límites.
C4: Estado en la Entrega 1 | D4: Aprobado | G4: Ciclo 2 | H4: 46307 | I4: Luzzi | J4: Aprobado | K4: En los bordes abajo (13,8), derecha (7,15), arriba (1,8) e izquierda (7,1), con la tecla hacia afuera, Pacman no salió del mapa y quedó visible. (Fantasmas retirados y posiciones preparadas por script para aislar la condición.)
A5: Prioridad (Alta, Media, Baja) | B5: Alta | C5: Técnica de diseño | D5: Valores límite | G5: Ciclo 3
G6: Ciclo 1 = Entrega 1 (V1). Ciclo 2 = Entrega 2 (V2): ejecución con script de navegador; las precondiciones preparadas por script se aclaran en el resultado obtenido.
A7: # | B7: Pre-requisitos | D7: Datos de prueba
A8: 1 | B8: Abrir la aplicación en un navegador de escritorio. | D8: Entorno: | E8: Build del commit 7ec70df (V2)
A9: 2 | B9: Elegir «Modo PacMan» en el menú principal y presionar Enter (HU-22). | D9: Navegador: | E9: Chromium 141 de escritorio
A10: 3 | B10: Partida en curso (N1). | D10: Modo de juego: | E10: Pacman
A12: Título del CP | B12: Pacman no sale de los límites del mapa
A15: Historias de Usuario | B15: HU-02 | C15: Épica | D15: E1 — Núcleo de juego y movimiento
A16: Estado Automatización | B16: Automatizado (script de navegador, Entrega 2) | C16: Camino feliz | D16: No
A18: Mutación (Entrega 2) | B18: Bordes recorridos en otro orden: abajo, derecha, arriba, izquierda.
A20: Pasos # | B20: Detalle de pasos | D20: Resultado esperado
A21: 1 | B21: Llevar a Pacman al borde del mapa por cada uno de los cuatro lados. | D21: Pacman llega al borde del mapa en cada lado.
A22: 2 | B22: Presionar la tecla que apunta hacia afuera del mapa. | D22: Pacman no sale del mapa por ninguno de los cuatro lados y permanece visible en pantalla.
A23: El caso se aprueba solo si se cumple todo el resultado esperado del último paso (en negrita); si cualquier parte no se cumple, se registra como Fallido.

Sheet CP-009
A1: Test Case ID | B1: CP-009 | C1: Descripción / Funcionalidad | D1: HU-02 · Impedir el paso a través de los muros | G1: Registro de ejecución
A2: Creado por | B2: Cruz, Luzzi (mutación: Luzzi) | C2: Versión | D2: 2 | G2: Ciclo | H2: Fecha | I2: Ejecutor | J2: Estado | K2: Resultado obtenido | L2: Defecto
A3: Reporte de ejecución 2 | C3: Estado en la Entrega 2 | D3: =IFERROR(IF(INDEX('Reporte de ejecución - Entrega2'!$I$4:$I$132,MATCH($B$1,'Reporte de ejecución - Entrega2'!$A$4:$A$132,0))="","Sin ejecutar",INDEX('Reporte de ejecución - Entrega2'!$I$4:$I$132,MATCH($B$1,'Reporte de ejecución - Entrega2'!$A$4:$A$132,0))),"Sin ejecutar") | G3: Ciclo 1 | H3: 46294 | I3: Rodriguez Castro | J3: Aprobado | K3: Aprobado. Pacman quieto: murió 24 veces y la partida se reinició 8 veces para mantener a los fantasmas en movimiento los 60 s. Los fantasmas recorrieron 13 celdas cada uno.
C4: Estado en la Entrega 1 | D4: Aprobado | G4: Ciclo 2 | H4: 46307 | I4: Luzzi | J4: Aprobado | K4: Nivel 2 durante 60 s: ningún fantasma clásico entró a un muro ni salió del mapa (tipos observados: ['classic']). (Vidas repuestas por script para que la partida no termine.)
A5: Prioridad (Alta, Media, Baja) | B5: Alta | C5: Técnica de diseño | D5: Adivinación de errores | G5: Ciclo 3
G6: Ciclo 1 = Entrega 1 (V1). Ciclo 2 = Entrega 2 (V2): ejecución con script de navegador; las precondiciones preparadas por script se aclaran en el resultado obtenido.
A7: # | B7: Pre-requisitos | D7: Datos de prueba
A8: 1 | B8: Abrir la aplicación en un navegador de escritorio. | D8: Entorno: | E8: Build del commit 7ec70df (V2)
A9: 2 | B9: Elegir «Modo PacMan» en el menú principal y presionar Enter (HU-22). | D9: Navegador: | E9: Chromium 141 de escritorio
A10: 3 | B10: Partida en curso (N1). | D10: Modo de juego: | E10: Pacman
A12: Título del CP | B12: Los fantasmas clásicos no atraviesan muros
A15: Historias de Usuario | B15: HU-02 | C15: Épica | D15: E1 — Núcleo de juego y movimiento
A16: Estado Automatización | B16: Automatizado (script de navegador, Entrega 2) | C16: Camino feliz | D16: No
A18: Mutación (Entrega 2) | B18: Observación en el nivel 2 en lugar del 1 (solo clásicos al inicio), 60 s.
A20: Pasos # | B20: Detalle de pasos | D20: Resultado esperado
A21: 1 | B21: Observar el desplazamiento de los cuatro fantasmas durante 60 segundos. | D21: Ningún fantasma atraviesa un muro ni sale de los límites del mapa en ningún momento.
A22: El caso se aprueba solo si se cumple todo el resultado esperado del último paso (en negrita); si cualquier parte no se cumple, se registra como Fallido.

Sheet CP-010
A1: Test Case ID | B1: CP-010 | C1: Descripción / Funcionalidad | D1: HU-02 · Impedir el paso a través de los muros | G1: Registro de ejecución
A2: Creado por | B2: Cruz, Luzzi | C2: Versión | D2: 1 | G2: Ciclo | H2: Fecha | I2: Ejecutor | J2: Estado | K2: Resultado obtenido | L2: Defecto
A3: Reporte de ejecución 2 | C3: Estado en la Entrega 2 | D3: =IFERROR(IF(INDEX('Reporte de ejecución - Entrega2'!$I$4:$I$132,MATCH($B$1,'Reporte de ejecución - Entrega2'!$A$4:$A$132,0))="","Sin ejecutar",INDEX('Reporte de ejecución - Entrega2'!$I$4:$I$132,MATCH($B$1,'Reporte de ejecución - Entrega2'!$A$4:$A$132,0))),"Sin ejecutar") | G3: Ciclo 1 | H3: 46294 | I3: Rodriguez Castro | J3: Aprobado | K3: Aprobado. Recorrido parcial con Pacman, complementado con la comparación completa entre dibujo y lógica. Los 107 caminos coinciden con lo dibujado. Única celda transitable sin punto: la de inicio de Pacman (7,8); se asume por diseño, a confirmar con el equipo.
C4: Estado en la Entrega 1 | D4: Aprobado | G4: Ciclo 2 | H4: 46323 | I4: Luzzi | J4: Aprobado | K4: Nivel 1: 107 celdas transitables, todas alcanzables desde la posición de Pacman; 106 marcadas con esfera y la única sin marca es la celda inicial de Pacman (7,8), que ocupa él mismo. Ningún muro tiene esfera. (Recorrido verificado sobre el mapa del juego.)
A5: Prioridad (Alta, Media, Baja) | B5: Media | C5: Técnica de diseño | D5: Adivinación de errores | G5: Ciclo 3
G6: Ciclo 1 = Entrega 1 (V1). Ciclo 2 = Entrega 2 (V2): ejecución con script de navegador; las precondiciones preparadas por script se aclaran en el resultado obtenido.
A7: # | B7: Pre-requisitos | D7: Datos de prueba
A8: 1 | B8: Abrir la aplicación en un navegador de escritorio. | D8: Entorno: | E8: Build del commit 7ec70df (V2)
A9: 2 | B9: Elegir «Modo PacMan» en el menú principal y presionar Enter (HU-22). | D9: Navegador: | E9: Chromium 141 de escritorio
A10: 3 | B10: Partida en curso (N1). | D10: Modo de juego: | E10: Pacman
A12: Título del CP | B12: Zona transitable coincidente con el mapa dibujado
A15: Historias de Usuario | B15: HU-02 | C15: Épica | D15: E1 — Núcleo de juego y movimiento
A16: Estado Automatización | B16: Automatizado (script de navegador, Entrega 2) | C16: Camino feliz | D16: No
A18: Pasos # | B18: Detalle de pasos | D18: Resultado esperado
A19: 1 | B19: Recorrer con Pacman los caminos marcados con puntos blancos. | D19: Todos los caminos marcados son transitables, y no existe ninguna celda transitable que no esté marcada como camino.
A20: El caso se aprueba solo si se cumple todo el resultado esperado del último paso (en negrita); si cualquier parte no se cumple, se registra como Fallido.

Sheet CP-011
A1: Test Case ID | B1: CP-011 | C1: Descripción / Funcionalidad | D1: HU-03 · Consumir las esferas del mapa | G1: Registro de ejecución
A2: Creado por | B2: Cruz, Luzzi (mutación: Luzzi) | C2: Versión | D2: 2 | G2: Ciclo | H2: Fecha | I2: Ejecutor | J2: Estado | K2: Resultado obtenido | L2: Defecto
A3: Reporte de ejecución 2 | C3: Estado en la Entrega 2 | D3: =IFERROR(IF(INDEX('Reporte de ejecución - Entrega2'!$I$4:$I$132,MATCH($B$1,'Reporte de ejecución - Entrega2'!$A$4:$A$132,0))="","Sin ejecutar",INDEX('Reporte de ejecución - Entrega2'!$I$4:$I$132,MATCH($B$1,'Reporte de ejecución - Entrega2'!$A$4:$A$132,0))),"Sin ejecutar") | G3: Ciclo 1 | H3: 46294 | I3: Rodriguez Castro | J3: Aprobado | K3: Aprobado.
C4: Estado en la Entrega 1 | D4: Aprobado | G4: Ciclo 2 | H4: 46307 | I4: Luzzi | J4: Aprobado | K4: Esfera de (4,3): desapareció; puntaje 0 → 10 (+10); esferas restantes 105 → 104. (Fantasmas retirados y posiciones preparadas por script para aislar la condición.)
A5: Prioridad (Alta, Media, Baja) | B5: Alta | C5: Técnica de diseño | D5: Partición de equivalencia | G5: Ciclo 3
G6: Ciclo 1 = Entrega 1 (V1). Ciclo 2 = Entrega 2 (V2): ejecución con script de navegador; las precondiciones preparadas por script se aclaran en el resultado obtenido.
A7: # | B7: Pre-requisitos | D7: Datos de prueba
A8: 1 | B8: Abrir la aplicación en un navegador de escritorio. | D8: Entorno: | E8: Build del commit 7ec70df (V2)
A9: 2 | B9: Elegir «Modo PacMan» en el menú principal y presionar Enter (HU-22). | D9: Navegador: | E9: Chromium 141 de escritorio
A10: 3 | B10: Partida en curso (N1), puntaje 0. | D10: Modo de juego: | E10: Pacman
A12: Título del CP | B12: Consumo de una esfera común
A15: Historias de Usuario | B15: HU-03 | C15: Épica | D15: E1 — Núcleo de juego y movimiento
A16: Estado Automatización | B16: Automatizado (script de navegador, Entrega 2) | C16: Camino feliz | D16: Sí
A18: Mutación (Entrega 2) | B18: Esfera común de otra fila (fila 4).
A20: Pasos # | B20: Detalle de pasos | D20: Resultado esperado
A21: 1 | B21: Registrar el puntaje y el contador de esferas restantes. | D21: Puntaje y contador de esferas anotados como valores de referencia.
A22: 2 | B22: Desplazar a Pacman sobre una esfera común. | D22: Pacman pasa por la celda de la esfera.
A23: 3 | B23: Registrar ambos valores. | D23: La esfera desaparece del mapa, el puntaje aumenta exactamente 10 y el contador de esferas restantes disminuye exactamente 1.
A24: El caso se aprueba solo si se cumple todo el resultado esperado del último paso (en negrita); si cualquier parte no se cumple, se registra como Fallido.

Sheet CP-012
A1: Test Case ID | B1: CP-012 | C1: Descripción / Funcionalidad | D1: HU-03 · Consumir las esferas del mapa | G1: Registro de ejecución
A2: Creado por | B2: Cruz, Luzzi (mutación: Luzzi) | C2: Versión | D2: 2 | G2: Ciclo | H2: Fecha | I2: Ejecutor | J2: Estado | K2: Resultado obtenido | L2: Defecto
A3: Reporte de ejecución 2 | C3: Estado en la Entrega 2 | D3: =IFERROR(IF(INDEX('Reporte de ejecución - Entrega2'!$I$4:$I$132,MATCH($B$1,'Reporte de ejecución - Entrega2'!$A$4:$A$132,0))="","Sin ejecutar",INDEX('Reporte de ejecución - Entrega2'!$I$4:$I$132,MATCH($B$1,'Reporte de ejecución - Entrega2'!$A$4:$A$132,0))),"Sin ejecutar") | G3: Ciclo 1 | H3: 46294 | I3: Rodriguez Castro | J3: Aprobado | K3: Aprobado. En la corrida Pacman comió también la esfera grande de (1,1), por lo que la vida se perdió más tarde de lo previsto. La verificación posterior a la pérdida de vidas no se ve afectada.
C4: Estado en la Entrega 1 | D4: Aprobado | G4: Ciclo 2 | H4: 46307 | I4: Luzzi | J4: Aprobado | K4: Pacman consumió 14 esferas en la fila 10; tras perder una vida (3 → 2) la fila sigue despejada (15 de 15 celdas sin esfera). (Fantasmas retirados y posiciones preparadas por script para aislar la condición.)
A5: Prioridad (Alta, Media, Baja) | B5: Alta | C5: Técnica de diseño | D5: Adivinación de errores | G5: Ciclo 3
G6: Ciclo 1 = Entrega 1 (V1). Ciclo 2 = Entrega 2 (V2): ejecución con script de navegador; las precondiciones preparadas por script se aclaran en el resultado obtenido.
A7: # | B7: Pre-requisitos | D7: Datos de prueba
A8: 1 | B8: Abrir la aplicación en un navegador de escritorio. | D8: Entorno: | E8: Build del commit 7ec70df (V2)
A9: 2 | B9: Elegir «Modo PacMan» en el menú principal y presionar Enter (HU-22). | D9: Navegador: | E9: Chromium 141 de escritorio
A10: 3 | B10: Partida en curso (N1). | D10: Modo de juego: | E10: Pacman
A12: Título del CP | B12: Una esfera consumida no reaparece al perder una vida
A15: Historias de Usuario | B15: HU-03 | C15: Épica | D15: E1 — Núcleo de juego y movimiento
A16: Estado Automatización | B16: Automatizado (script de navegador, Entrega 2) | C16: Camino feliz | D16: No
A18: Mutación (Entrega 2) | B18: 15 esferas en lugar de 10, en la fila 10.
A20: Pasos # | B20: Detalle de pasos | D20: Resultado esperado
A21: 1 | B21: Consumir al menos 10 esferas y registrar la zona despejada. | D21: Contador disminuido en 10 y zona sin esferas identificada.
A22: 2 | B22: Dejar que un fantasma alcance a Pacman. | D22: Se descuenta una vida y los personajes vuelven a su posición inicial.
A23: 3 | B23: Observar la zona despejada al reanudarse el nivel. | D23: Las esferas consumidas antes de perder la vida siguen ausentes del mapa.
A24: El caso se aprueba solo si se cumple todo el resultado esperado del último paso (en negrita); si cualquier parte no se cumple, se registra como Fallido.

Sheet CP-013
A1: Test Case ID | B1: CP-013 | C1: Descripción / Funcionalidad | D1: HU-03 · Consumir las esferas del mapa | G1: Registro de ejecución
A2: Creado por | B2: Cruz, Luzzi | C2: Versión | D2: 1 | G2: Ciclo | H2: Fecha | I2: Ejecutor | J2: Estado | K2: Resultado obtenido | L2: Defecto
A3: Reporte de ejecución 2 | C3: Estado en la Entrega 2 | D3: =IFERROR(IF(INDEX('Reporte de ejecución - Entrega2'!$I$4:$I$132,MATCH($B$1,'Reporte de ejecución - Entrega2'!$A$4:$A$132,0))="","Sin ejecutar",INDEX('Reporte de ejecución - Entrega2'!$I$4:$I$132,MATCH($B$1,'Reporte de ejecución - Entrega2'!$A$4:$A$132,0))),"Sin ejecutar") | G3: Ciclo 1 | H3: 46294 | I3: Rodriguez Castro | J3: Aprobado | K3: Aprobado. Pacman quieto: murió 12 veces y la partida se reinició 4 veces para completar los 30 s. En ningún momento cambió el contador.
C4: Estado en la Entrega 1 | D4: Aprobado | G4: Ciclo 2 | H4: 46323 | I4: Luzzi | J4: Aprobado | K4: 30 s con Pacman quieto: los fantasmas pasaron por 48 celdas distintas; el contador siguió en 106 → 106 y las esferas del mapa no cambiaron. (Pacman detenido y vidas repuestas por script.)
A5: Prioridad (Alta, Media, Baja) | B5: Media | C5: Técnica de diseño | D5: Adivinación de errores | G5: Ciclo 3
G6: Ciclo 1 = Entrega 1 (V1). Ciclo 2 = Entrega 2 (V2): ejecución con script de navegador; las precondiciones preparadas por script se aclaran en el resultado obtenido.
A7: # | B7: Pre-requisitos | D7: Datos de prueba
A8: 1 | B8: Abrir la aplicación en un navegador de escritorio. | D8: Entorno: | E8: Build del commit 7ec70df (V2)
A9: 2 | B9: Elegir «Modo PacMan» en el menú principal y presionar Enter (HU-22). | D9: Navegador: | E9: Chromium 141 de escritorio
A10: 3 | B10: Partida en curso (N1). | D10: Modo de juego: | E10: Pacman
A12: Título del CP | B12: Los fantasmas no consumen esferas
A15: Historias de Usuario | B15: HU-03 | C15: Épica | D15: E1 — Núcleo de juego y movimiento
A16: Estado Automatización | B16: Automatizado (script de navegador, Entrega 2) | C16: Camino feliz | D16: No
A18: Pasos # | B18: Detalle de pasos | D18: Resultado esperado
A19: 1 | B19: Registrar el contador de esferas restantes. | D19: Valor del contador anotado como referencia.
A20: 2 | B20: Observar durante 30 segundos sin mover a Pacman, mientras los fantasmas recorren el mapa sobre celdas con esferas. | D20: El contador de esferas restantes no cambia y las esferas por las que pasaron los fantasmas siguen en el mapa.
A21: El caso se aprueba solo si se cumple todo el resultado esperado del último paso (en negrita); si cualquier parte no se cumple, se registra como Fallido.

Sheet CP-014
A1: Test Case ID | B1: CP-014 | C1: Descripción / Funcionalidad | D1: HU-04 · Completar el nivel al consumir todas las esferas | G1: Registro de ejecución
A2: Creado por | B2: Cruz, Luzzi (mutación: Luzzi) | C2: Versión | D2: 2 | G2: Ciclo | H2: Fecha | I2: Ejecutor | J2: Estado | K2: Resultado obtenido | L2: Defecto
A3: Reporte de ejecución 2 | C3: Estado en la Entrega 2 | D3: =IFERROR(IF(INDEX('Reporte de ejecución - Entrega2'!$I$4:$I$132,MATCH($B$1,'Reporte de ejecución - Entrega2'!$A$4:$A$132,0))="","Sin ejecutar",INDEX('Reporte de ejecución - Entrega2'!$I$4:$I$132,MATCH($B$1,'Reporte de ejecución - Entrega2'!$A$4:$A$132,0))),"Sin ejecutar") | G3: Ciclo 1 | H3: 46294 | I3: Rodriguez Castro | J3: Aprobado | K3: Aprobado. El puntaje cierra: 1770 + 50 de la esfera grande + 750 de bonus = 2570. El nivel se llevó hasta la última esfera con un piloto automático en la página que envía las teclas de flecha al juego, sin modificar su estado. Se repitió en una segunda corrida con igual resultado.
C4: Estado en la Entrega 1 | D4: Aprobado | G4: Ciclo 2 | H4: 46307 | I4: Luzzi | J4: Aprobado | K4: Al consumir la última esfera (13,5) el nivel se completó, la partida se detuvo y se mostró «¡Nivel 1 completado!» con el puntaje. (Mapa reducido a una esfera por script.)
A5: Prioridad (Alta, Media, Baja) | B5: Alta | C5: Técnica de diseño | D5: Valores límite | G5: Ciclo 3
G6: Ciclo 1 = Entrega 1 (V1). Ciclo 2 = Entrega 2 (V2): ejecución con script de navegador; las precondiciones preparadas por script se aclaran en el resultado obtenido.
A7: # | B7: Pre-requisitos | D7: Datos de prueba
A8: 1 | B8: Abrir la aplicación en un navegador de escritorio. | D8: Entorno: | E8: Build del commit 7ec70df (V2)
A9: 2 | B9: Elegir «Modo PacMan» en el menú principal y presionar Enter (HU-22). | D9: Navegador: | E9: Chromium 141 de escritorio
A10: 3 | B10: Partida en curso (N1) con una sola esfera restante en el mapa. | D10: Modo de juego: | E10: Pacman
A12: Título del CP | B12: Finalización del nivel al consumir la última esfera
A15: Historias de Usuario | B15: HU-04 | C15: Épica | D15: E1 — Núcleo de juego y movimiento
A16: Estado Automatización | B16: Automatizado (script de navegador, Entrega 2) | C16: Camino feliz | D16: Sí
A18: Mutación (Entrega 2) | B18: La última esfera es una de la fila 13.
A20: Pasos # | B20: Detalle de pasos | D20: Resultado esperado
A21: 1 | B21: Consumir la última esfera. | D21: El nivel se completa, la partida se detiene y se muestra el resultado del nivel con su puntaje.
A22: El caso se aprueba solo si se cumple todo el resultado esperado del último paso (en negrita); si cualquier parte no se cumple, se registra como Fallido.

Sheet CP-015
A1: Test Case ID | B1: CP-015 | C1: Descripción / Funcionalidad | D1: HU-04 · Completar el nivel al consumir todas las esferas | G1: Registro de ejecución
A2: Creado por | B2: Cruz, Luzzi (mutación: Luzzi) | C2: Versión | D2: 2 | G2: Ciclo | H2: Fecha | I2: Ejecutor | J2: Estado | K2: Resultado obtenido | L2: Defecto
A3: Reporte de ejecución 2 | C3: Estado en la Entrega 2 | D3: =IFERROR(IF(INDEX('Reporte de ejecución - Entrega2'!$I$4:$I$132,MATCH($B$1,'Reporte de ejecución - Entrega2'!$A$4:$A$132,0))="","Sin ejecutar",INDEX('Reporte de ejecución - Entrega2'!$I$4:$I$132,MATCH($B$1,'Reporte de ejecución - Entrega2'!$A$4:$A$132,0))),"Sin ejecutar") | G3: Ciclo 1 | H3: 46294 | I3: Rodriguez Castro | J3: Aprobado | K3: Aprobado. Al alcanzar el estado, el PowerUp de una esfera grande anterior seguía activo (terminó 1,9 s después); no afecta al resultado. Mismo resultado en dos corridas. Estado alcanzado con el piloto automático, que tenía prohibido comer esa esfera.
C4: Estado en la Entrega 1 | D4: Aprobado | G4: Ciclo 2 | H4: 46307 | I4: Luzzi | J4: Aprobado | K4: Con solo la esfera grande de (13,15) sin consumir, el nivel no se completó y quedan 1 esferas; la partida sigue. (Mapa preparado por script.)
A5: Prioridad (Alta, Media, Baja) | B5: Alta | C5: Técnica de diseño | D5: Valores límite | G5: Ciclo 3
G6: Ciclo 1 = Entrega 1 (V1). Ciclo 2 = Entrega 2 (V2): ejecución con script de navegador; las precondiciones preparadas por script se aclaran en el resultado obtenido.
A7: # | B7: Pre-requisitos | D7: Datos de prueba
A8: 1 | B8: Abrir la aplicación en un navegador de escritorio. | D8: Entorno: | E8: Build del commit 7ec70df (V2)
A9: 2 | B9: Elegir «Modo PacMan» en el menú principal y presionar Enter (HU-22). | D9: Navegador: | E9: Chromium 141 de escritorio
A10: 3 | B10: Partida en curso (N1) con todas las esferas comunes consumidas y una esfera grande sin consumir. | D10: Modo de juego: | E10: Pacman
A12: Título del CP | B12: El nivel no se completa si queda una esfera grande
A15: Historias de Usuario | B15: HU-04 | C15: Épica | D15: E1 — Núcleo de juego y movimiento
A16: Estado Automatización | B16: Automatizado (script de navegador, Entrega 2) | C16: Camino feliz | D16: No
A18: Mutación (Entrega 2) | B18: La esfera grande pendiente es la de (13,15) en lugar de la de (1,1).
A20: Pasos # | B20: Detalle de pasos | D20: Resultado esperado
A21: 1 | B21: Observar el estado de la partida. | D21: La partida sigue en curso: el nivel no se da por completado.
A22: 2 | B22: Verificar el contador de esferas restantes. | D22: El nivel no se completa y el contador indica 1 esfera restante. La partida continúa.
A23: El caso se aprueba solo si se cumple todo el resultado esperado del último paso (en negrita); si cualquier parte no se cumple, se registra como Fallido.

Sheet CP-016
A1: Test Case ID | B1: CP-016 | C1: Descripción / Funcionalidad | D1: HU-04 · Completar el nivel al consumir todas las esferas | G1: Registro de ejecución
A2: Creado por | B2: Cruz, Luzzi (mutación: Luzzi) | C2: Versión | D2: 2 | G2: Ciclo | H2: Fecha | I2: Ejecutor | J2: Estado | K2: Resultado obtenido | L2: Defecto
A3: Reporte de ejecución 2 | C3: Estado en la Entrega 2 | D3: =IFERROR(IF(INDEX('Reporte de ejecución - Entrega2'!$I$4:$I$132,MATCH($B$1,'Reporte de ejecución - Entrega2'!$A$4:$A$132,0))="","Sin ejecutar",INDEX('Reporte de ejecución - Entrega2'!$I$4:$I$132,MATCH($B$1,'Reporte de ejecución - Entrega2'!$A$4:$A$132,0))),"Sin ejecutar") | G3: Ciclo 1 | H3: 46294 | I3: Rodriguez Castro | J3: Aprobado | K3: Aprobado. La vida se perdió a propósito tras CP-015 para cumplir el prerrequisito de 2 vidas. Observación para E4: en el nivel 2 los fantasmas arrancan en celdas contiguas a Pacman ((7,7), (7,9), (8,6), (8,10)) y los cuatro figuran como clásicos; revisar en CP-047 a CP-053.
C4: Estado en la Entrega 1 | D4: Aprobado | G4: Ciclo 2 | H4: 46307 | I4: Luzzi | J4: Aprobado | K4: Completado el nivel 1 con 3 vidas y 1200 puntos: empezó el nivel 2 con 1200 puntos y 3 vidas. (Mapa reducido por script.)
A5: Prioridad (Alta, Media, Baja) | B5: Alta | C5: Técnica de diseño | D5: Transición de estados | G5: Ciclo 3
G6: Ciclo 1 = Entrega 1 (V1). Ciclo 2 = Entrega 2 (V2): ejecución con script de navegador; las precondiciones preparadas por script se aclaran en el resultado obtenido.
A7: # | B7: Pre-requisitos | D7: Datos de prueba
A8: 1 | B8: Abrir la aplicación en un navegador de escritorio. | D8: Entorno: | E8: Build del commit 7ec70df (V2)
A9: 2 | B9: Elegir «Modo PacMan» en el menú principal y presionar Enter (HU-22). | D9: Navegador: | E9: Chromium 141 de escritorio
A10: 3 | B10: Partida en curso (N1) próxima a completarse, con 2 vidas restantes y puntaje registrado. | D10: Modo de juego: | E10: Pacman
A12: Título del CP | B12: Paso al nivel siguiente conservando puntaje y vidas
A15: Historias de Usuario | B15: HU-04 | C15: Épica | D15: E1 — Núcleo de juego y movimiento
A16: Estado Automatización | B16: Automatizado (script de navegador, Entrega 2) | C16: Camino feliz | D16: Sí
A18: Mutación (Entrega 2) | B18: Se completa el nivel con 3 vidas en lugar de 2.
A20: Pasos # | B20: Detalle de pasos | D20: Resultado esperado
A21: 1 | B21: Registrar puntaje y vidas. | D21: Puntaje y vidas anotados como valores de referencia.
A22: 2 | B22: Completar el nivel 1. | D22: Se muestra el resultado del nivel 1 con su puntaje.
A23: 3 | B23: Registrar puntaje, vidas y número de nivel. | D23: Se inicia el nivel 2, el puntaje acumulado se conserva y el contador de vidas sigue en 2.
A24: El caso se aprueba solo si se cumple todo el resultado esperado del último paso (en negrita); si cualquier parte no se cumple, se registra como Fallido.

Sheet CP-017
A1: Test Case ID | B1: CP-017 | C1: Descripción / Funcionalidad | D1: HU-04 · Completar el nivel al consumir todas las esferas | G1: Registro de ejecución
A2: Creado por | B2: Cruz, Luzzi (mutación: Luzzi) | C2: Versión | D2: 2 | G2: Ciclo | H2: Fecha | I2: Ejecutor | J2: Estado | K2: Resultado obtenido | L2: Defecto
A3: Reporte de ejecución 2 | C3: Estado en la Entrega 2 | D3: =IFERROR(IF(INDEX('Reporte de ejecución - Entrega2'!$I$4:$I$132,MATCH($B$1,'Reporte de ejecución - Entrega2'!$A$4:$A$132,0))="","Sin ejecutar",INDEX('Reporte de ejecución - Entrega2'!$I$4:$I$132,MATCH($B$1,'Reporte de ejecución - Entrega2'!$A$4:$A$132,0))),"Sin ejecutar") | G3: Ciclo 1 | H3: 46294 | I3: Rodriguez Castro | J3: Aprobado | K3: Aprobado. Partida completa N1 → N2 → N3 en una sola corrida, jugada con el piloto automático (envía teclas de flecha, no modifica el estado). Terminó con 2 vidas (una perdida en N2). El total coincide con la suma del desglose. En N2 los 4 fantasmas fueron clásicos y en N3 los 4 fueron espectros (velocidad 3,5, atraviesan muros).
C4: Estado en la Entrega 1 | D4: Aprobado | G4: Ciclo 2 | H4: 46307 | I4: Luzzi | J4: Aprobado | K4: Partida N1 → N2 → N3; en el nivel 3 los fantasmas fueron ['specter', 'jumper', 'naval', 'accelerated']; al consumir la última esfera se mostró «¡Nivel 3 completado!» y luego «¡Victoria!» con el puntaje final. (Mapas reducidos por script.)
A5: Prioridad (Alta, Media, Baja) | B5: Alta | C5: Técnica de diseño | D5: Transición de estados | G5: Ciclo 3
G6: Ciclo 1 = Entrega 1 (V1). Ciclo 2 = Entrega 2 (V2): ejecución con script de navegador; las precondiciones preparadas por script se aclaran en el resultado obtenido.
A7: # | B7: Pre-requisitos | D7: Datos de prueba
A8: 1 | B8: Abrir la aplicación en un navegador de escritorio. | D8: Entorno: | E8: Build del commit 7ec70df (V2)
A9: 2 | B9: Elegir «Modo PacMan» en el menú principal y presionar Enter (HU-22). | D9: Navegador: | E9: Chromium 141 de escritorio
A10: 3 | B10: Partida en curso en el nivel 3, próxima a completarse. | D10: Modo de juego: | E10: Pacman
A12: Título del CP | B12: Victoria al completar el nivel 3
A15: Historias de Usuario | B15: HU-04 | C15: Épica | D15: E1 — Núcleo de juego y movimiento
A16: Estado Automatización | B16: Automatizado (script de navegador, Entrega 2) | C16: Camino feliz | D16: Sí
A18: Mutación (Entrega 2) | B18: Partida completa N1 → N2 → N3 con los fantasmas nuevos de la V2.
A20: Pasos # | B20: Detalle de pasos | D20: Resultado esperado
A21: 1 | B21: Consumir la última esfera del nivel 3. | D21: La partida termina en victoria y se muestra la pantalla de Victoria con el puntaje final.
A22: El caso se aprueba solo si se cumple todo el resultado esperado del último paso (en negrita); si cualquier parte no se cumple, se registra como Fallido.

Sheet CP-018
A1: Test Case ID | B1: CP-018 | C1: Descripción / Funcionalidad | D1: HU-05 · Obtener el PowerUp al consumir una esfera grande | G1: Registro de ejecución
A2: Creado por | B2: Cruz, Luzzi (mutación: Luzzi) | C2: Versión | D2: 2 | G2: Ciclo | H2: Fecha | I2: Ejecutor | J2: Estado | K2: Resultado obtenido | L2: Defecto
A3: Reporte de ejecución 2 | C3: Estado en la Entrega 2 | D3: =IFERROR(IF(INDEX('Reporte de ejecución - Entrega2'!$I$4:$I$132,MATCH($B$1,'Reporte de ejecución - Entrega2'!$A$4:$A$132,0))="","Sin ejecutar",INDEX('Reporte de ejecución - Entrega2'!$I$4:$I$132,MATCH($B$1,'Reporte de ejecución - Entrega2'!$A$4:$A$132,0))),"Sin ejecutar") | G3: Ciclo 1 | H3: 46294 | I3: Rodriguez Castro | J3: Aprobado | K3: Aprobado. Alejamiento medido en la misma corrida (ver CP-020).
C4: Estado en la Entrega 1 | D4: Aprobado | G4: Ciclo 2 | H4: 46307 | I4: Luzzi | J4: Aprobado | K4: Al pasar por (13,1) el PowerUp se activó solo; puntaje +50; los fantasmas cambiaron al diseño vulnerable y se alejaron (suma de distancias 48 → 76). (Fantasmas ubicados en el centro por script.)
A5: Prioridad (Alta, Media, Baja) | B5: Alta | C5: Técnica de diseño | D5: Transición de estados | G5: Ciclo 3
G6: Ciclo 1 = Entrega 1 (V1). Ciclo 2 = Entrega 2 (V2): ejecución con script de navegador; las precondiciones preparadas por script se aclaran en el resultado obtenido.
A7: # | B7: Pre-requisitos | D7: Datos de prueba
A8: 1 | B8: Abrir la aplicación en un navegador de escritorio. | D8: Entorno: | E8: Build del commit 7ec70df (V2)
A9: 2 | B9: Elegir «Modo PacMan» en el menú principal y presionar Enter (HU-22). | D9: Navegador: | E9: Chromium 141 de escritorio
A10: 3 | B10: Partida en curso (N1), sin PowerUp activo. | D10: Modo de juego: | E10: Pacman
A12: Título del CP | B12: Activación automática del PowerUp
A15: Historias de Usuario | B15: HU-05 | C15: Épica | D15: E2 — PowerUp e interacción con fantasmas
A16: Estado Automatización | B16: Automatizado (script de navegador, Entrega 2) | C16: Camino feliz | D16: Sí
A18: Mutación (Entrega 2) | B18: Esfera grande de (13,1).
A20: Pasos # | B20: Detalle de pasos | D20: Resultado esperado
A21: 1 | B21: Registrar el puntaje. | D21: Puntaje anotado como valor de referencia.
A22: 2 | B22: Consumir una esfera grande sin presionar ninguna otra tecla. | D22: El PowerUp se activa de inmediato sin intervención del jugador, el puntaje aumenta exactamente 50, los fantasmas cambian su diseño y se alejan de Pacman.
A23: El caso se aprueba solo si se cumple todo el resultado esperado del último paso (en negrita); si cualquier parte no se cumple, se registra como Fallido.

Sheet CP-019
A1: Test Case ID | B1: CP-019 | C1: Descripción / Funcionalidad | D1: HU-05 · Obtener el PowerUp al consumir una esfera grande | G1: Registro de ejecución
A2: Creado por | B2: Cruz, Luzzi (mutación: Luzzi) | C2: Versión | D2: 2 | G2: Ciclo | H2: Fecha | I2: Ejecutor | J2: Estado | K2: Resultado obtenido | L2: Defecto
A3: Reporte de ejecución 2 | C3: Estado en la Entrega 2 | D3: =IFERROR(IF(INDEX('Reporte de ejecución - Entrega2'!$I$4:$I$132,MATCH($B$1,'Reporte de ejecución - Entrega2'!$A$4:$A$132,0))="","Sin ejecutar",INDEX('Reporte de ejecución - Entrega2'!$I$4:$I$132,MATCH($B$1,'Reporte de ejecución - Entrega2'!$A$4:$A$132,0))),"Sin ejecutar") | G3: Ciclo 1 | H3: 46294 | I3: Rodriguez Castro | J3: Aprobado | K3: Aprobado. Tiempos en tiempo de juego, sin contar las pausas usadas para las capturas.
C4: Estado en la Entrega 1 | D4: Aprobado | G4: Ciclo 2 | H4: 46307 | I4: Luzzi | J4: Aprobado | K4: Esfera grande de (1,15): a los 7,5 s los fantasmas seguían vulnerables; a los 8,5 s recuperaron su diseño y volvieron a perseguir. Duración: 8 s.
A5: Prioridad (Alta, Media, Baja) | B5: Alta | C5: Técnica de diseño | D5: Valores límite | G5: Ciclo 3
G6: Ciclo 1 = Entrega 1 (V1). Ciclo 2 = Entrega 2 (V2): ejecución con script de navegador; las precondiciones preparadas por script se aclaran en el resultado obtenido.
A7: # | B7: Pre-requisitos | D7: Datos de prueba
A8: 1 | B8: Abrir la aplicación en un navegador de escritorio. | D8: Entorno: | E8: Build del commit 7ec70df (V2)
A9: 2 | B9: Elegir «Modo PacMan» en el menú principal y presionar Enter (HU-22). | D9: Navegador: | E9: Chromium 141 de escritorio
A10: 3 | B10: Partida en curso (N1). | D10: Modo de juego: | E10: Pacman
A12: Título del CP | B12: Duración del PowerUp
A15: Historias de Usuario | B15: HU-05 | C15: Épica | D15: E2 — PowerUp e interacción con fantasmas
A16: Estado Automatización | B16: Automatizado (script de navegador, Entrega 2) | C16: Camino feliz | D16: No
A18: Mutación (Entrega 2) | B18: Esfera grande de (1,15); observaciones a 7,5 s y 8,5 s.
A20: Pasos # | B20: Detalle de pasos | D20: Resultado esperado
A21: 1 | B21: Consumir una esfera grande y cronometrar desde ese instante. | D21: El PowerUp se activa y los fantasmas cambian a su diseño vulnerable.
A22: 2 | B22: Observar el estado de los fantasmas a los 7 segundos. | D22: A los 7 segundos los fantasmas siguen vulnerables (parpadeando).
A23: 3 | B23: Observarlo a los 9 segundos. | D23: A los 7 segundos los fantasmas siguen en estado vulnerable; a los 9 segundos recuperaron su diseño normal y volvieron a perseguir a Pacman. La duración total es de 8 segundos.
A24: El caso se aprueba solo si se cumple todo el resultado esperado del último paso (en negrita); si cualquier parte no se cumple, se registra como Fallido.

Sheet CP-020
A1: Test Case ID | B1: CP-020 | C1: Descripción / Funcionalidad | D1: HU-05 · Obtener el PowerUp al consumir una esfera grande | G1: Registro de ejecución
A2: Creado por | B2: Cruz, Luzzi (mutación: Luzzi) | C2: Versión | D2: 2 | G2: Ciclo | H2: Fecha | I2: Ejecutor | J2: Estado | K2: Resultado obtenido | L2: Defecto
A3: Reporte de ejecución 2 | C3: Estado en la Entrega 2 | D3: =IFERROR(IF(INDEX('Reporte de ejecución - Entrega2'!$I$4:$I$132,MATCH($B$1,'Reporte de ejecución - Entrega2'!$A$4:$A$132,0))="","Sin ejecutar",INDEX('Reporte de ejecución - Entrega2'!$I$4:$I$132,MATCH($B$1,'Reporte de ejecución - Entrega2'!$A$4:$A$132,0))),"Sin ejecutar") | G3: Ciclo 1 | H3: 46294 | I3: Rodriguez Castro | J3: Aprobado | K3: Aprobado. Según el código del juego, un fantasma vulnerable huye hacia un punto opuesto a Pacman. Observación: los fantasmas se mueven de a pares superpuestos (rojo/celeste y rosa/naranja) porque todos persiguen exactamente a Pacman.
C4: Estado en la Entrega 1 | D4: Aprobado | G4: Ciclo 2 | H4: 46307 | I4: Luzzi | J4: Aprobado | K4: El fantasma rosa venía hacia Pacman por la fila 4; al consumir la esfera grande dejó de acercarse y se alejó (distancia 2 → 7 celdas). (Fantasmas retirados y posiciones preparadas por script para aislar la condición.)
A5: Prioridad (Alta, Media, Baja) | B5: Alta | C5: Técnica de diseño | D5: Adivinación de errores | G5: Ciclo 3
G6: Ciclo 1 = Entrega 1 (V1). Ciclo 2 = Entrega 2 (V2): ejecución con script de navegador; las precondiciones preparadas por script se aclaran en el resultado obtenido.
A7: # | B7: Pre-requisitos | D7: Datos de prueba
A8: 1 | B8: Abrir la aplicación en un navegador de escritorio. | D8: Entorno: | E8: Build del commit 7ec70df (V2)
A9: 2 | B9: Elegir «Modo PacMan» en el menú principal y presionar Enter (HU-22). | D9: Navegador: | E9: Chromium 141 de escritorio
A10: 3 | B10: Partida en curso (N1), un fantasma persiguiendo a Pacman a corta distancia. | D10: Modo de juego: | E10: Pacman
A12: Título del CP | B12: Los fantasmas huyen durante el PowerUp
A15: Historias de Usuario | B15: HU-05 | C15: Épica | D15: E2 — PowerUp e interacción con fantasmas
A16: Estado Automatización | B16: Automatizado (script de navegador, Entrega 2) | C16: Camino feliz | D16: No
A18: Mutación (Entrega 2) | B18: Fantasma perseguidor distinto (el rosa).
A20: Pasos # | B20: Detalle de pasos | D20: Resultado esperado
A21: 1 | B21: Consumir una esfera grande. | D21: El PowerUp se activa y los fantasmas cambian a su diseño vulnerable.
A22: 2 | B22: Observar la trayectoria del fantasma que perseguía a Pacman. | D22: El fantasma deja de acercarse a Pacman y se desplaza alejándose de él.
A23: El caso se aprueba solo si se cumple todo el resultado esperado del último paso (en negrita); si cualquier parte no se cumple, se registra como Fallido.

Sheet CP-021
A1: Test Case ID | B1: CP-021 | C1: Descripción / Funcionalidad | D1: HU-05 · Obtener el PowerUp al consumir una esfera grande | G1: Registro de ejecución
A2: Creado por | B2: Cruz, Luzzi | C2: Versión | D2: 1 | G2: Ciclo | H2: Fecha | I2: Ejecutor | J2: Estado | K2: Resultado obtenido | L2: Defecto
A3: Reporte de ejecución 2 | C3: Estado en la Entrega 2 | D3: =IFERROR(IF(INDEX('Reporte de ejecución - Entrega2'!$I$4:$I$132,MATCH($B$1,'Reporte de ejecución - Entrega2'!$A$4:$A$132,0))="","Sin ejecutar",INDEX('Reporte de ejecución - Entrega2'!$I$4:$I$132,MATCH($B$1,'Reporte de ejecución - Entrega2'!$A$4:$A$132,0))),"Sin ejecutar") | G3: Ciclo 1 | H3: 46294 | I3: Rodriguez Castro | J3: Aprobado | K3: Aprobado. No terminó ni a los 3 s (lo que quedaba) ni a los 11 s (3 + 8).
C4: Estado en la Entrega 1 | D4: Aprobado | G4: Ciclo 2 | H4: 46323 | I4: Luzzi | J4: Aprobado | K4: Primera esfera grande (13,1) y, a los 5 s, la segunda (1,1): el PowerUp siguió activo a los 7,8 s del segundo consumo y terminó antes de los 8,2 s (8 s completos, no 3). (Fantasmas retirados y posiciones preparadas por script para aislar la condición.)
A5: Prioridad (Alta, Media, Baja) | B5: Media | C5: Técnica de diseño | D5: Valores límite | G5: Ciclo 3
G6: Ciclo 1 = Entrega 1 (V1). Ciclo 2 = Entrega 2 (V2): ejecución con script de navegador; las precondiciones preparadas por script se aclaran en el resultado obtenido.
A7: # | B7: Pre-requisitos | D7: Datos de prueba
A8: 1 | B8: Abrir la aplicación en un navegador de escritorio. | D8: Entorno: | E8: Build del commit 7ec70df (V2)
A9: 2 | B9: Elegir «Modo PacMan» en el menú principal y presionar Enter (HU-22). | D9: Navegador: | E9: Chromium 141 de escritorio
A10: 3 | B10: Partida en curso (N1), dos esferas grandes accesibles. | D10: Modo de juego: | E10: Pacman
A12: Título del CP | B12: Reinicio del temporizador por una segunda esfera grande
A15: Historias de Usuario | B15: HU-05 | C15: Épica | D15: E2 — PowerUp e interacción con fantasmas
A16: Estado Automatización | B16: Automatizado (script de navegador, Entrega 2) | C16: Camino feliz | D16: No
A18: Pasos # | B18: Detalle de pasos | D18: Resultado esperado
A19: 1 | B19: Consumir una esfera grande. | D19: El PowerUp se activa.
A20: 2 | B20: A los 5 segundos, consumir la segunda esfera grande. | D20: La segunda esfera grande desaparece y el PowerUp sigue activo.
A21: 3 | B21: Cronometrar desde el segundo consumo. | D21: El PowerUp permanece activo 8 segundos completos a partir del segundo consumo, no 3.
A22: El caso se aprueba solo si se cumple todo el resultado esperado del último paso (en negrita); si cualquier parte no se cumple, se registra como Fallido.

Sheet CP-022
A1: Test Case ID | B1: CP-022 | C1: Descripción / Funcionalidad | D1: HU-05 · Obtener el PowerUp al consumir una esfera grande | G1: Registro de ejecución
A2: Creado por | B2: Cruz, Luzzi | C2: Versión | D2: 1 | G2: Ciclo | H2: Fecha | I2: Ejecutor | J2: Estado | K2: Resultado obtenido | L2: Defecto
A3: Reporte de ejecución 2 | C3: Estado en la Entrega 2 | D3: =IFERROR(IF(INDEX('Reporte de ejecución - Entrega2'!$I$4:$I$132,MATCH($B$1,'Reporte de ejecución - Entrega2'!$A$4:$A$132,0))="","Sin ejecutar",INDEX('Reporte de ejecución - Entrega2'!$I$4:$I$132,MATCH($B$1,'Reporte de ejecución - Entrega2'!$A$4:$A$132,0))),"Sin ejecutar") | G3: Ciclo 1 | H3: 46294 | I3: Rodriguez Castro | J3: Aprobado | K3: Aprobado. Los fantasmas se mueven superpuestos de a pares, por lo que se comen dos en el mismo cuadro; el incremento se descompone con el contador interno de fantasmas comidos (200 + 400). El primer fantasma de cada tramo sumó 200.
C4: Estado en la Entrega 1 | D4: Aprobado | G4: Ciclo 2 | H4: 46323 | I4: Luzzi | J4: Aprobado | K4: Fantasma comido con la primera esfera grande: +200; tras la segunda esfera grande (PowerUp activo), el siguiente fantasma sumó +200: la escala se reinició. (Fantasmas retirados y posiciones preparadas por script para aislar la condición.)
A5: Prioridad (Alta, Media, Baja) | B5: Media | C5: Técnica de diseño | D5: Tabla de decisión | G5: Ciclo 3
G6: Ciclo 1 = Entrega 1 (V1). Ciclo 2 = Entrega 2 (V2): ejecución con script de navegador; las precondiciones preparadas por script se aclaran en el resultado obtenido.
A7: # | B7: Pre-requisitos | D7: Datos de prueba
A8: 1 | B8: Abrir la aplicación en un navegador de escritorio. | D8: Entorno: | E8: Build del commit 7ec70df (V2)
A9: 2 | B9: Elegir «Modo PacMan» en el menú principal y presionar Enter (HU-22). | D9: Navegador: | E9: Chromium 141 de escritorio
A10: 3 | B10: Partida en curso (N1), dos esferas grandes accesibles. | D10: Modo de juego: | E10: Pacman
A12: Título del CP | B12: Reinicio de la escala de puntos por una segunda esfera grande
A15: Historias de Usuario | B15: HU-05 | C15: Épica | D15: E2 — PowerUp e interacción con fantasmas
A16: Estado Automatización | B16: Automatizado (script de navegador, Entrega 2) | C16: Camino feliz | D16: No
A18: Pasos # | B18: Detalle de pasos | D18: Resultado esperado
A19: 1 | B19: Consumir una esfera grande. | D19: El PowerUp se activa.
A20: 2 | B20: Comer un fantasma y registrar los puntos obtenidos. | D20: El fantasma es comido y suma 200 puntos.
A21: 3 | B21: Consumir la segunda esfera grande. | D21: La segunda esfera grande desaparece y el PowerUp sigue activo.
A22: 4 | B22: Comer otro fantasma y registrar los puntos obtenidos. | D22: El fantasma del paso 2 suma 200 puntos y el del paso 4 suma 200 puntos, no 400.
A23: El caso se aprueba solo si se cumple todo el resultado esperado del último paso (en negrita); si cualquier parte no se cumple, se registra como Fallido.

Sheet CP-023
A1: Test Case ID | B1: CP-023 | C1: Descripción / Funcionalidad | D1: HU-06 · Comer fantasmas durante el PowerUp | G1: Registro de ejecución
A2: Creado por | B2: Cruz, Luzzi (mutación: Luzzi) | C2: Versión | D2: 2 | G2: Ciclo | H2: Fecha | I2: Ejecutor | J2: Estado | K2: Resultado obtenido | L2: Defecto
A3: Reporte de ejecución 2 | C3: Estado en la Entrega 2 | D3: =IFERROR(IF(INDEX('Reporte de ejecución - Entrega2'!$I$4:$I$132,MATCH($B$1,'Reporte de ejecución - Entrega2'!$A$4:$A$132,0))="","Sin ejecutar",INDEX('Reporte de ejecución - Entrega2'!$I$4:$I$132,MATCH($B$1,'Reporte de ejecución - Entrega2'!$A$4:$A$132,0))),"Sin ejecutar") | G3: Ciclo 1 | H3: 46294 | I3: Rodriguez Castro | J3: Aprobado | K3: Aprobado. Los fantasmas van superpuestos de a pares y se comen dos en el mismo cuadro, por lo que no se pudo registrar el puntaje entre el 1.º y el 2.º, ni entre el 3.º y el 4.º. Los incrementos coinciden con la escala en orden. Ver observación de CP-020.
C4: Estado en la Entrega 1 | D4: Aprobado | G4: Ciclo 2 | H4: 46307 | I4: Luzzi | J4: Aprobado | K4: Con la esfera grande de (13,15), los cuatro fantasmas comidos sumaron [200, 400, 800, 1600]. (Fantasmas retirados y posiciones preparadas por script para aislar la condición.)
A5: Prioridad (Alta, Media, Baja) | B5: Alta | C5: Técnica de diseño | D5: Valores límite | G5: Ciclo 3
G6: Ciclo 1 = Entrega 1 (V1). Ciclo 2 = Entrega 2 (V2): ejecución con script de navegador; las precondiciones preparadas por script se aclaran en el resultado obtenido.
A7: # | B7: Pre-requisitos | D7: Datos de prueba
A8: 1 | B8: Abrir la aplicación en un navegador de escritorio. | D8: Entorno: | E8: Build del commit 7ec70df (V2)
A9: 2 | B9: Elegir «Modo PacMan» en el menú principal y presionar Enter (HU-22). | D9: Navegador: | E9: Chromium 141 de escritorio
A10: 3 | B10: Partida en curso (N1), cuatro fantasmas próximos a Pacman. | D10: Modo de juego: | E10: Pacman
A12: Título del CP | B12: Escala de puntos por fantasmas comidos
A15: Historias de Usuario | B15: HU-06 | C15: Épica | D15: E2 — PowerUp e interacción con fantasmas
A16: Estado Automatización | B16: Automatizado (script de navegador, Entrega 2) | C16: Camino feliz | D16: Sí
A18: Mutación (Entrega 2) | B18: Se usa la esfera grande de (13,15).
A20: Pasos # | B20: Detalle de pasos | D20: Resultado esperado
A21: 1 | B21: Consumir una esfera grande. | D21: El PowerUp se activa.
A22: 2 | B22: Comer los cuatro fantasmas dentro de la duración del PowerUp, registrando el puntaje antes y después de cada uno. | D22: Los incrementos de puntaje son exactamente 200, 400, 800 y 1600, en ese orden.
A23: El caso se aprueba solo si se cumple todo el resultado esperado del último paso (en negrita); si cualquier parte no se cumple, se registra como Fallido.

Sheet CP-024
A1: Test Case ID | B1: CP-024 | C1: Descripción / Funcionalidad | D1: HU-06 · Comer fantasmas durante el PowerUp | G1: Registro de ejecución
A2: Creado por | B2: Cruz, Luzzi (mutación: Luzzi) | C2: Versión | D2: 2 | G2: Ciclo | H2: Fecha | I2: Ejecutor | J2: Estado | K2: Resultado obtenido | L2: Defecto
A3: Reporte de ejecución 2 | C3: Estado en la Entrega 2 | D3: =IFERROR(IF(INDEX('Reporte de ejecución - Entrega2'!$I$4:$I$132,MATCH($B$1,'Reporte de ejecución - Entrega2'!$A$4:$A$132,0))="","Sin ejecutar",INDEX('Reporte de ejecución - Entrega2'!$I$4:$I$132,MATCH($B$1,'Reporte de ejecución - Entrega2'!$A$4:$A$132,0))),"Sin ejecutar") | G3: Ciclo 1 | H3: 46294 | I3: Rodriguez Castro | J3: Aprobado | K3: Aprobado. El primer fantasma del segundo PowerUp sumó 200. Ver observación de CP-022 sobre los pares superpuestos.
C4: Estado en la Entrega 1 | D4: Aprobado | G4: Ciclo 2 | H4: 46307 | I4: Luzzi | J4: Aprobado | K4: Primer PowerUp (13,15): fantasma +200; terminado el PowerUp, segundo PowerUp con la esfera de (1,1): fantasma +200. (Fantasmas retirados y posiciones preparadas por script para aislar la condición.)
A5: Prioridad (Alta, Media, Baja) | B5: Alta | C5: Técnica de diseño | D5: Transición de estados | G5: Ciclo 3
G6: Ciclo 1 = Entrega 1 (V1). Ciclo 2 = Entrega 2 (V2): ejecución con script de navegador; las precondiciones preparadas por script se aclaran en el resultado obtenido.
A7: # | B7: Pre-requisitos | D7: Datos de prueba
A8: 1 | B8: Abrir la aplicación en un navegador de escritorio. | D8: Entorno: | E8: Build del commit 7ec70df (V2)
A9: 2 | B9: Elegir «Modo PacMan» en el menú principal y presionar Enter (HU-22). | D9: Navegador: | E9: Chromium 141 de escritorio
A10: 3 | B10: Partida en curso (N1). | D10: Modo de juego: | E10: Pacman
A12: Título del CP | B12: Reinicio de la escala al terminar el PowerUp
A15: Historias de Usuario | B15: HU-06 | C15: Épica | D15: E2 — PowerUp e interacción con fantasmas
A16: Estado Automatización | B16: Automatizado (script de navegador, Entrega 2) | C16: Camino feliz | D16: No
A18: Mutación (Entrega 2) | B18: Segundo PowerUp con una esfera grande distinta.
A20: Pasos # | B20: Detalle de pasos | D20: Resultado esperado
A21: 1 | B21: Consumir una esfera grande y comer un fantasma (200 puntos). | D21: El fantasma es comido y el puntaje aumenta 200.
A22: 2 | B22: Esperar a que el PowerUp termine. | D22: Los fantasmas recuperan su diseño normal.
A23: 3 | B23: Consumir otra esfera grande y comer un fantasma, registrando el incremento. | D23: El fantasma del paso 3 suma 200 puntos, no 400.
A24: El caso se aprueba solo si se cumple todo el resultado esperado del último paso (en negrita); si cualquier parte no se cumple, se registra como Fallido.

Sheet CP-025
A1: Test Case ID | B1: CP-025 | C1: Descripción / Funcionalidad | D1: HU-06 · Comer fantasmas durante el PowerUp | G1: Registro de ejecución
A2: Creado por | B2: Cruz, Luzzi (mutación: Luzzi) | C2: Versión | D2: 2 | G2: Ciclo | H2: Fecha | I2: Ejecutor | J2: Estado | K2: Resultado obtenido | L2: Defecto
A3: Reporte de ejecución 2 | C3: Estado en la Entrega 2 | D3: =IFERROR(IF(INDEX('Reporte de ejecución - Entrega2'!$I$4:$I$132,MATCH($B$1,'Reporte de ejecución - Entrega2'!$A$4:$A$132,0))="","Sin ejecutar",INDEX('Reporte de ejecución - Entrega2'!$I$4:$I$132,MATCH($B$1,'Reporte de ejecución - Entrega2'!$A$4:$A$132,0))),"Sin ejecutar") | G3: Ciclo 1 | H3: 46294 | I3: Rodriguez Castro | J3: Aprobado | K3: Aprobado.
C4: Estado en la Entrega 1 | D4: Aprobado | G4: Ciclo 2 | H4: 46307 | I4: Luzzi | J4: Aprobado | K4: Con 2 vidas y PowerUp activo, el fantasma tocado desapareció; vidas 2 → 2; el nivel no se reinició (Pacman siguió en la fila 4). (Vidas fijadas en 2 por script.)
A5: Prioridad (Alta, Media, Baja) | B5: Alta | C5: Técnica de diseño | D5: Tabla de decisión | G5: Ciclo 3
G6: Ciclo 1 = Entrega 1 (V1). Ciclo 2 = Entrega 2 (V2): ejecución con script de navegador; las precondiciones preparadas por script se aclaran en el resultado obtenido.
A7: # | B7: Pre-requisitos | D7: Datos de prueba
A8: 1 | B8: Abrir la aplicación en un navegador de escritorio. | D8: Entorno: | E8: Build del commit 7ec70df (V2)
A9: 2 | B9: Elegir «Modo PacMan» en el menú principal y presionar Enter (HU-22). | D9: Navegador: | E9: Chromium 141 de escritorio
A10: 3 | B10: Partida en curso (N1), 3 vidas, PowerUp activo. | D10: Modo de juego: | E10: Pacman
A12: Título del CP | B12: Comer un fantasma no descuenta vidas
A15: Historias de Usuario | B15: HU-06 | C15: Épica | D15: E2 — PowerUp e interacción con fantasmas
A16: Estado Automatización | B16: Automatizado (script de navegador, Entrega 2) | C16: Camino feliz | D16: No
A18: Mutación (Entrega 2) | B18: Con 2 vidas en lugar de 3.
A20: Pasos # | B20: Detalle de pasos | D20: Resultado esperado
A21: 1 | B21: Registrar el contador de vidas. | D21: Contador de vidas anotado como referencia.
A22: 2 | B22: Tocar un fantasma con el PowerUp activo. | D22: El fantasma es comido y desaparece del mapa.
A23: 3 | B23: Registrar el contador de vidas. | D23: El fantasma desaparece del mapa, el contador de vidas sigue en 3 y el nivel no se reinicia.
A24: El caso se aprueba solo si se cumple todo el resultado esperado del último paso (en negrita); si cualquier parte no se cumple, se registra como Fallido.

Sheet CP-026
A1: Test Case ID | B1: CP-026 | C1: Descripción / Funcionalidad | D1: HU-06 · Comer fantasmas durante el PowerUp | G1: Registro de ejecución
A2: Creado por | B2: Cruz, Luzzi | C2: Versión | D2: 1 | G2: Ciclo | H2: Fecha | I2: Ejecutor | J2: Estado | K2: Resultado obtenido | L2: Defecto
A3: Reporte de ejecución 2 | C3: Estado en la Entrega 2 | D3: =IFERROR(IF(INDEX('Reporte de ejecución - Entrega2'!$I$4:$I$132,MATCH($B$1,'Reporte de ejecución - Entrega2'!$A$4:$A$132,0))="","Sin ejecutar",INDEX('Reporte de ejecución - Entrega2'!$I$4:$I$132,MATCH($B$1,'Reporte de ejecución - Entrega2'!$A$4:$A$132,0))),"Sin ejecutar") | G3: Ciclo 1 | H3: 46294 | I3: Rodriguez Castro | J3: Aprobado | K3: Aprobado.
C4: Estado en la Entrega 1 | D4: Aprobado | G4: Ciclo 2 | H4: 46323 | I4: Luzzi | J4: Aprobado | K4: El fantasma rojo comido desapareció y reapareció a los 5.00 s en su punto de reaparición (1, 1); luego siguió moviéndose. (PowerUp prolongado por script para observar la reaparición.)
A5: Prioridad (Alta, Media, Baja) | B5: Media | C5: Técnica de diseño | D5: Valores límite | G5: Ciclo 3
G6: Ciclo 1 = Entrega 1 (V1). Ciclo 2 = Entrega 2 (V2): ejecución con script de navegador; las precondiciones preparadas por script se aclaran en el resultado obtenido.
A7: # | B7: Pre-requisitos | D7: Datos de prueba
A8: 1 | B8: Abrir la aplicación en un navegador de escritorio. | D8: Entorno: | E8: Build del commit 7ec70df (V2)
A9: 2 | B9: Elegir «Modo PacMan» en el menú principal y presionar Enter (HU-22). | D9: Navegador: | E9: Chromium 141 de escritorio
A10: 3 | B10: Partida en curso (N1), PowerUp activo. | D10: Modo de juego: | E10: Pacman
A12: Título del CP | B12: Reaparición del fantasma comido
A15: Historias de Usuario | B15: HU-06 | C15: Épica | D15: E2 — PowerUp e interacción con fantasmas
A16: Estado Automatización | B16: Automatizado (script de navegador, Entrega 2) | C16: Camino feliz | D16: No
A18: Pasos # | B18: Detalle de pasos | D18: Resultado esperado
A19: 1 | B19: Comer un fantasma y cronometrar. | D19: El fantasma desaparece del mapa.
A20: 2 | B20: Observar el punto de reaparición y el momento en que reaparece. | D20: El fantasma reaparece en su punto de reaparición a los 5 segundos y retoma su comportamiento normal.
A21: El caso se aprueba solo si se cumple todo el resultado esperado del último paso (en negrita); si cualquier parte no se cumple, se registra como Fallido.

Sheet CP-027
A1: Test Case ID | B1: CP-027 | C1: Descripción / Funcionalidad | D1: HU-06 · Comer fantasmas durante el PowerUp | G1: Registro de ejecución
A2: Creado por | B2: Cruz, Luzzi | C2: Versión | D2: 1 | G2: Ciclo | H2: Fecha | I2: Ejecutor | J2: Estado | K2: Resultado obtenido | L2: Defecto
A3: Reporte de ejecución 2 | C3: Estado en la Entrega 2 | D3: =IFERROR(IF(INDEX('Reporte de ejecución - Entrega2'!$I$4:$I$132,MATCH($B$1,'Reporte de ejecución - Entrega2'!$A$4:$A$132,0))="","Sin ejecutar",INDEX('Reporte de ejecución - Entrega2'!$I$4:$I$132,MATCH($B$1,'Reporte de ejecución - Entrega2'!$A$4:$A$132,0))),"Sin ejecutar") | G3: Ciclo 1 | H3: 46294 | I3: Rodriguez Castro | J3: Aprobado | K3: Aprobado. El paso 2 comió 2 fantasmas a la vez (van superpuestos de a pares), por eso el siguiente valor de la escala fue 800 y no 400. Lo que valida el caso es que continúa (800) en lugar de reiniciarse (200).
C4: Estado en la Entrega 1 | D4: Aprobado | G4: Ciclo 2 | H4: 46323 | I4: Luzzi | J4: Aprobado | K4: Primer bocado +200; el fantasma reapareció a los 5.03 s con el PowerUp activo y en estado vulnerable; comido otra vez sumó +400: la escala siguió. (Fantasmas retirados y posiciones preparadas por script para aislar la condición.)
A5: Prioridad (Alta, Media, Baja) | B5: Media | C5: Técnica de diseño | D5: Tabla de decisión | G5: Ciclo 3
G6: Ciclo 1 = Entrega 1 (V1). Ciclo 2 = Entrega 2 (V2): ejecución con script de navegador; las precondiciones preparadas por script se aclaran en el resultado obtenido.
A7: # | B7: Pre-requisitos | D7: Datos de prueba
A8: 1 | B8: Abrir la aplicación en un navegador de escritorio. | D8: Entorno: | E8: Build del commit 7ec70df (V2)
A9: 2 | B9: Elegir «Modo PacMan» en el menú principal y presionar Enter (HU-22). | D9: Navegador: | E9: Chromium 141 de escritorio
A10: 3 | B10: Partida en curso (N1). | D10: Modo de juego: | E10: Pacman
A12: Título del CP | B12: Fantasma que reaparece con el PowerUp aún activo
A15: Historias de Usuario | B15: HU-06 | C15: Épica | D15: E2 — PowerUp e interacción con fantasmas
A16: Estado Automatización | B16: Automatizado (script de navegador, Entrega 2) | C16: Camino feliz | D16: No
A18: Pasos # | B18: Detalle de pasos | D18: Resultado esperado
A19: 1 | B19: Consumir una esfera grande. | D19: El PowerUp se activa.
A20: 2 | B20: Comer un fantasma de inmediato (200 puntos). | D20: El fantasma es comido y suma 200 puntos.
A21: 3 | B21: Esperar su reaparición dentro de los 8 segundos del PowerUp. | D21: El fantasma reaparece en su punto de reaparición a los 5 segundos.
A22: 4 | B22: Comerlo otra vez y registrar el incremento. | D22: El fantasma reaparece en estado vulnerable, puede volver a ser comido y el incremento del paso 4 es de 400 puntos: la escala continúa y no se reinicia.
A23: El caso se aprueba solo si se cumple todo el resultado esperado del último paso (en negrita); si cualquier parte no se cumple, se registra como Fallido.

Sheet CP-028
A1: Test Case ID | B1: CP-028 | C1: Descripción / Funcionalidad | D1: HU-07 · Advertir el fin del PowerUp | G1: Registro de ejecución
A2: Creado por | B2: Cruz, Luzzi | C2: Versión | D2: 1 | G2: Ciclo | H2: Fecha | I2: Ejecutor | J2: Estado | K2: Resultado obtenido | L2: Defecto
A3: Reporte de ejecución 2 | C3: Estado en la Entrega 2 | D3: =IFERROR(IF(INDEX('Reporte de ejecución - Entrega2'!$I$4:$I$132,MATCH($B$1,'Reporte de ejecución - Entrega2'!$A$4:$A$132,0))="","Sin ejecutar",INDEX('Reporte de ejecución - Entrega2'!$I$4:$I$132,MATCH($B$1,'Reporte de ejecución - Entrega2'!$A$4:$A$132,0))),"Sin ejecutar") | G3: Ciclo 1 | H3: 46294 | I3: Rodriguez Castro | J3: Aprobado | K3: Aprobado. El ciclo de parpadeo arranca en su fase azul, por lo que el primer cambio visible a blanco ocurre a los 6,2 s y no a los 6,0 s exactos.
C4: Estado en la Entrega 1 | D4: Aprobado | G4: Ciclo 2 | H4: 46323 | I4: Luzzi | J4: Aprobado | K4: A los 5 s los fantasmas se veían azules fijos (colores muestreados: ['azul']); a los 7 s alternaban azul y blanco (parpadeo, colores: ['azul', 'blanco']), distinto del azul fijo y del color normal. (Capturas CP-028-5s y CP-028-7s; colores leídos del canvas.)
A5: Prioridad (Alta, Media, Baja) | B5: Media | C5: Técnica de diseño | D5: Valores límite | G5: Ciclo 3
G6: Ciclo 1 = Entrega 1 (V1). Ciclo 2 = Entrega 2 (V2): ejecución con script de navegador; las precondiciones preparadas por script se aclaran en el resultado obtenido.
A7: # | B7: Pre-requisitos | D7: Datos de prueba
A8: 1 | B8: Abrir la aplicación en un navegador de escritorio. | D8: Entorno: | E8: Build del commit 7ec70df (V2)
A9: 2 | B9: Elegir «Modo PacMan» en el menú principal y presionar Enter (HU-22). | D9: Navegador: | E9: Chromium 141 de escritorio
A10: 3 | B10: Partida en curso (N1). | D10: Modo de juego: | E10: Pacman
A12: Título del CP | B12: Parpadeo en los últimos 2 segundos del PowerUp
A15: Historias de Usuario | B15: HU-07 | C15: Épica | D15: E2 — PowerUp e interacción con fantasmas
A16: Estado Automatización | B16: Automatizado (script de navegador, Entrega 2) | C16: Camino feliz | D16: No
A18: Pasos # | B18: Detalle de pasos | D18: Resultado esperado
A19: 1 | B19: Consumir una esfera grande y cronometrar. | D19: El PowerUp se activa y los fantasmas cambian a su diseño vulnerable estable.
A20: 2 | B20: Observar el aspecto de los fantasmas a los 5 segundos y a los 7 segundos. | D20: A los 5 segundos los fantasmas muestran el estado vulnerable estable; a los 7 segundos parpadean. El parpadeo se distingue tanto del estado vulnerable estable como del diseño normal.
A21: El caso se aprueba solo si se cumple todo el resultado esperado del último paso (en negrita); si cualquier parte no se cumple, se registra como Fallido.

Sheet CP-029
A1: Test Case ID | B1: CP-029 | C1: Descripción / Funcionalidad | D1: HU-07 · Advertir el fin del PowerUp | G1: Registro de ejecución
A2: Creado por | B2: Cruz, Luzzi | C2: Versión | D2: 1 | G2: Ciclo | H2: Fecha | I2: Ejecutor | J2: Estado | K2: Resultado obtenido | L2: Defecto
A3: Reporte de ejecución 2 | C3: Estado en la Entrega 2 | D3: =IFERROR(IF(INDEX('Reporte de ejecución - Entrega2'!$I$4:$I$132,MATCH($B$1,'Reporte de ejecución - Entrega2'!$A$4:$A$132,0))="","Sin ejecutar",INDEX('Reporte de ejecución - Entrega2'!$I$4:$I$132,MATCH($B$1,'Reporte de ejecución - Entrega2'!$A$4:$A$132,0))),"Sin ejecutar") | G3: Ciclo 1 | H3: 46294 | I3: Rodriguez Castro | J3: Aprobado | K3: Aprobado.
C4: Estado en la Entrega 1 | D4: Aprobado | G4: Ciclo 2 | H4: 46323 | I4: Luzzi | J4: Aprobado | K4: Al empezar el parpadeo se consumió la segunda esfera grande: el parpadeo cesó (colores después: ['azul']), el temporizador volvió a 7.97 s y el PowerUp seguía activo a los 7,8 s. (Fantasmas retirados y posiciones preparadas por script para aislar la condición.)
A5: Prioridad (Alta, Media, Baja) | B5: Media | C5: Técnica de diseño | D5: Transición de estados | G5: Ciclo 3
G6: Ciclo 1 = Entrega 1 (V1). Ciclo 2 = Entrega 2 (V2): ejecución con script de navegador; las precondiciones preparadas por script se aclaran en el resultado obtenido.
A7: # | B7: Pre-requisitos | D7: Datos de prueba
A8: 1 | B8: Abrir la aplicación en un navegador de escritorio. | D8: Entorno: | E8: Build del commit 7ec70df (V2)
A9: 2 | B9: Elegir «Modo PacMan» en el menú principal y presionar Enter (HU-22). | D9: Navegador: | E9: Chromium 141 de escritorio
A10: 3 | B10: Partida en curso (N1), una esfera grande accesible. | D10: Modo de juego: | E10: Pacman
A12: Título del CP | B12: Esfera grande consumida durante el parpadeo
A15: Historias de Usuario | B15: HU-07 | C15: Épica | D15: E2 — PowerUp e interacción con fantasmas
A16: Estado Automatización | B16: Automatizado (script de navegador, Entrega 2) | C16: Camino feliz | D16: No
A18: Pasos # | B18: Detalle de pasos | D18: Resultado esperado
A19: 1 | B19: Consumir una esfera grande. | D19: El PowerUp se activa.
A20: 2 | B20: Al iniciarse el parpadeo, consumir la segunda esfera grande. | D20: La segunda esfera grande desaparece.
A21: 3 | B21: Observar el aspecto de los fantasmas. | D21: El parpadeo cesa, los fantasmas vuelven al estado vulnerable estable y el PowerUp se extiende 8 segundos desde el segundo consumo.
A22: El caso se aprueba solo si se cumple todo el resultado esperado del último paso (en negrita); si cualquier parte no se cumple, se registra como Fallido.

Sheet CP-030
A1: Test Case ID | B1: CP-030 | C1: Descripción / Funcionalidad | D1: HU-08 · Perder una vida al ser alcanzado por un fantasma | G1: Registro de ejecución
A2: Creado por | B2: Cruz, Luzzi (mutación: Luzzi) | C2: Versión | D2: 2 | G2: Ciclo | H2: Fecha | I2: Ejecutor | J2: Estado | K2: Resultado obtenido | L2: Defecto
A3: Reporte de ejecución 2 | C3: Estado en la Entrega 2 | D3: =IFERROR(IF(INDEX('Reporte de ejecución - Entrega2'!$I$4:$I$132,MATCH($B$1,'Reporte de ejecución - Entrega2'!$A$4:$A$132,0))="","Sin ejecutar",INDEX('Reporte de ejecución - Entrega2'!$I$4:$I$132,MATCH($B$1,'Reporte de ejecución - Entrega2'!$A$4:$A$132,0))),"Sin ejecutar") | G3: Ciclo 1 | H3: 46294 | I3: Rodriguez Castro | J3: Aprobado | K3: Aprobado.
C4: Estado en la Entrega 1 | D4: Aprobado | G4: Ciclo 2 | H4: 46307 | I4: Luzzi | J4: Aprobado | K4: Con 2 vidas, el contacto con el fantasma celeste dejó las vidas en 1; puntaje 10 → 10; Pacman volvió a (7,8) y los fantasmas a sus posiciones iniciales [[1, 1], [1, 15], [13, 1], [13, 15]]. (Vidas fijadas en 2 por script.)
A5: Prioridad (Alta, Media, Baja) | B5: Alta | C5: Técnica de diseño | D5: Tabla de decisión | G5: Ciclo 3
G6: Ciclo 1 = Entrega 1 (V1). Ciclo 2 = Entrega 2 (V2): ejecución con script de navegador; las precondiciones preparadas por script se aclaran en el resultado obtenido.
A7: # | B7: Pre-requisitos | D7: Datos de prueba
A8: 1 | B8: Abrir la aplicación en un navegador de escritorio. | D8: Entorno: | E8: Build del commit 7ec70df (V2)
A9: 2 | B9: Elegir «Modo PacMan» en el menú principal y presionar Enter (HU-22). | D9: Navegador: | E9: Chromium 141 de escritorio
A10: 3 | B10: Partida en curso (N1), 3 vidas, sin PowerUp activo. | D10: Modo de juego: | E10: Pacman
A12: Título del CP | B12: Descuento de una vida por contacto con un fantasma
A15: Historias de Usuario | B15: HU-08 | C15: Épica | D15: E2 — PowerUp e interacción con fantasmas
A16: Estado Automatización | B16: Automatizado (script de navegador, Entrega 2) | C16: Camino feliz | D16: Sí
A18: Mutación (Entrega 2) | B18: Con 2 vidas en lugar de 3, contacto con el fantasma celeste.
A20: Pasos # | B20: Detalle de pasos | D20: Resultado esperado
A21: 1 | B21: Registrar el contador de vidas y el puntaje. | D21: Vidas y puntaje anotados como valores de referencia.
A22: 2 | B22: Dejar que un fantasma alcance a Pacman. | D22: Se produce el contacto entre Pacman y el fantasma.
A23: 3 | B23: Registrar ambos valores. | D23: El contador de vidas baja a 2, el puntaje acumulado se conserva, y Pacman y los fantasmas vuelven a sus posiciones iniciales.
A24: El caso se aprueba solo si se cumple todo el resultado esperado del último paso (en negrita); si cualquier parte no se cumple, se registra como Fallido.

Sheet CP-031
A1: Test Case ID | B1: CP-031 | C1: Descripción / Funcionalidad | D1: HU-08 · Perder una vida al ser alcanzado por un fantasma | G1: Registro de ejecución
A2: Creado por | B2: Cruz, Luzzi (mutación: Luzzi) | C2: Versión | D2: 2 | G2: Ciclo | H2: Fecha | I2: Ejecutor | J2: Estado | K2: Resultado obtenido | L2: Defecto
A3: Reporte de ejecución 2 | C3: Estado en la Entrega 2 | D3: =IFERROR(IF(INDEX('Reporte de ejecución - Entrega2'!$I$4:$I$132,MATCH($B$1,'Reporte de ejecución - Entrega2'!$A$4:$A$132,0))="","Sin ejecutar",INDEX('Reporte de ejecución - Entrega2'!$I$4:$I$132,MATCH($B$1,'Reporte de ejecución - Entrega2'!$A$4:$A$132,0))),"Sin ejecutar") | G3: Ciclo 1 | H3: 46294 | I3: Rodriguez Castro | J3: Aprobado | K3: Aprobado.
C4: Estado en la Entrega 1 | D4: Aprobado | G4: Ciclo 2 | H4: 46307 | I4: Luzzi | J4: Aprobado | K4: Contacto de frente en la columna 1 (Pacman subiendo, fantasma bajando): se descontó una sola vida (3 → 2). (Fantasmas retirados y posiciones preparadas por script para aislar la condición.)
A5: Prioridad (Alta, Media, Baja) | B5: Alta | C5: Técnica de diseño | D5: Adivinación de errores | G5: Ciclo 3
G6: Ciclo 1 = Entrega 1 (V1). Ciclo 2 = Entrega 2 (V2): ejecución con script de navegador; las precondiciones preparadas por script se aclaran en el resultado obtenido.
A7: # | B7: Pre-requisitos | D7: Datos de prueba
A8: 1 | B8: Abrir la aplicación en un navegador de escritorio. | D8: Entorno: | E8: Build del commit 7ec70df (V2)
A9: 2 | B9: Elegir «Modo PacMan» en el menú principal y presionar Enter (HU-22). | D9: Navegador: | E9: Chromium 141 de escritorio
A10: 3 | B10: Partida en curso (N1), 3 vidas. | D10: Modo de juego: | E10: Pacman
A12: Título del CP | B12: Un solo contacto no descuenta más de una vida
A15: Historias de Usuario | B15: HU-08 | C15: Épica | D15: E2 — PowerUp e interacción con fantasmas
A16: Estado Automatización | B16: Automatizado (script de navegador, Entrega 2) | C16: Camino feliz | D16: No
A18: Mutación (Entrega 2) | B18: Contacto de frente en sentido vertical (columna 1).
A20: Pasos # | B20: Detalle de pasos | D20: Resultado esperado
A21: 1 | B21: Dirigir a Pacman de frente contra un fantasma, sin cambiar de dirección durante el contacto. | D21: Se produce un único contacto con el fantasma.
A22: 2 | B22: Registrar el contador de vidas inmediatamente después. | D22: Se descuenta exactamente una vida. El contador queda en 2 y no en 1 ni en 0.
A23: El caso se aprueba solo si se cumple todo el resultado esperado del último paso (en negrita); si cualquier parte no se cumple, se registra como Fallido.

Sheet CP-032
A1: Test Case ID | B1: CP-032 | C1: Descripción / Funcionalidad | D1: HU-08 · Perder una vida al ser alcanzado por un fantasma | G1: Registro de ejecución
A2: Creado por | B2: Cruz, Luzzi | C2: Versión | D2: 1 | G2: Ciclo | H2: Fecha | I2: Ejecutor | J2: Estado | K2: Resultado obtenido | L2: Defecto
A3: Reporte de ejecución 2 | C3: Estado en la Entrega 2 | D3: =IFERROR(IF(INDEX('Reporte de ejecución - Entrega2'!$I$4:$I$132,MATCH($B$1,'Reporte de ejecución - Entrega2'!$A$4:$A$132,0))="","Sin ejecutar",INDEX('Reporte de ejecución - Entrega2'!$I$4:$I$132,MATCH($B$1,'Reporte de ejecución - Entrega2'!$A$4:$A$132,0))),"Sin ejecutar") | G3: Ciclo 1 | H3: 46294 | I3: Rodriguez Castro | J3: Bloqueado | K3: Bloqueado: el prerrequisito no se puede alcanzar con las reglas del juego (verificado en la lógica del juego y en las corridas de CP-018 a CP-029). En la lógica, perder una vida sí cancela el PowerUp y quita la vulnerabilidad. Se sugiere revisar el diseño del caso con el equipo.
C4: Estado en la Entrega 1 | D4: Bloqueado | G4: Ciclo 2 | H4: 46307 | I4: Luzzi | J4: Bloqueado | K4: Sigue Bloqueado. La precondición no se puede dar en el juego: un fantasma que reaparece con el PowerUp activo reaparece vulnerable (lo verifica CP-027) y ninguna otra situación (estado de gracia del espectro, frutas falsas, explosiones, dash) le hace perder una vida a Pacman con el PowerUp activo. Corrige el resultado del 12/10/2026, que se obtuvo forzando por script un fantasma no vulnerable durante el PowerUp, un estado que el juego no produce. Se propone que el equipo revise el criterio de la HU-08 y marque el caso como No aplica o lo reformule.
A5: Prioridad (Alta, Media, Baja) | B5: Media | C5: Técnica de diseño | D5: Transición de estados | G5: Ciclo 3
G6: Ciclo 1 = Entrega 1 (V1). Ciclo 2 = Entrega 2 (V2): ejecución con script de navegador; las precondiciones preparadas por script se aclaran en el resultado obtenido.
A7: # | B7: Pre-requisitos | D7: Datos de prueba
A8: 1 | B8: Abrir la aplicación en un navegador de escritorio. | D8: Entorno: | E8: Build del commit 7ec70df (V2)
A9: 2 | B9: Elegir «Modo PacMan» en el menú principal y presionar Enter (HU-22). | D9: Navegador: | E9: Chromium 141 de escritorio
A10: 3 | B10: Partida en curso (N1), PowerUp activo, un fantasma en estado de gracia o recién reaparecido. | D10: Modo de juego: | E10: Pacman
A12: Título del CP | B12: El PowerUp se cancela al perder una vida
A15: Historias de Usuario | B15: HU-08 | C15: Épica | D15: E2 — PowerUp e interacción con fantasmas
A16: Estado Automatización | B16: Automatizado (script de navegador, Entrega 2) | C16: Camino feliz | D16: No
A18: Pasos # | B18: Detalle de pasos | D18: Resultado esperado
A19: 1 | B19: Con el PowerUp activo, perder una vida por contacto con un fantasma no vulnerable. | D19: Se descuenta una vida.
A20: 2 | B20: Observar el estado de los fantasmas al reanudarse el nivel. | D20: El PowerUp queda cancelado: los fantasmas muestran su diseño normal y persiguen a Pacman.
A21: El caso se aprueba solo si se cumple todo el resultado esperado del último paso (en negrita); si cualquier parte no se cumple, se registra como Fallido.

Sheet CP-033
A1: Test Case ID | B1: CP-033 | C1: Descripción / Funcionalidad | D1: HU-08 · Perder una vida al ser alcanzado por un fantasma | G1: Registro de ejecución
A2: Creado por | B2: Cruz, Luzzi (mutación: Luzzi) | C2: Versión | D2: 2 | G2: Ciclo | H2: Fecha | I2: Ejecutor | J2: Estado | K2: Resultado obtenido | L2: Defecto
A3: Reporte de ejecución 2 | C3: Estado en la Entrega 2 | D3: =IFERROR(IF(INDEX('Reporte de ejecución - Entrega2'!$I$4:$I$132,MATCH($B$1,'Reporte de ejecución - Entrega2'!$A$4:$A$132,0))="","Sin ejecutar",INDEX('Reporte de ejecución - Entrega2'!$I$4:$I$132,MATCH($B$1,'Reporte de ejecución - Entrega2'!$A$4:$A$132,0))),"Sin ejecutar") | G3: Ciclo 1 | H3: 46294 | I3: Rodriguez Castro | J3: Aprobado | K3: Aprobado. Coincide con lo observado en CP-012.
C4: Estado en la Entrega 1 | D4: Aprobado | G4: Ciclo 2 | H4: 46307 | I4: Luzzi | J4: Aprobado | K4: Con 20 esferas consumidas se perdió una vida: siguió el nivel 1, puntaje 200 → 200, las esferas consumidas siguen ausentes y los personajes volvieron a sus posiciones iniciales. (Fantasmas retirados y posiciones preparadas por script para aislar la condición.)
A5: Prioridad (Alta, Media, Baja) | B5: Alta | C5: Técnica de diseño | D5: Transición de estados | G5: Ciclo 3
G6: Ciclo 1 = Entrega 1 (V1). Ciclo 2 = Entrega 2 (V2): ejecución con script de navegador; las precondiciones preparadas por script se aclaran en el resultado obtenido.
A7: # | B7: Pre-requisitos | D7: Datos de prueba
A8: 1 | B8: Abrir la aplicación en un navegador de escritorio. | D8: Entorno: | E8: Build del commit 7ec70df (V2)
A9: 2 | B9: Elegir «Modo PacMan» en el menú principal y presionar Enter (HU-22). | D9: Navegador: | E9: Chromium 141 de escritorio
A10: 3 | B10: Partida en curso (N1), 3 vidas, al menos 15 esferas consumidas. | D10: Modo de juego: | E10: Pacman
A12: Título del CP | B12: Reanudación del nivel tras perder una vida
A15: Historias de Usuario | B15: HU-08 | C15: Épica | D15: E2 — PowerUp e interacción con fantasmas
A16: Estado Automatización | B16: Automatizado (script de navegador, Entrega 2) | C16: Camino feliz | D16: No
A18: Mutación (Entrega 2) | B18: Con 20 esferas consumidas.
A20: Pasos # | B20: Detalle de pasos | D20: Resultado esperado
A21: 1 | B21: Perder una vida. | D21: Se descuenta una vida.
A22: 2 | B22: Observar el nivel, el puntaje, las esferas y las posiciones de los personajes. | D22: Se reanuda el mismo nivel 1, con el puntaje conservado, las esferas consumidas ausentes y los personajes en sus posiciones iniciales.
A23: El caso se aprueba solo si se cumple todo el resultado esperado del último paso (en negrita); si cualquier parte no se cumple, se registra como Fallido.

Sheet CP-034
A1: Test Case ID | B1: CP-034 | C1: Descripción / Funcionalidad | D1: HU-09 · Ver la cantidad de vidas restantes | G1: Registro de ejecución
A2: Creado por | B2: Cruz, Luzzi (mutación: Luzzi) | C2: Versión | D2: 2 | G2: Ciclo | H2: Fecha | I2: Ejecutor | J2: Estado | K2: Resultado obtenido | L2: Defecto
A3: Reporte de ejecución 2 | C3: Estado en la Entrega 2 | D3: =IFERROR(IF(INDEX('Reporte de ejecución - Entrega2'!$I$4:$I$132,MATCH($B$1,'Reporte de ejecución - Entrega2'!$A$4:$A$132,0))="","Sin ejecutar",INDEX('Reporte de ejecución - Entrega2'!$I$4:$I$132,MATCH($B$1,'Reporte de ejecución - Entrega2'!$A$4:$A$132,0))),"Sin ejecutar") | G3: Ciclo 1 | H3: 46294 | I3: Rodriguez Castro | J3: Fallido | K3: Fallido. Se cumple que no es un número, pero no la ubicación ni el tipo de ícono. Ver DEF-001. | L3: DEF-001
C4: Estado en la Entrega 1 | D4: Fallido | G4: Ciclo 2 | H4: 46307 | I4: Luzzi | J4: Aprobado | K4: Las vidas se muestran abajo a la izquierda, debajo del mapa, como 3 íconos de Pacman (sin número); al perder una vida quedan 2. CP-034: Fallido en Entrega 1 → Aprobado.
A5: Prioridad (Alta, Media, Baja) | B5: Media | C5: Técnica de diseño | D5: Partición de equivalencia | G5: Ciclo 3
G6: Ciclo 1 = Entrega 1 (V1). Ciclo 2 = Entrega 2 (V2): ejecución con script de navegador; las precondiciones preparadas por script se aclaran en el resultado obtenido.
A7: # | B7: Pre-requisitos | D7: Datos de prueba
A8: 1 | B8: Abrir la aplicación en un navegador de escritorio. | D8: Entorno: | E8: Build del commit 7ec70df (V2)
A9: 2 | B9: Elegir «Modo PacMan» en el menú principal y presionar Enter (HU-22). | D9: Navegador: | E9: Chromium 141 de escritorio
A10: 3 | B10: Partida recién iniciada en modo Pacman. | D10: Modo de juego: | E10: Pacman
A12: Título del CP | B12: Presentación del contador de vidas
A15: Historias de Usuario | B15: HU-09 | C15: Épica | D15: E3 — Vidas, puntaje y fin de partida
A16: Estado Automatización | B16: Automatizado (script de navegador, Entrega 2) | C16: Camino feliz | D16: No
A18: Mutación (Entrega 2) | B18: Prueba de confirmación de DEF-001: se repite el caso sin cambios. Además se pierde una vida para ver que se retira un ícono.
A20: Pasos # | B20: Detalle de pasos | D20: Resultado esperado
A21: 1 | B21: Observar el extremo inferior izquierdo de la pantalla. | D21: Se muestran 3 íconos de Pacman como contador de vidas, no un número.
A22: El caso se aprueba solo si se cumple todo el resultado esperado del último paso (en negrita); si cualquier parte no se cumple, se registra como Fallido.

Sheet CP-035
A1: Test Case ID | B1: CP-035 | C1: Descripción / Funcionalidad | D1: HU-09 · Ver la cantidad de vidas restantes | G1: Registro de ejecución
A2: Creado por | B2: Cruz, Luzzi | C2: Versión | D2: 1 | G2: Ciclo | H2: Fecha | I2: Ejecutor | J2: Estado | K2: Resultado obtenido | L2: Defecto
A3: Reporte de ejecución 2 | C3: Estado en la Entrega 2 | D3: =IFERROR(IF(INDEX('Reporte de ejecución - Entrega2'!$I$4:$I$132,MATCH($B$1,'Reporte de ejecución - Entrega2'!$A$4:$A$132,0))="","Sin ejecutar",INDEX('Reporte de ejecución - Entrega2'!$I$4:$I$132,MATCH($B$1,'Reporte de ejecución - Entrega2'!$A$4:$A$132,0))),"Sin ejecutar") | G3: Ciclo 1 | H3: 46294 | I3: Rodriguez Castro | J3: Aprobado | K3: Aprobado. Los íconos evaluados son los círculos amarillos del HUD (ver CP-034 / DEF-001).
C4: Estado en la Entrega 1 | D4: Aprobado | G4: Ciclo 2 | H4: 46323 | I4: Luzzi | J4: Aprobado | K4: Íconos de vidas tras cada pérdida: 3 → 2 → 1 → 0; el contador se actualizó en el momento de cada pérdida (la tercera terminó en Game Over). (Fantasmas retirados y posiciones preparadas por script para aislar la condición.)
A5: Prioridad (Alta, Media, Baja) | B5: Media | C5: Técnica de diseño | D5: Valores límite | G5: Ciclo 3
G6: Ciclo 1 = Entrega 1 (V1). Ciclo 2 = Entrega 2 (V2): ejecución con script de navegador; las precondiciones preparadas por script se aclaran en el resultado obtenido.
A7: # | B7: Pre-requisitos | D7: Datos de prueba
A8: 1 | B8: Abrir la aplicación en un navegador de escritorio. | D8: Entorno: | E8: Build del commit 7ec70df (V2)
A9: 2 | B9: Elegir «Modo PacMan» en el menú principal y presionar Enter (HU-22). | D9: Navegador: | E9: Chromium 141 de escritorio
A10: 3 | B10: Partida en curso (N1), 3 vidas. | D10: Modo de juego: | E10: Pacman
A12: Título del CP | B12: Actualización inmediata del contador de vidas
A15: Historias de Usuario | B15: HU-09 | C15: Épica | D15: E3 — Vidas, puntaje y fin de partida
A16: Estado Automatización | B16: Automatizado (script de navegador, Entrega 2) | C16: Camino feliz | D16: No
A18: Pasos # | B18: Detalle de pasos | D18: Resultado esperado
A19: 1 | B19: Perder una vida y observar el contador. | D19: El contador pasa de 3 a 2 íconos en el momento de la pérdida.
A20: 2 | B20: Perder una segunda vida y observar. | D20: El contador pasa de 2 a 1 ícono en el momento de la pérdida.
A21: 3 | B21: Perder la tercera y observar. | D21: El contador muestra 2 íconos, luego 1, y finalmente ninguno. La actualización ocurre en el momento de cada pérdida.
A22: El caso se aprueba solo si se cumple todo el resultado esperado del último paso (en negrita); si cualquier parte no se cumple, se registra como Fallido.

Sheet CP-036
A1: Test Case ID | B1: CP-036 | C1: Descripción / Funcionalidad | D1: HU-10 · Terminar la partida al agotar las vidas | G1: Registro de ejecución
A2: Creado por | B2: Cruz, Luzzi (mutación: Luzzi) | C2: Versión | D2: 2 | G2: Ciclo | H2: Fecha | I2: Ejecutor | J2: Estado | K2: Resultado obtenido | L2: Defecto
A3: Reporte de ejecución 2 | C3: Estado en la Entrega 2 | D3: =IFERROR(IF(INDEX('Reporte de ejecución - Entrega2'!$I$4:$I$132,MATCH($B$1,'Reporte de ejecución - Entrega2'!$A$4:$A$132,0))="","Sin ejecutar",INDEX('Reporte de ejecución - Entrega2'!$I$4:$I$132,MATCH($B$1,'Reporte de ejecución - Entrega2'!$A$4:$A$132,0))),"Sin ejecutar") | G3: Ciclo 1 | H3: 46294 | I3: Rodriguez Castro | J3: Aprobado | K3: Aprobado.
C4: Estado en la Entrega 1 | D4: Aprobado | G4: Ciclo 2 | H4: 46307 | I4: Luzzi | J4: Aprobado | K4: Última vida perdida en el nivel 2: se mostró «Game Over» con el puntaje final (0); 5 s después la partida seguía terminada, sin reiniciarse ni reanudarse. (Vidas fijadas en 1 por script.)
A5: Prioridad (Alta, Media, Baja) | B5: Alta | C5: Técnica de diseño | D5: Valores límite | G5: Ciclo 3
G6: Ciclo 1 = Entrega 1 (V1). Ciclo 2 = Entrega 2 (V2): ejecución con script de navegador; las precondiciones preparadas por script se aclaran en el resultado obtenido.
A7: # | B7: Pre-requisitos | D7: Datos de prueba
A8: 1 | B8: Abrir la aplicación en un navegador de escritorio. | D8: Entorno: | E8: Build del commit 7ec70df (V2)
A9: 2 | B9: Elegir «Modo PacMan» en el menú principal y presionar Enter (HU-22). | D9: Navegador: | E9: Chromium 141 de escritorio
A10: 3 | B10: Partida en curso (N1), 1 vida restante. | D10: Modo de juego: | E10: Pacman
A12: Título del CP | B12: Game Over al perder la tercera vida
A15: Historias de Usuario | B15: HU-10 | C15: Épica | D15: E3 — Vidas, puntaje y fin de partida
A16: Estado Automatización | B16: Automatizado (script de navegador, Entrega 2) | C16: Camino feliz | D16: Sí
A18: Mutación (Entrega 2) | B18: Última vida perdida en el nivel 2.
A20: Pasos # | B20: Detalle de pasos | D20: Resultado esperado
A21: 1 | B21: Perder la última vida. | D21: El contador de vidas queda sin íconos.
A22: 2 | B22: Observar la pantalla y esperar 5 segundos. | D22: La partida termina, se muestra la pantalla de Game Over con el puntaje final, y el nivel no se reinicia ni se reanuda.
A23: El caso se aprueba solo si se cumple todo el resultado esperado del último paso (en negrita); si cualquier parte no se cumple, se registra como Fallido.

Sheet CP-037
A1: Test Case ID | B1: CP-037 | C1: Descripción / Funcionalidad | D1: HU-10 · Terminar la partida al agotar las vidas | G1: Registro de ejecución
A2: Creado por | B2: Cruz, Luzzi | C2: Versión | D2: 1 | G2: Ciclo | H2: Fecha | I2: Ejecutor | J2: Estado | K2: Resultado obtenido | L2: Defecto
A3: Reporte de ejecución 2 | C3: Estado en la Entrega 2 | D3: =IFERROR(IF(INDEX('Reporte de ejecución - Entrega2'!$I$4:$I$132,MATCH($B$1,'Reporte de ejecución - Entrega2'!$A$4:$A$132,0))="","Sin ejecutar",INDEX('Reporte de ejecución - Entrega2'!$I$4:$I$132,MATCH($B$1,'Reporte de ejecución - Entrega2'!$A$4:$A$132,0))),"Sin ejecutar") | G3: Ciclo 1 | H3: 46294 | I3: Rodriguez Castro | J3: Aprobado | K3: Aprobado. Niveles 1 a 3 jugados con el piloto automático (envía teclas, no modifica el estado); en N3 se apagó el piloto para perder las vidas.
C4: Estado en la Entrega 1 | D4: Aprobado | G4: Ciclo 2 | H4: 46323 | I4: Luzzi | J4: Aprobado | K4: Última vida perdida en el nivel 3: pantalla «Game Over» con el puntaje final y «Volver a jugar», igual que en el nivel 1; la partida no se reanudó. (Vidas fijadas en 1 por script.)
A5: Prioridad (Alta, Media, Baja) | B5: Media | C5: Técnica de diseño | D5: Partición de equivalencia | G5: Ciclo 3
G6: Ciclo 1 = Entrega 1 (V1). Ciclo 2 = Entrega 2 (V2): ejecución con script de navegador; las precondiciones preparadas por script se aclaran en el resultado obtenido.
A7: # | B7: Pre-requisitos | D7: Datos de prueba
A8: 1 | B8: Abrir la aplicación en un navegador de escritorio. | D8: Entorno: | E8: Build del commit 7ec70df (V2)
A9: 2 | B9: Elegir «Modo PacMan» en el menú principal y presionar Enter (HU-22). | D9: Navegador: | E9: Chromium 141 de escritorio
A10: 3 | B10: Partida en curso en el nivel 3, 1 vida restante. | D10: Modo de juego: | E10: Pacman
A12: Título del CP | B12: Game Over en un nivel distinto del primero
A15: Historias de Usuario | B15: HU-10 | C15: Épica | D15: E3 — Vidas, puntaje y fin de partida
A16: Estado Automatización | B16: Automatizado (script de navegador, Entrega 2) | C16: Camino feliz | D16: No
A18: Pasos # | B18: Detalle de pasos | D18: Resultado esperado
A19: 1 | B19: Perder la última vida. | D19: La partida termina con Game Over en el nivel 3, con el mismo comportamiento que en el nivel 1.
A20: El caso se aprueba solo si se cumple todo el resultado esperado del último paso (en negrita); si cualquier parte no se cumple, se registra como Fallido.

Sheet CP-038
A1: Test Case ID | B1: CP-038 | C1: Descripción / Funcionalidad | D1: HU-11 · Ver el puntaje durante la partida | G1: Registro de ejecución
A2: Creado por | B2: Cruz, Luzzi | C2: Versión | D2: 1 | G2: Ciclo | H2: Fecha | I2: Ejecutor | J2: Estado | K2: Resultado obtenido | L2: Defecto
A3: Reporte de ejecución 2 | C3: Estado en la Entrega 2 | D3: =IFERROR(IF(INDEX('Reporte de ejecución - Entrega2'!$I$4:$I$132,MATCH($B$1,'Reporte de ejecución - Entrega2'!$A$4:$A$132,0))="","Sin ejecutar",INDEX('Reporte de ejecución - Entrega2'!$I$4:$I$132,MATCH($B$1,'Reporte de ejecución - Entrega2'!$A$4:$A$132,0))),"Sin ejecutar") | G3: Ciclo 1 | H3: 46294 | I3: Rodriguez Castro | J3: Aprobado | K3: Aprobado. Se comparó cuadro a cuadro el puntaje interno con el texto del HUD.
C4: Estado en la Entrega 1 | D4: Aprobado | G4: Ciclo 2 | H4: 46323 | I4: Luzzi | J4: Aprobado | K4: HUD: puntaje inicial 0; después de cada acción [10, 60, 260] (incrementos [10, 50, 200]: esfera común, esfera grande y fantasma). (Fantasmas retirados y posiciones preparadas por script para aislar la condición.)
A5: Prioridad (Alta, Media, Baja) | B5: Media | C5: Técnica de diseño | D5: Partición de equivalencia | G5: Ciclo 3
G6: Ciclo 1 = Entrega 1 (V1). Ciclo 2 = Entrega 2 (V2): ejecución con script de navegador; las precondiciones preparadas por script se aclaran en el resultado obtenido.
A7: # | B7: Pre-requisitos | D7: Datos de prueba
A8: 1 | B8: Abrir la aplicación en un navegador de escritorio. | D8: Entorno: | E8: Build del commit 7ec70df (V2)
A9: 2 | B9: Elegir «Modo PacMan» en el menú principal y presionar Enter (HU-22). | D9: Navegador: | E9: Chromium 141 de escritorio
A10: 3 | B10: Partida recién iniciada en modo Pacman. | D10: Modo de juego: | E10: Pacman
A12: Título del CP | B12: Puntaje visible y actualizado en el HUD
A15: Historias de Usuario | B15: HU-11 | C15: Épica | D15: E3 — Vidas, puntaje y fin de partida
A16: Estado Automatización | B16: Automatizado (script de navegador, Entrega 2) | C16: Camino feliz | D16: Sí
A18: Pasos # | B18: Detalle de pasos | D18: Resultado esperado
A19: 1 | B19: Verificar el puntaje inicial. | D19: El HUD muestra puntaje 0.
A20: 2 | B20: Consumir una esfera común, una esfera grande y un fantasma con el PowerUp activo, observando el HUD después de cada acción. | D20: El puntaje inicia en 0 y se actualiza de manera inmediata tras cada acción, en +10, +50 y +200 respectivamente.
A21: El caso se aprueba solo si se cumple todo el resultado esperado del último paso (en negrita); si cualquier parte no se cumple, se registra como Fallido.

Sheet CP-039
A1: Test Case ID | B1: CP-039 | C1: Descripción / Funcionalidad | D1: HU-11 · Ver el puntaje durante la partida | G1: Registro de ejecución
A2: Creado por | B2: Cruz, Luzzi | C2: Versión | D2: 1 | G2: Ciclo | H2: Fecha | I2: Ejecutor | J2: Estado | K2: Resultado obtenido | L2: Defecto
A3: Reporte de ejecución 2 | C3: Estado en la Entrega 2 | D3: =IFERROR(IF(INDEX('Reporte de ejecución - Entrega2'!$I$4:$I$132,MATCH($B$1,'Reporte de ejecución - Entrega2'!$A$4:$A$132,0))="","Sin ejecutar",INDEX('Reporte de ejecución - Entrega2'!$I$4:$I$132,MATCH($B$1,'Reporte de ejecución - Entrega2'!$A$4:$A$132,0))),"Sin ejecutar") | G3: Ciclo 1 | H3: 46294 | I3: Rodriguez Castro | J3: Aprobado | K3: Aprobado. Entre la referencia y la pérdida de vida el puntaje subió porque Pacman siguió comiendo; lo que se verifica es que nunca baja.
C4: Estado en la Entrega 1 | D4: Aprobado | G4: Ciclo 2 | H4: 46323 | I4: Luzzi | J4: Aprobado | K4: Puntaje 60; tras perder una vida: 60; al completar el nivel 1: 1240; al iniciar el nivel 2: 1240. Nunca disminuyó. (Mapa reducido por script para completar el nivel.)
A5: Prioridad (Alta, Media, Baja) | B5: Media | C5: Técnica de diseño | D5: Adivinación de errores | G5: Ciclo 3
G6: Ciclo 1 = Entrega 1 (V1). Ciclo 2 = Entrega 2 (V2): ejecución con script de navegador; las precondiciones preparadas por script se aclaran en el resultado obtenido.
A7: # | B7: Pre-requisitos | D7: Datos de prueba
A8: 1 | B8: Abrir la aplicación en un navegador de escritorio. | D8: Entorno: | E8: Build del commit 7ec70df (V2)
A9: 2 | B9: Elegir «Modo PacMan» en el menú principal y presionar Enter (HU-22). | D9: Navegador: | E9: Chromium 141 de escritorio
A10: 3 | B10: Partida en curso (N1) con puntaje mayor a 0. | D10: Modo de juego: | E10: Pacman
A12: Título del CP | B12: El puntaje no disminuye ni se reinicia entre niveles
A15: Historias de Usuario | B15: HU-11 | C15: Épica | D15: E3 — Vidas, puntaje y fin de partida
A16: Estado Automatización | B16: Automatizado (script de navegador, Entrega 2) | C16: Camino feliz | D16: No
A18: Pasos # | B18: Detalle de pasos | D18: Resultado esperado
A19: 1 | B19: Registrar el puntaje. | D19: Puntaje anotado como valor de referencia.
A20: 2 | B20: Perder una vida y registrar. | D20: El puntaje es igual al anotado en el paso anterior.
A21: 3 | B21: Completar el nivel y registrar al inicio del nivel 2. | D21: El puntaje no disminuye en ningún momento y se conserva al cambiar de nivel.
A22: El caso se aprueba solo si se cumple todo el resultado esperado del último paso (en negrita); si cualquier parte no se cumple, se registra como Fallido.

Sheet CP-040
A1: Test Case ID | B1: CP-040 | C1: Descripción / Funcionalidad | D1: HU-12 · Sumar puntos por las frutas | G1: Registro de ejecución
A2: Creado por | B2: Cruz, Luzzi | C2: Versión | D2: 1 | G2: Ciclo | H2: Fecha | I2: Ejecutor | J2: Estado | K2: Resultado obtenido | L2: Defecto
A3: Reporte de ejecución 2 | C3: Estado en la Entrega 2 | D3: =IFERROR(IF(INDEX('Reporte de ejecución - Entrega2'!$I$4:$I$132,MATCH($B$1,'Reporte de ejecución - Entrega2'!$A$4:$A$132,0))="","Sin ejecutar",INDEX('Reporte de ejecución - Entrega2'!$I$4:$I$132,MATCH($B$1,'Reporte de ejecución - Entrega2'!$A$4:$A$132,0))),"Sin ejecutar") | G3: Ciclo 1 | H3: 46294 | I3: Rodriguez Castro | J3: Aprobado | K3: Aprobado.
C4: Estado en la Entrega 1 | D4: Aprobado | G4: Ciclo 2 | H4: 46323 | I4: Luzzi | J4: Aprobado | K4: Fruta aparecida en (9,8) en el nivel 3: Pacman la consumió, desapareció del mapa, el puntaje subió +100 y el contador de esferas quedó en 124 → 124. (Esfera de la celda retirada por script para medir solo la fruta.)
A5: Prioridad (Alta, Media, Baja) | B5: Media | C5: Técnica de diseño | D5: Partición de equivalencia | G5: Ciclo 3
G6: Ciclo 1 = Entrega 1 (V1). Ciclo 2 = Entrega 2 (V2): ejecución con script de navegador; las precondiciones preparadas por script se aclaran en el resultado obtenido.
A7: # | B7: Pre-requisitos | D7: Datos de prueba
A8: 1 | B8: Abrir la aplicación en un navegador de escritorio. | D8: Entorno: | E8: Build del commit 7ec70df (V2)
A9: 2 | B9: Elegir «Modo PacMan» en el menú principal y presionar Enter (HU-22). | D9: Navegador: | E9: Chromium 141 de escritorio
A10: 3 | B10: Partida en curso en el nivel 3, con una fruta presente en el mapa. | D10: Modo de juego: | E10: Pacman
A12: Título del CP | B12: Consumo de una fruta
A15: Historias de Usuario | B15: HU-12 | C15: Épica | D15: E3 — Vidas, puntaje y fin de partida
A16: Estado Automatización | B16: Automatizado (script de navegador, Entrega 2) | C16: Camino feliz | D16: Sí
A18: Pasos # | B18: Detalle de pasos | D18: Resultado esperado
A19: 1 | B19: Registrar el puntaje y el contador de esferas restantes. | D19: Puntaje y contador de esferas anotados como valores de referencia.
A20: 2 | B20: Consumir la fruta. | D20: La fruta desaparece del mapa.
A21: 3 | B21: Registrar ambos valores. | D21: La fruta desaparece, el puntaje aumenta exactamente 100 y el contador de esferas restantes no cambia.
A22: El caso se aprueba solo si se cumple todo el resultado esperado del último paso (en negrita); si cualquier parte no se cumple, se registra como Fallido.

Sheet CP-041
A1: Test Case ID | B1: CP-041 | C1: Descripción / Funcionalidad | D1: HU-12 · Sumar puntos por las frutas | G1: Registro de ejecución
A2: Creado por | B2: Cruz, Luzzi | C2: Versión | D2: 1 | G2: Ciclo | H2: Fecha | I2: Ejecutor | J2: Estado | K2: Resultado obtenido | L2: Defecto
A3: Reporte de ejecución 2 | C3: Estado en la Entrega 2 | D3: =IFERROR(IF(INDEX('Reporte de ejecución - Entrega2'!$I$4:$I$132,MATCH($B$1,'Reporte de ejecución - Entrega2'!$A$4:$A$132,0))="","Sin ejecutar",INDEX('Reporte de ejecución - Entrega2'!$I$4:$I$132,MATCH($B$1,'Reporte de ejecución - Entrega2'!$A$4:$A$132,0))),"Sin ejecutar") | G3: Ciclo 1 | H3: 46294 | I3: Rodriguez Castro | J3: Aprobado | K3: Aprobado. Según la configuración del juego, las frutas duran 15 s.
C4: Estado en la Entrega 1 | D4: Aprobado | G4: Ciclo 2 | H4: 46323 | I4: Luzzi | J4: Aprobado | K4: Fruta aparecida en (9,4): a los 14 s seguía en el mapa; a los 16 s ya no estaba.
A5: Prioridad (Alta, Media, Baja) | B5: Baja | C5: Técnica de diseño | D5: Valores límite | G5: Ciclo 3
G6: Ciclo 1 = Entrega 1 (V1). Ciclo 2 = Entrega 2 (V2): ejecución con script de navegador; las precondiciones preparadas por script se aclaran en el resultado obtenido.
A7: # | B7: Pre-requisitos | D7: Datos de prueba
A8: 1 | B8: Abrir la aplicación en un navegador de escritorio. | D8: Entorno: | E8: Build del commit 7ec70df (V2)
A9: 2 | B9: Elegir «Modo PacMan» en el menú principal y presionar Enter (HU-22). | D9: Navegador: | E9: Chromium 141 de escritorio
A10: 3 | B10: Partida en curso en el nivel 3, con una fruta que acaba de aparecer. | D10: Modo de juego: | E10: Pacman
A12: Título del CP | B12: Desaparición de una fruta no consumida
A15: Historias de Usuario | B15: HU-12 | C15: Épica | D15: E3 — Vidas, puntaje y fin de partida
A16: Estado Automatización | B16: Automatizado (script de navegador, Entrega 2) | C16: Camino feliz | D16: No
A18: Pasos # | B18: Detalle de pasos | D18: Resultado esperado
A19: 1 | B19: Cronometrar desde la aparición de la fruta sin consumirla. | D19: Cronómetro iniciado en el instante en que aparece la fruta.
A20: 2 | B20: Observar el mapa a los 14 segundos y a los 16 segundos. | D20: A los 14 segundos la fruta sigue en el mapa; a los 16 segundos ya no está.
A21: El caso se aprueba solo si se cumple todo el resultado esperado del último paso (en negrita); si cualquier parte no se cumple, se registra como Fallido.

Sheet CP-042
A1: Test Case ID | B1: CP-042 | C1: Descripción / Funcionalidad | D1: HU-13 · Conocer el puntaje final desglosado | G1: Registro de ejecución
A2: Creado por | B2: Cruz, Luzzi | C2: Versión | D2: 1 | G2: Ciclo | H2: Fecha | I2: Ejecutor | J2: Estado | K2: Resultado obtenido | L2: Defecto
A3: Reporte de ejecución 2 | C3: Estado en la Entrega 2 | D3: =IFERROR(IF(INDEX('Reporte de ejecución - Entrega2'!$I$4:$I$132,MATCH($B$1,'Reporte de ejecución - Entrega2'!$A$4:$A$132,0))="","Sin ejecutar",INDEX('Reporte de ejecución - Entrega2'!$I$4:$I$132,MATCH($B$1,'Reporte de ejecución - Entrega2'!$A$4:$A$132,0))),"Sin ejecutar") | G3: Ciclo 1 | H3: 46294 | I3: Rodriguez Castro | J3: Aprobado | K3: Aprobado. Nivel jugado con el piloto automático.
C4: Estado en la Entrega 1 | D4: Aprobado | G4: Ciclo 2 | H4: 46323 | I4: Luzzi | J4: Aprobado | K4: Nivel 1 completado en 3.68 s: bonus por tiempo 1160 = 10 × 116 s enteros restantes (fracción descartada); el desglose lo suma. (Mapa reducido a una esfera por script.)
A5: Prioridad (Alta, Media, Baja) | B5: Media | C5: Técnica de diseño | D5: Valores límite | G5: Ciclo 3
G6: Ciclo 1 = Entrega 1 (V1). Ciclo 2 = Entrega 2 (V2): ejecución con script de navegador; las precondiciones preparadas por script se aclaran en el resultado obtenido.
A7: # | B7: Pre-requisitos | D7: Datos de prueba
A8: 1 | B8: Abrir la aplicación en un navegador de escritorio. | D8: Entorno: | E8: Build del commit 7ec70df (V2)
A9: 2 | B9: Elegir «Modo PacMan» en el menú principal y presionar Enter (HU-22). | D9: Navegador: | E9: Chromium 141 de escritorio
A10: 3 | B10: Partida en curso (N1). | D10: Modo de juego: | E10: Pacman
A12: Título del CP | B12: Cálculo del bonus por tiempo
A15: Historias de Usuario | B15: HU-13 | C15: Épica | D15: E3 — Vidas, puntaje y fin de partida
A16: Estado Automatización | B16: Automatizado (script de navegador, Entrega 2) | C16: Camino feliz | D16: No
A18: Pasos # | B18: Detalle de pasos | D18: Resultado esperado
A19: 1 | B19: Completar el nivel 1 en menos de 120 segundos, registrando el tiempo empleado. | D19: Nivel completado y tiempo empleado anotado.
A20: 2 | B20: Verificar el bonus por tiempo en el desglose. | D20: El bonus por tiempo es igual a 10 multiplicado por los segundos **enteros** restantes respecto de los 120 segundos objetivo, descartando la fracción. Por ejemplo, un tiempo de 100,5 s deja 19 s y da un bonus de 190 (sección 4.2).
A21: El caso se aprueba solo si se cumple todo el resultado esperado del último paso (en negrita); si cualquier parte no se cumple, se registra como Fallido.

Sheet CP-043
A1: Test Case ID | B1: CP-043 | C1: Descripción / Funcionalidad | D1: HU-13 · Conocer el puntaje final desglosado | G1: Registro de ejecución
A2: Creado por | B2: Cruz, Luzzi | C2: Versión | D2: 1 | G2: Ciclo | H2: Fecha | I2: Ejecutor | J2: Estado | K2: Resultado obtenido | L2: Defecto
A3: Reporte de ejecución 2 | C3: Estado en la Entrega 2 | D3: =IFERROR(IF(INDEX('Reporte de ejecución - Entrega2'!$I$4:$I$132,MATCH($B$1,'Reporte de ejecución - Entrega2'!$A$4:$A$132,0))="","Sin ejecutar",INDEX('Reporte de ejecución - Entrega2'!$I$4:$I$132,MATCH($B$1,'Reporte de ejecución - Entrega2'!$A$4:$A$132,0))),"Sin ejecutar") | G3: Ciclo 1 | H3: 46294 | I3: Rodriguez Castro | J3: Aprobado | K3: Aprobado. Para superar los 120 s el piloto reservó las esferas grandes como recurso de emergencia; llegó al final con 1 vida.
C4: Estado en la Entrega 1 | D4: Aprobado | G4: Ciclo 2 | H4: 46323 | I4: Luzzi | J4: Aprobado | K4: Nivel 1 completado a los 121.75 s (más de 120 s reales de juego): bonus por tiempo 0, no negativo. (Mapa reducido a una esfera por script al final.)
A5: Prioridad (Alta, Media, Baja) | B5: Media | C5: Técnica de diseño | D5: Valores límite | G5: Ciclo 3
G6: Ciclo 1 = Entrega 1 (V1). Ciclo 2 = Entrega 2 (V2): ejecución con script de navegador; las precondiciones preparadas por script se aclaran en el resultado obtenido.
A7: # | B7: Pre-requisitos | D7: Datos de prueba
A8: 1 | B8: Abrir la aplicación en un navegador de escritorio. | D8: Entorno: | E8: Build del commit 7ec70df (V2)
A9: 2 | B9: Elegir «Modo PacMan» en el menú principal y presionar Enter (HU-22). | D9: Navegador: | E9: Chromium 141 de escritorio
A10: 3 | B10: Partida en curso (N1). | D10: Modo de juego: | E10: Pacman
A12: Título del CP | B12: Bonus por tiempo al exceder el tiempo objetivo
A15: Historias de Usuario | B15: HU-13 | C15: Épica | D15: E3 — Vidas, puntaje y fin de partida
A16: Estado Automatización | B16: Automatizado (script de navegador, Entrega 2) | C16: Camino feliz | D16: No
A18: Pasos # | B18: Detalle de pasos | D18: Resultado esperado
A19: 1 | B19: Completar el nivel 1 en más de 120 segundos. | D19: Nivel completado después de los 120 segundos.
A20: 2 | B20: Verificar el bonus por tiempo. | D20: El bonus por tiempo es 0 y en ningún caso un valor negativo.
A21: El caso se aprueba solo si se cumple todo el resultado esperado del último paso (en negrita); si cualquier parte no se cumple, se registra como Fallido.

Sheet CP-044
A1: Test Case ID | B1: CP-044 | C1: Descripción / Funcionalidad | D1: HU-13 · Conocer el puntaje final desglosado | G1: Registro de ejecución
A2: Creado por | B2: Cruz, Luzzi | C2: Versión | D2: 1 | G2: Ciclo | H2: Fecha | I2: Ejecutor | J2: Estado | K2: Resultado obtenido | L2: Defecto
A3: Reporte de ejecución 2 | C3: Estado en la Entrega 2 | D3: =IFERROR(IF(INDEX('Reporte de ejecución - Entrega2'!$I$4:$I$132,MATCH($B$1,'Reporte de ejecución - Entrega2'!$A$4:$A$132,0))="","Sin ejecutar",INDEX('Reporte de ejecución - Entrega2'!$I$4:$I$132,MATCH($B$1,'Reporte de ejecución - Entrega2'!$A$4:$A$132,0))),"Sin ejecutar") | G3: Ciclo 1 | H3: 46294 | I3: Rodriguez Castro | J3: Aprobado | K3: Aprobado. Evidencia tomada de la victoria de CP-017 (mismo ciclo y misma versión), que cumple el prerrequisito de 2 vidas.
C4: Estado en la Entrega 1 | D4: Aprobado | G4: Ciclo 2 | H4: 46323 | I4: Luzzi | J4: Aprobado | K4: Victoria con 2 vidas: desglose {'Esferas': '30', 'Fantasmas comidos': '0', 'Frutas': '0', 'Bonus por tiempo': '4470', 'Bonus por vidas': '1000', 'Total': '5500'}; bonus por vidas 1000 (500 × 2) y la suma de los componentes coincide con el total. (Vidas fijadas en 2 y mapas reducidos por script.)
A5: Prioridad (Alta, Media, Baja) | B5: Media | C5: Técnica de diseño | D5: Valores límite | G5: Ciclo 3
G6: Ciclo 1 = Entrega 1 (V1). Ciclo 2 = Entrega 2 (V2): ejecución con script de navegador; las precondiciones preparadas por script se aclaran en el resultado obtenido.
A7: # | B7: Pre-requisitos | D7: Datos de prueba
A8: 1 | B8: Abrir la aplicación en un navegador de escritorio. | D8: Entorno: | E8: Build del commit 7ec70df (V2)
A9: 2 | B9: Elegir «Modo PacMan» en el menú principal y presionar Enter (HU-22). | D9: Navegador: | E9: Chromium 141 de escritorio
A10: 3 | B10: Partida completada en victoria con 2 vidas restantes. | D10: Modo de juego: | E10: Pacman
A12: Título del CP | B12: Bonus por vidas restantes y consistencia del desglose
A15: Historias de Usuario | B15: HU-13 | C15: Épica | D15: E3 — Vidas, puntaje y fin de partida
A16: Estado Automatización | B16: Automatizado (script de navegador, Entrega 2) | C16: Camino feliz | D16: No
A18: Pasos # | B18: Detalle de pasos | D18: Resultado esperado
A19: 1 | B19: Registrar cada componente del desglose y el total. | D19: Componentes del desglose y total anotados.
A20: 2 | B20: Sumar los componentes manualmente. | D20: El bonus por vidas es de 1000 puntos (500 por cada una de las 2 vidas) y la suma de todos los componentes coincide exactamente con el total mostrado.
A21: El caso se aprueba solo si se cumple todo el resultado esperado del último paso (en negrita); si cualquier parte no se cumple, se registra como Fallido.

Sheet CP-045
A1: Test Case ID | B1: CP-045 | C1: Descripción / Funcionalidad | D1: HU-13 · Conocer el puntaje final desglosado | G1: Registro de ejecución
A2: Creado por | B2: Cruz, Luzzi | C2: Versión | D2: 1 | G2: Ciclo | H2: Fecha | I2: Ejecutor | J2: Estado | K2: Resultado obtenido | L2: Defecto
A3: Reporte de ejecución 2 | C3: Estado en la Entrega 2 | D3: =IFERROR(IF(INDEX('Reporte de ejecución - Entrega2'!$I$4:$I$132,MATCH($B$1,'Reporte de ejecución - Entrega2'!$A$4:$A$132,0))="","Sin ejecutar",INDEX('Reporte de ejecución - Entrega2'!$I$4:$I$132,MATCH($B$1,'Reporte de ejecución - Entrega2'!$A$4:$A$132,0))),"Sin ejecutar") | G3: Ciclo 1 | H3: 46294 | I3: Rodriguez Castro | J3: Aprobado | K3: Aprobado.
C4: Estado en la Entrega 1 | D4: Aprobado | G4: Ciclo 2 | H4: 46323 | I4: Luzzi | J4: Aprobado | K4: Game Over: desglose {'Esferas': '0', 'Fantasmas comidos': '0', 'Frutas': '0', 'Bonus por tiempo': '0', 'Bonus por vidas': '0', 'Total': '0'}; bonus por vidas restantes 0. (Vidas fijadas en 1 por script.)
A5: Prioridad (Alta, Media, Baja) | B5: Media | C5: Técnica de diseño | D5: Valores límite | G5: Ciclo 3
G6: Ciclo 1 = Entrega 1 (V1). Ciclo 2 = Entrega 2 (V2): ejecución con script de navegador; las precondiciones preparadas por script se aclaran en el resultado obtenido.
A7: # | B7: Pre-requisitos | D7: Datos de prueba
A8: 1 | B8: Abrir la aplicación en un navegador de escritorio. | D8: Entorno: | E8: Build del commit 7ec70df (V2)
A9: 2 | B9: Elegir «Modo PacMan» en el menú principal y presionar Enter (HU-22). | D9: Navegador: | E9: Chromium 141 de escritorio
A10: 3 | B10: Partida terminada en Game Over. | D10: Modo de juego: | E10: Pacman
A12: Título del CP | B12: Bonus por vidas en un Game Over
A15: Historias de Usuario | B15: HU-13 | C15: Épica | D15: E3 — Vidas, puntaje y fin de partida
A16: Estado Automatización | B16: Automatizado (script de navegador, Entrega 2) | C16: Camino feliz | D16: No
A18: Pasos # | B18: Detalle de pasos | D18: Resultado esperado
A19: 1 | B19: Verificar el bonus por vidas restantes en el desglose. | D19: El bonus por vidas restantes es 0.
A20: El caso se aprueba solo si se cumple todo el resultado esperado del último paso (en negrita); si cualquier parte no se cumple, se registra como Fallido.

Sheet CP-046
A1: Test Case ID | B1: CP-046 | C1: Descripción / Funcionalidad | D1: HU-14 · Ver el progreso de esferas del nivel | G1: Registro de ejecución
A2: Creado por | B2: Cruz, Luzzi | C2: Versión | D2: 1 | G2: Ciclo | H2: Fecha | I2: Ejecutor | J2: Estado | K2: Resultado obtenido | L2: Defecto
A3: Reporte de ejecución 2 | C3: Estado en la Entrega 2 | D3: =IFERROR(IF(INDEX('Reporte de ejecución - Entrega2'!$I$4:$I$132,MATCH($B$1,'Reporte de ejecución - Entrega2'!$A$4:$A$132,0))="","Sin ejecutar",INDEX('Reporte de ejecución - Entrega2'!$I$4:$I$132,MATCH($B$1,'Reporte de ejecución - Entrega2'!$A$4:$A$132,0))),"Sin ejecutar") | G3: Ciclo 1 | H3: 46294 | I3: Rodriguez Castro | J3: Aprobado | K3: Aprobado. Contador comparado cuadro a cuadro contra el conteo del mapa; también se contaron los puntos dibujados en el canvas. Partida jugada con el piloto automático.
C4: Estado en la Entrega 1 | D4: Aprobado | G4: Ciclo 2 | H4: 46323 | I4: Luzzi | J4: Aprobado | K4: Inicio: contador 106 = 106 esferas del mapa (incluidas las 4 grandes); tras 5 esferas: 100 (−5); al consumir la última: 0; nivel 2: 131 = 131 esferas de su mapa. (Para la parte final, mapa del nivel 1 reducido a una esfera por script.)
A5: Prioridad (Alta, Media, Baja) | B5: Baja | C5: Técnica de diseño | D5: Valores límite | G5: Ciclo 3
G6: Ciclo 1 = Entrega 1 (V1). Ciclo 2 = Entrega 2 (V2): ejecución con script de navegador; las precondiciones preparadas por script se aclaran en el resultado obtenido.
A7: # | B7: Pre-requisitos | D7: Datos de prueba
A8: 1 | B8: Abrir la aplicación en un navegador de escritorio. | D8: Entorno: | E8: Build del commit 7ec70df (V2)
A9: 2 | B9: Elegir «Modo PacMan» en el menú principal y presionar Enter (HU-22). | D9: Navegador: | E9: Chromium 141 de escritorio
A10: 3 | B10: Partida recién iniciada en modo Pacman. | D10: Modo de juego: | E10: Pacman
A12: Título del CP | B12: Contador de esferas restantes
A15: Historias de Usuario | B15: HU-14 | C15: Épica | D15: E3 — Vidas, puntaje y fin de partida
A16: Estado Automatización | B16: Automatizado (script de navegador, Entrega 2) | C16: Camino feliz | D16: No
A18: Pasos # | B18: Detalle de pasos | D18: Resultado esperado
A19: 1 | B19: Registrar el valor inicial del contador y contar las esferas del mapa, incluidas las grandes. | D19: El valor inicial coincide con el total de esferas contadas, incluidas las grandes.
A20: 2 | B20: Consumir 5 esferas y verificar el contador. | D20: El contador disminuyó exactamente 5.
A21: 3 | B21: Completar el nivel y verificar el contador al llegar a la última esfera. | D21: El contador llega a 0 al consumir la última esfera.
A22: 4 | B22: Verificar el contador al iniciar el nivel 2. | D22: El valor inicial coincide con el total de esferas del mapa incluidas las grandes, disminuye en 1 por esfera consumida, llega a 0 exactamente al completarse el nivel, y se reinicia al total del nivel 2.
A23: El caso se aprueba solo si se cumple todo el resultado esperado del último paso (en negrita); si cualquier parte no se cumple, se registra como Fallido.

Sheet CP-047
A1: Test Case ID | B1: CP-047 | C1: Descripción / Funcionalidad | D1: HU-15 · Jugar tres niveles con mapas propios | G1: Registro de ejecución
A2: Creado por | B2: Cruz, Luzzi (mutación: Luzzi) | C2: Versión | D2: 2 | G2: Ciclo | H2: Fecha | I2: Ejecutor | J2: Estado | K2: Resultado obtenido | L2: Defecto
A3: Reporte de ejecución 2 | C3: Estado en la Entrega 2 | D3: =IFERROR(IF(INDEX('Reporte de ejecución - Entrega2'!$I$4:$I$132,MATCH($B$1,'Reporte de ejecución - Entrega2'!$A$4:$A$132,0))="","Sin ejecutar",INDEX('Reporte de ejecución - Entrega2'!$I$4:$I$132,MATCH($B$1,'Reporte de ejecución - Entrega2'!$A$4:$A$132,0))),"Sin ejecutar") | G3: Ciclo 1 | H3: 46294 | I3: Rodriguez Castro | J3: Aprobado | K3: Aprobado. Colores verificados en capturas y en los píxeles de los muros, y coinciden con la configuración del juego (N1 \#c81e2c / \#38f0e8; N2 \#0b1d4d / \#2f6bff; N3 \#0d4d12 / \#39ff14).
C4: Estado en la Entrega 1 | D4: Aprobado | G4: Ciclo 2 | H4: 46307 | I4: Luzzi | J4: Aprobado | K4: Niveles 1, 2 y 3 en orden; HUD: ['Nivel 1', 'Nivel 2', 'Nivel 3']. Los tres mapas tienen forma distinta. Color medio de muros: N1 [168, 25, 37] con 148 muestras rojas (franjas), N2 [11, 29, 77] (azul, sin rojo), N3 [14, 78, 18] (verde). Barra inferior de vidas con 3 íconos de Pacman en los tres niveles (DEF-001). (Mapas reducidos por script para avanzar; capturas REG-CP-047-N1..N3.)
A5: Prioridad (Alta, Media, Baja) | B5: Alta | C5: Técnica de diseño | D5: Partición de equivalencia | G5: Ciclo 3
G6: Ciclo 1 = Entrega 1 (V1). Ciclo 2 = Entrega 2 (V2): ejecución con script de navegador; las precondiciones preparadas por script se aclaran en el resultado obtenido.
A7: # | B7: Pre-requisitos | D7: Datos de prueba
A8: 1 | B8: Abrir la aplicación en un navegador de escritorio. | D8: Entorno: | E8: Build del commit 7ec70df (V2)
A9: 2 | B9: Elegir «Modo PacMan» en el menú principal y presionar Enter (HU-22). | D9: Navegador: | E9: Chromium 141 de escritorio
A10: 3 | B10: Ninguna. | D10: Modo de juego: | E10: Pacman
A12: Título del CP | B12: Los tres niveles y sus mapas
A15: Historias de Usuario | B15: HU-15 | C15: Épica | D15: E4 — Niveles y progresión de dificultad
A16: Estado Automatización | B16: Automatizado (script de navegador, Entrega 2) | C16: Camino feliz | D16: Sí
A18: Mutación (Entrega 2) | B18: Partida completa; se registra además la barra inferior de vidas (DEF-001).
A20: Pasos # | B20: Detalle de pasos | D20: Resultado esperado
A21: 1 | B21: Jugar una partida completando los tres niveles. | D21: La partida recorre los niveles 1, 2 y 3 en ese orden.
A22: 2 | B22: Registrar la forma y la paleta de cada mapa, y el número de nivel del HUD. | D22: Los niveles se juegan en orden 1, 2, 3; cada mapa tiene forma propia distinta de la de los otros dos; el nivel 1 es negro con franjas rojas y contorno celeste, el 2 azul sobre negro con contorno azul y sin franjas, el 3 verde brillante; los caminos están marcados con puntos blancos en los tres; el HUD indica el nivel en curso.
A23: El caso se aprueba solo si se cumple todo el resultado esperado del último paso (en negrita); si cualquier parte no se cumple, se registra como Fallido.

Sheet CP-048
A1: Test Case ID | B1: CP-048 | C1: Descripción / Funcionalidad | D1: HU-15 · Jugar tres niveles con mapas propios | G1: Registro de ejecución
A2: Creado por | B2: Cruz, Luzzi | C2: Versión | D2: 1 | G2: Ciclo | H2: Fecha | I2: Ejecutor | J2: Estado | K2: Resultado obtenido | L2: Defecto
A3: Reporte de ejecución 2 | C3: Estado en la Entrega 2 | D3: =IFERROR(IF(INDEX('Reporte de ejecución - Entrega2'!$I$4:$I$132,MATCH($B$1,'Reporte de ejecución - Entrega2'!$A$4:$A$132,0))="","Sin ejecutar",INDEX('Reporte de ejecución - Entrega2'!$I$4:$I$132,MATCH($B$1,'Reporte de ejecución - Entrega2'!$A$4:$A$132,0))),"Sin ejecutar") | G3: Ciclo 1 | H3: 46294 | I3: Rodriguez Castro | J3: Aprobado | K3: Aprobado. Coincide además con el mapa usado en CP-010.
C4: Estado en la Entrega 1 | D4: Aprobado | G4: Ciclo 2 | H4: 46323 | I4: Luzzi | J4: Aprobado | K4: Dos partidas nuevas: el mapa del nivel 1 es idéntico en forma, esferas y ubicación de las esferas grandes.
A5: Prioridad (Alta, Media, Baja) | B5: Media | C5: Técnica de diseño | D5: Adivinación de errores | G5: Ciclo 3
G6: Ciclo 1 = Entrega 1 (V1). Ciclo 2 = Entrega 2 (V2): ejecución con script de navegador; las precondiciones preparadas por script se aclaran en el resultado obtenido.
A7: # | B7: Pre-requisitos | D7: Datos de prueba
A8: 1 | B8: Abrir la aplicación en un navegador de escritorio. | D8: Entorno: | E8: Build del commit 7ec70df (V2)
A9: 2 | B9: Elegir «Modo PacMan» en el menú principal y presionar Enter (HU-22). | D9: Navegador: | E9: Chromium 141 de escritorio
A10: 3 | B10: Una partida jugada, con el mapa del nivel 1 registrado. | D10: Modo de juego: | E10: Pacman
A12: Título del CP | B12: Los mapas no varían entre partidas
A15: Historias de Usuario | B15: HU-15 | C15: Épica | D15: E4 — Niveles y progresión de dificultad
A16: Estado Automatización | B16: Automatizado (script de navegador, Entrega 2) | C16: Camino feliz | D16: No
A18: Pasos # | B18: Detalle de pasos | D18: Resultado esperado
A19: 1 | B19: Iniciar una partida nueva. | D19: Se inicia una partida nueva en el nivel 1.
A20: 2 | B20: Comparar el mapa del nivel 1 con el registrado. | D20: El mapa del nivel 1 es idéntico al de la partida anterior, en forma, distribución de esferas y ubicación de las esferas grandes.
A21: El caso se aprueba solo si se cumple todo el resultado esperado del último paso (en negrita); si cualquier parte no se cumple, se registra como Fallido.

Sheet CP-049
A1: Test Case ID | B1: CP-049 | C1: Descripción / Funcionalidad | D1: HU-16 · Enfrentar solo fantasmas clásicos en el nivel 1 | G1: Registro de ejecución
A2: Creado por | B2: Cruz, Luzzi (mutación: Luzzi) | C2: Versión | D2: 2 | G2: Ciclo | H2: Fecha | I2: Ejecutor | J2: Estado | K2: Resultado obtenido | L2: Defecto
A3: Reporte de ejecución 2 | C3: Estado en la Entrega 2 | D3: =IFERROR(IF(INDEX('Reporte de ejecución - Entrega2'!$I$4:$I$132,MATCH($B$1,'Reporte de ejecución - Entrega2'!$A$4:$A$132,0))="","Sin ejecutar",INDEX('Reporte de ejecución - Entrega2'!$I$4:$I$132,MATCH($B$1,'Reporte de ejecución - Entrega2'!$A$4:$A$132,0))),"Sin ejecutar") | G3: Ciclo 1 | H3: 46294 | I3: Rodriguez Castro | J3: Aprobado | K3: Aprobado.
C4: Estado en la Entrega 1 | D4: Aprobado | G4: Ciclo 2 | H4: 46307 | I4: Luzzi | J4: Aprobado | K4: Nivel 1 observado 40 s (30 s más que en la V1): tipos ['classic'], velocidades [5] celdas/s; ninguno atravesó muros, saltó, colocó frutas ni hizo dash. (Vidas repuestas por script.)
A5: Prioridad (Alta, Media, Baja) | B5: Alta | C5: Técnica de diseño | D5: Partición de equivalencia | G5: Ciclo 3 | H5: 46323 | I5: Luzzi | J5: Aprobado | K5: Nivel 1 observado 40 s (30 s más que en la V1): tipos ['classic'], velocidades [3.1875] celdas/s; ninguno atravesó muros, saltó, colocó frutas ni hizo dash. (Vidas repuestas por script.) Ciclo 3: build con las decisiones 39 y 40 (velocidad −25 % y fantasmas del modo Pacman −15 %).
G6: Ciclo 1 = Entrega 1 (V1). Ciclo 2 = Entrega 2 (V2): ejecución con script de navegador; las precondiciones preparadas por script se aclaran en el resultado obtenido.
A7: # | B7: Pre-requisitos | D7: Datos de prueba
A8: 1 | B8: Abrir la aplicación en un navegador de escritorio. | D8: Entorno: | E8: Build del commit 7ec70df (V2)
A9: 2 | B9: Elegir «Modo PacMan» en el menú principal y presionar Enter (HU-22). | D9: Navegador: | E9: Chromium 141 de escritorio
A10: 3 | B10: Partida en curso (N1). | D10: Modo de juego: | E10: Pacman
A12: Título del CP | B12: Solo fantasmas clásicos en el nivel 1
A15: Historias de Usuario | B15: HU-16 | C15: Épica | D15: E4 — Niveles y progresión de dificultad
A16: Estado Automatización | B16: Automatizado (script de navegador, Entrega 2) | C16: Camino feliz | D16: No
A18: Mutación (Entrega 2) | B18: Se agregan 30 s más de observación.
A20: Pasos # | B20: Detalle de pasos | D20: Resultado esperado
A21: 1 | B21: Observar los cuatro fantasmas durante todo el nivel 1. | D21: Durante el nivel 1 se observan los cuatro fantasmas.
A22: 2 | B22: Comparar sus velocidades de desplazamiento. | D22: Los cuatro fantasmas son clásicos, ninguno atraviesa muros, se teletransporta, coloca frutas falsas ni ejecuta un dash, y los cuatro se desplazan a la misma velocidad.
A23: El caso se aprueba solo si se cumple todo el resultado esperado del último paso (en negrita); si cualquier parte no se cumple, se registra como Fallido.

Sheet CP-050
A1: Test Case ID | B1: CP-050 | C1: Descripción / Funcionalidad | D1: HU-16 · Enfrentar solo fantasmas clásicos en el nivel 1 | G1: Registro de ejecución
A2: Creado por | B2: Cruz, Luzzi (mutación: Luzzi) | C2: Versión | D2: 2 | G2: Ciclo | H2: Fecha | I2: Ejecutor | J2: Estado | K2: Resultado obtenido | L2: Defecto
A3: Reporte de ejecución 2 | C3: Estado en la Entrega 2 | D3: =IFERROR(IF(INDEX('Reporte de ejecución - Entrega2'!$I$4:$I$132,MATCH($B$1,'Reporte de ejecución - Entrega2'!$A$4:$A$132,0))="","Sin ejecutar",INDEX('Reporte de ejecución - Entrega2'!$I$4:$I$132,MATCH($B$1,'Reporte de ejecución - Entrega2'!$A$4:$A$132,0))),"Sin ejecutar") | G3: Ciclo 1 | H3: 46294 | I3: Rodriguez Castro | J3: Aprobado | K3: Aprobado.
C4: Estado en la Entrega 1 | D4: Aprobado | G4: Ciclo 2 | H4: 46307 | I4: Luzzi | J4: Aprobado | K4: Nivel 1: 6 fantasmas comidos; reaparecieron como ['classic', 'classic', 'classic', 'classic', 'classic', 'classic']. (PowerUp prolongado y reaparición acelerada por script.)
A5: Prioridad (Alta, Media, Baja) | B5: Alta | C5: Técnica de diseño | D5: Partición de equivalencia | G5: Ciclo 3
G6: Ciclo 1 = Entrega 1 (V1). Ciclo 2 = Entrega 2 (V2): ejecución con script de navegador; las precondiciones preparadas por script se aclaran en el resultado obtenido.
A7: # | B7: Pre-requisitos | D7: Datos de prueba
A8: 1 | B8: Abrir la aplicación en un navegador de escritorio. | D8: Entorno: | E8: Build del commit 7ec70df (V2)
A9: 2 | B9: Elegir «Modo PacMan» en el menú principal y presionar Enter (HU-22). | D9: Navegador: | E9: Chromium 141 de escritorio
A10: 3 | B10: Partida en curso (N1). | D10: Modo de juego: | E10: Pacman
A12: Título del CP | B12: Reaparición como clásico en el nivel 1
A15: Historias de Usuario | B15: HU-16 | C15: Épica | D15: E4 — Niveles y progresión de dificultad
A16: Estado Automatización | B16: Automatizado (script de navegador, Entrega 2) | C16: Camino feliz | D16: No
A18: Mutación (Entrega 2) | B18: 6 fantasmas comidos en lugar de 4.
A20: Pasos # | B20: Detalle de pasos | D20: Resultado esperado
A21: 1 | B21: Comer al menos 4 fantasmas a lo largo del nivel 1. | D21: Cada fantasma comido desaparece del mapa y reaparece a los 5 segundos.
A22: 2 | B22: Observar el tipo de cada fantasma que reaparece. | D22: Todos los fantasmas reaparecen como clásicos, sin excepción.
A23: El caso se aprueba solo si se cumple todo el resultado esperado del último paso (en negrita); si cualquier parte no se cumple, se registra como Fallido.

Sheet CP-051
A1: Test Case ID | B1: CP-051 | C1: Descripción / Funcionalidad | D1: HU-17 · Enfrentar fantasmas con poderes a partir del nivel 2 | G1: Registro de ejecución
A2: Creado por | B2: Cruz, Luzzi (mutación: Luzzi) | C2: Versión | D2: 2 | G2: Ciclo | H2: Fecha | I2: Ejecutor | J2: Estado | K2: Resultado obtenido | L2: Defecto
A3: Reporte de ejecución 2 | C3: Estado en la Entrega 2 | D3: =IFERROR(IF(INDEX('Reporte de ejecución - Entrega2'!$I$4:$I$132,MATCH($B$1,'Reporte de ejecución - Entrega2'!$A$4:$A$132,0))="","Sin ejecutar",INDEX('Reporte de ejecución - Entrega2'!$I$4:$I$132,MATCH($B$1,'Reporte de ejecución - Entrega2'!$A$4:$A$132,0))),"Sin ejecutar") | G3: Ciclo 1 | H3: 46294 | I3: Rodriguez Castro | J3: Aprobado | K3: Aprobado.
C4: Estado en la Entrega 1 | D4: Aprobado | G4: Ciclo 2 | H4: 46307 | I4: Luzzi | J4: Aprobado | K4: Nivel 1 completado con 2 vidas; al iniciar el nivel 2 los cuatro fantasmas son ['classic', 'classic', 'classic', 'classic']. (Mapa reducido por script.)
